Workbook

Sheet Income Statement
C1: Ticker Name: | D1: mrk
C3: Current Price | D3: =IFERROR(__xludf.DUMMYFUNCTION("GOOGLEFINANCE(D1,""PRICE"")"),125.37) -> 125.37 | E3: %-change from implied | F3: =D4/D3-1 -> 0.19622026
C4: Implied Share Value | D4: =DCF!C85 -> 149.97013 | E4: %-change (1 month) | F4: =IFERROR(__xludf.DUMMYFUNCTION("(D3-INDEX(GOOGLEFINANCE(D1,""price"",EDATE(TODAY(),-1)),2,2))/D3"),0.0813591768365638) -> 0.081359177
C6: Chart (1 years) | D6: =IFERROR(__xludf.DUMMYFUNCTION("SPARKLINE(INDEX(GOOGLEFINANCE(D1,""price"",EDATE(today(),-12),today()), ,2),{""charttype"",""column"";""color"",""red""})"),"") | E6: %-change (6 months) | F6: =IFERROR(__xludf.DUMMYFUNCTION("(D3-INDEX(GOOGLEFINANCE(D1,""price"",EDATE(TODAY(),-6)),2,2))/D3"),0.15091329664193986) -> 0.1509133
C8: Chart (5 years) | D8: =IFERROR(__xludf.DUMMYFUNCTION("SPARKLINE(INDEX(GOOGLEFINANCE(D1,""price"",EDATE(today(),-60),today()), ,2),{""charttype"",""column"";""color"",""red""})"),"") | E8: %-change (12 months) | F8: =IFERROR(__xludf.DUMMYFUNCTION("(D3-INDEX(GOOGLEFINANCE(D1,""price"",EDATE(TODAY(),-12)),2,2))/D3"),0.3474515434314429) -> 0.34745154
B11: Income Statement | C11: FY | H11: Future FY
C12: 2020 | D12: 2021 | E12: 2022 | F12: 2023 | G12: 2024 | H12: 2025 | I12: 2026 | J12: 2027 | K12: 2028 | L12: 2029
B15: Revenue | C15: =IFERROR(__xludf.DUMMYFUNCTION("IFERROR( LET( x, UPPER(SUBSTITUTE(TRIM(Data!B5),CHAR(160),"""")), base, VALUE(SUBSTITUTE(REGEXEXTRACT(x,""[0-9.,]+""),"","","""")), mult, IF(REGEXMATCH(x,""B""),1000000000, IF(REGEXMATCH(x,""M""),1000000, 1)), base * mult ), 0 )"),4.891E10) -> 48910000000 | D15: =IFERROR(__xludf.DUMMYFUNCTION("IFERROR( LET( x, UPPER(SUBSTITUTE(TRIM(Data!C5),CHAR(160),"""")), base, VALUE(SUBSTITUTE(REGEXEXTRACT(x,""[0-9.,]+""),"","","""")), mult, IF(REGEXMATCH(x,""B""),1000000000, IF(REGEXMATCH(x,""M""),1000000, 1)), base * mult ), 0 )"),5.847E10) -> 58470000000 | E15: =IFERROR(__xludf.DUMMYFUNCTION("IFERROR( LET( x, UPPER(SUBSTITUTE(TRIM(Data!D5),CHAR(160),"""")), base, VALUE(SUBSTITUTE(REGEXEXTRACT(x,""[0-9.,]+""),"","","""")), mult, IF(REGEXMATCH(x,""B""),1000000000, IF(REGEXMATCH(x,""M""),1000000, 1)), base * mult ), 0 )"),5.987E10) -> 59870000000 | F15: =IFERROR(__xludf.DUMMYFUNCTION("IFERROR( LET( x, UPPER(SUBSTITUTE(TRIM(Data!E5),CHAR(160),"""")), base, VALUE(SUBSTITUTE(REGEXEXTRACT(x,""[0-9.,]+""),"","","""")), mult, IF(REGEXMATCH(x,""B""),1000000000, IF(REGEXMATCH(x,""M""),1000000, 1)), base * mult ), 0 )"),6.397E10) -> 63970000000 | G15: =IFERROR(__xludf.DUMMYFUNCTION("IFERROR( LET( x, UPPER(SUBSTITUTE(TRIM(Data!F5),CHAR(160),"""")), base, VALUE(SUBSTITUTE(REGEXEXTRACT(x,""[0-9.,]+""),"","","""")), mult, IF(REGEXMATCH(x,""B""),1000000000, IF(REGEXMATCH(x,""M""),1000000, 1)), base * mult ), 0 )"),6.493000000000001E10) -> 64930000000 | H15: =DCF!H8 -> 66680000000 | I15: =H15*(1+H16) -> 71574368703 | J15: =I15*(1+I16) -> 76827988232 | K15: =J15*(1+J16) -> 82467227901 | L15: =K15*(1+K16) -> 88520392558
B16: Revenue Growth | C16: =Data!B6 -> - | D16: =Data!C6 -> 0.1956 | E16: =Data!D6 -> 0.0239 | F16: =Data!E6 -> 0.0685 | G16: =Data!F6 -> 0.0149 | H16: =(G15/C15)^(1/4)-1 -> 0.07340085 | I16: =H16 -> 0.07340085 | J16: =I16 -> 0.07340085 | K16: =J16 -> 0.07340085 | L16: =K16 -> 0.07340085
B18: Cost of Sales | C18: =Data!B7 -> 13.47B | D18: =Data!C7 -> 17.21B | E18: =Data!D7 -> 15.98B | F18: =Data!E7 -> 16.8B | G18: =Data!F7 -> 18.2B | H18: =H15-H19 -> 16604960796 | I18: =I15-I19 -> 17914844816 | J18: =J15-J19 -> 19327394131 | K18: =K15-K19 -> 20850611084 | L18: =L15-L19 -> 22493118799
B19: Gross Profit | C19: =Data!B13 -> 35.44B | D19: =Data!C13 -> 41.27B | E19: =Data!D13 -> 43.89B | F19: =Data!E13 -> 47.17B | G19: =Data!F13 -> 46.73B | H19: =IFERROR(__xludf.DUMMYFUNCTION("REGEXREPLACE(G19,""B"","""")*1000000000*(1+H20)"),5.007503920394899E10) -> 50075039204 | I19: =H19*(1+I20) -> 53659523888 | J19: =I19*(1+J20) -> 57500594101 | K19: =J19*(1+K20) -> 61616616817 | L19: =K19*(1+L20) -> 66027273758
B20: Gross Profit Growth | C20: =Data!B14 -> - | D20: =Data!C14 -> 0.1644 | E20: =Data!D14 -> 0.0637 | F20: =Data!E14 -> 0.0747 | G20: =Data!F14 -> -0.0093 | H20: =IFERROR(__xludf.DUMMYFUNCTION("(REGEXREPLACE(G19,""B"","""")/REGEXREPLACE(C19,""B"",""""))^(1/4)-1"),0.07158226415469704) -> 0.071582264 | I20: =H20 -> 0.071582264 | J20: =I20 -> 0.071582264 | K20: =J20 -> 0.071582264 | L20: =K20 -> 0.071582264
B23: Selling, General & Admin | C23: =IFERROR(__xludf.DUMMYFUNCTION("IFERROR( LET( x, UPPER(SUBSTITUTE(TRIM(Data!B16),CHAR(160),"""")), base, VALUE(SUBSTITUTE(REGEXEXTRACT(x,""[0-9.,]+""),"","","""")), mult, IF(REGEXMATCH(x,""B""),1000000000, IF(REGEXMATCH(x,""M""),1000000, 1)), base * mult ), 0 )"),1.982E10) -> 19820000000 | D23: =IFERROR(__xludf.DUMMYFUNCTION("IFERROR( LET( x, UPPER(SUBSTITUTE(TRIM(Data!C16),CHAR(160),"""")), base, VALUE(SUBSTITUTE(REGEXEXTRACT(x,""[0-9.,]+""),"","","""")), mult, IF(REGEXMATCH(x,""B""),1000000000, IF(REGEXMATCH(x,""M""),1000000, 1)), base * mult ), 0 )"),2.177E10) -> 21770000000 | E23: =IFERROR(__xludf.DUMMYFUNCTION("IFERROR( LET( x, UPPER(SUBSTITUTE(TRIM(Data!D16),CHAR(160),"""")), base, VALUE(SUBSTITUTE(REGEXEXTRACT(x,""[0-9.,]+""),"","","""")), mult, IF(REGEXMATCH(x,""B""),1000000000, IF(REGEXMATCH(x,""M""),1000000, 1)), base * mult ), 0 )"),4.091E10) -> 40910000000 | F23: =IFERROR(__xludf.DUMMYFUNCTION("IFERROR( LET( x, UPPER(SUBSTITUTE(TRIM(Data!E16),CHAR(160),"""")), base, VALUE(SUBSTITUTE(REGEXEXTRACT(x,""[0-9.,]+""),"","","""")), mult, IF(REGEXMATCH(x,""B""),1000000000, IF(REGEXMATCH(x,""M""),1000000, 1)), base * mult ), 0 )"),2.653E10) -> 26530000000 | G23: =IFERROR(__xludf.DUMMYFUNCTION("IFERROR( LET( x, UPPER(SUBSTITUTE(TRIM(Data!F16),CHAR(160),"""")), base, VALUE(SUBSTITUTE(REGEXEXTRACT(x,""[0-9.,]+""),"","","""")), mult, IF(REGEXMATCH(x,""B""),1000000000, IF(REGEXMATCH(x,""M""),1000000, 1)), base * mult ), 0 )"),2.325E10) -> 23250000000 | H23: - | I23: - | J23: - | K23: - | L23: -
B24: Depreciation & Amortization Expense | C24: =Data!B10 -> 3.21B | D24: =Data!C10 -> 3.91B | E24: =Data!D10 -> 3.87B | F24: =Data!E10 -> 4.5B | G24: =Data!F10 -> 5.84B | H24: - | I24: - | J24: - | K24: - | L24: -
B25: Unusual Expense | C25: =Data!B21 -> 3.16B | D25: =Data!C21 -> 2.27B | E25: =Data!D21 -> 1.03B | F25: =Data!E21 -> 1.18B | G25: =Data!F21 -> 1.7B | H25: - | I25: - | J25: - | K25: - | L25: -
B26: Operating Expenses | C26: =C23 -> 19820000000 | D26: =D23 -> 21770000000 | E26: =E23 -> 40910000000 | F26: =F23 -> 26530000000 | G26: =G23 -> 23250000000 | H26: =G26*(1+H27) -> 24196513023 | I26: =H26*(1+I27) -> 25181558816 | J26: =I26*(1+J27) -> 26206706057 | K26: =J26*(1+K27) -> 27273587286 | L26: =K26*(1+L27) -> 28383901503
B27: Operating Expenses Growth | C27: - | D27: =D26/C26-1 -> 0.098385469 | E27: =E26/D26-1 -> 0.87919155 | F27: =F26/E26-1 -> -0.3515033 | G27: =G26/F26-1 -> -0.12363362 | H27: =(G26/C26)^(1/4)-1 -> 0.040710238 | I27: =H27 -> 0.040710238 | J27: =I27 -> 0.040710238 | K27: =J27 -> 0.040710238 | L27: =K27 -> 0.040710238
B28: Operating Income | C28: =IFERROR(__xludf.DUMMYFUNCTION("(REGEXREPLACE(C19,""B"","""")*1000000000)-C26"),1.562E10) -> 15620000000 | D28: =IFERROR(__xludf.DUMMYFUNCTION("(REGEXREPLACE(D19,""B"","""")*1000000000)-D26"),1.95E10) -> 19500000000 | E28: =IFERROR(__xludf.DUMMYFUNCTION("(REGEXREPLACE(E19,""B"","""")*1000000000)-E26"),2.98E9) -> 2980000000 | F28: =IFERROR(__xludf.DUMMYFUNCTION("(REGEXREPLACE(F19,""B"","""")*1000000000)-F26"),2.064E10) -> 20640000000 | G28: =IFERROR(__xludf.DUMMYFUNCTION("(REGEXREPLACE(G19,""B"","""")*1000000000)-G26"),2.348E10) -> 23480000000 | H28: =G28*(1+H29) -> 25998743439 | I28: =H28*(1+I29) -> 29047664625 | J28: =I28*(1+J29) -> 32744615136 | K28: =J28*(1+K29) -> 37239529593 | L28: =K28*(1+L29) -> 42723864646
B29: Operating Income Growth | C29: - | D29: =D28/C28-1 -> 0.24839949 | E29: =E28/D28-1 -> -0.84717949 | F29: =F28/E28-1 -> 5.9261745 | G29: =G28/F28-1 -> 0.1375969 | H29: =(G28/C28)^(1/4)-1 -> 0.10727187 | I29: =H29+1% -> 0.11727187 | J29: =I29+1% -> 0.12727187 | K29: =J29+1% -> 0.13727187 | L29: =K29+1% -> 0.14727187
B32: EBIT | C32: =Data!B22 -> 12.46B | D32: =Data!C22 -> 17.23B | E32: =Data!D22 -> 1.95B | F32: =Data!E22 -> 19.47B | G32: =Data!F22 -> 21.78B | H32: - | I32: - | J32: - | K32: - | L32: -
B33: EBITDA | C33: =IFERROR(__xludf.DUMMYFUNCTION("IFERROR( LET( x, UPPER(SUBSTITUTE(TRIM(Data!B59),CHAR(160),"""")), base, VALUE(SUBSTITUTE(REGEXEXTRACT(x,""[0-9.,]+""),"","","""")), mult, IF(REGEXMATCH(x,""B""),1000000000, IF(REGEXMATCH(x,""M""),1000000, 1)), base * mult ), 0 )"),1.883E10) -> 18830000000 | D33: =IFERROR(__xludf.DUMMYFUNCTION("IFERROR( LET( x, UPPER(SUBSTITUTE(TRIM(Data!C59),CHAR(160),"""")), base, VALUE(SUBSTITUTE(REGEXEXTRACT(x,""[0-9.,]+""),"","","""")), mult, IF(REGEXMATCH(x,""B""),1000000000, IF(REGEXMATCH(x,""M""),1000000, 1)), base * mult ), 0 )"),2.341E10) -> 23410000000 | E33: =IFERROR(__xludf.DUMMYFUNCTION("IFERROR( LET( x, UPPER(SUBSTITUTE(TRIM(Data!D59),CHAR(160),"""")), base, VALUE(SUBSTITUTE(REGEXEXTRACT(x,""[0-9.,]+""),"","","""")), mult, IF(REGEXMATCH(x,""B""),1000000000, IF(REGEXMATCH(x,""M""),1000000, 1)), base * mult ), 0 )"),6.85E9) -> 6850000000 | F33: =IFERROR(__xludf.DUMMYFUNCTION("IFERROR( LET( x, UPPER(SUBSTITUTE(TRIM(Data!E59),CHAR(160),"""")), base, VALUE(SUBSTITUTE(REGEXEXTRACT(x,""[0-9.,]+""),"","","""")), mult, IF(REGEXMATCH(x,""B""),1000000000, IF(REGEXMATCH(x,""M""),1000000, 1)), base * mult ), 0 )"),2.514E10) -> 25140000000 | G33: =IFERROR(__xludf.DUMMYFUNCTION("IFERROR( LET( x, UPPER(SUBSTITUTE(TRIM(Data!F59),CHAR(160),"""")), base, VALUE(SUBSTITUTE(REGEXEXTRACT(x,""[0-9.,]+""),"","","""")), mult, IF(REGEXMATCH(x,""B""),1000000000, IF(REGEXMATCH(x,""M""),1000000, 1)), base * mult ), 0 )"),2.932E10) -> 29320000000 | H33: =G33*(1+H34) -> 32752343298 | I33: =H33*(1+I34) -> 36586493571 | J33: =I33*(1+J34) -> 40869488319 | K33: =J33*(1+K34) -> 45653871482 | L33: =K33*(1+L34) -> 50998338051
B34: EBITDA Growth | C34: =Data!B60 -> - | D34: =Data!C60 -> 0.243 | E34: =Data!D60 -> -0.7072 | F34: =Data!E60 -> 2.6684 | G34: =Data!F60 -> 0.1663 | H34: =(G33/C33)^(1/4)-1 -> 0.11706491 | I34: =H34 -> 0.11706491 | J34: =I34 -> 0.11706491 | K34: =J34 -> 0.11706491 | L34: =K34 -> 0.11706491
B35: EBITDA Margin | C35: =Data!B61 -> - | D35: =Data!C61 -> - | E35: =Data!D61 -> - | F35: =Data!E61 -> - | G35: =Data!F61 -> 0.4517
B38: Pretax Income | C38: =Data!B30 -> 13.88B | D38: =Data!C30 -> 16.44B | E38: =Data!D30 -> 1.89B | F38: =Data!E30 -> 19.94B | G38: =Data!F30 -> 21.07B | H38: - | I38: - | J38: - | K38: - | L38: -
B39: Income Tax | C39: =Data!B33 -> 1.52B | D39: =Data!C33 -> 1.92B | E39: =Data!D33 -> 1.51B | F39: =Data!E33 -> 2.8B | G39: =Data!F33 -> 2.8B | H39: - | I39: - | J39: - | K39: - | L39: -
B40: Net Income | C40: =IFERROR(__xludf.DUMMYFUNCTION("IFERROR( LET( x, UPPER(SUBSTITUTE(TRIM(Data!B43),CHAR(160),"""")), base, VALUE(SUBSTITUTE(REGEXEXTRACT(x,""[0-9.,]+""),"","","""")), mult, IF(REGEXMATCH(x,""B""),1000000000, IF(REGEXMATCH(x,""M""),1000000, 1)), base * mult ), 0 )"),1.235E10) -> 12350000000 | D40: =IFERROR(__xludf.DUMMYFUNCTION("IFERROR( LET( x, UPPER(SUBSTITUTE(TRIM(Data!C43),CHAR(160),"""")), base, VALUE(SUBSTITUTE(REGEXEXTRACT(x,""[0-9.,]+""),"","","""")), mult, IF(REGEXMATCH(x,""B""),1000000000, IF(REGEXMATCH(x,""M""),1000000, 1)), base * mult ), 0 )"),1.452E10) -> 14520000000 | E40: =IFERROR(__xludf.DUMMYFUNCTION("IFERROR( LET( x, UPPER(SUBSTITUTE(TRIM(Data!D43),CHAR(160),"""")), base, VALUE(SUBSTITUTE(REGEXEXTRACT(x,""[0-9.,]+""),"","","""")), mult, IF(REGEXMATCH(x,""B""),1000000000, IF(REGEXMATCH(x,""M""),1000000, 1)), base * mult ), 0 )"),3.65E8) -> 365000000 | F40: =IFERROR(__xludf.DUMMYFUNCTION("IFERROR( LET( x, UPPER(SUBSTITUTE(TRIM(Data!E43),CHAR(160),"""")), base, VALUE(SUBSTITUTE(REGEXEXTRACT(x,""[0-9.,]+""),"","","""")), mult, IF(REGEXMATCH(x,""B""),1000000000, IF(REGEXMATCH(x,""M""),1000000, 1)), base * mult ), 0 )"),1.7120000000000002E10) -> 17120000000 | G40: =IFERROR(__xludf.DUMMYFUNCTION("IFERROR( LET( x, UPPER(SUBSTITUTE(TRIM(Data!F43),CHAR(160),"""")), base, VALUE(SUBSTITUTE(REGEXEXTRACT(x,""[0-9.,]+""),"","","""")), mult, IF(REGEXMATCH(x,""B""),1000000000, IF(REGEXMATCH(x,""M""),1000000, 1)), base * mult ), 0 )"),1.825E10) -> 18250000000 | H40: =G40*(1+H42) -> 13794566667 | I40: =H40*(1+I42) -> 8494540880 | J40: =I40*(1+J42) -> 6903387528 | K40: =J40*(1+K42) -> 5610280772 | L40: =K40*(1+L42) -> 4203539231
B41: Net Income to Common | C41: =Data!B52 -> 13.05B | D41: =Data!C52 -> 14.52B | E41: =Data!D52 -> 365M | F41: =Data!E52 -> 17.12B | G41: =Data!F52 -> 18.25B | H41: - | I41: - | J41: - | K41: - | L41: -
B42: Net Income Growth | C42: =Data!B44 -> - | D42: =Data!C44 -> 0.1761 | E42: =Data!D44 -> -0.9749 | F42: =Data!E44 -> 45.8959 | G42: =Data!F44 -> 0.0664 | H42: =AVERAGEIF(D42:G42,"<0.70") -> -0.24413333 | I42: =AVERAGEIF(E42:H42,"<0.80") -> -0.38421111 | J42: =AVERAGEIF(F42:I42,"<0.80") -> -0.18731481 | K42: =AVERAGEIF(G42:J42,"<0.80") -> -0.18731481 | L42: =AVERAGEIF(H42:K42,"<0.80") -> -0.25074352
B45: EPS (Diluted) | C45: =Data!B56 -> 5.14 | D45: =Data!C56 -> 5.71 | E45: =Data!D56 -> 0.14 | F45: =Data!E56 -> 6.74 | G45: =Data!F56 -> 7.28 | H45: =Forecast(H12,$C$45:G45,$C$12:G12) -> 6.595 | I45: =FORECAST(I12,$C$45:H45,$C$12:H12) -> 7.126 | J45: =FORECAST(J12,$C$45:I45,$C$12:I12) -> 7.657 | K45: =FORECAST(K12,$C$45:J45,$C$12:J12) -> 8.188 | L45: =FORECAST(L12,$C$45:K45,$C$12:K12) -> 8.719
B46: EPS (Diluted) Growth | C46: =Data!B57 -> - | D46: =Data!C57 -> 0.1109 | E46: =Data!D57 -> -0.9749 | F46: =Data!E57 -> 46.0084 | G46: =Data!F57 -> 0.0809 | H46: =H45/G45-1 -> -0.094093407 | I46: =I45/H45-1 -> 0.080515542 | J46: =J45/I45-1 -> 0.074515857 | K46: =K45/J45-1 -> 0.069348309 | L46: =L45/K45-1 -> 0.064851001
D1006: =1.56*L33 -> 79557407359

Sheet Balance Sheet
B2: Balance Sheet | C2: FY | H2: Future FY
C3: 2020 | D3: 2021 | E3: 2022 | F3: 2023 | G3: 2024 | H3: 2025 | I3: 2026 | J3: 2027 | K3: 2028 | L3: 2029
B6: Cash Only | C6: =IFERROR(__xludf.DUMMYFUNCTION("IFERROR( LET( x, UPPER(SUBSTITUTE(TRIM(Data!B71),CHAR(160),"""")), base, VALUE(SUBSTITUTE(REGEXEXTRACT(x,""[0-9.,]+""),"","","""")), mult, IF(REGEXMATCH(x,""B""),1000000000, IF(REGEXMATCH(x,""M""),1000000, 1)), base * mult ), 0 )"),8.1E9) -> 8100000000 | D6: =IFERROR(__xludf.DUMMYFUNCTION("IFERROR( LET( x, UPPER(SUBSTITUTE(TRIM(Data!C71),CHAR(160),"""")), base, VALUE(SUBSTITUTE(REGEXEXTRACT(x,""[0-9.,]+""),"","","""")), mult, IF(REGEXMATCH(x,""B""),1000000000, IF(REGEXMATCH(x,""M""),1000000, 1)), base * mult ), 0 )"),1.277E10) -> 12770000000 | E6: =IFERROR(__xludf.DUMMYFUNCTION("IFERROR( LET( x, UPPER(SUBSTITUTE(TRIM(Data!D71),CHAR(160),"""")), base, VALUE(SUBSTITUTE(REGEXEXTRACT(x,""[0-9.,]+""),"","","""")), mult, IF(REGEXMATCH(x,""B""),1000000000, IF(REGEXMATCH(x,""M""),1000000, 1)), base * mult ), 0 )"),6.91E9) -> 6910000000 | F6: =IFERROR(__xludf.DUMMYFUNCTION("IFERROR( LET( x, UPPER(SUBSTITUTE(TRIM(Data!E71),CHAR(160),"""")), base, VALUE(SUBSTITUTE(REGEXEXTRACT(x,""[0-9.,]+""),"","","""")), mult, IF(REGEXMATCH(x,""B""),1000000000, IF(REGEXMATCH(x,""M""),1000000, 1)), base * mult ), 0 )"),1.332E10) -> 13320000000 | G6: =IFERROR(__xludf.DUMMYFUNCTION("IFERROR( LET( x, UPPER(SUBSTITUTE(TRIM(Data!F71),CHAR(160),"""")), base, VALUE(SUBSTITUTE(REGEXEXTRACT(x,""[0-9.,]+""),"","","""")), mult, IF(REGEXMATCH(x,""B""),1000000000, IF(REGEXMATCH(x,""M""),1000000, 1)), base * mult ), 0 )"),1.469E10) -> 14690000000 | H6: =FORECAST(H3,$C$6:G6,$C$3:G3) -> 15277000000 | I6: =FORECAST(I3,$C$6:H6,$C$3:H3) -> 16650000000 | J6: =FORECAST(J3,$C$6:I6,$C$3:I3) -> 18023000000 | K6: =FORECAST(K3,$C$6:J6,$C$3:J3) -> 19396000000 | L6: =FORECAST(L3,$C$6:K6,$C$3:K3) -> 20769000000
B7: Short-Term Investments | C7: =Data!B72:F72 -> - | D7: =Data!C72 -> - | E7: =Data!D72 -> - | F7: =Data!E72 -> - | G7: =Data!F72 -> - | H7: - | I7: - | J7: - | K7: - | L7: -
B8: Cash & Short Term Invesments | C8: =IFERROR(__xludf.DUMMYFUNCTION("IFERROR( LET( x, UPPER(SUBSTITUTE(TRIM(Data!B69),CHAR(160),"""")), base, VALUE(SUBSTITUTE(REGEXEXTRACT(x,""[0-9.,]+""),"","","""")), mult, IF(REGEXMATCH(x,""B""),1000000000, IF(REGEXMATCH(x,""M""),1000000, 1)), base * mult ), 0 )"),8.1E9) -> 8100000000 | D8: =IFERROR(__xludf.DUMMYFUNCTION("IFERROR( LET( x, UPPER(SUBSTITUTE(TRIM(Data!C69),CHAR(160),"""")), base, VALUE(SUBSTITUTE(REGEXEXTRACT(x,""[0-9.,]+""),"","","""")), mult, IF(REGEXMATCH(x,""B""),1000000000, IF(REGEXMATCH(x,""M""),1000000, 1)), base * mult ), 0 )"),1.327E10) -> 13270000000 | E8: =IFERROR(__xludf.DUMMYFUNCTION("IFERROR( LET( x, UPPER(SUBSTITUTE(TRIM(Data!D69),CHAR(160),"""")), base, VALUE(SUBSTITUTE(REGEXEXTRACT(x,""[0-9.,]+""),"","","""")), mult, IF(REGEXMATCH(x,""B""),1000000000, IF(REGEXMATCH(x,""M""),1000000, 1)), base * mult ), 0 )"),7.16E9) -> 7160000000 | F8: =IFERROR(__xludf.DUMMYFUNCTION("IFERROR( LET( x, UPPER(SUBSTITUTE(TRIM(Data!E69),CHAR(160),"""")), base, VALUE(SUBSTITUTE(REGEXEXTRACT(x,""[0-9.,]+""),"","","""")), mult, IF(REGEXMATCH(x,""B""),1000000000, IF(REGEXMATCH(x,""M""),1000000, 1)), base * mult ), 0 )"),1.377E10) -> 13770000000 | G8: =IFERROR(__xludf.DUMMYFUNCTION("IFERROR( LET( x, UPPER(SUBSTITUTE(TRIM(Data!F69),CHAR(160),"""")), base, VALUE(SUBSTITUTE(REGEXEXTRACT(x,""[0-9.,]+""),"","","""")), mult, IF(REGEXMATCH(x,""B""),1000000000, IF(REGEXMATCH(x,""M""),1000000, 1)), base * mult ), 0 )"),1.469E10) -> 14690000000 | H8: =H6 -> 15277000000 | I8: =I6 -> 16650000000 | J8: =J6 -> 18023000000 | K8: =K6 -> 19396000000 | L8: =L6 -> 20769000000
B9: Cash & Short Term Invesments Growth | C9: =Data!B70 -> - | D9: =Data!C70 -> 0.6392 | E9: =Data!D70 -> -0.4604 | F9: =Data!E70 -> 0.9222 | G9: =Data!F70 -> 0.0672 | H9: =H8/G8-1 -> 0.039959156 | I9: =I8/H8-1 -> 0.089873666 | J9: =J8/I8-1 -> 0.082462462 | K9: =K8/J8-1 -> 0.076180436 | L9: =L8/K8-1 -> 0.070787791
B12: Finished Goods | C12: =IFERROR(__xludf.DUMMYFUNCTION("IFERROR( LET( x, UPPER(SUBSTITUTE(TRIM(Data!B82),CHAR(160),"""")), base, VALUE(SUBSTITUTE(REGEXEXTRACT(x,""[0-9.,]+""),"","","""")), mult, IF(REGEXMATCH(x,""B""),1000000000, IF(REGEXMATCH(x,""M""),1000000, 1)), base * mult ), 0 )"),1.75E9) -> 1750000000 | D12: =IFERROR(__xludf.DUMMYFUNCTION("IFERROR( LET( x, UPPER(SUBSTITUTE(TRIM(Data!C82),CHAR(160),"""")), base, VALUE(SUBSTITUTE(REGEXEXTRACT(x,""[0-9.,]+""),"","","""")), mult, IF(REGEXMATCH(x,""B""),1000000000, IF(REGEXMATCH(x,""M""),1000000, 1)), base * mult ), 0 )"),1.84E9) -> 1840000000 | E12: =IFERROR(__xludf.DUMMYFUNCTION("IFERROR( LET( x, UPPER(SUBSTITUTE(TRIM(Data!D82),CHAR(160),"""")), base, VALUE(SUBSTITUTE(REGEXEXTRACT(x,""[0-9.,]+""),"","","""")), mult, IF(REGEXMATCH(x,""B""),1000000000, IF(REGEXMATCH(x,""M""),1000000, 1)), base * mult ), 0 )"),1.95E9) -> 1950000000 | F12: =IFERROR(__xludf.DUMMYFUNCTION("IFERROR( LET( x, UPPER(SUBSTITUTE(TRIM(Data!E82),CHAR(160),"""")), base, VALUE(SUBSTITUTE(REGEXEXTRACT(x,""[0-9.,]+""),"","","""")), mult, IF(REGEXMATCH(x,""B""),1000000000, IF(REGEXMATCH(x,""M""),1000000, 1)), base * mult ), 0 )"),2.02E9) -> 2020000000 | G12: =IFERROR(__xludf.DUMMYFUNCTION("IFERROR( LET( x, UPPER(SUBSTITUTE(TRIM(Data!F82),CHAR(160),"""")), base, VALUE(SUBSTITUTE(REGEXEXTRACT(x,""[0-9.,]+""),"","","""")), mult, IF(REGEXMATCH(x,""B""),1000000000, IF(REGEXMATCH(x,""M""),1000000, 1)), base * mult ), 0 )"),2.28E9) -> 2280000000 | H12: =AVERAGE(C12:G12) -> 1968000000 | I12: =AVERAGE(D12:H12) -> 2011600000 | J12: =AVERAGE(E12:I12) -> 2045920000 | K12: =AVERAGE(F12:J12) -> 2065104000 | L12: =AVERAGE(G12:K12) -> 2074124800
B13: Work in Progress | C13: =IFERROR(__xludf.DUMMYFUNCTION("regexreplace(Data!B83,""M"","""")*1000000"),"#VALUE!") -> #VALUE! | D13: =IFERROR(__xludf.DUMMYFUNCTION("IFERROR( LET( x, UPPER(SUBSTITUTE(TRIM(Data!C83),CHAR(160),"""")), base, VALUE(SUBSTITUTE(REGEXEXTRACT(x,""[0-9.,]+""),"","","""")), mult, IF(REGEXMATCH(x,""B""),1000000000, IF(REGEXMATCH(x,""M""),1000000, 1)), base * mult ), 0 )"),0.0) -> 0 | E13: =IFERROR(__xludf.DUMMYFUNCTION("IFERROR( LET( x, UPPER(SUBSTITUTE(TRIM(Data!D83),CHAR(160),"""")), base, VALUE(SUBSTITUTE(REGEXEXTRACT(x,""[0-9.,]+""),"","","""")), mult, IF(REGEXMATCH(x,""B""),1000000000, IF(REGEXMATCH(x,""M""),1000000, 1)), base * mult ), 0 )"),0.0) -> 0 | F13: =IFERROR(__xludf.DUMMYFUNCTION("IFERROR( LET( x, UPPER(SUBSTITUTE(TRIM(Data!E83),CHAR(160),"""")), base, VALUE(SUBSTITUTE(REGEXEXTRACT(x,""[0-9.,]+""),"","","""")), mult, IF(REGEXMATCH(x,""B""),1000000000, IF(REGEXMATCH(x,""M""),1000000, 1)), base * mult ), 0 )"),0.0) -> 0 | G13: =IFERROR(__xludf.DUMMYFUNCTION("IFERROR( LET( x, UPPER(SUBSTITUTE(TRIM(Data!F83),CHAR(160),"""")), base, VALUE(SUBSTITUTE(REGEXEXTRACT(x,""[0-9.,]+""),"","","""")), mult, IF(REGEXMATCH(x,""B""),1000000000, IF(REGEXMATCH(x,""M""),1000000, 1)), base * mult ), 0 )"),0.0) -> 0 | H13: =AVERAGE(C13:G13) -> #VALUE! | I13: =AVERAGE(D13:H13) -> #VALUE! | J13: =AVERAGE(E13:I13) -> #VALUE! | K13: =AVERAGE(F13:J13) -> #VALUE! | L13: =AVERAGE(G13:K13) -> #VALUE!
B14: Raw Materials | C14: =IFERROR(__xludf.DUMMYFUNCTION("IFERROR( LET( x, UPPER(SUBSTITUTE(TRIM(Data!B84),CHAR(160),"""")), base, VALUE(SUBSTITUTE(REGEXEXTRACT(x,""[0-9.,]+""),"","","""")), mult, IF(REGEXMATCH(x,""B""),1000000000, IF(REGEXMATCH(x,""M""),1000000, 1)), base * mult ), 0 )"),4.2199999999999995E9) -> 4220000000 | D14: =IFERROR(__xludf.DUMMYFUNCTION("IFERROR( LET( x, UPPER(SUBSTITUTE(TRIM(Data!C84),CHAR(160),"""")), base, VALUE(SUBSTITUTE(REGEXEXTRACT(x,""[0-9.,]+""),"","","""")), mult, IF(REGEXMATCH(x,""B""),1000000000, IF(REGEXMATCH(x,""M""),1000000, 1)), base * mult ), 0 )"),4.36E9) -> 4360000000 | E14: =IFERROR(__xludf.DUMMYFUNCTION("IFERROR( LET( x, UPPER(SUBSTITUTE(TRIM(Data!D84),CHAR(160),"""")), base, VALUE(SUBSTITUTE(REGEXEXTRACT(x,""[0-9.,]+""),"","","""")), mult, IF(REGEXMATCH(x,""B""),1000000000, IF(REGEXMATCH(x,""M""),1000000, 1)), base * mult ), 0 )"),4.97E9) -> 4970000000 | F14: =IFERROR(__xludf.DUMMYFUNCTION("IFERROR( LET( x, UPPER(SUBSTITUTE(TRIM(Data!E84),CHAR(160),"""")), base, VALUE(SUBSTITUTE(REGEXEXTRACT(x,""[0-9.,]+""),"","","""")), mult, IF(REGEXMATCH(x,""B""),1000000000, IF(REGEXMATCH(x,""M""),1000000, 1)), base * mult ), 0 )"),4.93E9) -> 4930000000 | G14: =IFERROR(__xludf.DUMMYFUNCTION("IFERROR( LET( x, UPPER(SUBSTITUTE(TRIM(Data!F84),CHAR(160),"""")), base, VALUE(SUBSTITUTE(REGEXEXTRACT(x,""[0-9.,]+""),"","","""")), mult, IF(REGEXMATCH(x,""B""),1000000000, IF(REGEXMATCH(x,""M""),1000000, 1)), base * mult ), 0 )"),5.3E9) -> 5300000000 | H14: =AVERAGE(C14:G14) -> 4756000000 | I14: =AVERAGE(D14:H14) -> 4863200000 | J14: =AVERAGE(E14:I14) -> 4963840000 | K14: =AVERAGE(F14:J14) -> 4962608000 | L14: =AVERAGE(G14:K14) -> 4969129600
B15: Inventories | C15: =IFERROR(__xludf.DUMMYFUNCTION("IFERROR( LET( x, UPPER(SUBSTITUTE(TRIM(Data!B81),CHAR(160),"""")), base, VALUE(SUBSTITUTE(REGEXEXTRACT(x,""[0-9.,]+""),"","","""")), mult, IF(REGEXMATCH(x,""B""),1000000000, IF(REGEXMATCH(x,""M""),1000000, 1)), base * mult ), 0 )"),5.95E9) -> 5950000000 | D15: =IFERROR(__xludf.DUMMYFUNCTION("IFERROR( LET( x, UPPER(SUBSTITUTE(TRIM(Data!C81),CHAR(160),"""")), base, VALUE(SUBSTITUTE(REGEXEXTRACT(x,""[0-9.,]+""),"","","""")), mult, IF(REGEXMATCH(x,""B""),1000000000, IF(REGEXMATCH(x,""M""),1000000, 1)), base * mult ), 0 )"),5.91E9) -> 5910000000 | E15: =IFERROR(__xludf.DUMMYFUNCTION("IFERROR( LET( x, UPPER(SUBSTITUTE(TRIM(Data!D81),CHAR(160),"""")), base, VALUE(SUBSTITUTE(REGEXEXTRACT(x,""[0-9.,]+""),"","","""")), mult, IF(REGEXMATCH(x,""B""),1000000000, IF(REGEXMATCH(x,""M""),1000000, 1)), base * mult ), 0 )"),6.36E9) -> 6360000000 | F15: =IFERROR(__xludf.DUMMYFUNCTION("IFERROR( LET( x, UPPER(SUBSTITUTE(TRIM(Data!E81),CHAR(160),"""")), base, VALUE(SUBSTITUTE(REGEXEXTRACT(x,""[0-9.,]+""),"","","""")), mult, IF(REGEXMATCH(x,""B""),1000000000, IF(REGEXMATCH(x,""M""),1000000, 1)), base * mult ), 0 )"),6.11E9) -> 6110000000 | G15: =IFERROR(__xludf.DUMMYFUNCTION("IFERROR( LET( x, UPPER(SUBSTITUTE(TRIM(Data!F81),CHAR(160),"""")), base, VALUE(SUBSTITUTE(REGEXEXTRACT(x,""[0-9.,]+""),"","","""")), mult, IF(REGEXMATCH(x,""B""),1000000000, IF(REGEXMATCH(x,""M""),1000000, 1)), base * mult ), 0 )"),6.66E9) -> 6660000000 | H15: =AVERAGE(C15:G15) -> 6198000000 | I15: =AVERAGE(D15:H15) -> 6247600000 | J15: =AVERAGE(E15:I15) -> 6315120000 | K15: =AVERAGE(F15:J15) -> 6306144000 | L15: =AVERAGE(G15:K15) -> 6345372800
B18: Accounts Receivables, Net | C18: =IFERROR(__xludf.DUMMYFUNCTION("IFERROR( LET( x, UPPER(SUBSTITUTE(TRIM(Data!B76),CHAR(160),"""")), base, VALUE(SUBSTITUTE(REGEXEXTRACT(x,""[0-9.,]+""),"","","""")), mult, IF(REGEXMATCH(x,""B""),1000000000, IF(REGEXMATCH(x,""M""),1000000, 1)), base * mult ), 0 )"),9.23E9) -> 9230000000 | D18: =IFERROR(__xludf.DUMMYFUNCTION("IFERROR( LET( x, UPPER(SUBSTITUTE(TRIM(Data!C76),CHAR(160),"""")), base, VALUE(SUBSTITUTE(REGEXEXTRACT(x,""[0-9.,]+""),"","","""")), mult, IF(REGEXMATCH(x,""B""),1000000000, IF(REGEXMATCH(x,""M""),1000000, 1)), base * mult ), 0 )"),9.45E9) -> 9450000000 | E18: =IFERROR(__xludf.DUMMYFUNCTION("IFERROR( LET( x, UPPER(SUBSTITUTE(TRIM(Data!D76),CHAR(160),"""")), base, VALUE(SUBSTITUTE(REGEXEXTRACT(x,""[0-9.,]+""),"","","""")), mult, IF(REGEXMATCH(x,""B""),1000000000, IF(REGEXMATCH(x,""M""),1000000, 1)), base * mult ), 0 )"),1.035E10) -> 10350000000 | F18: =IFERROR(__xludf.DUMMYFUNCTION("IFERROR( LET( x, UPPER(SUBSTITUTE(TRIM(Data!E76),CHAR(160),"""")), base, VALUE(SUBSTITUTE(REGEXEXTRACT(x,""[0-9.,]+""),"","","""")), mult, IF(REGEXMATCH(x,""B""),1000000000, IF(REGEXMATCH(x,""M""),1000000, 1)), base * mult ), 0 )"),1.028E10) -> 10280000000 | G18: =IFERROR(__xludf.DUMMYFUNCTION("IFERROR( LET( x, UPPER(SUBSTITUTE(TRIM(Data!F76),CHAR(160),"""")), base, VALUE(SUBSTITUTE(REGEXEXTRACT(x,""[0-9.,]+""),"","","""")), mult, IF(REGEXMATCH(x,""B""),1000000000, IF(REGEXMATCH(x,""M""),1000000, 1)), base * mult ), 0 )"),1.178E10) -> 11780000000 | H18: =FORECAST(H3,$C$18:G18,$C$3:G3) -> 11997000000 | I18: =FORECAST(I3,$C$18:H18,$C$3:H3) -> 12590000000 | J18: =FORECAST(J3,$C$18:I18,$C$3:I3) -> 13183000000 | K18: =FORECAST(K3,$C$18:J18,$C$3:J3) -> 13776000000 | L18: =FORECAST(L3,$C$18:K18,$C$3:K3) -> 14369000000
B19: Other Receivable | C19: =Data!B79 -> 585M | D19: =Data!C79 -> 660M | E19: =Data!D79 -> 723M | F19: =Data!E79 -> 849M | G19: =Data!F79 -> 904M | H19: - | I19: - | J19: - | K19: - | L19: -
B20: Total Accounts Receivable | C20: =IFERROR(__xludf.DUMMYFUNCTION("IFERROR( LET( x, UPPER(SUBSTITUTE(TRIM(Data!B74),CHAR(160),"""")), base, VALUE(SUBSTITUTE(REGEXEXTRACT(x,""[0-9.,]+""),"","","""")), mult, IF(REGEXMATCH(x,""B""),1000000000, IF(REGEXMATCH(x,""M""),1000000, 1)), base * mult ), 0 )"),9.82E9) -> 9820000000 | D20: =IFERROR(__xludf.DUMMYFUNCTION("IFERROR( LET( x, UPPER(SUBSTITUTE(TRIM(Data!C74),CHAR(160),"""")), base, VALUE(SUBSTITUTE(REGEXEXTRACT(x,""[0-9.,]+""),"","","""")), mult, IF(REGEXMATCH(x,""B""),1000000000, IF(REGEXMATCH(x,""M""),1000000, 1)), base * mult ), 0 )"),1.011E10) -> 10110000000 | E20: =IFERROR(__xludf.DUMMYFUNCTION("IFERROR( LET( x, UPPER(SUBSTITUTE(TRIM(Data!D74),CHAR(160),"""")), base, VALUE(SUBSTITUTE(REGEXEXTRACT(x,""[0-9.,]+""),"","","""")), mult, IF(REGEXMATCH(x,""B""),1000000000, IF(REGEXMATCH(x,""M""),1000000, 1)), base * mult ), 0 )"),1.107E10) -> 11070000000 | F20: =IFERROR(__xludf.DUMMYFUNCTION("IFERROR( LET( x, UPPER(SUBSTITUTE(TRIM(Data!E74),CHAR(160),"""")), base, VALUE(SUBSTITUTE(REGEXEXTRACT(x,""[0-9.,]+""),"","","""")), mult, IF(REGEXMATCH(x,""B""),1000000000, IF(REGEXMATCH(x,""M""),1000000, 1)), base * mult ), 0 )"),1.113E10) -> 11130000000 | G20: =IFERROR(__xludf.DUMMYFUNCTION("IFERROR( LET( x, UPPER(SUBSTITUTE(TRIM(Data!F74),CHAR(160),"""")), base, VALUE(SUBSTITUTE(REGEXEXTRACT(x,""[0-9.,]+""),"","","""")), mult, IF(REGEXMATCH(x,""B""),1000000000, IF(REGEXMATCH(x,""M""),1000000, 1)), base * mult ), 0 )"),1.268E10) -> 12680000000 | H20: =FORECAST(H3,$C$20:G20,$C$3:G3) -> 12984000000 | I20: =FORECAST(I3,$C$20:H20,$C$3:H3) -> 13658000000 | J20: =FORECAST(J3,$C$20:I20,$C$3:I3) -> 14332000000 | K20: =FORECAST(K3,$C$20:J20,$C$3:J3) -> 15006000000 | L20: =FORECAST(L3,$C$20:K20,$C$3:K3) -> 15680000000
B21: Total Accounts Receivable Growth | C21: =Data!B75 -> - | D21: =Data!C75 -> 0.0301 | E21: =Data!D75 -> 0.0952 | F21: =Data!E75 -> 0.005 | G21: =Data!F75 -> 0.1395 | H21: =H20/G20-1 -> 0.023974763 | I21: =I20/H20-1 -> 0.051910043 | J21: =J20/I20-1 -> 0.049348367 | K21: =K20/J20-1 -> 0.04702763 | L21: =L20/K20-1 -> 0.044915367
B24: Other Current Assets | C24: =IFERROR(__xludf.DUMMYFUNCTION("IFERROR( LET( x, UPPER(SUBSTITUTE(TRIM(Data!B86),CHAR(160),"""")), base, VALUE(SUBSTITUTE(REGEXEXTRACT(x,""[0-9.,]+""),"","","""")), mult, IF(REGEXMATCH(x,""B""),1000000000, IF(REGEXMATCH(x,""M""),1000000, 1)), base * mult ), 0 )"),6.4E9) -> 6400000000 | D24: =IFERROR(__xludf.DUMMYFUNCTION("IFERROR( LET( x, UPPER(SUBSTITUTE(TRIM(Data!C86),CHAR(160),"""")), base, VALUE(SUBSTITUTE(REGEXEXTRACT(x,""[0-9.,]+""),"","","""")), mult, IF(REGEXMATCH(x,""B""),1000000000, IF(REGEXMATCH(x,""M""),1000000, 1)), base * mult ), 0 )"),6.43E9) -> 6430000000 | E24: =IFERROR(__xludf.DUMMYFUNCTION("IFERROR( LET( x, UPPER(SUBSTITUTE(TRIM(Data!D86),CHAR(160),"""")), base, VALUE(SUBSTITUTE(REGEXEXTRACT(x,""[0-9.,]+""),"","","""")), mult, IF(REGEXMATCH(x,""B""),1000000000, IF(REGEXMATCH(x,""M""),1000000, 1)), base * mult ), 0 )"),7.58E9) -> 7580000000 | F24: =IFERROR(__xludf.DUMMYFUNCTION("IFERROR( LET( x, UPPER(SUBSTITUTE(TRIM(Data!E86),CHAR(160),"""")), base, VALUE(SUBSTITUTE(REGEXEXTRACT(x,""[0-9.,]+""),"","","""")), mult, IF(REGEXMATCH(x,""B""),1000000000, IF(REGEXMATCH(x,""M""),1000000, 1)), base * mult ), 0 )"),7.78E9) -> 7780000000 | G24: =IFERROR(__xludf.DUMMYFUNCTION("IFERROR( LET( x, UPPER(SUBSTITUTE(TRIM(Data!F86),CHAR(160),"""")), base, VALUE(SUBSTITUTE(REGEXEXTRACT(x,""[0-9.,]+""),"","","""")), mult, IF(REGEXMATCH(x,""B""),1000000000, IF(REGEXMATCH(x,""M""),1000000, 1)), base * mult ), 0 )"),9.49E9) -> 9490000000 | H24: =AVERAGE(C24:G24) -> 7536000000 | I24: =AVERAGE(D24:H24) -> 7763200000 | J24: =AVERAGE(E24:I24) -> 8029840000 | K24: =AVERAGE(F24:J24) -> 8119808000 | L24: =AVERAGE(G24:K24) -> 8187769600
B25: Total Current Assets | C25: =IFERROR(__xludf.DUMMYFUNCTION("IFERROR( LET( x, UPPER(SUBSTITUTE(TRIM(Data!B88),CHAR(160),"""")), base, VALUE(SUBSTITUTE(REGEXEXTRACT(x,""[0-9.,]+""),"","","""")), mult, IF(REGEXMATCH(x,""B""),1000000000, IF(REGEXMATCH(x,""M""),1000000, 1)), base * mult ), 0 )"),3.027E10) -> 30270000000 | D25: =IFERROR(__xludf.DUMMYFUNCTION("IFERROR( LET( x, UPPER(SUBSTITUTE(TRIM(Data!C88),CHAR(160),"""")), base, VALUE(SUBSTITUTE(REGEXEXTRACT(x,""[0-9.,]+""),"","","""")), mult, IF(REGEXMATCH(x,""B""),1000000000, IF(REGEXMATCH(x,""M""),1000000, 1)), base * mult ), 0 )"),3.572E10) -> 35720000000 | E25: =IFERROR(__xludf.DUMMYFUNCTION("IFERROR( LET( x, UPPER(SUBSTITUTE(TRIM(Data!D88),CHAR(160),"""")), base, VALUE(SUBSTITUTE(REGEXEXTRACT(x,""[0-9.,]+""),"","","""")), mult, IF(REGEXMATCH(x,""B""),1000000000, IF(REGEXMATCH(x,""M""),1000000, 1)), base * mult ), 0 )"),3.217E10) -> 32170000000 | F25: =IFERROR(__xludf.DUMMYFUNCTION("IFERROR( LET( x, UPPER(SUBSTITUTE(TRIM(Data!E88),CHAR(160),"""")), base, VALUE(SUBSTITUTE(REGEXEXTRACT(x,""[0-9.,]+""),"","","""")), mult, IF(REGEXMATCH(x,""B""),1000000000, IF(REGEXMATCH(x,""M""),1000000, 1)), base * mult ), 0 )"),3.878E10) -> 38780000000 | G25: =IFERROR(__xludf.DUMMYFUNCTION("IFERROR( LET( x, UPPER(SUBSTITUTE(TRIM(Data!F88),CHAR(160),"""")), base, VALUE(SUBSTITUTE(REGEXEXTRACT(x,""[0-9.,]+""),"","","""")), mult, IF(REGEXMATCH(x,""B""),1000000000, IF(REGEXMATCH(x,""M""),1000000, 1)), base * mult ), 0 )"),4.352E10) -> 43520000000 | H25: =FORECAST(H3,$C$25:G25,$C$3:G3) -> 44960000000 | I25: =FORECAST(I3,$C$25:H25,$C$3:H3) -> 47916000000 | J25: =FORECAST(J3,$C$25:I25,$C$3:I3) -> 50872000000 | K25: =FORECAST(K3,$C$25:J25,$C$3:J3) -> 53828000000 | L25: =FORECAST(L3,$C$25:K25,$C$3:K3) -> 56784000000
B26: Total Current Assets Growth | C26: - | D26: =D25/C25-1 -> 0.18004625 | E26: =E25/D25-1 -> -0.099384099 | F26: =F25/E25-1 -> 0.20547094 | G26: =G25/F25-1 -> 0.12222795 | H26: =H25/G25-1 -> 0.033088235 | I26: =I25/H25-1 -> 0.065747331 | J26: =J25/I25-1 -> 0.061691293 | K26: =K25/J25-1 -> 0.058106621 | L26: =L25/K25-1 -> 0.054915657
B29: Property, Plant & Equipment | C29: =IFERROR(__xludf.DUMMYFUNCTION("IFERROR( LET( x, UPPER(SUBSTITUTE(TRIM(Data!B90),CHAR(160),"""")), base, VALUE(SUBSTITUTE(REGEXEXTRACT(x,""[0-9.,]+""),"","","""")), mult, IF(REGEXMATCH(x,""B""),1000000000, IF(REGEXMATCH(x,""M""),1000000, 1)), base * mult ), 0 )"),3.906E10) -> 39060000000 | D29: =IFERROR(__xludf.DUMMYFUNCTION("IFERROR( LET( x, UPPER(SUBSTITUTE(TRIM(Data!C90),CHAR(160),"""")), base, VALUE(SUBSTITUTE(REGEXEXTRACT(x,""[0-9.,]+""),"","","""")), mult, IF(REGEXMATCH(x,""B""),1000000000, IF(REGEXMATCH(x,""M""),1000000, 1)), base * mult ), 0 )"),4.075E10) -> 40750000000 | E29: =IFERROR(__xludf.DUMMYFUNCTION("IFERROR( LET( x, UPPER(SUBSTITUTE(TRIM(Data!D90),CHAR(160),"""")), base, VALUE(SUBSTITUTE(REGEXEXTRACT(x,""[0-9.,]+""),"","","""")), mult, IF(REGEXMATCH(x,""B""),1000000000, IF(REGEXMATCH(x,""M""),1000000, 1)), base * mult ), 0 )"),4.275E10) -> 42750000000 | F29: =IFERROR(__xludf.DUMMYFUNCTION("IFERROR( LET( x, UPPER(SUBSTITUTE(TRIM(Data!E90),CHAR(160),"""")), base, VALUE(SUBSTITUTE(REGEXEXTRACT(x,""[0-9.,]+""),"","","""")), mult, IF(REGEXMATCH(x,""B""),1000000000, IF(REGEXMATCH(x,""M""),1000000, 1)), base * mult ), 0 )"),4.43E10) -> 44300000000 | G29: =IFERROR(__xludf.DUMMYFUNCTION("IFERROR( LET( x, UPPER(SUBSTITUTE(TRIM(Data!F90),CHAR(160),"""")), base, VALUE(SUBSTITUTE(REGEXEXTRACT(x,""[0-9.,]+""),"","","""")), mult, IF(REGEXMATCH(x,""B""),1000000000, IF(REGEXMATCH(x,""M""),1000000, 1)), base * mult ), 0 )"),4.874E10) -> 48740000000 | H29: =AVERAGE(C29:G29) -> 43120000000 | I29: =AVERAGE(D29:H29) -> 43932000000 | J29: =AVERAGE(E29:I29) -> 44568400000 | K29: =AVERAGE(F29:J29) -> 44932080000 | L29: =AVERAGE(G29:K29) -> 45058496000
B30: Accumulated Depreciation | C30: =IFERROR(__xludf.DUMMYFUNCTION("IFERROR( LET( x, UPPER(SUBSTITUTE(TRIM(Data!B95),CHAR(160),"""")), base, VALUE(SUBSTITUTE(REGEXEXTRACT(x,""[0-9.,]+""),"","","""")), mult, IF(REGEXMATCH(x,""B""),1000000000, IF(REGEXMATCH(x,""M""),1000000, 1)), base * mult ), 0 )"),1.819E10) -> 18190000000 | D30: =IFERROR(__xludf.DUMMYFUNCTION("IFERROR( LET( x, UPPER(SUBSTITUTE(TRIM(Data!C95),CHAR(160),"""")), base, VALUE(SUBSTITUTE(REGEXEXTRACT(x,""[0-9.,]+""),"","","""")), mult, IF(REGEXMATCH(x,""B""),1000000000, IF(REGEXMATCH(x,""M""),1000000, 1)), base * mult ), 0 )"),1.799E10) -> 17990000000 | E30: =IFERROR(__xludf.DUMMYFUNCTION("IFERROR( LET( x, UPPER(SUBSTITUTE(TRIM(Data!D95),CHAR(160),"""")), base, VALUE(SUBSTITUTE(REGEXEXTRACT(x,""[0-9.,]+""),"","","""")), mult, IF(REGEXMATCH(x,""B""),1000000000, IF(REGEXMATCH(x,""M""),1000000, 1)), base * mult ), 0 )"),1.827E10) -> 18270000000 | F30: =IFERROR(__xludf.DUMMYFUNCTION("IFERROR( LET( x, UPPER(SUBSTITUTE(TRIM(Data!E95),CHAR(160),"""")), base, VALUE(SUBSTITUTE(REGEXEXTRACT(x,""[0-9.,]+""),"","","""")), mult, IF(REGEXMATCH(x,""B""),1000000000, IF(REGEXMATCH(x,""M""),1000000, 1)), base * mult ), 0 )"),1.916E10) -> 19160000000 | G30: =IFERROR(__xludf.DUMMYFUNCTION("IFERROR( LET( x, UPPER(SUBSTITUTE(TRIM(Data!F95),CHAR(160),"""")), base, VALUE(SUBSTITUTE(REGEXEXTRACT(x,""[0-9.,]+""),"","","""")), mult, IF(REGEXMATCH(x,""B""),1000000000, IF(REGEXMATCH(x,""M""),1000000, 1)), base * mult ), 0 )"),2.191E10) -> 21910000000 | H30: =AVERAGE(C30:G30) -> 19104000000 | I30: =AVERAGE(D30:H30) -> 19286800000 | J30: =AVERAGE(E30:I30) -> 19546160000 | K30: =AVERAGE(F30:J30) -> 19801392000 | L30: =AVERAGE(G30:K30) -> 19929670400
B31: Net Property, Plant & Equipment | C31: =IFERROR(__xludf.DUMMYFUNCTION("IFERROR( LET( x, UPPER(SUBSTITUTE(TRIM(Data!B89),CHAR(160),"""")), base, VALUE(SUBSTITUTE(REGEXEXTRACT(x,""[0-9.,]+""),"","","""")), mult, IF(REGEXMATCH(x,""B""),1000000000, IF(REGEXMATCH(x,""M""),1000000, 1)), base * mult ), 0 )"),2.087E10) -> 20870000000 | D31: =IFERROR(__xludf.DUMMYFUNCTION("IFERROR( LET( x, UPPER(SUBSTITUTE(TRIM(Data!C89),CHAR(160),"""")), base, VALUE(SUBSTITUTE(REGEXEXTRACT(x,""[0-9.,]+""),"","","""")), mult, IF(REGEXMATCH(x,""B""),1000000000, IF(REGEXMATCH(x,""M""),1000000, 1)), base * mult ), 0 )"),2.277E10) -> 22770000000 | E31: =IFERROR(__xludf.DUMMYFUNCTION("IFERROR( LET( x, UPPER(SUBSTITUTE(TRIM(Data!D89),CHAR(160),"""")), base, VALUE(SUBSTITUTE(REGEXEXTRACT(x,""[0-9.,]+""),"","","""")), mult, IF(REGEXMATCH(x,""B""),1000000000, IF(REGEXMATCH(x,""M""),1000000, 1)), base * mult ), 0 )"),2.449E10) -> 24490000000 | F31: =IFERROR(__xludf.DUMMYFUNCTION("IFERROR( LET( x, UPPER(SUBSTITUTE(TRIM(Data!E89),CHAR(160),"""")), base, VALUE(SUBSTITUTE(REGEXEXTRACT(x,""[0-9.,]+""),"","","""")), mult, IF(REGEXMATCH(x,""B""),1000000000, IF(REGEXMATCH(x,""M""),1000000, 1)), base * mult ), 0 )"),2.515E10) -> 25150000000 | G31: =IFERROR(__xludf.DUMMYFUNCTION("IFERROR( LET( x, UPPER(SUBSTITUTE(TRIM(Data!F89),CHAR(160),"""")), base, VALUE(SUBSTITUTE(REGEXEXTRACT(x,""[0-9.,]+""),"","","""")), mult, IF(REGEXMATCH(x,""B""),1000000000, IF(REGEXMATCH(x,""M""),1000000, 1)), base * mult ), 0 )"),2.682E10) -> 26820000000 | H31: =AVERAGE(C31:G31) -> 24020000000 | I31: =AVERAGE(D31:H31) -> 24650000000 | J31: =AVERAGE(E31:I31) -> 25026000000 | K31: =AVERAGE(F31:J31) -> 25133200000 | L31: =AVERAGE(G31:K31) -> 25129840000
B34: Intangible Assets | C34: =IFERROR(__xludf.DUMMYFUNCTION("IFERROR( LET( x, UPPER(SUBSTITUTE(TRIM(Data!B99),CHAR(160),"""")), base, VALUE(SUBSTITUTE(REGEXEXTRACT(x,""[0-9.,]+""),"","","""")), mult, IF(REGEXMATCH(x,""B""),1000000000, IF(REGEXMATCH(x,""M""),1000000, 1)), base * mult ), )"),4.42E10) -> 44200000000 | D34: =IFERROR(__xludf.DUMMYFUNCTION("IFERROR( LET( x, UPPER(SUBSTITUTE(TRIM(Data!C99),CHAR(160),"""")), base, VALUE(SUBSTITUTE(REGEXEXTRACT(x,""[0-9.,]+""),"","","""")), mult, IF(REGEXMATCH(x,""B""),1000000000, IF(REGEXMATCH(x,""M""),1000000, 1)), base * mult ), )"),4.147E10) -> 41470000000 | E34: =IFERROR(__xludf.DUMMYFUNCTION("IFERROR( LET( x, UPPER(SUBSTITUTE(TRIM(Data!D99),CHAR(160),"""")), base, VALUE(SUBSTITUTE(REGEXEXTRACT(x,""[0-9.,]+""),"","","""")), mult, IF(REGEXMATCH(x,""B""),1000000000, IF(REGEXMATCH(x,""M""),1000000, 1)), base * mult ), )"),3.921E10) -> 39210000000 | F34: =IFERROR(__xludf.DUMMYFUNCTION("IFERROR( LET( x, UPPER(SUBSTITUTE(TRIM(Data!E99),CHAR(160),"""")), base, VALUE(SUBSTITUTE(REGEXEXTRACT(x,""[0-9.,]+""),"","","""")), mult, IF(REGEXMATCH(x,""B""),1000000000, IF(REGEXMATCH(x,""M""),1000000, 1)), base * mult ), )"),3.804E10) -> 38040000000 | G34: =IFERROR(__xludf.DUMMYFUNCTION("IFERROR( LET( x, UPPER(SUBSTITUTE(TRIM(Data!B99),CHAR(160),"""")), base, VALUE(SUBSTITUTE(REGEXEXTRACT(x,""[0-9.,]+""),"","","""")), mult, IF(REGEXMATCH(x,""B""),1000000000, IF(REGEXMATCH(x,""M""),1000000, 1)), base * mult ), 0 )"),4.42E10) -> 44200000000 | H34: =FORECAST(H3,$C$34:G34,$C$3:G3) -> 40395000000 | I34: =FORECAST(I3,$C$34:H34,$C$3:H3) -> 40052000000 | J34: =FORECAST(J3,$C$34:I34,$C$3:I3) -> 39709000000 | K34: =FORECAST(K3,$C$34:J34,$C$3:J3) -> 39366000000 | L34: =FORECAST(L3,$C$34:K34,$C$3:K3) -> 39023000000
B35: Other Assets | C35: =IFERROR(__xludf.DUMMYFUNCTION("IFERROR( LET( x, UPPER(SUBSTITUTE(TRIM(Data!B102),CHAR(160),"""")), base, VALUE(SUBSTITUTE(REGEXEXTRACT(x,""[0-9.,]+""),"","","""")), mult, IF(REGEXMATCH(x,""B""),1000000000, IF(REGEXMATCH(x,""M""),1000000, 1)), base * mult ), 0 )"),9.29E9) -> 9290000000 | D35: =IFERROR(__xludf.DUMMYFUNCTION("IFERROR( LET( x, UPPER(SUBSTITUTE(TRIM(Data!C102),CHAR(160),"""")), base, VALUE(SUBSTITUTE(REGEXEXTRACT(x,""[0-9.,]+""),"","","""")), mult, IF(REGEXMATCH(x,""B""),1000000000, IF(REGEXMATCH(x,""M""),1000000, 1)), base * mult ), 0 )"),7.24E9) -> 7240000000 | E35: =IFERROR(__xludf.DUMMYFUNCTION("IFERROR( LET( x, UPPER(SUBSTITUTE(TRIM(Data!D102),CHAR(160),"""")), base, VALUE(SUBSTITUTE(REGEXEXTRACT(x,""[0-9.,]+""),"","","""")), mult, IF(REGEXMATCH(x,""B""),1000000000, IF(REGEXMATCH(x,""M""),1000000, 1)), base * mult ), 0 )"),9.23E9) -> 9230000000 | F35: =IFERROR(__xludf.DUMMYFUNCTION("IFERROR( LET( x, UPPER(SUBSTITUTE(TRIM(Data!E102),CHAR(160),"""")), base, VALUE(SUBSTITUTE(REGEXEXTRACT(x,""[0-9.,]+""),"","","""")), mult, IF(REGEXMATCH(x,""B""),1000000000, IF(REGEXMATCH(x,""M""),1000000, 1)), base * mult ), 0 )"),1.346E10) -> 13460000000 | G35: =IFERROR(__xludf.DUMMYFUNCTION("IFERROR( LET( x, UPPER(SUBSTITUTE(TRIM(Data!F102),CHAR(160),"""")), base, VALUE(SUBSTITUTE(REGEXEXTRACT(x,""[0-9.,]+""),"","","""")), mult, IF(REGEXMATCH(x,""B""),1000000000, IF(REGEXMATCH(x,""M""),1000000, 1)), base * mult ), 0 )"),1.6030000000000002E10) -> 16030000000 | H35: =FORECAST(H3,$C$35:G35,$C$3:G3) -> 16960000000 | I35: =FORECAST(I3,$C$35:H35,$C$3:H3) -> 18930000000 | J35: =FORECAST(J3,$C$35:I35,$C$3:I3) -> 20900000000 | K35: =FORECAST(K3,$C$35:J35,$C$3:J3) -> 22870000000 | L35: =FORECAST(L3,$C$35:K35,$C$3:K3) -> 24840000000
B36: Total Assets | C36: =IFERROR(__xludf.DUMMYFUNCTION("regexreplace(Data!B103,""B"","""")*1000000000"),1.0569E11) -> 105690000000 | D36: =IFERROR(__xludf.DUMMYFUNCTION("regexreplace(Data!C103,""B"","""")*1000000000"),1.0916E11) -> 109160000000 | E36: =IFERROR(__xludf.DUMMYFUNCTION("regexreplace(Data!D103,""B"","""")*1000000000"),1.0668E11) -> 106680000000 | F36: =IFERROR(__xludf.DUMMYFUNCTION("regexreplace(Data!E103,""B"","""")*1000000000"),1.1711E11) -> 117110000000 | G36: =IFERROR(__xludf.DUMMYFUNCTION("regexreplace(Data!F103,""B"","""")*1000000000"),1.3687E11) -> 136870000000 | H36: =G36*(1+H37) -> 146008069762 | I36: =H36*(1+I37) -> 155756239027 | J36: =I36*(1+J37) -> 166155240840 | K36: =J36*(1+K37) -> 177248527770 | L36: =K36*(1+L37) -> 189082453480
B37: Total Assets Growth | C37: - | D37: =Data!C104 -> 0.0328 | E37: =Data!D104 -> -0.0228 | F37: =Data!E104 -> 0.0978 | G37: =Data!F104 -> 0.1687 | H37: =(G36/C36)^(1/4)-1 -> 0.066764592 | I37: =H37 -> 0.066764592 | J37: =I37 -> 0.066764592 | K37: =J37 -> 0.066764592 | L37: =K37 -> 0.066764592
B40: Short Term Debt | C40: =IFERROR(__xludf.DUMMYFUNCTION("IFERROR( LET( x, UPPER(SUBSTITUTE(TRIM(Data!B334),CHAR(160),"""")), base, VALUE(SUBSTITUTE(REGEXEXTRACT(x,""[0-9.,]+""),"","","""")), mult, IF(REGEXMATCH(x,""B""),1000000000, IF(REGEXMATCH(x,""M""),1000000, 1)), base * mult ), 0 )"),2.72E9) -> 2720000000 | D40: =IFERROR(__xludf.DUMMYFUNCTION("IFERROR( LET( x, UPPER(SUBSTITUTE(TRIM(Data!C334),CHAR(160),"""")), base, VALUE(SUBSTITUTE(REGEXEXTRACT(x,""[0-9.,]+""),"","","""")), mult, IF(REGEXMATCH(x,""B""),1000000000, IF(REGEXMATCH(x,""M""),1000000, 1)), base * mult ), 0 )"),2.23E9) -> 2230000000 | E40: =IFERROR(__xludf.DUMMYFUNCTION("IFERROR( LET( x, UPPER(SUBSTITUTE(TRIM(Data!D334),CHAR(160),"""")), base, VALUE(SUBSTITUTE(REGEXEXTRACT(x,""[0-9.,]+""),"","","""")), mult, IF(REGEXMATCH(x,""B""),1000000000, IF(REGEXMATCH(x,""M""),1000000, 1)), base * mult ), 0 )"),1.66E9) -> 1660000000 | F40: =IFERROR(__xludf.DUMMYFUNCTION("IFERROR( LET( x, UPPER(SUBSTITUTE(TRIM(Data!E334),CHAR(160),"""")), base, VALUE(SUBSTITUTE(REGEXEXTRACT(x,""[0-9.,]+""),"","","""")), mult, IF(REGEXMATCH(x,""B""),1000000000, IF(REGEXMATCH(x,""M""),1000000, 1)), base * mult ), 0 )"),2.93E9) -> 2930000000 | G40: =IFERROR(__xludf.DUMMYFUNCTION("IFERROR( LET( x, UPPER(SUBSTITUTE(TRIM(Data!F334),CHAR(160),"""")), base, VALUE(SUBSTITUTE(REGEXEXTRACT(x,""[0-9.,]+""),"","","""")), mult, IF(REGEXMATCH(x,""B""),1000000000, IF(REGEXMATCH(x,""M""),1000000, 1)), base * mult ), 0 )"),2.88E9) -> 2880000000 | H40: =FORECAST(H3,$C$40:G40,$C$3:G3) -> 2790000000 | I40: =FORECAST(I3,$C$40:H40,$C$3:H3) -> 2892000000 | J40: =FORECAST(J3,$C$40:I40,$C$3:I3) -> 2994000000 | K40: =FORECAST(K3,$C$40:J40,$C$3:J3) -> 3096000000 | L40: =FORECAST(L3,$C$40:K40,$C$3:K3) -> 3198000000
B41: Current Portion of Long Term Debt | C41: =IFERROR(__xludf.DUMMYFUNCTION("IFERROR( LET( x, UPPER(SUBSTITUTE(TRIM(Data!B335),CHAR(160),"""")), base, VALUE(SUBSTITUTE(REGEXEXTRACT(x,""[0-9.,]+""),"","","""")), mult, IF(REGEXMATCH(x,""B""),1000000000, IF(REGEXMATCH(x,""M""),1000000, 1)), base * mult ), 0 )"),0.0) -> 0 | D41: =IFERROR(__xludf.DUMMYFUNCTION("IFERROR( LET( x, UPPER(SUBSTITUTE(TRIM(Data!C335),CHAR(160),"""")), base, VALUE(SUBSTITUTE(REGEXEXTRACT(x,""[0-9.,]+""),"","","""")), mult, IF(REGEXMATCH(x,""B""),1000000000, IF(REGEXMATCH(x,""M""),1000000, 1)), base * mult ), 0 )"),0.0) -> 0 | E41: =IFERROR(__xludf.DUMMYFUNCTION("IFERROR( LET( x, UPPER(SUBSTITUTE(TRIM(Data!D335),CHAR(160),"""")), base, VALUE(SUBSTITUTE(REGEXEXTRACT(x,""[0-9.,]+""),"","","""")), mult, IF(REGEXMATCH(x,""B""),1000000000, IF(REGEXMATCH(x,""M""),1000000, 1)), base * mult ), 0 )"),0.0) -> 0 | F41: =IFERROR(__xludf.DUMMYFUNCTION("IFERROR( LET( x, UPPER(SUBSTITUTE(TRIM(Data!E335),CHAR(160),"""")), base, VALUE(SUBSTITUTE(REGEXEXTRACT(x,""[0-9.,]+""),"","","""")), mult, IF(REGEXMATCH(x,""B""),1000000000, IF(REGEXMATCH(x,""M""),1000000, 1)), base * mult ), 0 )"),0.0) -> 0 | G41: =IFERROR(__xludf.DUMMYFUNCTION("IFERROR( LET( x, UPPER(SUBSTITUTE(TRIM(Data!F335),CHAR(160),"""")), base, VALUE(SUBSTITUTE(REGEXEXTRACT(x,""[0-9.,]+""),"","","""")), mult, IF(REGEXMATCH(x,""B""),1000000000, IF(REGEXMATCH(x,""M""),1000000, 1)), base * mult ), 0 )"),0.0) -> 0 | H41: =AVERAGE(C41:G41) -> 0 | I41: =AVERAGE(D41:H41) -> 0 | J41: =AVERAGE(E41:I41) -> 0 | K41: =AVERAGE(F41:J41) -> 0 | L41: =AVERAGE(G41:K41) -> 0
B42: ST Debt & Current Portion LT Debt | C42: =IFERROR(__xludf.DUMMYFUNCTION("IFERROR( LET( x, UPPER(SUBSTITUTE(TRIM(Data!B333),CHAR(160),"""")), base, VALUE(SUBSTITUTE(REGEXEXTRACT(x,""[0-9.,]+""),"","","""")), mult, IF(REGEXMATCH(x,""B""),1000000000, IF(REGEXMATCH(x,""M""),1000000, 1)), base * mult ), 0 )"),2.72E9) -> 2720000000 | D42: =IFERROR(__xludf.DUMMYFUNCTION("IFERROR( LET( x, UPPER(SUBSTITUTE(TRIM(Data!C333),CHAR(160),"""")), base, VALUE(SUBSTITUTE(REGEXEXTRACT(x,""[0-9.,]+""),"","","""")), mult, IF(REGEXMATCH(x,""B""),1000000000, IF(REGEXMATCH(x,""M""),1000000, 1)), base * mult ), 0 )"),2.23E9) -> 2230000000 | E42: =IFERROR(__xludf.DUMMYFUNCTION("IFERROR( LET( x, UPPER(SUBSTITUTE(TRIM(Data!D333),CHAR(160),"""")), base, VALUE(SUBSTITUTE(REGEXEXTRACT(x,""[0-9.,]+""),"","","""")), mult, IF(REGEXMATCH(x,""B""),1000000000, IF(REGEXMATCH(x,""M""),1000000, 1)), base * mult ), 0 )"),1.66E9) -> 1660000000 | F42: =IFERROR(__xludf.DUMMYFUNCTION("IFERROR( LET( x, UPPER(SUBSTITUTE(TRIM(Data!E333),CHAR(160),"""")), base, VALUE(SUBSTITUTE(REGEXEXTRACT(x,""[0-9.,]+""),"","","""")), mult, IF(REGEXMATCH(x,""B""),1000000000, IF(REGEXMATCH(x,""M""),1000000, 1)), base * mult ), 0 )"),2.93E9) -> 2930000000 | G42: =IFERROR(__xludf.DUMMYFUNCTION("IFERROR( LET( x, UPPER(SUBSTITUTE(TRIM(Data!F333),CHAR(160),"""")), base, VALUE(SUBSTITUTE(REGEXEXTRACT(x,""[0-9.,]+""),"","","""")), mult, IF(REGEXMATCH(x,""B""),1000000000, IF(REGEXMATCH(x,""M""),1000000, 1)), base * mult ), 0 )"),2.88E9) -> 2880000000 | H42: =FORECAST(H3,$C$42:G42,$C$3:G3) -> 2790000000 | I42: =FORECAST(I3,$C$42:H42,$C$3:H3) -> 2892000000 | J42: =FORECAST(J3,$C$42:I42,$C$3:I3) -> 2994000000 | K42: =FORECAST(K3,$C$42:J42,$C$3:J3) -> 3096000000 | L42: =FORECAST(L3,$C$42:K42,$C$3:K3) -> 3198000000

Sheet Cash Flow
B2: Balance Sheet | C2: FY | H2: Future FY
C3: 2020 | D3: 2021 | E3: 2022 | F3: 2023 | G3: 2024 | H3: 2025 | I3: 2026 | J3: 2027 | K3: 2028 | L3: 2029
B6: Net Income before Extraordinaries | C6: =IFERROR(__xludf.DUMMYFUNCTION("IFERROR( LET( x, UPPER(SUBSTITUTE(TRIM(Data!B112),CHAR(160),"""")), base, VALUE(SUBSTITUTE(REGEXEXTRACT(x,""[0-9.,]+""),"","","""")), mult, IF(REGEXMATCH(x,""B""),1000000000, IF(REGEXMATCH(x,""M""),1000000, 1)), base * mult ), 0 ) "),1.236E10) -> 12360000000 | D6: =IFERROR(__xludf.DUMMYFUNCTION("IFERROR( LET( x, UPPER(SUBSTITUTE(TRIM(Data!C112),CHAR(160),"""")), base, VALUE(SUBSTITUTE(REGEXEXTRACT(x,""[0-9.,]+""),"","","""")), mult, IF(REGEXMATCH(x,""B""),1000000000, IF(REGEXMATCH(x,""M""),1000000, 1)), base * mult ), )"),1.453E10) -> 14530000000 | E6: =IFERROR(__xludf.DUMMYFUNCTION("IFERROR( LET( x, UPPER(SUBSTITUTE(TRIM(Data!D112),CHAR(160),"""")), base, VALUE(SUBSTITUTE(REGEXEXTRACT(x,""[0-9.,]+""),"","","""")), mult, IF(REGEXMATCH(x,""B""),1000000000, IF(REGEXMATCH(x,""M""),1000000, 1)), base * mult ), )"),3.77E8) -> 377000000 | F6: =IFERROR(__xludf.DUMMYFUNCTION("IFERROR( LET( x, UPPER(SUBSTITUTE(TRIM(Data!E112),CHAR(160),"""")), base, VALUE(SUBSTITUTE(REGEXEXTRACT(x,""[0-9.,]+""),"","","""")), mult, IF(REGEXMATCH(x,""B""),1000000000, IF(REGEXMATCH(x,""M""),1000000, 1)), base * mult ), )"),1.7129999999999998E10) -> 17130000000 | G6: =IFERROR(__xludf.DUMMYFUNCTION("IFERROR( LET( x, UPPER(SUBSTITUTE(TRIM(Data!F112),CHAR(160),"""")), base, VALUE(SUBSTITUTE(REGEXEXTRACT(x,""[0-9.,]+""),"","","""")), mult, IF(REGEXMATCH(x,""B""),1000000000, IF(REGEXMATCH(x,""M""),1000000, 1)), base * mult ), )"),1.826E10) -> 18260000000 | H6: =FORECAST(H3,$C$6:G6,$C$3:G3) -> 16851400000 | I6: =FORECAST(I3,$C$6:H6,$C$3:H3) -> 18291400000 | J6: =FORECAST(J3,$C$6:I6,$C$3:I3) -> 19731400000 | K6: =FORECAST(K3,$C$6:J6,$C$3:J3) -> 21171400000 | L6: =FORECAST(L3,$C$6:K6,$C$3:K3) -> 22611400000
B7: Net Income Growth | C7: =Data!B113 -> - | D7: =Data!C113 -> 0.1754 | E7: =Data!D113 -> -0.974 | F7: =Data!E113 -> 44.4456 | G7: =Data!F113 -> 0.066 | H7: =H6/G6-1 -> -0.077141292 | I7: =I6/H6-1 -> 0.085452841 | J7: =J6/I6-1 -> 0.078725521 | K7: =K6/J6-1 -> 0.072980123 | L7: =L6/K6-1 -> 0.068016286
B10: Depreciation, Depletion & Amortization | C10: =IFERROR(__xludf.DUMMYFUNCTION("IFERROR( LET( x, UPPER(SUBSTITUTE(TRIM(Data!B114),CHAR(160),"""")), base, VALUE(SUBSTITUTE(REGEXEXTRACT(x,""[0-9.,]+""),"","","""")), mult, IF(REGEXMATCH(x,""B""),1000000000, IF(REGEXMATCH(x,""M""),1000000, 1)), base * mult ), 0 ) "),3.21E9) -> 3210000000 | D10: =IFERROR(__xludf.DUMMYFUNCTION("IFERROR( LET( x, UPPER(SUBSTITUTE(TRIM(Data!C114),CHAR(160),"""")), base, VALUE(SUBSTITUTE(REGEXEXTRACT(x,""[0-9.,]+""),"","","""")), mult, IF(REGEXMATCH(x,""B""),1000000000, IF(REGEXMATCH(x,""M""),1000000, 1)), base * mult ), 0 ) "),3.91E9) -> 3910000000 | E10: =IFERROR(__xludf.DUMMYFUNCTION("IFERROR( LET( x, UPPER(SUBSTITUTE(TRIM(Data!D114),CHAR(160),"""")), base, VALUE(SUBSTITUTE(REGEXEXTRACT(x,""[0-9.,]+""),"","","""")), mult, IF(REGEXMATCH(x,""B""),1000000000, IF(REGEXMATCH(x,""M""),1000000, 1)), base * mult ), 0 ) "),3.87E9) -> 3870000000 | F10: =IFERROR(__xludf.DUMMYFUNCTION("IFERROR( LET( x, UPPER(SUBSTITUTE(TRIM(Data!E114),CHAR(160),"""")), base, VALUE(SUBSTITUTE(REGEXEXTRACT(x,""[0-9.,]+""),"","","""")), mult, IF(REGEXMATCH(x,""B""),1000000000, IF(REGEXMATCH(x,""M""),1000000, 1)), base * mult ), 0 ) "),4.5E9) -> 4500000000 | G10: =IFERROR(__xludf.DUMMYFUNCTION("IFERROR( LET( x, UPPER(SUBSTITUTE(TRIM(Data!F114),CHAR(160),"""")), base, VALUE(SUBSTITUTE(REGEXEXTRACT(x,""[0-9.,]+""),"","","""")), mult, IF(REGEXMATCH(x,""B""),1000000000, IF(REGEXMATCH(x,""M""),1000000, 1)), base * mult ), 0 ) "),5.84E9) -> 5840000000 | H10: =FORECAST(H3,$C$10:G10,$C$3:G3) -> 6021000000 | I10: =FORECAST(I3,$C$10:H10,$C$3:H3) -> 6606000000 | J10: =FORECAST(J3,$C$10:I10,$C$3:I3) -> 7191000000 | K10: =FORECAST(K3,$C$10:J10,$C$3:J3) -> 7776000000 | L10: =FORECAST(L3,$C$10:K10,$C$3:K3) -> 8361000000
B13: Net Operating Cash Flow | C13: =IFERROR(__xludf.DUMMYFUNCTION("IFERROR( LET( x, UPPER(SUBSTITUTE(TRIM(Data!B127),CHAR(160),"""")), base, VALUE(SUBSTITUTE(REGEXEXTRACT(x,""[0-9.,]+""),"","","""")), mult, IF(REGEXMATCH(x,""B""),1000000000, IF(REGEXMATCH(x,""M""),1000000, 1)), base * mult ), 0 ) "),1.411E10) -> 14110000000 | D13: =IFERROR(__xludf.DUMMYFUNCTION("IFERROR( LET( x, UPPER(SUBSTITUTE(TRIM(Data!C127),CHAR(160),"""")), base, VALUE(SUBSTITUTE(REGEXEXTRACT(x,""[0-9.,]+""),"","","""")), mult, IF(REGEXMATCH(x,""B""),1000000000, IF(REGEXMATCH(x,""M""),1000000, 1)), base * mult ), 0 ) "),1.91E10) -> 19100000000 | E13: =IFERROR(__xludf.DUMMYFUNCTION("IFERROR( LET( x, UPPER(SUBSTITUTE(TRIM(Data!D127),CHAR(160),"""")), base, VALUE(SUBSTITUTE(REGEXEXTRACT(x,""[0-9.,]+""),"","","""")), mult, IF(REGEXMATCH(x,""B""),1000000000, IF(REGEXMATCH(x,""M""),1000000, 1)), base * mult ), 0 ) "),1.301E10) -> 13010000000 | F13: =IFERROR(__xludf.DUMMYFUNCTION("IFERROR( LET( x, UPPER(SUBSTITUTE(TRIM(Data!E127),CHAR(160),"""")), base, VALUE(SUBSTITUTE(REGEXEXTRACT(x,""[0-9.,]+""),"","","""")), mult, IF(REGEXMATCH(x,""B""),1000000000, IF(REGEXMATCH(x,""M""),1000000, 1)), base * mult ), 0 ) "),2.147E10) -> 21470000000 | G13: =IFERROR(__xludf.DUMMYFUNCTION("IFERROR( LET( x, UPPER(SUBSTITUTE(TRIM(Data!F127),CHAR(160),"""")), base, VALUE(SUBSTITUTE(REGEXEXTRACT(x,""[0-9.,]+""),"","","""")), mult, IF(REGEXMATCH(x,""B""),1000000000, IF(REGEXMATCH(x,""M""),1000000, 1)), base * mult ), 0 ) "),1.6469999999999998E10) -> 16470000000 | H13: =FORECAST(H3,$C$13:G13,$C$3:G3) -> 18959000000 | I13: =FORECAST(I3,$C$13:H13,$C$3:H3) -> 19668000000 | J13: =FORECAST(J3,$C$13:I13,$C$3:I3) -> 20377000000 | K13: =FORECAST(K3,$C$13:J13,$C$3:J3) -> 21086000000 | L13: =FORECAST(L3,$C$13:K13,$C$3:K3) -> 21795000000
B14: Net Operating Cash Flow Growth | C14: =Data!B128 -> - | D14: =Data!C128 -> 0.3534 | E14: =Data!D128 -> -0.3189 | F14: =Data!E128 -> 0.6506 | G14: =Data!F128 -> -0.2327 | H14: =H13/G13-1 -> 0.15112325 | I14: =I13/H13-1 -> 0.037396487 | J14: =J13/I13-1 -> 0.036048403 | K14: =K13/J13-1 -> 0.034794131 | L14: =L13/K13-1 -> 0.033624206
B17: Net Change in Cash | C17: =IFERROR(__xludf.DUMMYFUNCTION("IFERROR( LET( x, UPPER(SUBSTITUTE(TRIM(Data!B153),CHAR(160),"""")), base, VALUE(SUBSTITUTE(REGEXEXTRACT(x,""[0-9.,]+""),"","","""")), mult, IF(REGEXMATCH(x,""B""),1000000000, IF(REGEXMATCH(x,""M""),1000000, 1)), base * mult ), 0 ) "),1.4E7) -> 14000000 | D17: =IFERROR(__xludf.DUMMYFUNCTION("IFERROR( LET( x, UPPER(SUBSTITUTE(TRIM(Data!C153),CHAR(160),"""")), base, VALUE(SUBSTITUTE(REGEXEXTRACT(x,""[0-9.,]+""),"","","""")), mult, IF(REGEXMATCH(x,""B""),1000000000, IF(REGEXMATCH(x,""M""),1000000, 1)), base * mult ), 0 ) "),4.61E9) -> 4610000000 | E17: =IFERROR(__xludf.DUMMYFUNCTION("IFERROR( LET( x, UPPER(SUBSTITUTE(TRIM(Data!D153),CHAR(160),"""")), base, VALUE(SUBSTITUTE(REGEXEXTRACT(x,""[0-9.,]+""),"","","""")), mult, IF(REGEXMATCH(x,""B""),1000000000, IF(REGEXMATCH(x,""M""),1000000, 1)), base * mult ), 0 ) "),5.86E9) -> 5860000000 | F17: =IFERROR(__xludf.DUMMYFUNCTION("IFERROR( LET( x, UPPER(SUBSTITUTE(TRIM(Data!E153),CHAR(160),"""")), base, VALUE(SUBSTITUTE(REGEXEXTRACT(x,""[0-9.,]+""),"","","""")), mult, IF(REGEXMATCH(x,""B""),1000000000, IF(REGEXMATCH(x,""M""),1000000, 1)), base * mult ), 0 ) "),6.41E9) -> 6410000000 | G17: =IFERROR(__xludf.DUMMYFUNCTION("IFERROR( LET( x, UPPER(SUBSTITUTE(TRIM(Data!F153),CHAR(160),"""")), base, VALUE(SUBSTITUTE(REGEXEXTRACT(x,""[0-9.,]+""),"","","""")), mult, IF(REGEXMATCH(x,""B""),1000000000, IF(REGEXMATCH(x,""M""),1000000, 1)), base * mult ), 0 ) "),1.37E9) -> 1370000000 | H17: =AVERAGEIF(C17:G17,">0.5") -> 3652800000 | I17: =AVERAGEIF(D17:H17,">0.5") -> 4380560000 | J17: =AVERAGEIF(E17:I17,">0.5") -> 4334672000 | K17: =AVERAGEIF(F17:J17,">0.5") -> 4029606400 | L17: =AVERAGEIF(G17:K17,">0.5") -> 3553527680
B18: Free Cash Flow | C18: =IFERROR(__xludf.DUMMYFUNCTION("IFERROR( LET( x, UPPER(SUBSTITUTE(TRIM(Data!B154),CHAR(160),"""")), base, VALUE(SUBSTITUTE(REGEXEXTRACT(x,""[0-9.,]+""),"","","""")), mult, IF(REGEXMATCH(x,""B""),1000000000, IF(REGEXMATCH(x,""M""),1000000, 1)), base * mult ), 0 ) "),9.66E9) -> 9660000000 | D18: =IFERROR(__xludf.DUMMYFUNCTION("IFERROR( LET( x, UPPER(SUBSTITUTE(TRIM(Data!C154),CHAR(160),"""")), base, VALUE(SUBSTITUTE(REGEXEXTRACT(x,""[0-9.,]+""),"","","""")), mult, IF(REGEXMATCH(x,""B""),1000000000, IF(REGEXMATCH(x,""M""),1000000, 1)), base * mult ), 0 ) "),1.471E10) -> 14710000000 | E18: =IFERROR(__xludf.DUMMYFUNCTION("IFERROR( LET( x, UPPER(SUBSTITUTE(TRIM(Data!D154),CHAR(160),"""")), base, VALUE(SUBSTITUTE(REGEXEXTRACT(x,""[0-9.,]+""),"","","""")), mult, IF(REGEXMATCH(x,""B""),1000000000, IF(REGEXMATCH(x,""M""),1000000, 1)), base * mult ), 0 ) "),9.14E9) -> 9140000000 | F18: =IFERROR(__xludf.DUMMYFUNCTION("IFERROR( LET( x, UPPER(SUBSTITUTE(TRIM(Data!E154),CHAR(160),"""")), base, VALUE(SUBSTITUTE(REGEXEXTRACT(x,""[0-9.,]+""),"","","""")), mult, IF(REGEXMATCH(x,""B""),1000000000, IF(REGEXMATCH(x,""M""),1000000, 1)), base * mult ), 0 ) "),1.81E10) -> 18100000000 | G18: =IFERROR(__xludf.DUMMYFUNCTION("IFERROR( LET( x, UPPER(SUBSTITUTE(TRIM(Data!F154),CHAR(160),"""")), base, VALUE(SUBSTITUTE(REGEXEXTRACT(x,""[0-9.,]+""),"","","""")), mult, IF(REGEXMATCH(x,""B""),1000000000, IF(REGEXMATCH(x,""M""),1000000, 1)), base * mult ), 0 ) "),1.236E10) -> 12360000000 | H18: =G18*(1+H19) -> 13145551376 | I18: =H18*(1+I19) -> 13586662664 | J18: =I18*(1+J19) -> 13634975975 | K18: =J18*(1+K19) -> 13274411805 | L18: =K18*(1+L19) -> 12525150063
B19: Free Cash Flow Growth | C19: =Data!B155 -> - | D19: =Data!C155 -> 0.5223 | E19: =Data!D155 -> -0.3783 | F19: =Data!E155 -> 0.9792 | G19: =Data!F155 -> -0.317 | H19: =(G18/C18)^(1/4)-1 -> 0.063555937 | I19: =H19-3% -> 0.033555937 | J19: =I19-3% -> 0.0035559366 | K19: =J19-3% -> -0.026444063 | L19: =K19-3% -> -0.056444063

Sheet DCF
G2: TradingView Revenue Estimates
B4: Discounted Cash Flow | C4: FY | H4: Future FY
C5: 2020 | D5: 2021 | E5: 2022 | F5: 2023 | G5: 2024 | H5: 2025 | I5: 2026 | J5: 2027 | K5: 2028
B8: Revenue | C8: ='Income Statement'!C15 -> 48910000000 | D8: ='Income Statement'!D15 -> 58470000000 | E8: ='Income Statement'!E15 -> 59870000000 | F8: ='Income Statement'!F15 -> 63970000000 | G8: ='Income Statement'!G15 -> 64930000000 | H8: 66680000000 | I8: 70170000000 | J8: 74750000000 | K8: 74520000000
B9: % growth | C9: - | D9: =D8/C8-1 -> 0.19546105 | E9: =E8/D8-1 -> 0.023943903 | F9: =F8/E8-1 -> 0.06848171 | G9: =G8/F8-1 -> 0.015007035 | H9: =H8/G8-1 -> 0.026952102 | I9: =I8/H8-1 -> 0.052339532 | J9: =J8/I8-1 -> 0.065270058 | K9: =K8/J8-1 -> -0.0030769231
B12: EBIT | C12: =IFERROR(__xludf.DUMMYFUNCTION("IFERROR( LET( x, UPPER(SUBSTITUTE(TRIM(Data!B22),CHAR(160),"""")), neg, IF(LEFT(x,1)=""("", -1, 1), numtext, REGEXEXTRACT(x,""[0-9.,]+""), base, VALUE(SUBSTITUTE(numtext,"","","""")), mult, IF(REGEXMATCH(x,""B""),1000000000, IF(REGEX"&"MATCH(x,""M""),1000000, 1)), neg * base * mult ), 0 ) "),1.246E10) -> 12460000000 | D12: =IFERROR(__xludf.DUMMYFUNCTION("IFERROR( LET( x, UPPER(SUBSTITUTE(TRIM(Data!C22),CHAR(160),"""")), neg, IF(LEFT(x,1)=""("", -1, 1), numtext, REGEXEXTRACT(x,""[0-9.,]+""), base, VALUE(SUBSTITUTE(numtext,"","","""")), mult, IF(REGEXMATCH(x,""B""),1000000000, IF(REGEX"&"MATCH(x,""M""),1000000, 1)), neg * base * mult ), 0 ) "),1.723E10) -> 17230000000 | E12: =IFERROR(__xludf.DUMMYFUNCTION("IFERROR( LET( x, UPPER(SUBSTITUTE(TRIM(Data!D22),CHAR(160),"""")), neg, IF(LEFT(x,1)=""("", -1, 1), numtext, REGEXEXTRACT(x,""[0-9.,]+""), base, VALUE(SUBSTITUTE(numtext,"","","""")), mult, IF(REGEXMATCH(x,""B""),1000000000, IF(REGEX"&"MATCH(x,""M""),1000000, 1)), neg * base * mult ), 0 ) "),1.95E9) -> 1950000000 | F12: =IFERROR(__xludf.DUMMYFUNCTION("IFERROR( LET( x, UPPER(SUBSTITUTE(TRIM(Data!E22),CHAR(160),"""")), neg, IF(LEFT(x,1)=""("", -1, 1), numtext, REGEXEXTRACT(x,""[0-9.,]+""), base, VALUE(SUBSTITUTE(numtext,"","","""")), mult, IF(REGEXMATCH(x,""B""),1000000000, IF(REGEX"&"MATCH(x,""M""),1000000, 1)), neg * base * mult ), 0 ) "),1.947E10) -> 19470000000 | G12: =IFERROR(__xludf.DUMMYFUNCTION("IFERROR( LET( x, UPPER(SUBSTITUTE(TRIM(Data!F22),CHAR(160),"""")), neg, IF(LEFT(x,1)=""("", -1, 1), numtext, REGEXEXTRACT(x,""[0-9.,]+""), base, VALUE(SUBSTITUTE(numtext,"","","""")), mult, IF(REGEXMATCH(x,""B""),1000000000, IF(REGEX"&"MATCH(x,""M""),1000000, 1)), neg * base * mult ), 0 ) "),2.178E10) -> 21780000000 | H12: =H8*H13 -> 14944547271 | I12: =I8*I13 -> 15726737882 | J12: =J8*J13 -> 16753222983 | K12: =K8*K13 -> 16701674604
B13: % of sales | C13: =C12/C8 -> 0.25475363 | D13: =D12/D8 -> 0.29468103 | E13: =E12/E8 -> 0.03257057 | F13: =F12/F8 -> 0.30436142 | G13: =G12/G8 -> 0.33543816 | H13: =AVERAGEIF(E13:G13,">0.01") -> 0.22412338 | I13: =H13 -> 0.22412338 | J13: =I13 -> 0.22412338 | K13: =J13 -> 0.22412338
B16: Taxes | C16: =IFERROR(__xludf.DUMMYFUNCTION("IFERROR( LET( x, UPPER(SUBSTITUTE(TRIM(Data!B33),CHAR(160),"""")), neg, IF(LEFT(x,1)=""("", -1, 1), numtext, REGEXEXTRACT(x,""[0-9.,]+""), base, VALUE(SUBSTITUTE(numtext,"","","""")), mult, IF(REGEXMATCH(x,""B""),1000000000, IF(REGEX"&"MATCH(x,""M""),1000000, 1)), neg * base * mult ), 0 ) "),1.52E9) -> 1520000000 | D16: =IFERROR(__xludf.DUMMYFUNCTION("IFERROR( LET( x, UPPER(SUBSTITUTE(TRIM(Data!C33),CHAR(160),"""")), neg, IF(LEFT(x,1)=""("", -1, 1), numtext, REGEXEXTRACT(x,""[0-9.,]+""), base, VALUE(SUBSTITUTE(numtext,"","","""")), mult, IF(REGEXMATCH(x,""B""),1000000000, IF(REGEX"&"MATCH(x,""M""),1000000, 1)), neg * base * mult ), 0 ) "),1.92E9) -> 1920000000 | E16: =IFERROR(__xludf.DUMMYFUNCTION("IFERROR( LET( x, UPPER(SUBSTITUTE(TRIM(Data!D33),CHAR(160),"""")), neg, IF(LEFT(x,1)=""("", -1, 1), numtext, REGEXEXTRACT(x,""[0-9.,]+""), base, VALUE(SUBSTITUTE(numtext,"","","""")), mult, IF(REGEXMATCH(x,""B""),1000000000, IF(REGEX"&"MATCH(x,""M""),1000000, 1)), neg * base * mult ), 0 ) "),1.51E9) -> 1510000000 | F16: =IFERROR(__xludf.DUMMYFUNCTION("IFERROR( LET( x, UPPER(SUBSTITUTE(TRIM(Data!E33),CHAR(160),"""")), neg, IF(LEFT(x,1)=""("", -1, 1), numtext, REGEXEXTRACT(x,""[0-9.,]+""), base, VALUE(SUBSTITUTE(numtext,"","","""")), mult, IF(REGEXMATCH(x,""B""),1000000000, IF(REGEX"&"MATCH(x,""M""),1000000, 1)), neg * base * mult ), 0 ) "),2.8E9) -> 2800000000 | G16: =IFERROR(__xludf.DUMMYFUNCTION("IFERROR( LET( x, UPPER(SUBSTITUTE(TRIM(Data!F33),CHAR(160),"""")), neg, IF(LEFT(x,1)=""("", -1, 1), numtext, REGEXEXTRACT(x,""[0-9.,]+""), base, VALUE(SUBSTITUTE(numtext,"","","""")), mult, IF(REGEXMATCH(x,""B""),1000000000, IF(REGEX"&"MATCH(x,""M""),1000000, 1)), neg * base * mult ), 0 ) "),2.8E9) -> 2800000000 | H16: =H17*H12 -> 5214293400 | I16: =I17*I12 -> 5487207077 | J16: =J17*J12 -> 5845357403 | K16: =K17*K12 -> 5827371688
B17: % of EBIT | C17: =C16/C12 -> 0.12199037 | D17: =D16/D12 -> 0.11143355 | E17: =E16/E12 -> 0.77435897 | F17: =F16/F12 -> 0.14381099 | G17: =G16/G12 -> 0.12855831 | H17: =AVERAGEIF(E17:G17,">0.01") -> 0.34890943 | I17: =H17 -> 0.34890943 | J17: =I17 -> 0.34890943 | K17: =J17 -> 0.34890943
B20: EBIAT | C20: - | D20: - | E20: - | F20: - | G20: - | H20: =H12-H16 -> 9730253871 | I20: =I12-I16 -> 10239530805 | J20: =J12-J16 -> 10907865579 | K20: =K12-K16 -> 10874302916
B23: D&A | C23: =IFERROR(__xludf.DUMMYFUNCTION("IFERROR( LET( x, UPPER(SUBSTITUTE(TRIM(Data!B114),CHAR(160),"""")), neg, IF(LEFT(x,1)=""("", -1, 1), numtext, REGEXEXTRACT(x,""[0-9.,]+""), base, VALUE(SUBSTITUTE(numtext,"","","""")), mult, IF(REGEXMATCH(x,""B""),1000000000, IF(REGE"&"XMATCH(x,""M""),1000000, 1)), neg * base * mult ), 0 ) "),3.21E9) -> 3210000000 | D23: =IFERROR(__xludf.DUMMYFUNCTION("IFERROR( LET( x, UPPER(SUBSTITUTE(TRIM(Data!C114),CHAR(160),"""")), neg, IF(LEFT(x,1)=""("", -1, 1), numtext, REGEXEXTRACT(x,""[0-9.,]+""), base, VALUE(SUBSTITUTE(numtext,"","","""")), mult, IF(REGEXMATCH(x,""B""),1000000000, IF(REGE"&"XMATCH(x,""M""),1000000, 1)), neg * base * mult ), 0 ) "),3.91E9) -> 3910000000 | E23: =IFERROR(__xludf.DUMMYFUNCTION("IFERROR( LET( x, UPPER(SUBSTITUTE(TRIM(Data!D114),CHAR(160),"""")), neg, IF(LEFT(x,1)=""("", -1, 1), numtext, REGEXEXTRACT(x,""[0-9.,]+""), base, VALUE(SUBSTITUTE(numtext,"","","""")), mult, IF(REGEXMATCH(x,""B""),1000000000, IF(REGE"&"XMATCH(x,""M""),1000000, 1)), neg * base * mult ), 0 ) "),3.87E9) -> 3870000000 | F23: =IFERROR(__xludf.DUMMYFUNCTION("IFERROR( LET( x, UPPER(SUBSTITUTE(TRIM(Data!E114),CHAR(160),"""")), neg, IF(LEFT(x,1)=""("", -1, 1), numtext, REGEXEXTRACT(x,""[0-9.,]+""), base, VALUE(SUBSTITUTE(numtext,"","","""")), mult, IF(REGEXMATCH(x,""B""),1000000000, IF(REGE"&"XMATCH(x,""M""),1000000, 1)), neg * base * mult ), 0 ) "),4.5E9) -> 4500000000 | G23: =IFERROR(__xludf.DUMMYFUNCTION("IFERROR( LET( x, UPPER(SUBSTITUTE(TRIM(Data!F114),CHAR(160),"""")), neg, IF(LEFT(x,1)=""("", -1, 1), numtext, REGEXEXTRACT(x,""[0-9.,]+""), base, VALUE(SUBSTITUTE(numtext,"","","""")), mult, IF(REGEXMATCH(x,""B""),1000000000, IF(REGE"&"XMATCH(x,""M""),1000000, 1)), neg * base * mult ), 0 ) "),5.84E9) -> 5840000000 | H23: =H8*H24 -> 4999411759 | I23: =I8*I24 -> 5261078631 | J23: =J8*J24 -> 5604469541 | K23: =K8*K24 -> 5587225019
B24: % of sales | C24: =C23/C8 -> 0.06563075 | D24: =D23/D8 -> 0.0668719 | E24: =E23/E8 -> 0.064640053 | F24: =F23/F8 -> 0.070345474 | G24: =G23/G8 -> 0.089943016 | H24: =AVERAGE(E24:G24) -> 0.074976181 | I24: =H24 -> 0.074976181 | J24: =I24 -> 0.074976181 | K24: =J24 -> 0.074976181
B27: CapEx | C27: =IFERROR(__xludf.DUMMYFUNCTION("IFERROR( LET( x, UPPER(SUBSTITUTE(TRIM(Data!B380),CHAR(160),"""")), neg, IF(LEFT(x,1)=""("", -1, 1), numtext, REGEXEXTRACT(x,""[0-9.,]+""), base, VALUE(SUBSTITUTE(numtext,"","","""")), mult, IF(REGEXMATCH(x,""B""),1000000000, IF(REGE"&"XMATCH(x,""M""),1000000, 1)), neg * base * mult ), 0 ) "),-4.45E9) -> -4450000000 | D27: =IFERROR(__xludf.DUMMYFUNCTION("IFERROR( LET( x, UPPER(SUBSTITUTE(TRIM(Data!C380),CHAR(160),"""")), neg, IF(LEFT(x,1)=""("", -1, 1), numtext, REGEXEXTRACT(x,""[0-9.,]+""), base, VALUE(SUBSTITUTE(numtext,"","","""")), mult, IF(REGEXMATCH(x,""B""),1000000000, IF(REGE"&"XMATCH(x,""M""),1000000, 1)), neg * base * mult ), 0 ) "),-4.39E9) -> -4390000000 | E27: =IFERROR(__xludf.DUMMYFUNCTION("IFERROR( LET( x, UPPER(SUBSTITUTE(TRIM(Data!D380),CHAR(160),"""")), neg, IF(LEFT(x,1)=""("", -1, 1), numtext, REGEXEXTRACT(x,""[0-9.,]+""), base, VALUE(SUBSTITUTE(numtext,"","","""")), mult, IF(REGEXMATCH(x,""B""),1000000000, IF(REGE"&"XMATCH(x,""M""),1000000, 1)), neg * base * mult ), 0 ) "),-3.86E9) -> -3860000000 | F27: =IFERROR(__xludf.DUMMYFUNCTION("IFERROR( LET( x, UPPER(SUBSTITUTE(TRIM(Data!E380),CHAR(160),"""")), neg, IF(LEFT(x,1)=""("", -1, 1), numtext, REGEXEXTRACT(x,""[0-9.,]+""), base, VALUE(SUBSTITUTE(numtext,"","","""")), mult, IF(REGEXMATCH(x,""B""),1000000000, IF(REGE"&"XMATCH(x,""M""),1000000, 1)), neg * base * mult ), 0 ) "),-3.37E9) -> -3370000000 | G27: =IFERROR(__xludf.DUMMYFUNCTION("IFERROR( LET( x, UPPER(SUBSTITUTE(TRIM(Data!F380),CHAR(160),"""")), neg, IF(LEFT(x,1)=""("", -1, 1), numtext, REGEXEXTRACT(x,""[0-9.,]+""), base, VALUE(SUBSTITUTE(numtext,"","","""")), mult, IF(REGEXMATCH(x,""B""),1000000000, IF(REGE"&"XMATCH(x,""M""),1000000, 1)), neg * base * mult ), 0 ) "),-4.1100000000000005E9) -> -4110000000 | H27: =H28*H8 -> -4010866600 | I27: =I28*I8 -> -4220793481 | J27: =J28*J8 -> -4496284918 | K27: =K28*K8 -> -4482450195
B28: % of sales | C28: =C27/C8 -> -0.090983439 | D28: =D27/D8 -> -0.075081238 | E28: =E27/E8 -> -0.064473025 | F28: =F27/F8 -> -0.052680944 | G28: =G27/G8 -> -0.063298937 | H28: =AVERAGE(E28:G28) -> -0.060150969 | I28: =H28 -> -0.060150969 | J28: =I28 -> -0.060150969 | K28: =J28 -> -0.060150969
B31: Changes in NWC | C31: =IFERROR(__xludf.DUMMYFUNCTION("IFERROR( LET( x, UPPER(SUBSTITUTE(TRIM(Data!B123),CHAR(160),"""")), neg, IF(LEFT(x,1)=""("", -1, 1), numtext, REGEXEXTRACT(x,""[0-9.,]+""), base, VALUE(SUBSTITUTE(numtext,"","","""")), mult, IF(REGEXMATCH(x,""B""),1000000000, IF(REGE"&"XMATCH(x,""M""),1000000, 1)), neg * base * mult ), 0 ) "),-3.84E9) -> -3840000000 | D31: =IFERROR(__xludf.DUMMYFUNCTION("IFERROR( LET( x, UPPER(SUBSTITUTE(TRIM(Data!C123),CHAR(160),"""")), neg, IF(LEFT(x,1)=""("", -1, 1), numtext, REGEXEXTRACT(x,""[0-9.,]+""), base, VALUE(SUBSTITUTE(numtext,"","","""")), mult, IF(REGEXMATCH(x,""B""),1000000000, IF(REGE"&"XMATCH(x,""M""),1000000, 1)), neg * base * mult ), 0 ) "),-2.78E9) -> -2780000000 | E31: =IFERROR(__xludf.DUMMYFUNCTION("IFERROR( LET( x, UPPER(SUBSTITUTE(TRIM(Data!D123),CHAR(160),"""")), neg, IF(LEFT(x,1)=""("", -1, 1), numtext, REGEXEXTRACT(x,""[0-9.,]+""), base, VALUE(SUBSTITUTE(numtext,"","","""")), mult, IF(REGEXMATCH(x,""B""),1000000000, IF(REGE"&"XMATCH(x,""M""),1000000, 1)), neg * base * mult ), 0 ) "),-2.21E9) -> -2210000000 | F31: =IFERROR(__xludf.DUMMYFUNCTION("IFERROR( LET( x, UPPER(SUBSTITUTE(TRIM(Data!E123),CHAR(160),"""")), neg, IF(LEFT(x,1)=""("", -1, 1), numtext, REGEXEXTRACT(x,""[0-9.,]+""), base, VALUE(SUBSTITUTE(numtext,"","","""")), mult, IF(REGEXMATCH(x,""B""),1000000000, IF(REGE"&"XMATCH(x,""M""),1000000, 1)), neg * base * mult ), 0 ) "),-3.67E9) -> -3670000000 | G31: =IFERROR(__xludf.DUMMYFUNCTION("IFERROR( LET( x, UPPER(SUBSTITUTE(TRIM(Data!F123),CHAR(160),"""")), neg, IF(LEFT(x,1)=""("", -1, 1), numtext, REGEXEXTRACT(x,""[0-9.,]+""), base, VALUE(SUBSTITUTE(numtext,"","","""")), mult, IF(REGEXMATCH(x,""B""),1000000000, IF(REGE"&"XMATCH(x,""M""),1000000, 1)), neg * base * mult ), 0 ) "),-6.98E9) -> -6980000000 | H31: =H32*H8 -> -4484993257 | I31: =I32*I8 -> -4719735705 | J31: =J32*J8 -> -5027793131 | K31: =K32*K8 -> -5012322998
B32: % of sales | C32: =C31/C8 -> -0.078511552 | D32: =D31/D8 -> -0.04754575 | E32: =E31/E8 -> -0.036913312 | F32: =F31/F8 -> -0.057370642 | G32: =G31/G8 -> -0.10750039 | H32: =AVERAGE(E32:G32) -> -0.067261447 | I32: =H32 -> -0.067261447 | J32: =I32 -> -0.067261447 | K32: =J32 -> -0.067261447
B35: Unlevered Free Cash Flow | C35: =C20 -> - | D35: =D20 -> - | E35: =E20 -> - | F35: =F20 -> - | G35: =G20 -> - | H35: =H20+H23-H27-H31 -> 23225525486 | I35: =I20+I23-I27-I31 -> 24441138623 | J35: =J20+J23-J27-J31 -> 26036413169 | K35: =K20+K23-K27-K31 -> 25956301128
B38: Discount Rate
B39: Discount Period | C39: - | D39: - | E39: - | F39: - | G39: -
B40: Discount Factor | C40: - | D40: - | E40: - | F40: - | G40: -
B43: Present Value of FCF | C43: - | D43: - | E43: - | F43: - | G43: - | H43: =H35/(1+$C$66)^1 -> 21670561742 | I43: =I35/(1+$C$66)^2 -> 21277993649 | J43: =J35/(1+$C$66)^3 -> 21149252183 | K43: =K35/(1+$C$66)^4 -> 19672578426
B46: Weighted Average Cost of Capital
B49: Equity Value | C49: =IFERROR(__xludf.DUMMYFUNCTION("GOOGLEFINANCE('Income Statement'!D1,""marketcap"")"),3.09641841663E11) -> 309641841663
B50: % Equity | C50: =C49/C63 -> 0.86663563
B51: Cost of Equity | C51: =C52+(C53*C54) -> 0.0789822
B52: Risk Free Rate | C52: =Data!A399 -> 0.04469
B53: Beta | C53: =Data!C315 -> 0.62
B54: Market Risk Premium | C54: =10%-C52 -> 0.05531
B57: Debt | C57: =IFERROR(__xludf.DUMMYFUNCTION("IFERROR( LET( x, UPPER(SUBSTITUTE(TRIM(Data!F344),CHAR(160),"""")), neg, IF(LEFT(x,1)=""("", -1, 1), numtext, REGEXEXTRACT(x,""[0-9.,]+""), base, VALUE(SUBSTITUTE(numtext,"","","""")), mult, IF(REGEXMATCH(x,""B""),1000000000, IF(REGE"&"XMATCH(x,""M""),1000000, 1)), neg * base * mult ), 0 ) "),4.765E10) -> 47650000000
B58: % Debt | C58: =C57/C63 -> 0.13336437
B59: Cost of Debt | C59: =IFERROR(__xludf.DUMMYFUNCTION("((IFERROR( LET( x, UPPER(SUBSTITUTE(TRIM(Data!F26),CHAR(160),"""")), neg, IF(LEFT(x,1)=""("", -1, 1), numtext, REGEXEXTRACT(x,""[0-9.,]+""), base, VALUE(SUBSTITUTE(numtext,"","","""")), mult, IF(REGEXMATCH(x,""B""),1000000000, IF(REG"&"EXMATCH(x,""M""),1000000, 1)), neg * base * mult ), 0 ))/C57)*(1-C60)"),0.02478824763903463) -> 0.024788248
B60: Tax Rate | C60: =Data!D320 -> 0.1315
B63: Debt+Equity | C63: =C57+C49 -> 357291841663
B66: Weighted Average Cost of Capital | C66: =(C50*C51)+(C58*C59) -> 0.071754658
B68: Terminal Value Calculation
B71: Terminal Growth Rate | C71: 0.02
B72: Terminal Value | C72: =(K35*(1+C71))/(C66-C71) -> 511556413055
B73: Present Value of Terminal Value | C73: =C72/((1+C66)^4) -> 387714474618
B74: Enterprise Value | C74: =SUM(H43,C73) -> 409385036360
B77: Implied Value per Share
B78: Enterprise Value | C78: =C74 -> 409385036360
B79: Cash + Short Term Investments | C79: =IFERROR(__xludf.DUMMYFUNCTION("IFERROR( LET( x, UPPER(SUBSTITUTE(TRIM(Data!F69),CHAR(160),"""")), neg, IF(LEFT(x,1)=""("", -1, 1), numtext, REGEXEXTRACT(x,""[0-9.,]+""), base, VALUE(SUBSTITUTE(numtext,"","","""")), mult, IF(REGEXMATCH(x,""B""),1000000000, IF(REGEX"&"MATCH(x,""M""),1000000, 1)), neg * base * mult ), 0 ) "),1.469E10) -> 14690000000
B80: Debt | C80: =C57 -> 47650000000
B81: Equity Value | C81: =C78+C79-C80 -> 376425036360
B84: Diluted Shares | C84: =IFERROR(__xludf.DUMMYFUNCTION("IFERROR( LET( x, UPPER(SUBSTITUTE(TRIM(Data!F58),CHAR(160),"""")), neg, IF(LEFT(x,1)=""("", -1, 1), numtext, REGEXEXTRACT(x,""[0-9.,]+""), base, VALUE(SUBSTITUTE(numtext,"","","""")), mult, IF(REGEXMATCH(x,""B""),1000000000, IF(REGEX"&"MATCH(x,""M""),1000000, 1)), neg * base * mult ), 0 ) "),2.51E9) -> 2510000000
B85: Implied Value per Share | C85: =C81/C84 -> 149.97013

Sheet Data
A4: =IFERROR(__xludf.DUMMYFUNCTION("IMPORTHTML(CONCAT(CONCAT(""https://www.marketwatch.com/investing/stock/"",'Income Statement'!D1),""/financials?mod=mw_quote_tab""),""table"",4) "),"Item Item") -> Item Item | B4: =IFERROR(__xludf.DUMMYFUNCTION("""COMPUTED_VALUE"""),2021.0) -> 2021 | C4: =IFERROR(__xludf.DUMMYFUNCTION("""COMPUTED_VALUE"""),2022.0) -> 2022 | D4: =IFERROR(__xludf.DUMMYFUNCTION("""COMPUTED_VALUE"""),2023.0) -> 2023 | E4: =IFERROR(__xludf.DUMMYFUNCTION("""COMPUTED_VALUE"""),2024.0) -> 2024 | F4: =IFERROR(__xludf.DUMMYFUNCTION("""COMPUTED_VALUE"""),2025.0) -> 2025 | G4: =IFERROR(__xludf.DUMMYFUNCTION("""COMPUTED_VALUE"""),"5-year trend") -> 5-year trend
A5: =IFERROR(__xludf.DUMMYFUNCTION("""COMPUTED_VALUE"""),"Sales/Revenue Sales/Revenue") -> Sales/Revenue Sales/Revenue | B5: =IFERROR(__xludf.DUMMYFUNCTION("""COMPUTED_VALUE"""),"48.91B") -> 48.91B | C5: =IFERROR(__xludf.DUMMYFUNCTION("""COMPUTED_VALUE"""),"58.47B") -> 58.47B | D5: =IFERROR(__xludf.DUMMYFUNCTION("""COMPUTED_VALUE"""),"59.87B") -> 59.87B | E5: =IFERROR(__xludf.DUMMYFUNCTION("""COMPUTED_VALUE"""),"63.97B") -> 63.97B | F5: =IFERROR(__xludf.DUMMYFUNCTION("""COMPUTED_VALUE"""),"64.93B") -> 64.93B
A6: =IFERROR(__xludf.DUMMYFUNCTION("""COMPUTED_VALUE"""),"Sales Growth Sales Growth") -> Sales Growth Sales Growth | B6: =IFERROR(__xludf.DUMMYFUNCTION("""COMPUTED_VALUE"""),"-") -> - | C6: =IFERROR(__xludf.DUMMYFUNCTION("""COMPUTED_VALUE"""),0.1956) -> 0.1956 | D6: =IFERROR(__xludf.DUMMYFUNCTION("""COMPUTED_VALUE"""),0.0239) -> 0.0239 | E6: =IFERROR(__xludf.DUMMYFUNCTION("""COMPUTED_VALUE"""),0.0685) -> 0.0685 | F6: =IFERROR(__xludf.DUMMYFUNCTION("""COMPUTED_VALUE"""),0.0149) -> 0.0149
A7: =IFERROR(__xludf.DUMMYFUNCTION("""COMPUTED_VALUE"""),"Cost of Goods Sold (COGS) incl. D&A Cost of Goods Sold (COGS) incl. D&A") -> Cost of Goods Sold (COGS) incl. D&A Cost of Goods Sold (COGS) incl. D&A | B7: =IFERROR(__xludf.DUMMYFUNCTION("""COMPUTED_VALUE"""),"13.47B") -> 13.47B | C7: =IFERROR(__xludf.DUMMYFUNCTION("""COMPUTED_VALUE"""),"17.21B") -> 17.21B | D7: =IFERROR(__xludf.DUMMYFUNCTION("""COMPUTED_VALUE"""),"15.98B") -> 15.98B | E7: =IFERROR(__xludf.DUMMYFUNCTION("""COMPUTED_VALUE"""),"16.8B") -> 16.8B | F7: =IFERROR(__xludf.DUMMYFUNCTION("""COMPUTED_VALUE"""),"18.2B") -> 18.2B
A8: =IFERROR(__xludf.DUMMYFUNCTION("""COMPUTED_VALUE"""),"COGS Growth COGS Growth") -> COGS Growth COGS Growth | B8: =IFERROR(__xludf.DUMMYFUNCTION("""COMPUTED_VALUE"""),"-") -> - | C8: =IFERROR(__xludf.DUMMYFUNCTION("""COMPUTED_VALUE"""),0.2777) -> 0.2777 | D8: =IFERROR(__xludf.DUMMYFUNCTION("""COMPUTED_VALUE"""),-0.0714) -> -0.0714 | E8: =IFERROR(__xludf.DUMMYFUNCTION("""COMPUTED_VALUE"""),0.0516) -> 0.0516 | F8: =IFERROR(__xludf.DUMMYFUNCTION("""COMPUTED_VALUE"""),0.0829) -> 0.0829
A9: =IFERROR(__xludf.DUMMYFUNCTION("""COMPUTED_VALUE"""),"COGS excluding D&A COGS excluding D&A") -> COGS excluding D&A COGS excluding D&A | B9: =IFERROR(__xludf.DUMMYFUNCTION("""COMPUTED_VALUE"""),"10.25B") -> 10.25B | C9: =IFERROR(__xludf.DUMMYFUNCTION("""COMPUTED_VALUE"""),"13.3B") -> 13.3B | D9: =IFERROR(__xludf.DUMMYFUNCTION("""COMPUTED_VALUE"""),"12.11B") -> 12.11B | E9: =IFERROR(__xludf.DUMMYFUNCTION("""COMPUTED_VALUE"""),"12.3B") -> 12.3B | F9: =IFERROR(__xludf.DUMMYFUNCTION("""COMPUTED_VALUE"""),"12.36B") -> 12.36B
A10: =IFERROR(__xludf.DUMMYFUNCTION("""COMPUTED_VALUE"""),"Depreciation & Amortization Expense Depreciation & Amortization Expense") -> Depreciation & Amortization Expense Depreciation & Amortization Expense | B10: =IFERROR(__xludf.DUMMYFUNCTION("""COMPUTED_VALUE"""),"3.21B") -> 3.21B | C10: =IFERROR(__xludf.DUMMYFUNCTION("""COMPUTED_VALUE"""),"3.91B") -> 3.91B | D10: =IFERROR(__xludf.DUMMYFUNCTION("""COMPUTED_VALUE"""),"3.87B") -> 3.87B | E10: =IFERROR(__xludf.DUMMYFUNCTION("""COMPUTED_VALUE"""),"4.5B") -> 4.5B | F10: =IFERROR(__xludf.DUMMYFUNCTION("""COMPUTED_VALUE"""),"5.84B") -> 5.84B
A11: =IFERROR(__xludf.DUMMYFUNCTION("""COMPUTED_VALUE"""),"Depreciation Depreciation") -> Depreciation Depreciation | B11: =IFERROR(__xludf.DUMMYFUNCTION("""COMPUTED_VALUE"""),"1.58B") -> 1.58B | C11: =IFERROR(__xludf.DUMMYFUNCTION("""COMPUTED_VALUE"""),"1.82B") -> 1.82B | D11: =IFERROR(__xludf.DUMMYFUNCTION("""COMPUTED_VALUE"""),"1.83B") -> 1.83B | E11: =IFERROR(__xludf.DUMMYFUNCTION("""COMPUTED_VALUE"""),"2.1B") -> 2.1B | F11: =IFERROR(__xludf.DUMMYFUNCTION("""COMPUTED_VALUE"""),"3.05B") -> 3.05B
A12: =IFERROR(__xludf.DUMMYFUNCTION("""COMPUTED_VALUE"""),"Amortization of Intangibles Amortization of Intangibles") -> Amortization of Intangibles Amortization of Intangibles | B12: =IFERROR(__xludf.DUMMYFUNCTION("""COMPUTED_VALUE"""),"1.64B") -> 1.64B | C12: =IFERROR(__xludf.DUMMYFUNCTION("""COMPUTED_VALUE"""),"2.09B") -> 2.09B | D12: =IFERROR(__xludf.DUMMYFUNCTION("""COMPUTED_VALUE"""),"2.04B") -> 2.04B | E12: =IFERROR(__xludf.DUMMYFUNCTION("""COMPUTED_VALUE"""),"2.4B") -> 2.4B | F12: =IFERROR(__xludf.DUMMYFUNCTION("""COMPUTED_VALUE"""),"2.79B") -> 2.79B
A13: =IFERROR(__xludf.DUMMYFUNCTION("""COMPUTED_VALUE"""),"Gross Income Gross Income") -> Gross Income Gross Income | B13: =IFERROR(__xludf.DUMMYFUNCTION("""COMPUTED_VALUE"""),"35.44B") -> 35.44B | C13: =IFERROR(__xludf.DUMMYFUNCTION("""COMPUTED_VALUE"""),"41.27B") -> 41.27B | D13: =IFERROR(__xludf.DUMMYFUNCTION("""COMPUTED_VALUE"""),"43.89B") -> 43.89B | E13: =IFERROR(__xludf.DUMMYFUNCTION("""COMPUTED_VALUE"""),"47.17B") -> 47.17B | F13: =IFERROR(__xludf.DUMMYFUNCTION("""COMPUTED_VALUE"""),"46.73B") -> 46.73B
A14: =IFERROR(__xludf.DUMMYFUNCTION("""COMPUTED_VALUE"""),"Gross Income Growth Gross Income Growth") -> Gross Income Growth Gross Income Growth | B14: =IFERROR(__xludf.DUMMYFUNCTION("""COMPUTED_VALUE"""),"-") -> - | C14: =IFERROR(__xludf.DUMMYFUNCTION("""COMPUTED_VALUE"""),0.1644) -> 0.1644 | D14: =IFERROR(__xludf.DUMMYFUNCTION("""COMPUTED_VALUE"""),0.0637) -> 0.0637 | E14: =IFERROR(__xludf.DUMMYFUNCTION("""COMPUTED_VALUE"""),0.0747) -> 0.0747 | F14: =IFERROR(__xludf.DUMMYFUNCTION("""COMPUTED_VALUE"""),-0.0093) -> -0.0093
A15: =IFERROR(__xludf.DUMMYFUNCTION("""COMPUTED_VALUE"""),"Gross Profit Margin Gross Profit Margin") -> Gross Profit Margin Gross Profit Margin | B15: =IFERROR(__xludf.DUMMYFUNCTION("""COMPUTED_VALUE"""),"-") -> - | C15: =IFERROR(__xludf.DUMMYFUNCTION("""COMPUTED_VALUE"""),"-") -> - | D15: =IFERROR(__xludf.DUMMYFUNCTION("""COMPUTED_VALUE"""),"-") -> - | E15: =IFERROR(__xludf.DUMMYFUNCTION("""COMPUTED_VALUE"""),"-") -> - | F15: =IFERROR(__xludf.DUMMYFUNCTION("""COMPUTED_VALUE"""),0.7198) -> 0.7198
A16: =IFERROR(__xludf.DUMMYFUNCTION("""COMPUTED_VALUE"""),"SG&A Expense SG&A Expense") -> SG&A Expense SG&A Expense | B16: =IFERROR(__xludf.DUMMYFUNCTION("""COMPUTED_VALUE"""),"19.82B") -> 19.82B | C16: =IFERROR(__xludf.DUMMYFUNCTION("""COMPUTED_VALUE"""),"21.77B") -> 21.77B | D16: =IFERROR(__xludf.DUMMYFUNCTION("""COMPUTED_VALUE"""),"40.91B") -> 40.91B | E16: =IFERROR(__xludf.DUMMYFUNCTION("""COMPUTED_VALUE"""),"26.53B") -> 26.53B | F16: =IFERROR(__xludf.DUMMYFUNCTION("""COMPUTED_VALUE"""),"23.25B") -> 23.25B
A17: =IFERROR(__xludf.DUMMYFUNCTION("""COMPUTED_VALUE"""),"SGA Growth SGA Growth") -> SGA Growth SGA Growth | B17: =IFERROR(__xludf.DUMMYFUNCTION("""COMPUTED_VALUE"""),"-") -> - | C17: =IFERROR(__xludf.DUMMYFUNCTION("""COMPUTED_VALUE"""),0.0981) -> 0.0981 | D17: =IFERROR(__xludf.DUMMYFUNCTION("""COMPUTED_VALUE"""),0.8796) -> 0.8796 | E17: =IFERROR(__xludf.DUMMYFUNCTION("""COMPUTED_VALUE"""),-0.3516) -> -0.3516 | F17: =IFERROR(__xludf.DUMMYFUNCTION("""COMPUTED_VALUE"""),-0.1237) -> -0.1237
A18: =IFERROR(__xludf.DUMMYFUNCTION("""COMPUTED_VALUE"""),"Research & Development Research & Development") -> Research & Development Research & Development | B18: =IFERROR(__xludf.DUMMYFUNCTION("""COMPUTED_VALUE"""),"10.21B") -> 10.21B | C18: =IFERROR(__xludf.DUMMYFUNCTION("""COMPUTED_VALUE"""),"11.82B") -> 11.82B | D18: =IFERROR(__xludf.DUMMYFUNCTION("""COMPUTED_VALUE"""),"30.53B") -> 30.53B | E18: =IFERROR(__xludf.DUMMYFUNCTION("""COMPUTED_VALUE"""),"15.79B") -> 15.79B | F18: =IFERROR(__xludf.DUMMYFUNCTION("""COMPUTED_VALUE"""),"12.51B") -> 12.51B
A19: =IFERROR(__xludf.DUMMYFUNCTION("""COMPUTED_VALUE"""),"Other SG&A Other SG&A") -> Other SG&A Other SG&A | B19: =IFERROR(__xludf.DUMMYFUNCTION("""COMPUTED_VALUE"""),"9.62B") -> 9.62B | C19: =IFERROR(__xludf.DUMMYFUNCTION("""COMPUTED_VALUE"""),"9.95B") -> 9.95B | D19: =IFERROR(__xludf.DUMMYFUNCTION("""COMPUTED_VALUE"""),"10.38B") -> 10.38B | E19: =IFERROR(__xludf.DUMMYFUNCTION("""COMPUTED_VALUE"""),"10.73B") -> 10.73B | F19: =IFERROR(__xludf.DUMMYFUNCTION("""COMPUTED_VALUE"""),"10.73B") -> 10.73B
A20: =IFERROR(__xludf.DUMMYFUNCTION("""COMPUTED_VALUE"""),"Other Operating Expense Other Operating Expense") -> Other Operating Expense Other Operating Expense | B20: =IFERROR(__xludf.DUMMYFUNCTION("""COMPUTED_VALUE"""),"-") -> - | C20: =IFERROR(__xludf.DUMMYFUNCTION("""COMPUTED_VALUE"""),"-") -> - | D20: =IFERROR(__xludf.DUMMYFUNCTION("""COMPUTED_VALUE"""),"-") -> - | E20: =IFERROR(__xludf.DUMMYFUNCTION("""COMPUTED_VALUE"""),"-") -> - | F20: =IFERROR(__xludf.DUMMYFUNCTION("""COMPUTED_VALUE"""),"-") -> -
A21: =IFERROR(__xludf.DUMMYFUNCTION("""COMPUTED_VALUE"""),"Unusual Expense Unusual Expense") -> Unusual Expense Unusual Expense | B21: =IFERROR(__xludf.DUMMYFUNCTION("""COMPUTED_VALUE"""),"3.16B") -> 3.16B | C21: =IFERROR(__xludf.DUMMYFUNCTION("""COMPUTED_VALUE"""),"2.27B") -> 2.27B | D21: =IFERROR(__xludf.DUMMYFUNCTION("""COMPUTED_VALUE"""),"1.03B") -> 1.03B | E21: =IFERROR(__xludf.DUMMYFUNCTION("""COMPUTED_VALUE"""),"1.18B") -> 1.18B | F21: =IFERROR(__xludf.DUMMYFUNCTION("""COMPUTED_VALUE"""),"1.7B") -> 1.7B
A22: =IFERROR(__xludf.DUMMYFUNCTION("""COMPUTED_VALUE"""),"EBIT after Unusual Expense EBIT after Unusual Expense") -> EBIT after Unusual Expense EBIT after Unusual Expense | B22: =IFERROR(__xludf.DUMMYFUNCTION("""COMPUTED_VALUE"""),"12.46B") -> 12.46B | C22: =IFERROR(__xludf.DUMMYFUNCTION("""COMPUTED_VALUE"""),"17.23B") -> 17.23B | D22: =IFERROR(__xludf.DUMMYFUNCTION("""COMPUTED_VALUE"""),"1.95B") -> 1.95B | E22: =IFERROR(__xludf.DUMMYFUNCTION("""COMPUTED_VALUE"""),"19.47B") -> 19.47B | F22: =IFERROR(__xludf.DUMMYFUNCTION("""COMPUTED_VALUE"""),"21.78B") -> 21.78B
A23: =IFERROR(__xludf.DUMMYFUNCTION("""COMPUTED_VALUE"""),"Non Operating Income/Expense Non Operating Income/Expense") -> Non Operating Income/Expense Non Operating Income/Expense | B23: =IFERROR(__xludf.DUMMYFUNCTION("""COMPUTED_VALUE"""),"249M") -> 249M | C23: =IFERROR(__xludf.DUMMYFUNCTION("""COMPUTED_VALUE"""),"1.44B") -> 1.44B | D23: =IFERROR(__xludf.DUMMYFUNCTION("""COMPUTED_VALUE"""),"823.5M") -> 823.5M | E23: =IFERROR(__xludf.DUMMYFUNCTION("""COMPUTED_VALUE"""),"1.36B") -> 1.36B | F23: =IFERROR(__xludf.DUMMYFUNCTION("""COMPUTED_VALUE"""),"354M") -> 354M
A24: =IFERROR(__xludf.DUMMYFUNCTION("""COMPUTED_VALUE"""),"Non-Operating Interest Income Non-Operating Interest Income") -> Non-Operating Interest Income Non-Operating Interest Income | B24: =IFERROR(__xludf.DUMMYFUNCTION("""COMPUTED_VALUE"""),"36M") -> 36M | C24: =IFERROR(__xludf.DUMMYFUNCTION("""COMPUTED_VALUE"""),"157M") -> 157M | D24: =IFERROR(__xludf.DUMMYFUNCTION("""COMPUTED_VALUE"""),"365M") -> 365M | E24: =IFERROR(__xludf.DUMMYFUNCTION("""COMPUTED_VALUE"""),"415M") -> 415M | F24: =IFERROR(__xludf.DUMMYFUNCTION("""COMPUTED_VALUE"""),"343M") -> 343M
A25: =IFERROR(__xludf.DUMMYFUNCTION("""COMPUTED_VALUE"""),"Equity in Affiliates (Pretax) Equity in Affiliates (Pretax)") -> Equity in Affiliates (Pretax) Equity in Affiliates (Pretax) | B25: =IFERROR(__xludf.DUMMYFUNCTION("""COMPUTED_VALUE"""),"1.94B") -> 1.94B | C25: =IFERROR(__xludf.DUMMYFUNCTION("""COMPUTED_VALUE"""),"(1.42B)") -> (1.42B) | D25: =IFERROR(__xludf.DUMMYFUNCTION("""COMPUTED_VALUE"""),"(106M)") -> (106M) | E25: =IFERROR(__xludf.DUMMYFUNCTION("""COMPUTED_VALUE"""),"(29M)") -> (29M) | F25: =IFERROR(__xludf.DUMMYFUNCTION("""COMPUTED_VALUE"""),"(55M)") -> (55M)
A26: =IFERROR(__xludf.DUMMYFUNCTION("""COMPUTED_VALUE"""),"Interest Expense Interest Expense") -> Interest Expense Interest Expense | B26: =IFERROR(__xludf.DUMMYFUNCTION("""COMPUTED_VALUE"""),"806M") -> 806M | C26: =IFERROR(__xludf.DUMMYFUNCTION("""COMPUTED_VALUE"""),"962M") -> 962M | D26: =IFERROR(__xludf.DUMMYFUNCTION("""COMPUTED_VALUE"""),"1.15B") -> 1.15B | E26: =IFERROR(__xludf.DUMMYFUNCTION("""COMPUTED_VALUE"""),"1.27B") -> 1.27B | F26: =IFERROR(__xludf.DUMMYFUNCTION("""COMPUTED_VALUE"""),"1.36B") -> 1.36B
A27: =IFERROR(__xludf.DUMMYFUNCTION("""COMPUTED_VALUE"""),"Interest Expense Growth Interest Expense Growth") -> Interest Expense Growth Interest Expense Growth | B27: =IFERROR(__xludf.DUMMYFUNCTION("""COMPUTED_VALUE"""),"-") -> - | C27: =IFERROR(__xludf.DUMMYFUNCTION("""COMPUTED_VALUE"""),0.1935) -> 0.1935 | D27: =IFERROR(__xludf.DUMMYFUNCTION("""COMPUTED_VALUE"""),0.1913) -> 0.1913 | E27: =IFERROR(__xludf.DUMMYFUNCTION("""COMPUTED_VALUE"""),0.1091) -> 0.1091 | F27: =IFERROR(__xludf.DUMMYFUNCTION("""COMPUTED_VALUE"""),0.0677) -> 0.0677
A28: =IFERROR(__xludf.DUMMYFUNCTION("""COMPUTED_VALUE"""),"Gross Interest Expense Gross Interest Expense") -> Gross Interest Expense Gross Interest Expense | B28: =IFERROR(__xludf.DUMMYFUNCTION("""COMPUTED_VALUE"""),"806M") -> 806M | C28: =IFERROR(__xludf.DUMMYFUNCTION("""COMPUTED_VALUE"""),"962M") -> 962M | D28: =IFERROR(__xludf.DUMMYFUNCTION("""COMPUTED_VALUE"""),"1.15B") -> 1.15B | E28: =IFERROR(__xludf.DUMMYFUNCTION("""COMPUTED_VALUE"""),"1.27B") -> 1.27B | F28: =IFERROR(__xludf.DUMMYFUNCTION("""COMPUTED_VALUE"""),"1.36B") -> 1.36B
A29: =IFERROR(__xludf.DUMMYFUNCTION("""COMPUTED_VALUE"""),"Interest Capitalized Interest Capitalized") -> Interest Capitalized Interest Capitalized | B29: =IFERROR(__xludf.DUMMYFUNCTION("""COMPUTED_VALUE"""),"-") -> - | C29: =IFERROR(__xludf.DUMMYFUNCTION("""COMPUTED_VALUE"""),"-") -> - | D29: =IFERROR(__xludf.DUMMYFUNCTION("""COMPUTED_VALUE"""),"-") -> - | E29: =IFERROR(__xludf.DUMMYFUNCTION("""COMPUTED_VALUE"""),"-") -> - | F29: =IFERROR(__xludf.DUMMYFUNCTION("""COMPUTED_VALUE"""),"-") -> -
A30: =IFERROR(__xludf.DUMMYFUNCTION("""COMPUTED_VALUE"""),"Pretax Income Pretax Income") -> Pretax Income Pretax Income | B30: =IFERROR(__xludf.DUMMYFUNCTION("""COMPUTED_VALUE"""),"13.88B") -> 13.88B | C30: =IFERROR(__xludf.DUMMYFUNCTION("""COMPUTED_VALUE"""),"16.44B") -> 16.44B | D30: =IFERROR(__xludf.DUMMYFUNCTION("""COMPUTED_VALUE"""),"1.89B") -> 1.89B | E30: =IFERROR(__xludf.DUMMYFUNCTION("""COMPUTED_VALUE"""),"19.94B") -> 19.94B | F30: =IFERROR(__xludf.DUMMYFUNCTION("""COMPUTED_VALUE"""),"21.07B") -> 21.07B
A31: =IFERROR(__xludf.DUMMYFUNCTION("""COMPUTED_VALUE"""),"Pretax Income Growth Pretax Income Growth") -> Pretax Income Growth Pretax Income Growth | B31: =IFERROR(__xludf.DUMMYFUNCTION("""COMPUTED_VALUE"""),"-") -> - | C31: =IFERROR(__xludf.DUMMYFUNCTION("""COMPUTED_VALUE"""),0.1848) -> 0.1848 | D31: =IFERROR(__xludf.DUMMYFUNCTION("""COMPUTED_VALUE"""),-0.8851) -> -0.8851 | E31: =IFERROR(__xludf.DUMMYFUNCTION("""COMPUTED_VALUE"""),9.5537) -> 9.5537 | F31: =IFERROR(__xludf.DUMMYFUNCTION("""COMPUTED_VALUE"""),0.0567) -> 0.0567
A32: =IFERROR(__xludf.DUMMYFUNCTION("""COMPUTED_VALUE"""),"Pretax Margin Pretax Margin") -> Pretax Margin Pretax Margin | B32: =IFERROR(__xludf.DUMMYFUNCTION("""COMPUTED_VALUE"""),"-") -> - | C32: =IFERROR(__xludf.DUMMYFUNCTION("""COMPUTED_VALUE"""),"-") -> - | D32: =IFERROR(__xludf.DUMMYFUNCTION("""COMPUTED_VALUE"""),"-") -> - | E32: =IFERROR(__xludf.DUMMYFUNCTION("""COMPUTED_VALUE"""),"-") -> - | F32: =IFERROR(__xludf.DUMMYFUNCTION("""COMPUTED_VALUE"""),0.3245) -> 0.3245
A33: =IFERROR(__xludf.DUMMYFUNCTION("""COMPUTED_VALUE"""),"Income Tax Income Tax") -> Income Tax Income Tax | B33: =IFERROR(__xludf.DUMMYFUNCTION("""COMPUTED_VALUE"""),"1.52B") -> 1.52B | C33: =IFERROR(__xludf.DUMMYFUNCTION("""COMPUTED_VALUE"""),"1.92B") -> 1.92B | D33: =IFERROR(__xludf.DUMMYFUNCTION("""COMPUTED_VALUE"""),"1.51B") -> 1.51B | E33: =IFERROR(__xludf.DUMMYFUNCTION("""COMPUTED_VALUE"""),"2.8B") -> 2.8B | F33: =IFERROR(__xludf.DUMMYFUNCTION("""COMPUTED_VALUE"""),"2.8B") -> 2.8B
A34: =IFERROR(__xludf.DUMMYFUNCTION("""COMPUTED_VALUE"""),"Income Tax - Current Domestic Income Tax - Current Domestic") -> Income Tax - Current Domestic Income Tax - Current Domestic | B34: =IFERROR(__xludf.DUMMYFUNCTION("""COMPUTED_VALUE"""),"61M") -> 61M | C34: =IFERROR(__xludf.DUMMYFUNCTION("""COMPUTED_VALUE"""),"2.32B") -> 2.32B | D34: =IFERROR(__xludf.DUMMYFUNCTION("""COMPUTED_VALUE"""),"976M") -> 976M | E34: =IFERROR(__xludf.DUMMYFUNCTION("""COMPUTED_VALUE"""),"929M") -> 929M | F34: =IFERROR(__xludf.DUMMYFUNCTION("""COMPUTED_VALUE"""),"403M") -> 403M
A35: =IFERROR(__xludf.DUMMYFUNCTION("""COMPUTED_VALUE"""),"Income Tax - Current Foreign Income Tax - Current Foreign") -> Income Tax - Current Foreign Income Tax - Current Foreign | B35: =IFERROR(__xludf.DUMMYFUNCTION("""COMPUTED_VALUE"""),"1.27B") -> 1.27B | C35: =IFERROR(__xludf.DUMMYFUNCTION("""COMPUTED_VALUE"""),"1.16B") -> 1.16B | D35: =IFERROR(__xludf.DUMMYFUNCTION("""COMPUTED_VALUE"""),"2.44B") -> 2.44B | E35: =IFERROR(__xludf.DUMMYFUNCTION("""COMPUTED_VALUE"""),"3.12B") -> 3.12B | F35: =IFERROR(__xludf.DUMMYFUNCTION("""COMPUTED_VALUE"""),"4.07B") -> 4.07B
A36: =IFERROR(__xludf.DUMMYFUNCTION("""COMPUTED_VALUE"""),"Income Tax - Deferred Domestic Income Tax - Deferred Domestic") -> Income Tax - Deferred Domestic Income Tax - Deferred Domestic | B36: =IFERROR(__xludf.DUMMYFUNCTION("""COMPUTED_VALUE"""),"264M") -> 264M | C36: =IFERROR(__xludf.DUMMYFUNCTION("""COMPUTED_VALUE"""),"(1.64B)") -> (1.64B) | D36: =IFERROR(__xludf.DUMMYFUNCTION("""COMPUTED_VALUE"""),"(1.67B)") -> (1.67B) | E36: =IFERROR(__xludf.DUMMYFUNCTION("""COMPUTED_VALUE"""),"(1.46B)") -> (1.46B) | F36: =IFERROR(__xludf.DUMMYFUNCTION("""COMPUTED_VALUE"""),"(1.59B)") -> (1.59B)
A37: =IFERROR(__xludf.DUMMYFUNCTION("""COMPUTED_VALUE"""),"Income Tax - Deferred Foreign Income Tax - Deferred Foreign") -> Income Tax - Deferred Foreign Income Tax - Deferred Foreign | B37: =IFERROR(__xludf.DUMMYFUNCTION("""COMPUTED_VALUE"""),"(77M)") -> (77M) | C37: =IFERROR(__xludf.DUMMYFUNCTION("""COMPUTED_VALUE"""),"71M") -> 71M | D37: =IFERROR(__xludf.DUMMYFUNCTION("""COMPUTED_VALUE"""),"(233M)") -> (233M) | E37: =IFERROR(__xludf.DUMMYFUNCTION("""COMPUTED_VALUE"""),"212M") -> 212M | F37: =IFERROR(__xludf.DUMMYFUNCTION("""COMPUTED_VALUE"""),"(83M)") -> (83M)
A38: =IFERROR(__xludf.DUMMYFUNCTION("""COMPUTED_VALUE"""),"Income Tax Credits Income Tax Credits") -> Income Tax Credits Income Tax Credits | B38: =IFERROR(__xludf.DUMMYFUNCTION("""COMPUTED_VALUE"""),"-") -> - | C38: =IFERROR(__xludf.DUMMYFUNCTION("""COMPUTED_VALUE"""),"-") -> - | D38: =IFERROR(__xludf.DUMMYFUNCTION("""COMPUTED_VALUE"""),"-") -> - | E38: =IFERROR(__xludf.DUMMYFUNCTION("""COMPUTED_VALUE"""),"-") -> - | F38: =IFERROR(__xludf.DUMMYFUNCTION("""COMPUTED_VALUE"""),"-") -> -
A39: =IFERROR(__xludf.DUMMYFUNCTION("""COMPUTED_VALUE"""),"Equity in Affiliates Equity in Affiliates") -> Equity in Affiliates Equity in Affiliates | B39: =IFERROR(__xludf.DUMMYFUNCTION("""COMPUTED_VALUE"""),"-") -> - | C39: =IFERROR(__xludf.DUMMYFUNCTION("""COMPUTED_VALUE"""),"-") -> - | D39: =IFERROR(__xludf.DUMMYFUNCTION("""COMPUTED_VALUE"""),"-") -> - | E39: =IFERROR(__xludf.DUMMYFUNCTION("""COMPUTED_VALUE"""),"-") -> - | F39: =IFERROR(__xludf.DUMMYFUNCTION("""COMPUTED_VALUE"""),"-") -> -
A40: =IFERROR(__xludf.DUMMYFUNCTION("""COMPUTED_VALUE"""),"Other After Tax Income (Expense) Other After Tax Income (Expense)") -> Other After Tax Income (Expense) Other After Tax Income (Expense) | B40: =IFERROR(__xludf.DUMMYFUNCTION("""COMPUTED_VALUE"""),"-") -> - | C40: =IFERROR(__xludf.DUMMYFUNCTION("""COMPUTED_VALUE"""),"-") -> - | D40: =IFERROR(__xludf.DUMMYFUNCTION("""COMPUTED_VALUE"""),"-") -> - | E40: =IFERROR(__xludf.DUMMYFUNCTION("""COMPUTED_VALUE"""),"-") -> - | F40: =IFERROR(__xludf.DUMMYFUNCTION("""COMPUTED_VALUE"""),"-") -> -
A41: =IFERROR(__xludf.DUMMYFUNCTION("""COMPUTED_VALUE"""),"Consolidated Net Income Consolidated Net Income") -> Consolidated Net Income Consolidated Net Income | B41: =IFERROR(__xludf.DUMMYFUNCTION("""COMPUTED_VALUE"""),"12.36B") -> 12.36B | C41: =IFERROR(__xludf.DUMMYFUNCTION("""COMPUTED_VALUE"""),"14.53B") -> 14.53B | D41: =IFERROR(__xludf.DUMMYFUNCTION("""COMPUTED_VALUE"""),"377M") -> 377M | E41: =IFERROR(__xludf.DUMMYFUNCTION("""COMPUTED_VALUE"""),"17.13B") -> 17.13B | F41: =IFERROR(__xludf.DUMMYFUNCTION("""COMPUTED_VALUE"""),"18.26B") -> 18.26B
A42: =IFERROR(__xludf.DUMMYFUNCTION("""COMPUTED_VALUE"""),"Minority Interest Expense Minority Interest Expense") -> Minority Interest Expense Minority Interest Expense | B42: =IFERROR(__xludf.DUMMYFUNCTION("""COMPUTED_VALUE"""),"13M") -> 13M | C42: =IFERROR(__xludf.DUMMYFUNCTION("""COMPUTED_VALUE"""),"7M") -> 7M | D42: =IFERROR(__xludf.DUMMYFUNCTION("""COMPUTED_VALUE"""),"12M") -> 12M | E42: =IFERROR(__xludf.DUMMYFUNCTION("""COMPUTED_VALUE"""),"16M") -> 16M | F42: =IFERROR(__xludf.DUMMYFUNCTION("""COMPUTED_VALUE"""),"9M") -> 9M
A43: =IFERROR(__xludf.DUMMYFUNCTION("""COMPUTED_VALUE"""),"Net Income Net Income") -> Net Income Net Income | B43: =IFERROR(__xludf.DUMMYFUNCTION("""COMPUTED_VALUE"""),"12.35B") -> 12.35B | C43: =IFERROR(__xludf.DUMMYFUNCTION("""COMPUTED_VALUE"""),"14.52B") -> 14.52B | D43: =IFERROR(__xludf.DUMMYFUNCTION("""COMPUTED_VALUE"""),"365M") -> 365M | E43: =IFERROR(__xludf.DUMMYFUNCTION("""COMPUTED_VALUE"""),"17.12B") -> 17.12B | F43: =IFERROR(__xludf.DUMMYFUNCTION("""COMPUTED_VALUE"""),"18.25B") -> 18.25B
A44: =IFERROR(__xludf.DUMMYFUNCTION("""COMPUTED_VALUE"""),"Net Income Growth Net Income Growth") -> Net Income Growth Net Income Growth | B44: =IFERROR(__xludf.DUMMYFUNCTION("""COMPUTED_VALUE"""),"-") -> - | C44: =IFERROR(__xludf.DUMMYFUNCTION("""COMPUTED_VALUE"""),0.1761) -> 0.1761 | D44: =IFERROR(__xludf.DUMMYFUNCTION("""COMPUTED_VALUE"""),-0.9749) -> -0.9749 | E44: =IFERROR(__xludf.DUMMYFUNCTION("""COMPUTED_VALUE"""),45.8959) -> 45.8959 | F44: =IFERROR(__xludf.DUMMYFUNCTION("""COMPUTED_VALUE"""),0.0664) -> 0.0664
A45: =IFERROR(__xludf.DUMMYFUNCTION("""COMPUTED_VALUE"""),"Net Margin Growth Net Margin Growth") -> Net Margin Growth Net Margin Growth | B45: =IFERROR(__xludf.DUMMYFUNCTION("""COMPUTED_VALUE"""),"-") -> - | C45: =IFERROR(__xludf.DUMMYFUNCTION("""COMPUTED_VALUE"""),"-") -> - | D45: =IFERROR(__xludf.DUMMYFUNCTION("""COMPUTED_VALUE"""),"-") -> - | E45: =IFERROR(__xludf.DUMMYFUNCTION("""COMPUTED_VALUE"""),"-") -> - | F45: =IFERROR(__xludf.DUMMYFUNCTION("""COMPUTED_VALUE"""),0.2812) -> 0.2812
A46: =IFERROR(__xludf.DUMMYFUNCTION("""COMPUTED_VALUE"""),"Extraordinaries & Discontinued Operations Extraordinaries & Discontinued Operations") -> Extraordinaries & Discontinued Operations Extraordinaries & Discontinued Operations | B46: =IFERROR(__xludf.DUMMYFUNCTION("""COMPUTED_VALUE"""),"704M") -> 704M | C46: =IFERROR(__xludf.DUMMYFUNCTION("""COMPUTED_VALUE"""),"-") -> - | D46: =IFERROR(__xludf.DUMMYFUNCTION("""COMPUTED_VALUE"""),"-") -> - | E46: =IFERROR(__xludf.DUMMYFUNCTION("""COMPUTED_VALUE"""),"-") -> - | F46: =IFERROR(__xludf.DUMMYFUNCTION("""COMPUTED_VALUE"""),"-") -> -
A47: =IFERROR(__xludf.DUMMYFUNCTION("""COMPUTED_VALUE"""),"Extra Items & Gain/Loss Sale Of Assets Extra Items & Gain/Loss Sale Of Assets") -> Extra Items & Gain/Loss Sale Of Assets Extra Items & Gain/Loss Sale Of Assets | B47: =IFERROR(__xludf.DUMMYFUNCTION("""COMPUTED_VALUE"""),"-") -> - | C47: =IFERROR(__xludf.DUMMYFUNCTION("""COMPUTED_VALUE"""),"-") -> - | D47: =IFERROR(__xludf.DUMMYFUNCTION("""COMPUTED_VALUE"""),"-") -> - | E47: =IFERROR(__xludf.DUMMYFUNCTION("""COMPUTED_VALUE"""),"-") -> - | F47: =IFERROR(__xludf.DUMMYFUNCTION("""COMPUTED_VALUE"""),"-") -> -
A48: =IFERROR(__xludf.DUMMYFUNCTION("""COMPUTED_VALUE"""),"Cumulative Effect - Accounting Chg Cumulative Effect - Accounting Chg") -> Cumulative Effect - Accounting Chg Cumulative Effect - Accounting Chg | B48: =IFERROR(__xludf.DUMMYFUNCTION("""COMPUTED_VALUE"""),"-") -> - | C48: =IFERROR(__xludf.DUMMYFUNCTION("""COMPUTED_VALUE"""),"-") -> - | D48: =IFERROR(__xludf.DUMMYFUNCTION("""COMPUTED_VALUE"""),"-") -> - | E48: =IFERROR(__xludf.DUMMYFUNCTION("""COMPUTED_VALUE"""),"-") -> - | F48: =IFERROR(__xludf.DUMMYFUNCTION("""COMPUTED_VALUE"""),"-") -> -
A49: =IFERROR(__xludf.DUMMYFUNCTION("""COMPUTED_VALUE"""),"Discontinued Operations Discontinued Operations") -> Discontinued Operations Discontinued Operations | B49: =IFERROR(__xludf.DUMMYFUNCTION("""COMPUTED_VALUE"""),"704M") -> 704M | C49: =IFERROR(__xludf.DUMMYFUNCTION("""COMPUTED_VALUE"""),"-") -> - | D49: =IFERROR(__xludf.DUMMYFUNCTION("""COMPUTED_VALUE"""),"-") -> - | E49: =IFERROR(__xludf.DUMMYFUNCTION("""COMPUTED_VALUE"""),"-") -> - | F49: =IFERROR(__xludf.DUMMYFUNCTION("""COMPUTED_VALUE"""),"-") -> -
A50: =IFERROR(__xludf.DUMMYFUNCTION("""COMPUTED_VALUE"""),"Net Income After Extraordinaries Net Income After Extraordinaries") -> Net Income After Extraordinaries Net Income After Extraordinaries | B50: =IFERROR(__xludf.DUMMYFUNCTION("""COMPUTED_VALUE"""),"13.05B") -> 13.05B | C50: =IFERROR(__xludf.DUMMYFUNCTION("""COMPUTED_VALUE"""),"14.52B") -> 14.52B | D50: =IFERROR(__xludf.DUMMYFUNCTION("""COMPUTED_VALUE"""),"365M") -> 365M | E50: =IFERROR(__xludf.DUMMYFUNCTION("""COMPUTED_VALUE"""),"17.12B") -> 17.12B | F50: =IFERROR(__xludf.DUMMYFUNCTION("""COMPUTED_VALUE"""),"18.25B") -> 18.25B
A51: =IFERROR(__xludf.DUMMYFUNCTION("""COMPUTED_VALUE"""),"Preferred Dividends Preferred Dividends") -> Preferred Dividends Preferred Dividends | B51: =IFERROR(__xludf.DUMMYFUNCTION("""COMPUTED_VALUE"""),"-") -> - | C51: =IFERROR(__xludf.DUMMYFUNCTION("""COMPUTED_VALUE"""),"-") -> - | D51: =IFERROR(__xludf.DUMMYFUNCTION("""COMPUTED_VALUE"""),"-") -> - | E51: =IFERROR(__xludf.DUMMYFUNCTION("""COMPUTED_VALUE"""),"-") -> - | F51: =IFERROR(__xludf.DUMMYFUNCTION("""COMPUTED_VALUE"""),"-") -> -
A52: =IFERROR(__xludf.DUMMYFUNCTION("""COMPUTED_VALUE"""),"Net Income Available to Common Net Income Available to Common") -> Net Income Available to Common Net Income Available to Common | B52: =IFERROR(__xludf.DUMMYFUNCTION("""COMPUTED_VALUE"""),"13.05B") -> 13.05B | C52: =IFERROR(__xludf.DUMMYFUNCTION("""COMPUTED_VALUE"""),"14.52B") -> 14.52B | D52: =IFERROR(__xludf.DUMMYFUNCTION("""COMPUTED_VALUE"""),"365M") -> 365M | E52: =IFERROR(__xludf.DUMMYFUNCTION("""COMPUTED_VALUE"""),"17.12B") -> 17.12B | F52: =IFERROR(__xludf.DUMMYFUNCTION("""COMPUTED_VALUE"""),"18.25B") -> 18.25B
A53: =IFERROR(__xludf.DUMMYFUNCTION("""COMPUTED_VALUE"""),"EPS (Basic) EPS (Basic)") -> EPS (Basic) EPS (Basic) | B53: =IFERROR(__xludf.DUMMYFUNCTION("""COMPUTED_VALUE"""),5.16) -> 5.16 | C53: =IFERROR(__xludf.DUMMYFUNCTION("""COMPUTED_VALUE"""),5.73) -> 5.73 | D53: =IFERROR(__xludf.DUMMYFUNCTION("""COMPUTED_VALUE"""),0.14) -> 0.14 | E53: =IFERROR(__xludf.DUMMYFUNCTION("""COMPUTED_VALUE"""),6.76) -> 6.76 | F53: =IFERROR(__xludf.DUMMYFUNCTION("""COMPUTED_VALUE"""),7.3) -> 7.3
A54: =IFERROR(__xludf.DUMMYFUNCTION("""COMPUTED_VALUE"""),"EPS (Basic) Growth EPS (Basic) Growth") -> EPS (Basic) Growth EPS (Basic) Growth | B54: =IFERROR(__xludf.DUMMYFUNCTION("""COMPUTED_VALUE"""),"-") -> - | C54: =IFERROR(__xludf.DUMMYFUNCTION("""COMPUTED_VALUE"""),0.1118) -> 0.1118 | D54: =IFERROR(__xludf.DUMMYFUNCTION("""COMPUTED_VALUE"""),-0.9749) -> -0.9749 | E54: =IFERROR(__xludf.DUMMYFUNCTION("""COMPUTED_VALUE"""),45.9792) -> 45.9792 | F54: =IFERROR(__xludf.DUMMYFUNCTION("""COMPUTED_VALUE"""),0.0792) -> 0.0792
A55: =IFERROR(__xludf.DUMMYFUNCTION("""COMPUTED_VALUE"""),"Basic Shares Outstanding Basic Shares Outstanding") -> Basic Shares Outstanding Basic Shares Outstanding | B55: =IFERROR(__xludf.DUMMYFUNCTION("""COMPUTED_VALUE"""),"2.53B") -> 2.53B | C55: =IFERROR(__xludf.DUMMYFUNCTION("""COMPUTED_VALUE"""),"2.53B") -> 2.53B | D55: =IFERROR(__xludf.DUMMYFUNCTION("""COMPUTED_VALUE"""),"2.54B") -> 2.54B | E55: =IFERROR(__xludf.DUMMYFUNCTION("""COMPUTED_VALUE"""),"2.53B") -> 2.53B | F55: =IFERROR(__xludf.DUMMYFUNCTION("""COMPUTED_VALUE"""),"2.5B") -> 2.5B
A56: =IFERROR(__xludf.DUMMYFUNCTION("""COMPUTED_VALUE"""),"EPS (Diluted) EPS (Diluted)") -> EPS (Diluted) EPS (Diluted) | B56: =IFERROR(__xludf.DUMMYFUNCTION("""COMPUTED_VALUE"""),5.14) -> 5.14 | C56: =IFERROR(__xludf.DUMMYFUNCTION("""COMPUTED_VALUE"""),5.71) -> 5.71 | D56: =IFERROR(__xludf.DUMMYFUNCTION("""COMPUTED_VALUE"""),0.14) -> 0.14 | E56: =IFERROR(__xludf.DUMMYFUNCTION("""COMPUTED_VALUE"""),6.74) -> 6.74 | F56: =IFERROR(__xludf.DUMMYFUNCTION("""COMPUTED_VALUE"""),7.28) -> 7.28
A57: =IFERROR(__xludf.DUMMYFUNCTION("""COMPUTED_VALUE"""),"EPS (Diluted) Growth EPS (Diluted) Growth") -> EPS (Diluted) Growth EPS (Diluted) Growth | B57: =IFERROR(__xludf.DUMMYFUNCTION("""COMPUTED_VALUE"""),"-") -> - | C57: =IFERROR(__xludf.DUMMYFUNCTION("""COMPUTED_VALUE"""),0.1109) -> 0.1109 | D57: =IFERROR(__xludf.DUMMYFUNCTION("""COMPUTED_VALUE"""),-0.9749) -> -0.9749 | E57: =IFERROR(__xludf.DUMMYFUNCTION("""COMPUTED_VALUE"""),46.0084) -> 46.0084 | F57: =IFERROR(__xludf.DUMMYFUNCTION("""COMPUTED_VALUE"""),0.0809) -> 0.0809
A58: =IFERROR(__xludf.DUMMYFUNCTION("""COMPUTED_VALUE"""),"Diluted Shares Outstanding Diluted Shares Outstanding") -> Diluted Shares Outstanding Diluted Shares Outstanding | B58: =IFERROR(__xludf.DUMMYFUNCTION("""COMPUTED_VALUE"""),"2.54B") -> 2.54B | C58: =IFERROR(__xludf.DUMMYFUNCTION("""COMPUTED_VALUE"""),"2.54B") -> 2.54B | D58: =IFERROR(__xludf.DUMMYFUNCTION("""COMPUTED_VALUE"""),"2.55B") -> 2.55B | E58: =IFERROR(__xludf.DUMMYFUNCTION("""COMPUTED_VALUE"""),"2.54B") -> 2.54B | F58: =IFERROR(__xludf.DUMMYFUNCTION("""COMPUTED_VALUE"""),"2.51B") -> 2.51B
A59: =IFERROR(__xludf.DUMMYFUNCTION("""COMPUTED_VALUE"""),"EBITDA EBITDA") -> EBITDA EBITDA | B59: =IFERROR(__xludf.DUMMYFUNCTION("""COMPUTED_VALUE"""),"18.83B") -> 18.83B | C59: =IFERROR(__xludf.DUMMYFUNCTION("""COMPUTED_VALUE"""),"23.41B") -> 23.41B | D59: =IFERROR(__xludf.DUMMYFUNCTION("""COMPUTED_VALUE"""),"6.85B") -> 6.85B | E59: =IFERROR(__xludf.DUMMYFUNCTION("""COMPUTED_VALUE"""),"25.14B") -> 25.14B | F59: =IFERROR(__xludf.DUMMYFUNCTION("""COMPUTED_VALUE"""),"29.32B") -> 29.32B
A60: =IFERROR(__xludf.DUMMYFUNCTION("""COMPUTED_VALUE"""),"EBITDA Growth EBITDA Growth") -> EBITDA Growth EBITDA Growth | B60: =IFERROR(__xludf.DUMMYFUNCTION("""COMPUTED_VALUE"""),"-") -> - | C60: =IFERROR(__xludf.DUMMYFUNCTION("""COMPUTED_VALUE"""),0.243) -> 0.243 | D60: =IFERROR(__xludf.DUMMYFUNCTION("""COMPUTED_VALUE"""),-0.7072) -> -0.7072 | E60: =IFERROR(__xludf.DUMMYFUNCTION("""COMPUTED_VALUE"""),2.6684) -> 2.6684 | F60: =IFERROR(__xludf.DUMMYFUNCTION("""COMPUTED_VALUE"""),0.1663) -> 0.1663
A61: =IFERROR(__xludf.DUMMYFUNCTION("""COMPUTED_VALUE"""),"EBITDA Margin EBITDA Margin") -> EBITDA Margin EBITDA Margin | B61: =IFERROR(__xludf.DUMMYFUNCTION("""COMPUTED_VALUE"""),"-") -> - | C61: =IFERROR(__xludf.DUMMYFUNCTION("""COMPUTED_VALUE"""),"-") -> - | D61: =IFERROR(__xludf.DUMMYFUNCTION("""COMPUTED_VALUE"""),"-") -> - | E61: =IFERROR(__xludf.DUMMYFUNCTION("""COMPUTED_VALUE"""),"-") -> - | F61: =IFERROR(__xludf.DUMMYFUNCTION("""COMPUTED_VALUE"""),0.4517) -> 0.4517
A68: =IFERROR(__xludf.DUMMYFUNCTION("IMPORTHTML(CONCAT(CONCAT(""https://www.marketwatch.com/investing/stock/"",'Income Statement'!D1),""/financials/balance-sheet""),""table"",4) "),"Item Item") -> Item Item | B68: =IFERROR(__xludf.DUMMYFUNCTION("""COMPUTED_VALUE"""),2021.0) -> 2021 | C68: =IFERROR(__xludf.DUMMYFUNCTION("""COMPUTED_VALUE"""),2022.0) -> 2022 | D68: =IFERROR(__xludf.DUMMYFUNCTION("""COMPUTED_VALUE"""),2023.0) -> 2023 | E68: =IFERROR(__xludf.DUMMYFUNCTION("""COMPUTED_VALUE"""),2024.0) -> 2024 | F68: =IFERROR(__xludf.DUMMYFUNCTION("""COMPUTED_VALUE"""),2025.0) -> 2025 | G68: =IFERROR(__xludf.DUMMYFUNCTION("""COMPUTED_VALUE"""),"5-year trend") -> 5-year trend
A69: =IFERROR(__xludf.DUMMYFUNCTION("""COMPUTED_VALUE"""),"Cash & Short Term Investments Cash & Short Term Investments") -> Cash & Short Term Investments Cash & Short Term Investments | B69: =IFERROR(__xludf.DUMMYFUNCTION("""COMPUTED_VALUE"""),"8.1B") -> 8.1B | C69: =IFERROR(__xludf.DUMMYFUNCTION("""COMPUTED_VALUE"""),"13.27B") -> 13.27B | D69: =IFERROR(__xludf.DUMMYFUNCTION("""COMPUTED_VALUE"""),"7.16B") -> 7.16B | E69: =IFERROR(__xludf.DUMMYFUNCTION("""COMPUTED_VALUE"""),"13.77B") -> 13.77B | F69: =IFERROR(__xludf.DUMMYFUNCTION("""COMPUTED_VALUE"""),"14.69B") -> 14.69B
A70: =IFERROR(__xludf.DUMMYFUNCTION("""COMPUTED_VALUE"""),"Cash & Short Term Investments Growth Cash & Short Term Investments Growth") -> Cash & Short Term Investments Growth Cash & Short Term Investments Growth | B70: =IFERROR(__xludf.DUMMYFUNCTION("""COMPUTED_VALUE"""),"-") -> - | C70: =IFERROR(__xludf.DUMMYFUNCTION("""COMPUTED_VALUE"""),0.6392) -> 0.6392 | D70: =IFERROR(__xludf.DUMMYFUNCTION("""COMPUTED_VALUE"""),-0.4604) -> -0.4604 | E70: =IFERROR(__xludf.DUMMYFUNCTION("""COMPUTED_VALUE"""),0.9222) -> 0.9222 | F70: =IFERROR(__xludf.DUMMYFUNCTION("""COMPUTED_VALUE"""),0.0672) -> 0.0672
A71: =IFERROR(__xludf.DUMMYFUNCTION("""COMPUTED_VALUE"""),"Cash Only Cash Only") -> Cash Only Cash Only | B71: =IFERROR(__xludf.DUMMYFUNCTION("""COMPUTED_VALUE"""),"8.1B") -> 8.1B | C71: =IFERROR(__xludf.DUMMYFUNCTION("""COMPUTED_VALUE"""),"12.77B") -> 12.77B | D71: =IFERROR(__xludf.DUMMYFUNCTION("""COMPUTED_VALUE"""),"6.91B") -> 6.91B | E71: =IFERROR(__xludf.DUMMYFUNCTION("""COMPUTED_VALUE"""),"13.32B") -> 13.32B | F71: =IFERROR(__xludf.DUMMYFUNCTION("""COMPUTED_VALUE"""),"14.69B") -> 14.69B
A72: =IFERROR(__xludf.DUMMYFUNCTION("""COMPUTED_VALUE"""),"Short-Term Investments Short-Term Investments") -> Short-Term Investments Short-Term Investments | B72: =IFERROR(__xludf.DUMMYFUNCTION("""COMPUTED_VALUE"""),"-") -> - | C72: =IFERROR(__xludf.DUMMYFUNCTION("""COMPUTED_VALUE"""),"-") -> - | D72: =IFERROR(__xludf.DUMMYFUNCTION("""COMPUTED_VALUE"""),"-") -> - | E72: =IFERROR(__xludf.DUMMYFUNCTION("""COMPUTED_VALUE"""),"-") -> - | F72: =IFERROR(__xludf.DUMMYFUNCTION("""COMPUTED_VALUE"""),"-") -> -
A73: =IFERROR(__xludf.DUMMYFUNCTION("""COMPUTED_VALUE"""),"Cash & ST Investments / Total Assets Cash & ST Investments / Total Assets") -> Cash & ST Investments / Total Assets Cash & ST Investments / Total Assets | B73: =IFERROR(__xludf.DUMMYFUNCTION("""COMPUTED_VALUE"""),0.0766) -> 0.0766 | C73: =IFERROR(__xludf.DUMMYFUNCTION("""COMPUTED_VALUE"""),0.1216) -> 0.1216 | D73: =IFERROR(__xludf.DUMMYFUNCTION("""COMPUTED_VALUE"""),0.0671) -> 0.0671 | E73: =IFERROR(__xludf.DUMMYFUNCTION("""COMPUTED_VALUE"""),0.1175) -> 0.1175 | F73: =IFERROR(__xludf.DUMMYFUNCTION("""COMPUTED_VALUE"""),0.1073) -> 0.1073
A74: =IFERROR(__xludf.DUMMYFUNCTION("""COMPUTED_VALUE"""),"Total Accounts Receivable Total Accounts Receivable") -> Total Accounts Receivable Total Accounts Receivable | B74: =IFERROR(__xludf.DUMMYFUNCTION("""COMPUTED_VALUE"""),"9.82B") -> 9.82B | C74: =IFERROR(__xludf.DUMMYFUNCTION("""COMPUTED_VALUE"""),"10.11B") -> 10.11B | D74: =IFERROR(__xludf.DUMMYFUNCTION("""COMPUTED_VALUE"""),"11.07B") -> 11.07B | E74: =IFERROR(__xludf.DUMMYFUNCTION("""COMPUTED_VALUE"""),"11.13B") -> 11.13B | F74: =IFERROR(__xludf.DUMMYFUNCTION("""COMPUTED_VALUE"""),"12.68B") -> 12.68B
A75: =IFERROR(__xludf.DUMMYFUNCTION("""COMPUTED_VALUE"""),"Total Accounts Receivable Growth Total Accounts Receivable Growth") -> Total Accounts Receivable Growth Total Accounts Receivable Growth | B75: =IFERROR(__xludf.DUMMYFUNCTION("""COMPUTED_VALUE"""),"-") -> - | C75: =IFERROR(__xludf.DUMMYFUNCTION("""COMPUTED_VALUE"""),0.0301) -> 0.0301 | D75: =IFERROR(__xludf.DUMMYFUNCTION("""COMPUTED_VALUE"""),0.0952) -> 0.0952 | E75: =IFERROR(__xludf.DUMMYFUNCTION("""COMPUTED_VALUE"""),0.005) -> 0.005 | F75: =IFERROR(__xludf.DUMMYFUNCTION("""COMPUTED_VALUE"""),0.1395) -> 0.1395
A76: =IFERROR(__xludf.DUMMYFUNCTION("""COMPUTED_VALUE"""),"Accounts Receivables, Net Accounts Receivables, Net") -> Accounts Receivables, Net Accounts Receivables, Net | B76: =IFERROR(__xludf.DUMMYFUNCTION("""COMPUTED_VALUE"""),"9.23B") -> 9.23B | C76: =IFERROR(__xludf.DUMMYFUNCTION("""COMPUTED_VALUE"""),"9.45B") -> 9.45B | D76: =IFERROR(__xludf.DUMMYFUNCTION("""COMPUTED_VALUE"""),"10.35B") -> 10.35B | E76: =IFERROR(__xludf.DUMMYFUNCTION("""COMPUTED_VALUE"""),"10.28B") -> 10.28B | F76: =IFERROR(__xludf.DUMMYFUNCTION("""COMPUTED_VALUE"""),"11.78B") -> 11.78B
A77: =IFERROR(__xludf.DUMMYFUNCTION("""COMPUTED_VALUE"""),"Accounts Receivables, Gross Accounts Receivables, Gross") -> Accounts Receivables, Gross Accounts Receivables, Gross | B77: =IFERROR(__xludf.DUMMYFUNCTION("""COMPUTED_VALUE"""),"9.29B") -> 9.29B | C77: =IFERROR(__xludf.DUMMYFUNCTION("""COMPUTED_VALUE"""),"9.52B") -> 9.52B | D77: =IFERROR(__xludf.DUMMYFUNCTION("""COMPUTED_VALUE"""),"10.44B") -> 10.44B | E77: =IFERROR(__xludf.DUMMYFUNCTION("""COMPUTED_VALUE"""),"10.37B") -> 10.37B | F77: =IFERROR(__xludf.DUMMYFUNCTION("""COMPUTED_VALUE"""),"11.87B") -> 11.87B
A78: =IFERROR(__xludf.DUMMYFUNCTION("""COMPUTED_VALUE"""),"Bad Debt/Doubtful Accounts Bad Debt/Doubtful Accounts") -> Bad Debt/Doubtful Accounts Bad Debt/Doubtful Accounts | B78: =IFERROR(__xludf.DUMMYFUNCTION("""COMPUTED_VALUE"""),"(62M)") -> (62M) | C78: =IFERROR(__xludf.DUMMYFUNCTION("""COMPUTED_VALUE"""),"(72M)") -> (72M) | D78: =IFERROR(__xludf.DUMMYFUNCTION("""COMPUTED_VALUE"""),"(88M)") -> (88M) | E78: =IFERROR(__xludf.DUMMYFUNCTION("""COMPUTED_VALUE"""),"(89M)") -> (89M) | F78: =IFERROR(__xludf.DUMMYFUNCTION("""COMPUTED_VALUE"""),"(97M)") -> (97M)
A79: =IFERROR(__xludf.DUMMYFUNCTION("""COMPUTED_VALUE"""),"Other Receivable Other Receivable") -> Other Receivable Other Receivable | B79: =IFERROR(__xludf.DUMMYFUNCTION("""COMPUTED_VALUE"""),"585M") -> 585M | C79: =IFERROR(__xludf.DUMMYFUNCTION("""COMPUTED_VALUE"""),"660M") -> 660M | D79: =IFERROR(__xludf.DUMMYFUNCTION("""COMPUTED_VALUE"""),"723M") -> 723M | E79: =IFERROR(__xludf.DUMMYFUNCTION("""COMPUTED_VALUE"""),"849M") -> 849M | F79: =IFERROR(__xludf.DUMMYFUNCTION("""COMPUTED_VALUE"""),"904M") -> 904M
A80: =IFERROR(__xludf.DUMMYFUNCTION("""COMPUTED_VALUE"""),"Accounts Receivable Turnover Accounts Receivable Turnover") -> Accounts Receivable Turnover Accounts Receivable Turnover | B80: =IFERROR(__xludf.DUMMYFUNCTION("""COMPUTED_VALUE"""),4.98) -> 4.98 | C80: =IFERROR(__xludf.DUMMYFUNCTION("""COMPUTED_VALUE"""),5.78) -> 5.78 | D80: =IFERROR(__xludf.DUMMYFUNCTION("""COMPUTED_VALUE"""),5.41) -> 5.41 | E80: =IFERROR(__xludf.DUMMYFUNCTION("""COMPUTED_VALUE"""),5.75) -> 5.75 | F80: =IFERROR(__xludf.DUMMYFUNCTION("""COMPUTED_VALUE"""),5.12) -> 5.12
A81: =IFERROR(__xludf.DUMMYFUNCTION("""COMPUTED_VALUE"""),"Inventories Inventories") -> Inventories Inventories | B81: =IFERROR(__xludf.DUMMYFUNCTION("""COMPUTED_VALUE"""),"5.95B") -> 5.95B | C81: =IFERROR(__xludf.DUMMYFUNCTION("""COMPUTED_VALUE"""),"5.91B") -> 5.91B | D81: =IFERROR(__xludf.DUMMYFUNCTION("""COMPUTED_VALUE"""),"6.36B") -> 6.36B | E81: =IFERROR(__xludf.DUMMYFUNCTION("""COMPUTED_VALUE"""),"6.11B") -> 6.11B | F81: =IFERROR(__xludf.DUMMYFUNCTION("""COMPUTED_VALUE"""),"6.66B") -> 6.66B
A82: =IFERROR(__xludf.DUMMYFUNCTION("""COMPUTED_VALUE"""),"Finished Goods Finished Goods") -> Finished Goods Finished Goods | B82: =IFERROR(__xludf.DUMMYFUNCTION("""COMPUTED_VALUE"""),"1.75B") -> 1.75B | C82: =IFERROR(__xludf.DUMMYFUNCTION("""COMPUTED_VALUE"""),"1.84B") -> 1.84B | D82: =IFERROR(__xludf.DUMMYFUNCTION("""COMPUTED_VALUE"""),"1.95B") -> 1.95B | E82: =IFERROR(__xludf.DUMMYFUNCTION("""COMPUTED_VALUE"""),"2.02B") -> 2.02B | F82: =IFERROR(__xludf.DUMMYFUNCTION("""COMPUTED_VALUE"""),"2.28B") -> 2.28B
A83: =IFERROR(__xludf.DUMMYFUNCTION("""COMPUTED_VALUE"""),"Work in Progress Work in Progress") -> Work in Progress Work in Progress | B83: =IFERROR(__xludf.DUMMYFUNCTION("""COMPUTED_VALUE"""),"-") -> - | C83: =IFERROR(__xludf.DUMMYFUNCTION("""COMPUTED_VALUE"""),"-") -> - | D83: =IFERROR(__xludf.DUMMYFUNCTION("""COMPUTED_VALUE"""),"-") -> - | E83: =IFERROR(__xludf.DUMMYFUNCTION("""COMPUTED_VALUE"""),"-") -> - | F83: =IFERROR(__xludf.DUMMYFUNCTION("""COMPUTED_VALUE"""),"-") -> -
A84: =IFERROR(__xludf.DUMMYFUNCTION("""COMPUTED_VALUE"""),"Raw Materials Raw Materials") -> Raw Materials Raw Materials | B84: =IFERROR(__xludf.DUMMYFUNCTION("""COMPUTED_VALUE"""),"4.22B") -> 4.22B | C84: =IFERROR(__xludf.DUMMYFUNCTION("""COMPUTED_VALUE"""),"4.36B") -> 4.36B | D84: =IFERROR(__xludf.DUMMYFUNCTION("""COMPUTED_VALUE"""),"4.97B") -> 4.97B | E84: =IFERROR(__xludf.DUMMYFUNCTION("""COMPUTED_VALUE"""),"4.93B") -> 4.93B | F84: =IFERROR(__xludf.DUMMYFUNCTION("""COMPUTED_VALUE"""),"5.3B") -> 5.3B
A85: =IFERROR(__xludf.DUMMYFUNCTION("""COMPUTED_VALUE"""),"Progress Payments & Other Progress Payments & Other") -> Progress Payments & Other Progress Payments & Other | B85: =IFERROR(__xludf.DUMMYFUNCTION("""COMPUTED_VALUE"""),"(16M)") -> (16M) | C85: =IFERROR(__xludf.DUMMYFUNCTION("""COMPUTED_VALUE"""),"(293M)") -> (293M) | D85: =IFERROR(__xludf.DUMMYFUNCTION("""COMPUTED_VALUE"""),"(562M)") -> (562M) | E85: =IFERROR(__xludf.DUMMYFUNCTION("""COMPUTED_VALUE"""),"(840M)") -> (840M) | F85: =IFERROR(__xludf.DUMMYFUNCTION("""COMPUTED_VALUE"""),"(912M)") -> (912M)
A86: =IFERROR(__xludf.DUMMYFUNCTION("""COMPUTED_VALUE"""),"Other Current Assets Other Current Assets") -> Other Current Assets Other Current Assets | B86: =IFERROR(__xludf.DUMMYFUNCTION("""COMPUTED_VALUE"""),"6.4B") -> 6.4B | C86: =IFERROR(__xludf.DUMMYFUNCTION("""COMPUTED_VALUE"""),"6.43B") -> 6.43B | D86: =IFERROR(__xludf.DUMMYFUNCTION("""COMPUTED_VALUE"""),"7.58B") -> 7.58B | E86: =IFERROR(__xludf.DUMMYFUNCTION("""COMPUTED_VALUE"""),"7.78B") -> 7.78B | F86: =IFERROR(__xludf.DUMMYFUNCTION("""COMPUTED_VALUE"""),"9.49B") -> 9.49B
A87: =IFERROR(__xludf.DUMMYFUNCTION("""COMPUTED_VALUE"""),"Miscellaneous Current Assets Miscellaneous Current Assets") -> Miscellaneous Current Assets Miscellaneous Current Assets | B87: =IFERROR(__xludf.DUMMYFUNCTION("""COMPUTED_VALUE"""),"6.4B") -> 6.4B | C87: =IFERROR(__xludf.DUMMYFUNCTION("""COMPUTED_VALUE"""),"6.43B") -> 6.43B | D87: =IFERROR(__xludf.DUMMYFUNCTION("""COMPUTED_VALUE"""),"7.58B") -> 7.58B | E87: =IFERROR(__xludf.DUMMYFUNCTION("""COMPUTED_VALUE"""),"7.78B") -> 7.78B | F87: =IFERROR(__xludf.DUMMYFUNCTION("""COMPUTED_VALUE"""),"9.49B") -> 9.49B
A88: =IFERROR(__xludf.DUMMYFUNCTION("""COMPUTED_VALUE"""),"Total Current Assets Total Current Assets") -> Total Current Assets Total Current Assets | B88: =IFERROR(__xludf.DUMMYFUNCTION("""COMPUTED_VALUE"""),"30.27B") -> 30.27B | C88: =IFERROR(__xludf.DUMMYFUNCTION("""COMPUTED_VALUE"""),"35.72B") -> 35.72B | D88: =IFERROR(__xludf.DUMMYFUNCTION("""COMPUTED_VALUE"""),"32.17B") -> 32.17B | E88: =IFERROR(__xludf.DUMMYFUNCTION("""COMPUTED_VALUE"""),"38.78B") -> 38.78B | F88: =IFERROR(__xludf.DUMMYFUNCTION("""COMPUTED_VALUE"""),"43.52B") -> 43.52B
A89: =IFERROR(__xludf.DUMMYFUNCTION("""COMPUTED_VALUE"""),"Net Property, Plant & Equipment Net Property, Plant & Equipment") -> Net Property, Plant & Equipment Net Property, Plant & Equipment | B89: =IFERROR(__xludf.DUMMYFUNCTION("""COMPUTED_VALUE"""),"20.87B") -> 20.87B | C89: =IFERROR(__xludf.DUMMYFUNCTION("""COMPUTED_VALUE"""),"22.77B") -> 22.77B | D89: =IFERROR(__xludf.DUMMYFUNCTION("""COMPUTED_VALUE"""),"24.49B") -> 24.49B | E89: =IFERROR(__xludf.DUMMYFUNCTION("""COMPUTED_VALUE"""),"25.15B") -> 25.15B | F89: =IFERROR(__xludf.DUMMYFUNCTION("""COMPUTED_VALUE"""),"26.82B") -> 26.82B
A90: =IFERROR(__xludf.DUMMYFUNCTION("""COMPUTED_VALUE"""),"Property, Plant & Equipment - Gross Property, Plant & Equipment - Gross") -> Property, Plant & Equipment - Gross Property, Plant & Equipment - Gross | B90: =IFERROR(__xludf.DUMMYFUNCTION("""COMPUTED_VALUE"""),"39.06B") -> 39.06B | C90: =IFERROR(__xludf.DUMMYFUNCTION("""COMPUTED_VALUE"""),"40.75B") -> 40.75B | D90: =IFERROR(__xludf.DUMMYFUNCTION("""COMPUTED_VALUE"""),"42.75B") -> 42.75B | E90: =IFERROR(__xludf.DUMMYFUNCTION("""COMPUTED_VALUE"""),"44.3B") -> 44.3B | F90: =IFERROR(__xludf.DUMMYFUNCTION("""COMPUTED_VALUE"""),"48.74B") -> 48.74B
A91: =IFERROR(__xludf.DUMMYFUNCTION("""COMPUTED_VALUE"""),"Buildings Buildings") -> Buildings Buildings | B91: =IFERROR(__xludf.DUMMYFUNCTION("""COMPUTED_VALUE"""),"12.53B") -> 12.53B | C91: =IFERROR(__xludf.DUMMYFUNCTION("""COMPUTED_VALUE"""),"13.17B") -> 13.17B | D91: =IFERROR(__xludf.DUMMYFUNCTION("""COMPUTED_VALUE"""),"14.97B") -> 14.97B | E91: =IFERROR(__xludf.DUMMYFUNCTION("""COMPUTED_VALUE"""),"16.36B") -> 16.36B | F91: =IFERROR(__xludf.DUMMYFUNCTION("""COMPUTED_VALUE"""),"17.98B") -> 17.98B
A92: =IFERROR(__xludf.DUMMYFUNCTION("""COMPUTED_VALUE"""),"Land & Improvements Land & Improvements") -> Land & Improvements Land & Improvements | B92: =IFERROR(__xludf.DUMMYFUNCTION("""COMPUTED_VALUE"""),"326M") -> 326M | C92: =IFERROR(__xludf.DUMMYFUNCTION("""COMPUTED_VALUE"""),"295M") -> 295M | D92: =IFERROR(__xludf.DUMMYFUNCTION("""COMPUTED_VALUE"""),"326M") -> 326M | E92: =IFERROR(__xludf.DUMMYFUNCTION("""COMPUTED_VALUE"""),"307M") -> 307M | F92: =IFERROR(__xludf.DUMMYFUNCTION("""COMPUTED_VALUE"""),"321M") -> 321M
A93: =IFERROR(__xludf.DUMMYFUNCTION("""COMPUTED_VALUE"""),"Computer Software and Equipment Computer Software and Equipment") -> Computer Software and Equipment Computer Software and Equipment | B93: =IFERROR(__xludf.DUMMYFUNCTION("""COMPUTED_VALUE"""),"-") -> - | C93: =IFERROR(__xludf.DUMMYFUNCTION("""COMPUTED_VALUE"""),"-") -> - | D93: =IFERROR(__xludf.DUMMYFUNCTION("""COMPUTED_VALUE"""),"-") -> - | E93: =IFERROR(__xludf.DUMMYFUNCTION("""COMPUTED_VALUE"""),"-") -> - | F93: =IFERROR(__xludf.DUMMYFUNCTION("""COMPUTED_VALUE"""),"-") -> -
A94: =IFERROR(__xludf.DUMMYFUNCTION("""COMPUTED_VALUE"""),"Other Property, Plant & Equipment Other Property, Plant & Equipment") -> Other Property, Plant & Equipment Other Property, Plant & Equipment | B94: =IFERROR(__xludf.DUMMYFUNCTION("""COMPUTED_VALUE"""),"-") -> - | C94: =IFERROR(__xludf.DUMMYFUNCTION("""COMPUTED_VALUE"""),"-") -> - | D94: =IFERROR(__xludf.DUMMYFUNCTION("""COMPUTED_VALUE"""),"-") -> - | E94: =IFERROR(__xludf.DUMMYFUNCTION("""COMPUTED_VALUE"""),"-") -> - | F94: =IFERROR(__xludf.DUMMYFUNCTION("""COMPUTED_VALUE"""),"-") -> -
A95: =IFERROR(__xludf.DUMMYFUNCTION("""COMPUTED_VALUE"""),"Accumulated Depreciation Accumulated Depreciation") -> Accumulated Depreciation Accumulated Depreciation | B95: =IFERROR(__xludf.DUMMYFUNCTION("""COMPUTED_VALUE"""),"18.19B") -> 18.19B | C95: =IFERROR(__xludf.DUMMYFUNCTION("""COMPUTED_VALUE"""),"17.99B") -> 17.99B | D95: =IFERROR(__xludf.DUMMYFUNCTION("""COMPUTED_VALUE"""),"18.27B") -> 18.27B | E95: =IFERROR(__xludf.DUMMYFUNCTION("""COMPUTED_VALUE"""),"19.16B") -> 19.16B | F95: =IFERROR(__xludf.DUMMYFUNCTION("""COMPUTED_VALUE"""),"21.91B") -> 21.91B
A96: =IFERROR(__xludf.DUMMYFUNCTION("""COMPUTED_VALUE"""),"Total Investments and Advances Total Investments and Advances") -> Total Investments and Advances Total Investments and Advances | B96: =IFERROR(__xludf.DUMMYFUNCTION("""COMPUTED_VALUE"""),"1.08B") -> 1.08B | C96: =IFERROR(__xludf.DUMMYFUNCTION("""COMPUTED_VALUE"""),"1.95B") -> 1.95B | D96: =IFERROR(__xludf.DUMMYFUNCTION("""COMPUTED_VALUE"""),"1.58B") -> 1.58B | E96: =IFERROR(__xludf.DUMMYFUNCTION("""COMPUTED_VALUE"""),"1.68B") -> 1.68B | F96: =IFERROR(__xludf.DUMMYFUNCTION("""COMPUTED_VALUE"""),"2.11B") -> 2.11B
A97: =IFERROR(__xludf.DUMMYFUNCTION("""COMPUTED_VALUE"""),"Other Long-Term Investments Other Long-Term Investments") -> Other Long-Term Investments Other Long-Term Investments | B97: =IFERROR(__xludf.DUMMYFUNCTION("""COMPUTED_VALUE"""),"1.08B") -> 1.08B | C97: =IFERROR(__xludf.DUMMYFUNCTION("""COMPUTED_VALUE"""),"1.95B") -> 1.95B | D97: =IFERROR(__xludf.DUMMYFUNCTION("""COMPUTED_VALUE"""),"1.17B") -> 1.17B | E97: =IFERROR(__xludf.DUMMYFUNCTION("""COMPUTED_VALUE"""),"1.41B") -> 1.41B | F97: =IFERROR(__xludf.DUMMYFUNCTION("""COMPUTED_VALUE"""),"1.89B") -> 1.89B
A98: =IFERROR(__xludf.DUMMYFUNCTION("""COMPUTED_VALUE"""),"Long-Term Note Receivables Long-Term Note Receivables") -> Long-Term Note Receivables Long-Term Note Receivables | B98: =IFERROR(__xludf.DUMMYFUNCTION("""COMPUTED_VALUE"""),"-") -> - | C98: =IFERROR(__xludf.DUMMYFUNCTION("""COMPUTED_VALUE"""),"-") -> - | D98: =IFERROR(__xludf.DUMMYFUNCTION("""COMPUTED_VALUE"""),"-") -> - | E98: =IFERROR(__xludf.DUMMYFUNCTION("""COMPUTED_VALUE"""),"-") -> - | F98: =IFERROR(__xludf.DUMMYFUNCTION("""COMPUTED_VALUE"""),"125M") -> 125M
A99: =IFERROR(__xludf.DUMMYFUNCTION("""COMPUTED_VALUE"""),"Intangible Assets Intangible Assets") -> Intangible Assets Intangible Assets | B99: =IFERROR(__xludf.DUMMYFUNCTION("""COMPUTED_VALUE"""),"44.2B") -> 44.2B | C99: =IFERROR(__xludf.DUMMYFUNCTION("""COMPUTED_VALUE"""),"41.47B") -> 41.47B | D99: =IFERROR(__xludf.DUMMYFUNCTION("""COMPUTED_VALUE"""),"39.21B") -> 39.21B | E99: =IFERROR(__xludf.DUMMYFUNCTION("""COMPUTED_VALUE"""),"38.04B") -> 38.04B | F99: =IFERROR(__xludf.DUMMYFUNCTION("""COMPUTED_VALUE"""),"48.26B") -> 48.26B
A100: =IFERROR(__xludf.DUMMYFUNCTION("""COMPUTED_VALUE"""),"Net Goodwill Net Goodwill") -> Net Goodwill Net Goodwill | B100: =IFERROR(__xludf.DUMMYFUNCTION("""COMPUTED_VALUE"""),"21.26B") -> 21.26B | C100: =IFERROR(__xludf.DUMMYFUNCTION("""COMPUTED_VALUE"""),"21.2B") -> 21.2B | D100: =IFERROR(__xludf.DUMMYFUNCTION("""COMPUTED_VALUE"""),"21.2B") -> 21.2B | E100: =IFERROR(__xludf.DUMMYFUNCTION("""COMPUTED_VALUE"""),"21.67B") -> 21.67B | F100: =IFERROR(__xludf.DUMMYFUNCTION("""COMPUTED_VALUE"""),"21.58B") -> 21.58B
A101: =IFERROR(__xludf.DUMMYFUNCTION("""COMPUTED_VALUE"""),"Net Other Intangibles Net Other Intangibles") -> Net Other Intangibles Net Other Intangibles | B101: =IFERROR(__xludf.DUMMYFUNCTION("""COMPUTED_VALUE"""),"22.93B") -> 22.93B | C101: =IFERROR(__xludf.DUMMYFUNCTION("""COMPUTED_VALUE"""),"20.27B") -> 20.27B | D101: =IFERROR(__xludf.DUMMYFUNCTION("""COMPUTED_VALUE"""),"18.01B") -> 18.01B | E101: =IFERROR(__xludf.DUMMYFUNCTION("""COMPUTED_VALUE"""),"16.37B") -> 16.37B | F101: =IFERROR(__xludf.DUMMYFUNCTION("""COMPUTED_VALUE"""),"26.68B") -> 26.68B
A102: =IFERROR(__xludf.DUMMYFUNCTION("""COMPUTED_VALUE"""),"Other Assets Other Assets") -> Other Assets Other Assets | B102: =IFERROR(__xludf.DUMMYFUNCTION("""COMPUTED_VALUE"""),"9.29B") -> 9.29B | C102: =IFERROR(__xludf.DUMMYFUNCTION("""COMPUTED_VALUE"""),"7.24B") -> 7.24B | D102: =IFERROR(__xludf.DUMMYFUNCTION("""COMPUTED_VALUE"""),"9.23B") -> 9.23B | E102: =IFERROR(__xludf.DUMMYFUNCTION("""COMPUTED_VALUE"""),"13.46B") -> 13.46B | F102: =IFERROR(__xludf.DUMMYFUNCTION("""COMPUTED_VALUE"""),"16.03B") -> 16.03B
A103: =IFERROR(__xludf.DUMMYFUNCTION("""COMPUTED_VALUE"""),"Total Assets Total Assets") -> Total Assets Total Assets | B103: =IFERROR(__xludf.DUMMYFUNCTION("""COMPUTED_VALUE"""),"105.69B") -> 105.69B | C103: =IFERROR(__xludf.DUMMYFUNCTION("""COMPUTED_VALUE"""),"109.16B") -> 109.16B | D103: =IFERROR(__xludf.DUMMYFUNCTION("""COMPUTED_VALUE"""),"106.68B") -> 106.68B | E103: =IFERROR(__xludf.DUMMYFUNCTION("""COMPUTED_VALUE"""),"117.11B") -> 117.11B | F103: =IFERROR(__xludf.DUMMYFUNCTION("""COMPUTED_VALUE"""),"136.87B") -> 136.87B
A104: =IFERROR(__xludf.DUMMYFUNCTION("""COMPUTED_VALUE"""),"Total Assets Growth Total Assets Growth") -> Total Assets Growth Total Assets Growth | B104: =IFERROR(__xludf.DUMMYFUNCTION("""COMPUTED_VALUE"""),"-") -> - | C104: =IFERROR(__xludf.DUMMYFUNCTION("""COMPUTED_VALUE"""),0.0328) -> 0.0328 | D104: =IFERROR(__xludf.DUMMYFUNCTION("""COMPUTED_VALUE"""),-0.0228) -> -0.0228 | E104: =IFERROR(__xludf.DUMMYFUNCTION("""COMPUTED_VALUE"""),0.0978) -> 0.0978 | F104: =IFERROR(__xludf.DUMMYFUNCTION("""COMPUTED_VALUE"""),0.1687) -> 0.1687
A111: =IFERROR(__xludf.DUMMYFUNCTION("IMPORTHTML(CONCAT(CONCAT(""https://www.marketwatch.com/investing/stock/"",'Income Statement'!D1),""/financials/cash-flow""),""table"",4) "),"Item Item") -> Item Item | B111: =IFERROR(__xludf.DUMMYFUNCTION("""COMPUTED_VALUE"""),2021.0) -> 2021 | C111: =IFERROR(__xludf.DUMMYFUNCTION("""COMPUTED_VALUE"""),2022.0) -> 2022 | D111: =IFERROR(__xludf.DUMMYFUNCTION("""COMPUTED_VALUE"""),2023.0) -> 2023 | E111: =IFERROR(__xludf.DUMMYFUNCTION("""COMPUTED_VALUE"""),2024.0) -> 2024 | F111: =IFERROR(__xludf.DUMMYFUNCTION("""COMPUTED_VALUE"""),2025.0) -> 2025 | G111: =IFERROR(__xludf.DUMMYFUNCTION("""COMPUTED_VALUE"""),"5-year trend") -> 5-year trend
A112: =IFERROR(__xludf.DUMMYFUNCTION("""COMPUTED_VALUE"""),"Net Income before Extraordinaries Net Income before Extraordinaries") -> Net Income before Extraordinaries Net Income before Extraordinaries | B112: =IFERROR(__xludf.DUMMYFUNCTION("""COMPUTED_VALUE"""),"12.36B") -> 12.36B | C112: =IFERROR(__xludf.DUMMYFUNCTION("""COMPUTED_VALUE"""),"14.53B") -> 14.53B | D112: =IFERROR(__xludf.DUMMYFUNCTION("""COMPUTED_VALUE"""),"377M") -> 377M | E112: =IFERROR(__xludf.DUMMYFUNCTION("""COMPUTED_VALUE"""),"17.13B") -> 17.13B | F112: =IFERROR(__xludf.DUMMYFUNCTION("""COMPUTED_VALUE"""),"18.26B") -> 18.26B
A113: =IFERROR(__xludf.DUMMYFUNCTION("""COMPUTED_VALUE"""),"Net Income Growth Net Income Growth") -> Net Income Growth Net Income Growth | B113: =IFERROR(__xludf.DUMMYFUNCTION("""COMPUTED_VALUE"""),"-") -> - | C113: =IFERROR(__xludf.DUMMYFUNCTION("""COMPUTED_VALUE"""),0.1754) -> 0.1754 | D113: =IFERROR(__xludf.DUMMYFUNCTION("""COMPUTED_VALUE"""),-0.974) -> -0.974 | E113: =IFERROR(__xludf.DUMMYFUNCTION("""COMPUTED_VALUE"""),44.4456) -> 44.4456 | F113: =IFERROR(__xludf.DUMMYFUNCTION("""COMPUTED_VALUE"""),0.066) -> 0.066
A114: =IFERROR(__xludf.DUMMYFUNCTION("""COMPUTED_VALUE"""),"Depreciation, Depletion & Amortization Depreciation, Depletion & Amortization") -> Depreciation, Depletion & Amortization Depreciation, Depletion & Amortization | B114: =IFERROR(__xludf.DUMMYFUNCTION("""COMPUTED_VALUE"""),"3.21B") -> 3.21B | C114: =IFERROR(__xludf.DUMMYFUNCTION("""COMPUTED_VALUE"""),"3.91B") -> 3.91B | D114: =IFERROR(__xludf.DUMMYFUNCTION("""COMPUTED_VALUE"""),"3.87B") -> 3.87B | E114: =IFERROR(__xludf.DUMMYFUNCTION("""COMPUTED_VALUE"""),"4.5B") -> 4.5B | F114: =IFERROR(__xludf.DUMMYFUNCTION("""COMPUTED_VALUE"""),"5.84B") -> 5.84B
A115: =IFERROR(__xludf.DUMMYFUNCTION("""COMPUTED_VALUE"""),"Depreciation and Depletion Depreciation and Depletion") -> Depreciation and Depletion Depreciation and Depletion | B115: =IFERROR(__xludf.DUMMYFUNCTION("""COMPUTED_VALUE"""),"1.58B") -> 1.58B | C115: =IFERROR(__xludf.DUMMYFUNCTION("""COMPUTED_VALUE"""),"1.82B") -> 1.82B | D115: =IFERROR(__xludf.DUMMYFUNCTION("""COMPUTED_VALUE"""),"1.83B") -> 1.83B | E115: =IFERROR(__xludf.DUMMYFUNCTION("""COMPUTED_VALUE"""),"2.1B") -> 2.1B | F115: =IFERROR(__xludf.DUMMYFUNCTION("""COMPUTED_VALUE"""),"3.05B") -> 3.05B
...
