Workbook

Sheet Income Statement
C1: Ticker Name: | D1: tsla
C3: Current Price | D3: =IFERROR(__xludf.DUMMYFUNCTION("GOOGLEFINANCE(D1,""PRICE"")"),393.45) -> 393.45 | E3: %-change from implied | F3: =D4/D3-1 -> -0.65042537
C4: Implied Share Value | D4: =DCF!C85 -> 137.54014 | E4: %-change (1 month) | F4: =IFERROR(__xludf.DUMMYFUNCTION("(D3-INDEX(GOOGLEFINANCE(D1,""price"",EDATE(TODAY(),-1)),2,2))/D3"),-0.0768839750921337) -> -0.076883975
C6: Chart (1 years) | D6: =IFERROR(__xludf.DUMMYFUNCTION("SPARKLINE(INDEX(GOOGLEFINANCE(D1,""price"",EDATE(today(),-12),today()), ,2),{""charttype"",""column"";""color"",""red""})"),"") | E6: %-change (6 months) | F6: =IFERROR(__xludf.DUMMYFUNCTION("(D3-INDEX(GOOGLEFINANCE(D1,""price"",EDATE(TODAY(),-6)),2,2))/D3"),-0.1479730588384802) -> -0.14797306
C8: Chart (5 years) | D8: =IFERROR(__xludf.DUMMYFUNCTION("SPARKLINE(INDEX(GOOGLEFINANCE(D1,""price"",EDATE(today(),-60),today()), ,2),{""charttype"",""column"";""color"",""red""})"),"") | E8: %-change (12 months) | F8: =IFERROR(__xludf.DUMMYFUNCTION("(D3-INDEX(GOOGLEFINANCE(D1,""price"",EDATE(TODAY(),-12)),2,2))/D3"),0.1985004447833269) -> 0.19850044
B11: Income Statement | C11: FY | H11: Future FY
C12: 2021 | D12: =C12+1 -> 2022 | E12: =D12+1 -> 2023 | F12: =E12+1 -> 2024 | G12: =F12+1 -> 2025 | H12: =G12+1 -> 2026 | I12: =H12+1 -> 2027 | J12: =I12+1 -> 2028 | K12: =J12+1 -> 2029 | L12: =K12+1 -> 2030
B15: Revenue | C15: =IFERROR(__xludf.DUMMYFUNCTION("IFERROR( LET( x, UPPER(SUBSTITUTE(TRIM(Data!B5),CHAR(160),"""")), base, VALUE(SUBSTITUTE(REGEXEXTRACT(x,""[0-9.,]+""),"","","""")), mult, IF(REGEXMATCH(x,""B""),1000000000, IF(REGEXMATCH(x,""M""),1000000, 1)), base * mult ), 0 )"),5.382E10) -> 53820000000 | D15: =IFERROR(__xludf.DUMMYFUNCTION("IFERROR( LET( x, UPPER(SUBSTITUTE(TRIM(Data!C5),CHAR(160),"""")), base, VALUE(SUBSTITUTE(REGEXEXTRACT(x,""[0-9.,]+""),"","","""")), mult, IF(REGEXMATCH(x,""B""),1000000000, IF(REGEXMATCH(x,""M""),1000000, 1)), base * mult ), 0 )"),8.146E10) -> 81460000000 | E15: =IFERROR(__xludf.DUMMYFUNCTION("IFERROR( LET( x, UPPER(SUBSTITUTE(TRIM(Data!D5),CHAR(160),"""")), base, VALUE(SUBSTITUTE(REGEXEXTRACT(x,""[0-9.,]+""),"","","""")), mult, IF(REGEXMATCH(x,""B""),1000000000, IF(REGEXMATCH(x,""M""),1000000, 1)), base * mult ), 0 )"),9.677E10) -> 96770000000 | F15: =IFERROR(__xludf.DUMMYFUNCTION("IFERROR( LET( x, UPPER(SUBSTITUTE(TRIM(Data!E5),CHAR(160),"""")), base, VALUE(SUBSTITUTE(REGEXEXTRACT(x,""[0-9.,]+""),"","","""")), mult, IF(REGEXMATCH(x,""B""),1000000000, IF(REGEXMATCH(x,""M""),1000000, 1)), base * mult ), 0 )"),9.769E10) -> 97690000000 | G15: =IFERROR(__xludf.DUMMYFUNCTION("IFERROR( LET( x, UPPER(SUBSTITUTE(TRIM(Data!F5),CHAR(160),"""")), base, VALUE(SUBSTITUTE(REGEXEXTRACT(x,""[0-9.,]+""),"","","""")), mult, IF(REGEXMATCH(x,""B""),1000000000, IF(REGEXMATCH(x,""M""),1000000, 1)), base * mult ), 0 )"),9.483E10) -> 94830000000 | H15: =DCF!H8 -> 102430000000 | I15: =H15*(1+H16) -> 118012412056 | J15: =I15*(1+I16) -> 135965336320 | K15: =J15*(1+J16) -> 156649392708 | L15: =K15*(1+K16) -> 180480061315
B16: Revenue Growth | C16: =Data!B6 -> - | D16: =Data!C6 -> 0.5135 | E16: =Data!D6 -> 0.188 | F16: =Data!E6 -> 0.0095 | G16: =Data!F6 -> -0.0293 | H16: =(G15/C15)^(1/4)-1 -> 0.15212742 | I16: =H16 -> 0.15212742 | J16: =I16 -> 0.15212742 | K16: =J16 -> 0.15212742 | L16: =K16 -> 0.15212742
B18: Cost of Sales | C18: =Data!B7 -> 40.22B | D18: =Data!C7 -> 60.61B | E18: =Data!D7 -> 79.11B | F18: =Data!E7 -> 80.24B | G18: =Data!F7 -> 77.73B | H18: =H15-H19 -> 84338980277 | I18: =I15-I19 -> 98861739463 | J18: =J15-J19 -> 115692943366 | K18: =K15-K19 -> 135189576396 | L18: =L15-L19 -> 157763270201
B19: Gross Profit | C19: =Data!B13 -> 13.61B | D19: =Data!C13 -> 20.85B | E19: =Data!D13 -> 17.66B | F19: =Data!E13 -> 17.45B | G19: =Data!F13 -> 17.09B | H19: =IFERROR(__xludf.DUMMYFUNCTION("REGEXREPLACE(G19,""B"","""")*1000000000*(1+H20)"),1.809101972289867E10) -> 18091019723 | I19: =H19*(1+I20) -> 19150672593 | J19: =I19*(1+J20) -> 20272392954 | K19: =J19*(1+K20) -> 21459816312 | L19: =K19*(1+L20) -> 22716791114
B20: Gross Profit Growth | C20: =Data!B14 -> - | D20: =Data!C14 -> 0.5326 | E20: =Data!D14 -> -0.1531 | F20: =Data!E14 -> -0.0119 | G20: =Data!F14 -> -0.0204 | H20: =IFERROR(__xludf.DUMMYFUNCTION("(REGEXREPLACE(G19,""B"","""")/REGEXREPLACE(C19,""B"",""""))^(1/4)-1"),0.058573418542929856) -> 0.058573419 | I20: =H20 -> 0.058573419 | J20: =I20 -> 0.058573419 | K20: =J20 -> 0.058573419 | L20: =K20 -> 0.058573419
B23: Selling, General & Admin | C23: =IFERROR(__xludf.DUMMYFUNCTION("IFERROR( LET( x, UPPER(SUBSTITUTE(TRIM(Data!B16),CHAR(160),"""")), base, VALUE(SUBSTITUTE(REGEXEXTRACT(x,""[0-9.,]+""),"","","""")), mult, IF(REGEXMATCH(x,""B""),1000000000, IF(REGEXMATCH(x,""M""),1000000, 1)), base * mult ), 0 )"),7.11E9) -> 7110000000 | D23: =IFERROR(__xludf.DUMMYFUNCTION("IFERROR( LET( x, UPPER(SUBSTITUTE(TRIM(Data!C16),CHAR(160),"""")), base, VALUE(SUBSTITUTE(REGEXEXTRACT(x,""[0-9.,]+""),"","","""")), mult, IF(REGEXMATCH(x,""B""),1000000000, IF(REGEXMATCH(x,""M""),1000000, 1)), base * mult ), 0 )"),7.02E9) -> 7020000000 | E23: =IFERROR(__xludf.DUMMYFUNCTION("IFERROR( LET( x, UPPER(SUBSTITUTE(TRIM(Data!D16),CHAR(160),"""")), base, VALUE(SUBSTITUTE(REGEXEXTRACT(x,""[0-9.,]+""),"","","""")), mult, IF(REGEXMATCH(x,""B""),1000000000, IF(REGEXMATCH(x,""M""),1000000, 1)), base * mult ), 0 )"),8.77E9) -> 8770000000 | F23: =IFERROR(__xludf.DUMMYFUNCTION("IFERROR( LET( x, UPPER(SUBSTITUTE(TRIM(Data!E16),CHAR(160),"""")), base, VALUE(SUBSTITUTE(REGEXEXTRACT(x,""[0-9.,]+""),"","","""")), mult, IF(REGEXMATCH(x,""B""),1000000000, IF(REGEXMATCH(x,""M""),1000000, 1)), base * mult ), 0 )"),9.69E9) -> 9690000000 | G23: =IFERROR(__xludf.DUMMYFUNCTION("IFERROR( LET( x, UPPER(SUBSTITUTE(TRIM(Data!F16),CHAR(160),"""")), base, VALUE(SUBSTITUTE(REGEXEXTRACT(x,""[0-9.,]+""),"","","""")), mult, IF(REGEXMATCH(x,""B""),1000000000, IF(REGEXMATCH(x,""M""),1000000, 1)), base * mult ), 0 )"),1.225E10) -> 12250000000 | H23: - | I23: - | J23: - | K23: - | L23: -
B24: Depreciation & Amortization Expense | C24: =Data!B10 -> 2.91B | D24: =Data!C10 -> 3.54B | E24: =Data!D10 -> 4.67B | F24: =Data!E10 -> 5.37B | G24: =Data!F10 -> 6.15B | H24: - | I24: - | J24: - | K24: - | L24: -
B25: Unusual Expense | C25: =Data!B21 -> (40M) | D25: =Data!C21 -> 150M | E25: =Data!D21 -> 4M | F25: =Data!E21 -> 670M | G25: =Data!F21 -> 562M | H25: - | I25: - | J25: - | K25: - | L25: -
B26: Operating Expenses | C26: =C23 -> 7110000000 | D26: =D23 -> 7020000000 | E26: =E23 -> 8770000000 | F26: =F23 -> 9690000000 | G26: =G23 -> 12250000000 | H26: =G26*(1+H27) -> 14034686328 | I26: =H26*(1+I27) -> 16079381251 | J26: =I26*(1+J27) -> 18421965078 | K26: =J26*(1+K27) -> 21105836850 | L26: =K26*(1+L27) -> 24180718357
B27: Operating Expenses Growth | C27: - | D27: =D26/C26-1 -> -0.012658228 | E27: =E26/D26-1 -> 0.24928775 | F27: =F26/E26-1 -> 0.10490308 | G27: =G26/F26-1 -> 0.26418989 | H27: =(G26/C26)^(1/4)-1 -> 0.14568868 | I27: =H27 -> 0.14568868 | J27: =I27 -> 0.14568868 | K27: =J27 -> 0.14568868 | L27: =K27 -> 0.14568868
B28: Operating Income | C28: =IFERROR(__xludf.DUMMYFUNCTION("(REGEXREPLACE(C19,""B"","""")*1000000000)-C26"),6.5E9) -> 6500000000 | D28: =IFERROR(__xludf.DUMMYFUNCTION("(REGEXREPLACE(D19,""B"","""")*1000000000)-D26"),1.383E10) -> 13830000000 | E28: =IFERROR(__xludf.DUMMYFUNCTION("(REGEXREPLACE(E19,""B"","""")*1000000000)-E26"),8.89E9) -> 8890000000 | F28: =IFERROR(__xludf.DUMMYFUNCTION("(REGEXREPLACE(F19,""B"","""")*1000000000)-F26"),7.76E9) -> 7760000000 | G28: =IFERROR(__xludf.DUMMYFUNCTION("(REGEXREPLACE(G19,""B"","""")*1000000000)-G26"),4.84E9) -> 4840000000 | H28: =G28*(1+H29) -> 4496021329 | I28: =H28*(1+I29) -> 4221449427 | J28: =I28*(1+J29) -> 4005860118 | K28: =J28*(1+K29) -> 3841339550 | L28: =K28*(1+L29) -> 3721989233
B29: Operating Income Growth | C29: - | D29: =D28/C28-1 -> 1.1276923 | E29: =E28/D28-1 -> -0.3571945 | F29: =F28/E28-1 -> -0.12710911 | G29: =G28/F28-1 -> -0.37628866 | H29: =(G28/C28)^(1/4)-1 -> -0.071069973 | I29: =H29+1% -> -0.061069973 | J29: =I29+1% -> -0.051069973 | K29: =J29+1% -> -0.041069973 | L29: =K29+1% -> -0.031069973
B32: EBIT | C32: =Data!B22 -> 6.54B | D32: =Data!C22 -> 13.68B | E32: =Data!D22 -> 8.89B | F32: =Data!E22 -> 7.09B | G32: =Data!F22 -> 4.29B | H32: - | I32: - | J32: - | K32: - | L32: -
B33: EBITDA | C33: =IFERROR(__xludf.DUMMYFUNCTION("IFERROR( LET( x, UPPER(SUBSTITUTE(TRIM(Data!B59),CHAR(160),"""")), base, VALUE(SUBSTITUTE(REGEXEXTRACT(x,""[0-9.,]+""),"","","""")), mult, IF(REGEXMATCH(x,""B""),1000000000, IF(REGEXMATCH(x,""M""),1000000, 1)), base * mult ), 0 )"),9.41E9) -> 9410000000 | D33: =IFERROR(__xludf.DUMMYFUNCTION("IFERROR( LET( x, UPPER(SUBSTITUTE(TRIM(Data!C59),CHAR(160),"""")), base, VALUE(SUBSTITUTE(REGEXEXTRACT(x,""[0-9.,]+""),"","","""")), mult, IF(REGEXMATCH(x,""B""),1000000000, IF(REGEXMATCH(x,""M""),1000000, 1)), base * mult ), 0 )"),1.738E10) -> 17380000000 | E33: =IFERROR(__xludf.DUMMYFUNCTION("IFERROR( LET( x, UPPER(SUBSTITUTE(TRIM(Data!D59),CHAR(160),"""")), base, VALUE(SUBSTITUTE(REGEXEXTRACT(x,""[0-9.,]+""),"","","""")), mult, IF(REGEXMATCH(x,""B""),1000000000, IF(REGEXMATCH(x,""M""),1000000, 1)), base * mult ), 0 )"),1.356E10) -> 13560000000 | F33: =IFERROR(__xludf.DUMMYFUNCTION("IFERROR( LET( x, UPPER(SUBSTITUTE(TRIM(Data!E59),CHAR(160),"""")), base, VALUE(SUBSTITUTE(REGEXEXTRACT(x,""[0-9.,]+""),"","","""")), mult, IF(REGEXMATCH(x,""B""),1000000000, IF(REGEXMATCH(x,""M""),1000000, 1)), base * mult ), 0 )"),1.313E10) -> 13130000000 | G33: =IFERROR(__xludf.DUMMYFUNCTION("IFERROR( LET( x, UPPER(SUBSTITUTE(TRIM(Data!F59),CHAR(160),"""")), base, VALUE(SUBSTITUTE(REGEXEXTRACT(x,""[0-9.,]+""),"","","""")), mult, IF(REGEXMATCH(x,""B""),1000000000, IF(REGEXMATCH(x,""M""),1000000, 1)), base * mult ), 0 )"),1.1E10) -> 11000000000 | H33: =G33*(1+H34) -> 11437825081 | I33: =H33*(1+I34) -> 11893076599 | J33: =I33*(1+J34) -> 12366448165 | K33: =J33*(1+K34) -> 12858660999 | L33: =K33*(1+L34) -> 13370465026
B34: EBITDA Growth | C34: =Data!B60 -> - | D34: =Data!C60 -> 0.847 | E34: =Data!D60 -> -0.2197 | F34: =Data!E60 -> -0.0317 | G34: =Data!F60 -> -0.1623 | H34: =(G33/C33)^(1/4)-1 -> 0.03980228 | I34: =H34 -> 0.03980228 | J34: =I34 -> 0.03980228 | K34: =J34 -> 0.03980228 | L34: =K34 -> 0.03980228
B35: EBITDA Margin | C35: =Data!B61 -> - | D35: =Data!C61 -> - | E35: =Data!D61 -> - | F35: =Data!E61 -> - | G35: =Data!F61 -> 0.116
B38: Pretax Income | C38: =Data!B30 -> 6.34B | D38: =Data!C30 -> 13.72B | E38: =Data!D30 -> 9.97B | F38: =Data!E30 -> 8.99B | G38: =Data!F30 -> 5.28B | H38: - | I38: - | J38: - | K38: - | L38: -
B39: Income Tax | C39: =Data!B33 -> 699M | D39: =Data!C33 -> 1.13B | E39: =Data!D33 -> (5B) | F39: =Data!E33 -> 1.84B | G39: =Data!F33 -> 1.42B | H39: - | I39: - | J39: - | K39: - | L39: -
B40: Net Income | C40: =IFERROR(__xludf.DUMMYFUNCTION("IFERROR( LET( x, UPPER(SUBSTITUTE(TRIM(Data!B43),CHAR(160),"""")), base, VALUE(SUBSTITUTE(REGEXEXTRACT(x,""[0-9.,]+""),"","","""")), mult, IF(REGEXMATCH(x,""B""),1000000000, IF(REGEXMATCH(x,""M""),1000000, 1)), base * mult ), 0 )"),5.52E9) -> 5520000000 | D40: =IFERROR(__xludf.DUMMYFUNCTION("IFERROR( LET( x, UPPER(SUBSTITUTE(TRIM(Data!C43),CHAR(160),"""")), base, VALUE(SUBSTITUTE(REGEXEXTRACT(x,""[0-9.,]+""),"","","""")), mult, IF(REGEXMATCH(x,""B""),1000000000, IF(REGEXMATCH(x,""M""),1000000, 1)), base * mult ), 0 )"),1.258E10) -> 12580000000 | E40: =IFERROR(__xludf.DUMMYFUNCTION("IFERROR( LET( x, UPPER(SUBSTITUTE(TRIM(Data!D43),CHAR(160),"""")), base, VALUE(SUBSTITUTE(REGEXEXTRACT(x,""[0-9.,]+""),"","","""")), mult, IF(REGEXMATCH(x,""B""),1000000000, IF(REGEXMATCH(x,""M""),1000000, 1)), base * mult ), 0 )"),1.5E10) -> 15000000000 | F40: =IFERROR(__xludf.DUMMYFUNCTION("IFERROR( LET( x, UPPER(SUBSTITUTE(TRIM(Data!E43),CHAR(160),"""")), base, VALUE(SUBSTITUTE(REGEXEXTRACT(x,""[0-9.,]+""),"","","""")), mult, IF(REGEXMATCH(x,""B""),1000000000, IF(REGEXMATCH(x,""M""),1000000, 1)), base * mult ), 0 )"),7.13E9) -> 7130000000 | G40: =IFERROR(__xludf.DUMMYFUNCTION("IFERROR( LET( x, UPPER(SUBSTITUTE(TRIM(Data!F43),CHAR(160),"""")), base, VALUE(SUBSTITUTE(REGEXEXTRACT(x,""[0-9.,]+""),"","","""")), mult, IF(REGEXMATCH(x,""B""),1000000000, IF(REGEXMATCH(x,""M""),1000000, 1)), base * mult ), 0 )"),3.79E9) -> 3790000000 | H40: =G40*(1+H42) -> 2778701667 | I40: =H40*(1+I42) -> 2037251439 | J40: =I40*(1+J42) -> 1259955129 | K40: =J40*(1+K42) -> 8.2429152e+08 | L40: =K40*(1+L42) -> 5.6443662e+08
B41: Net Income to Common | C41: =Data!B52 -> 5.52B | D41: =Data!C52 -> 12.58B | E41: =Data!D52 -> 15B | F41: =Data!E52 -> 7.13B | G41: =Data!F52 -> 3.79B | H41: - | I41: - | J41: - | K41: - | L41: -
B42: Net Income Growth | C42: =Data!B44 -> - | D42: =Data!C44 -> 1.2779 | E42: =Data!D44 -> 0.192 | F42: =Data!E44 -> -0.5246 | G42: =Data!F44 -> -0.4679 | H42: =AVERAGEIF(D42:G42,"<0.70") -> -0.26683333 | I42: =AVERAGEIF(E42:H42,"<0.80") -> -0.26683333 | J42: =AVERAGEIF(F42:I42,"<0.80") -> -0.38154167 | K42: =AVERAGEIF(G42:J42,"<0.80") -> -0.34577708 | L42: =AVERAGEIF(H42:K42,"<0.80") -> -0.31524635
B45: EPS (Diluted) | C45: =Data!B56 -> 1.63 | D45: =Data!C56 -> 3.62 | E45: =Data!D56 -> 4.3 | F45: =Data!E56 -> 2.04 | G45: =Data!F56 -> 1.08 | H45: =Forecast(H12,$C$45:G45,$C$12:G12) -> 1.73 | I45: =FORECAST(I12,$C$45:H45,$C$12:H12) -> 1.462 | J45: =FORECAST(J12,$C$45:I45,$C$12:I12) -> 1.194 | K45: =FORECAST(K12,$C$45:J45,$C$12:J12) -> 0.926 | L45: =FORECAST(L12,$C$45:K45,$C$12:K12) -> 0.658
B46: EPS (Diluted) Growth | C46: =Data!B57 -> - | D46: =Data!C57 -> 1.2204 | E46: =Data!D57 -> 0.1885 | F46: =Data!E57 -> -0.5264 | G46: =Data!F57 -> -0.4724 | H46: =H45/G45-1 -> 0.60185185 | I46: =I45/H45-1 -> -0.15491329 | J46: =J45/I45-1 -> -0.18331053 | K46: =K45/J45-1 -> -0.22445561 | L46: =L45/K45-1 -> -0.28941685
D1006: =1.56*L33 -> 20857925440

Sheet Balance Sheet
B2: Balance Sheet | C2: FY | H2: Future FY
C3: 2021 | D3: =C3+1 -> 2022 | E3: =D3+1 -> 2023 | F3: =E3+1 -> 2024 | G3: =F3+1 -> 2025 | H3: =G3+1 -> 2026 | I3: =H3+1 -> 2027 | J3: =I3+1 -> 2028 | K3: =J3+1 -> 2029 | L3: =K3+1 -> 2030
B6: Cash Only | C6: =IFERROR(__xludf.DUMMYFUNCTION("IFERROR( LET( x, UPPER(SUBSTITUTE(TRIM(Data!B71),CHAR(160),"""")), base, VALUE(SUBSTITUTE(REGEXEXTRACT(x,""[0-9.,]+""),"","","""")), mult, IF(REGEXMATCH(x,""B""),1000000000, IF(REGEXMATCH(x,""M""),1000000, 1)), base * mult ), 0 )"),1.792E10) -> 17920000000 | D6: =IFERROR(__xludf.DUMMYFUNCTION("IFERROR( LET( x, UPPER(SUBSTITUTE(TRIM(Data!C71),CHAR(160),"""")), base, VALUE(SUBSTITUTE(REGEXEXTRACT(x,""[0-9.,]+""),"","","""")), mult, IF(REGEXMATCH(x,""B""),1000000000, IF(REGEXMATCH(x,""M""),1000000, 1)), base * mult ), 0 )"),1.655E10) -> 16550000000 | E6: =IFERROR(__xludf.DUMMYFUNCTION("IFERROR( LET( x, UPPER(SUBSTITUTE(TRIM(Data!D71),CHAR(160),"""")), base, VALUE(SUBSTITUTE(REGEXEXTRACT(x,""[0-9.,]+""),"","","""")), mult, IF(REGEXMATCH(x,""B""),1000000000, IF(REGEXMATCH(x,""M""),1000000, 1)), base * mult ), 0 )"),1.6940000000000002E10) -> 16940000000 | F6: =IFERROR(__xludf.DUMMYFUNCTION("IFERROR( LET( x, UPPER(SUBSTITUTE(TRIM(Data!E71),CHAR(160),"""")), base, VALUE(SUBSTITUTE(REGEXEXTRACT(x,""[0-9.,]+""),"","","""")), mult, IF(REGEXMATCH(x,""B""),1000000000, IF(REGEXMATCH(x,""M""),1000000, 1)), base * mult ), 0 )"),1.6629999999999998E10) -> 16630000000 | G6: =IFERROR(__xludf.DUMMYFUNCTION("IFERROR( LET( x, UPPER(SUBSTITUTE(TRIM(Data!F71),CHAR(160),"""")), base, VALUE(SUBSTITUTE(REGEXEXTRACT(x,""[0-9.,]+""),"","","""")), mult, IF(REGEXMATCH(x,""B""),1000000000, IF(REGEXMATCH(x,""M""),1000000, 1)), base * mult ), 0 )"),1.6899999999999998E10) -> 16900000000 | H6: =FORECAST(H3,$C$6:G6,$C$3:G3) -> 16400000000 | I6: =FORECAST(I3,$C$6:H6,$C$3:H3) -> 16204000000 | J6: =FORECAST(J3,$C$6:I6,$C$3:I3) -> 16008000000 | K6: =FORECAST(K3,$C$6:J6,$C$3:J3) -> 15812000000 | L6: =FORECAST(L3,$C$6:K6,$C$3:K3) -> 15616000000
B7: Short-Term Investments | C7: =Data!B72:F72 -> - | D7: =Data!C72 -> - | E7: =Data!D72 -> - | F7: =Data!E72 -> - | G7: =Data!F72 -> - | H7: - | I7: - | J7: - | K7: - | L7: -
B8: Cash & Short Term Invesments | C8: =IFERROR(__xludf.DUMMYFUNCTION("IFERROR( LET( x, UPPER(SUBSTITUTE(TRIM(Data!B69),CHAR(160),"""")), base, VALUE(SUBSTITUTE(REGEXEXTRACT(x,""[0-9.,]+""),"","","""")), mult, IF(REGEXMATCH(x,""B""),1000000000, IF(REGEXMATCH(x,""M""),1000000, 1)), base * mult ), 0 )"),1.805E10) -> 18050000000 | D8: =IFERROR(__xludf.DUMMYFUNCTION("IFERROR( LET( x, UPPER(SUBSTITUTE(TRIM(Data!C69),CHAR(160),"""")), base, VALUE(SUBSTITUTE(REGEXEXTRACT(x,""[0-9.,]+""),"","","""")), mult, IF(REGEXMATCH(x,""B""),1000000000, IF(REGEXMATCH(x,""M""),1000000, 1)), base * mult ), 0 )"),2.248E10) -> 22480000000 | E8: =IFERROR(__xludf.DUMMYFUNCTION("IFERROR( LET( x, UPPER(SUBSTITUTE(TRIM(Data!D69),CHAR(160),"""")), base, VALUE(SUBSTITUTE(REGEXEXTRACT(x,""[0-9.,]+""),"","","""")), mult, IF(REGEXMATCH(x,""B""),1000000000, IF(REGEXMATCH(x,""M""),1000000, 1)), base * mult ), 0 )"),2.964E10) -> 29640000000 | F8: =IFERROR(__xludf.DUMMYFUNCTION("IFERROR( LET( x, UPPER(SUBSTITUTE(TRIM(Data!E69),CHAR(160),"""")), base, VALUE(SUBSTITUTE(REGEXEXTRACT(x,""[0-9.,]+""),"","","""")), mult, IF(REGEXMATCH(x,""B""),1000000000, IF(REGEXMATCH(x,""M""),1000000, 1)), base * mult ), 0 )"),3.706E10) -> 37060000000 | G8: =IFERROR(__xludf.DUMMYFUNCTION("IFERROR( LET( x, UPPER(SUBSTITUTE(TRIM(Data!F69),CHAR(160),"""")), base, VALUE(SUBSTITUTE(REGEXEXTRACT(x,""[0-9.,]+""),"","","""")), mult, IF(REGEXMATCH(x,""B""),1000000000, IF(REGEXMATCH(x,""M""),1000000, 1)), base * mult ), 0 )"),4.445E10) -> 44450000000 | H8: =H6 -> 16400000000 | I8: =I6 -> 16204000000 | J8: =J6 -> 16008000000 | K8: =K6 -> 15812000000 | L8: =L6 -> 15616000000
B9: Cash & Short Term Invesments Growth | C9: =Data!B70 -> - | D9: =Data!C70 -> 0.2452 | E9: =Data!D70 -> 0.3184 | F9: =Data!E70 -> 0.2504 | G9: =Data!F70 -> 0.1994 | H9: =H8/G8-1 -> -0.63104612 | I9: =I8/H8-1 -> -0.01195122 | J9: =J8/I8-1 -> -0.012095779 | K9: =K8/J8-1 -> -0.012243878 | L9: =L8/K8-1 -> -0.012395649
B12: Finished Goods | C12: =IFERROR(__xludf.DUMMYFUNCTION("IFERROR( LET( x, UPPER(SUBSTITUTE(TRIM(Data!B82),CHAR(160),"""")), base, VALUE(SUBSTITUTE(REGEXEXTRACT(x,""[0-9.,]+""),"","","""")), mult, IF(REGEXMATCH(x,""B""),1000000000, IF(REGEXMATCH(x,""M""),1000000, 1)), base * mult ), 0 )"),1.28E9) -> 1280000000 | D12: =IFERROR(__xludf.DUMMYFUNCTION("IFERROR( LET( x, UPPER(SUBSTITUTE(TRIM(Data!C82),CHAR(160),"""")), base, VALUE(SUBSTITUTE(REGEXEXTRACT(x,""[0-9.,]+""),"","","""")), mult, IF(REGEXMATCH(x,""B""),1000000000, IF(REGEXMATCH(x,""M""),1000000, 1)), base * mult ), 0 )"),3.48E9) -> 3480000000 | E12: =IFERROR(__xludf.DUMMYFUNCTION("IFERROR( LET( x, UPPER(SUBSTITUTE(TRIM(Data!D82),CHAR(160),"""")), base, VALUE(SUBSTITUTE(REGEXEXTRACT(x,""[0-9.,]+""),"","","""")), mult, IF(REGEXMATCH(x,""B""),1000000000, IF(REGEXMATCH(x,""M""),1000000, 1)), base * mult ), 0 )"),5.05E9) -> 5050000000 | F12: =IFERROR(__xludf.DUMMYFUNCTION("IFERROR( LET( x, UPPER(SUBSTITUTE(TRIM(Data!E82),CHAR(160),"""")), base, VALUE(SUBSTITUTE(REGEXEXTRACT(x,""[0-9.,]+""),"","","""")), mult, IF(REGEXMATCH(x,""B""),1000000000, IF(REGEXMATCH(x,""M""),1000000, 1)), base * mult ), 0 )"),3.94E9) -> 3940000000 | G12: =IFERROR(__xludf.DUMMYFUNCTION("IFERROR( LET( x, UPPER(SUBSTITUTE(TRIM(Data!F82),CHAR(160),"""")), base, VALUE(SUBSTITUTE(REGEXEXTRACT(x,""[0-9.,]+""),"","","""")), mult, IF(REGEXMATCH(x,""B""),1000000000, IF(REGEXMATCH(x,""M""),1000000, 1)), base * mult ), 0 )"),4.85E9) -> 4850000000 | H12: =AVERAGE(C12:G12) -> 3720000000 | I12: =AVERAGE(D12:H12) -> 4208000000 | J12: =AVERAGE(E12:I12) -> 4353600000 | K12: =AVERAGE(F12:J12) -> 4214320000 | L12: =AVERAGE(G12:K12) -> 4269184000
B13: Work in Progress | C13: =IFERROR(__xludf.DUMMYFUNCTION("regexreplace(Data!B83,""M"","""")*1000000"),"#VALUE!") -> #VALUE! | D13: =IFERROR(__xludf.DUMMYFUNCTION("IFERROR( LET( x, UPPER(SUBSTITUTE(TRIM(Data!C83),CHAR(160),"""")), base, VALUE(SUBSTITUTE(REGEXEXTRACT(x,""[0-9.,]+""),"","","""")), mult, IF(REGEXMATCH(x,""B""),1000000000, IF(REGEXMATCH(x,""M""),1000000, 1)), base * mult ), 0 )"),2.39E9) -> 2390000000 | E13: =IFERROR(__xludf.DUMMYFUNCTION("IFERROR( LET( x, UPPER(SUBSTITUTE(TRIM(Data!D83),CHAR(160),"""")), base, VALUE(SUBSTITUTE(REGEXEXTRACT(x,""[0-9.,]+""),"","","""")), mult, IF(REGEXMATCH(x,""B""),1000000000, IF(REGEXMATCH(x,""M""),1000000, 1)), base * mult ), 0 )"),2.02E9) -> 2020000000 | F13: =IFERROR(__xludf.DUMMYFUNCTION("IFERROR( LET( x, UPPER(SUBSTITUTE(TRIM(Data!E83),CHAR(160),"""")), base, VALUE(SUBSTITUTE(REGEXEXTRACT(x,""[0-9.,]+""),"","","""")), mult, IF(REGEXMATCH(x,""B""),1000000000, IF(REGEXMATCH(x,""M""),1000000, 1)), base * mult ), 0 )"),1.53E9) -> 1530000000 | G13: =IFERROR(__xludf.DUMMYFUNCTION("IFERROR( LET( x, UPPER(SUBSTITUTE(TRIM(Data!F83),CHAR(160),"""")), base, VALUE(SUBSTITUTE(REGEXEXTRACT(x,""[0-9.,]+""),"","","""")), mult, IF(REGEXMATCH(x,""B""),1000000000, IF(REGEXMATCH(x,""M""),1000000, 1)), base * mult ), 0 )"),1.73E9) -> 1730000000 | H13: =AVERAGE(C13:G13) -> #VALUE! | I13: =AVERAGE(D13:H13) -> #VALUE! | J13: =AVERAGE(E13:I13) -> #VALUE! | K13: =AVERAGE(F13:J13) -> #VALUE! | L13: =AVERAGE(G13:K13) -> #VALUE!
B14: Raw Materials | C14: =IFERROR(__xludf.DUMMYFUNCTION("IFERROR( LET( x, UPPER(SUBSTITUTE(TRIM(Data!B84),CHAR(160),"""")), base, VALUE(SUBSTITUTE(REGEXEXTRACT(x,""[0-9.,]+""),"","","""")), mult, IF(REGEXMATCH(x,""B""),1000000000, IF(REGEXMATCH(x,""M""),1000000, 1)), base * mult ), 0 )"),3.39E9) -> 3390000000 | D14: =IFERROR(__xludf.DUMMYFUNCTION("IFERROR( LET( x, UPPER(SUBSTITUTE(TRIM(Data!C84),CHAR(160),"""")), base, VALUE(SUBSTITUTE(REGEXEXTRACT(x,""[0-9.,]+""),"","","""")), mult, IF(REGEXMATCH(x,""B""),1000000000, IF(REGEXMATCH(x,""M""),1000000, 1)), base * mult ), 0 )"),6.98E9) -> 6980000000 | E14: =IFERROR(__xludf.DUMMYFUNCTION("IFERROR( LET( x, UPPER(SUBSTITUTE(TRIM(Data!D84),CHAR(160),"""")), base, VALUE(SUBSTITUTE(REGEXEXTRACT(x,""[0-9.,]+""),"","","""")), mult, IF(REGEXMATCH(x,""B""),1000000000, IF(REGEXMATCH(x,""M""),1000000, 1)), base * mult ), 0 )"),6.56E9) -> 6560000000 | F14: =IFERROR(__xludf.DUMMYFUNCTION("IFERROR( LET( x, UPPER(SUBSTITUTE(TRIM(Data!E84),CHAR(160),"""")), base, VALUE(SUBSTITUTE(REGEXEXTRACT(x,""[0-9.,]+""),"","","""")), mult, IF(REGEXMATCH(x,""B""),1000000000, IF(REGEXMATCH(x,""M""),1000000, 1)), base * mult ), 0 )"),6.55E9) -> 6550000000 | G14: =IFERROR(__xludf.DUMMYFUNCTION("IFERROR( LET( x, UPPER(SUBSTITUTE(TRIM(Data!F84),CHAR(160),"""")), base, VALUE(SUBSTITUTE(REGEXEXTRACT(x,""[0-9.,]+""),"","","""")), mult, IF(REGEXMATCH(x,""B""),1000000000, IF(REGEXMATCH(x,""M""),1000000, 1)), base * mult ), 0 )"),5.82E9) -> 5820000000 | H14: =AVERAGE(C14:G14) -> 5860000000 | I14: =AVERAGE(D14:H14) -> 6354000000 | J14: =AVERAGE(E14:I14) -> 6228800000 | K14: =AVERAGE(F14:J14) -> 6162560000 | L14: =AVERAGE(G14:K14) -> 6085072000
B15: Inventories | C15: =IFERROR(__xludf.DUMMYFUNCTION("IFERROR( LET( x, UPPER(SUBSTITUTE(TRIM(Data!B81),CHAR(160),"""")), base, VALUE(SUBSTITUTE(REGEXEXTRACT(x,""[0-9.,]+""),"","","""")), mult, IF(REGEXMATCH(x,""B""),1000000000, IF(REGEXMATCH(x,""M""),1000000, 1)), base * mult ), 0 )"),5.76E9) -> 5760000000 | D15: =IFERROR(__xludf.DUMMYFUNCTION("IFERROR( LET( x, UPPER(SUBSTITUTE(TRIM(Data!C81),CHAR(160),"""")), base, VALUE(SUBSTITUTE(REGEXEXTRACT(x,""[0-9.,]+""),"","","""")), mult, IF(REGEXMATCH(x,""B""),1000000000, IF(REGEXMATCH(x,""M""),1000000, 1)), base * mult ), 0 )"),1.284E10) -> 12840000000 | E15: =IFERROR(__xludf.DUMMYFUNCTION("IFERROR( LET( x, UPPER(SUBSTITUTE(TRIM(Data!D81),CHAR(160),"""")), base, VALUE(SUBSTITUTE(REGEXEXTRACT(x,""[0-9.,]+""),"","","""")), mult, IF(REGEXMATCH(x,""B""),1000000000, IF(REGEXMATCH(x,""M""),1000000, 1)), base * mult ), 0 )"),1.363E10) -> 13630000000 | F15: =IFERROR(__xludf.DUMMYFUNCTION("IFERROR( LET( x, UPPER(SUBSTITUTE(TRIM(Data!E81),CHAR(160),"""")), base, VALUE(SUBSTITUTE(REGEXEXTRACT(x,""[0-9.,]+""),"","","""")), mult, IF(REGEXMATCH(x,""B""),1000000000, IF(REGEXMATCH(x,""M""),1000000, 1)), base * mult ), 0 )"),1.202E10) -> 12020000000 | G15: =IFERROR(__xludf.DUMMYFUNCTION("IFERROR( LET( x, UPPER(SUBSTITUTE(TRIM(Data!F81),CHAR(160),"""")), base, VALUE(SUBSTITUTE(REGEXEXTRACT(x,""[0-9.,]+""),"","","""")), mult, IF(REGEXMATCH(x,""B""),1000000000, IF(REGEXMATCH(x,""M""),1000000, 1)), base * mult ), 0 )"),1.239E10) -> 12390000000 | H15: =AVERAGE(C15:G15) -> 11328000000 | I15: =AVERAGE(D15:H15) -> 12441600000 | J15: =AVERAGE(E15:I15) -> 12361920000 | K15: =AVERAGE(F15:J15) -> 12108304000 | L15: =AVERAGE(G15:K15) -> 12125964800
B18: Accounts Receivables, Net | C18: =IFERROR(__xludf.DUMMYFUNCTION("IFERROR( LET( x, UPPER(SUBSTITUTE(TRIM(Data!B76),CHAR(160),"""")), base, VALUE(SUBSTITUTE(REGEXEXTRACT(x,""[0-9.,]+""),"","","""")), mult, IF(REGEXMATCH(x,""B""),1000000000, IF(REGEXMATCH(x,""M""),1000000, 1)), base * mult ), 0 )"),1.91E9) -> 1910000000 | D18: =IFERROR(__xludf.DUMMYFUNCTION("IFERROR( LET( x, UPPER(SUBSTITUTE(TRIM(Data!C76),CHAR(160),"""")), base, VALUE(SUBSTITUTE(REGEXEXTRACT(x,""[0-9.,]+""),"","","""")), mult, IF(REGEXMATCH(x,""B""),1000000000, IF(REGEXMATCH(x,""M""),1000000, 1)), base * mult ), 0 )"),2.95E9) -> 2950000000 | E18: =IFERROR(__xludf.DUMMYFUNCTION("IFERROR( LET( x, UPPER(SUBSTITUTE(TRIM(Data!D76),CHAR(160),"""")), base, VALUE(SUBSTITUTE(REGEXEXTRACT(x,""[0-9.,]+""),"","","""")), mult, IF(REGEXMATCH(x,""B""),1000000000, IF(REGEXMATCH(x,""M""),1000000, 1)), base * mult ), 0 )"),3.51E9) -> 3510000000 | F18: =IFERROR(__xludf.DUMMYFUNCTION("IFERROR( LET( x, UPPER(SUBSTITUTE(TRIM(Data!E76),CHAR(160),"""")), base, VALUE(SUBSTITUTE(REGEXEXTRACT(x,""[0-9.,]+""),"","","""")), mult, IF(REGEXMATCH(x,""B""),1000000000, IF(REGEXMATCH(x,""M""),1000000, 1)), base * mult ), 0 )"),4.42E9) -> 4420000000 | G18: =IFERROR(__xludf.DUMMYFUNCTION("IFERROR( LET( x, UPPER(SUBSTITUTE(TRIM(Data!F76),CHAR(160),"""")), base, VALUE(SUBSTITUTE(REGEXEXTRACT(x,""[0-9.,]+""),"","","""")), mult, IF(REGEXMATCH(x,""B""),1000000000, IF(REGEXMATCH(x,""M""),1000000, 1)), base * mult ), 0 )"),4.58E9) -> 4580000000 | H18: =FORECAST(H3,$C$18:G18,$C$3:G3) -> 5517000000 | I18: =FORECAST(I3,$C$18:H18,$C$3:H3) -> 6198000000 | J18: =FORECAST(J3,$C$18:I18,$C$3:I3) -> 6879000000 | K18: =FORECAST(K3,$C$18:J18,$C$3:J3) -> 7560000000 | L18: =FORECAST(L3,$C$18:K18,$C$3:K3) -> 8241000000
B19: Other Receivable | C19: =Data!B79 -> - | D19: =Data!C79 -> - | E19: =Data!D79 -> - | F19: =Data!E79 -> - | G19: =Data!F79 -> 130M | H19: - | I19: - | J19: - | K19: - | L19: -
B20: Total Accounts Receivable | C20: =IFERROR(__xludf.DUMMYFUNCTION("IFERROR( LET( x, UPPER(SUBSTITUTE(TRIM(Data!B74),CHAR(160),"""")), base, VALUE(SUBSTITUTE(REGEXEXTRACT(x,""[0-9.,]+""),"","","""")), mult, IF(REGEXMATCH(x,""B""),1000000000, IF(REGEXMATCH(x,""M""),1000000, 1)), base * mult ), 0 )"),1.91E9) -> 1910000000 | D20: =IFERROR(__xludf.DUMMYFUNCTION("IFERROR( LET( x, UPPER(SUBSTITUTE(TRIM(Data!C74),CHAR(160),"""")), base, VALUE(SUBSTITUTE(REGEXEXTRACT(x,""[0-9.,]+""),"","","""")), mult, IF(REGEXMATCH(x,""B""),1000000000, IF(REGEXMATCH(x,""M""),1000000, 1)), base * mult ), 0 )"),2.95E9) -> 2950000000 | E20: =IFERROR(__xludf.DUMMYFUNCTION("IFERROR( LET( x, UPPER(SUBSTITUTE(TRIM(Data!D74),CHAR(160),"""")), base, VALUE(SUBSTITUTE(REGEXEXTRACT(x,""[0-9.,]+""),"","","""")), mult, IF(REGEXMATCH(x,""B""),1000000000, IF(REGEXMATCH(x,""M""),1000000, 1)), base * mult ), 0 )"),3.51E9) -> 3510000000 | F20: =IFERROR(__xludf.DUMMYFUNCTION("IFERROR( LET( x, UPPER(SUBSTITUTE(TRIM(Data!E74),CHAR(160),"""")), base, VALUE(SUBSTITUTE(REGEXEXTRACT(x,""[0-9.,]+""),"","","""")), mult, IF(REGEXMATCH(x,""B""),1000000000, IF(REGEXMATCH(x,""M""),1000000, 1)), base * mult ), 0 )"),4.42E9) -> 4420000000 | G20: =IFERROR(__xludf.DUMMYFUNCTION("IFERROR( LET( x, UPPER(SUBSTITUTE(TRIM(Data!F74),CHAR(160),"""")), base, VALUE(SUBSTITUTE(REGEXEXTRACT(x,""[0-9.,]+""),"","","""")), mult, IF(REGEXMATCH(x,""B""),1000000000, IF(REGEXMATCH(x,""M""),1000000, 1)), base * mult ), 0 )"),4.71E9) -> 4710000000 | H20: =FORECAST(H3,$C$20:G20,$C$3:G3) -> 5621000000 | I20: =FORECAST(I3,$C$20:H20,$C$3:H3) -> 6328000000 | J20: =FORECAST(J3,$C$20:I20,$C$3:I3) -> 7035000000 | K20: =FORECAST(K3,$C$20:J20,$C$3:J3) -> 7742000000 | L20: =FORECAST(L3,$C$20:K20,$C$3:K3) -> 8449000000
B21: Total Accounts Receivable Growth | C21: =Data!B75 -> - | D21: =Data!C75 -> 0.5431 | E21: =Data!D75 -> 0.1883 | F21: =Data!E75 -> 0.2594 | G21: =Data!F75 -> 0.0652 | H21: =H20/G20-1 -> 0.19341826 | I21: =I20/H20-1 -> 0.12577833 | J21: =J20/I20-1 -> 0.11172566 | K21: =K20/J20-1 -> 0.10049751 | L21: =L20/K20-1 -> 0.091320072
B24: Other Current Assets | C24: =IFERROR(__xludf.DUMMYFUNCTION("IFERROR( LET( x, UPPER(SUBSTITUTE(TRIM(Data!B86),CHAR(160),"""")), base, VALUE(SUBSTITUTE(REGEXEXTRACT(x,""[0-9.,]+""),"","","""")), mult, IF(REGEXMATCH(x,""B""),1000000000, IF(REGEXMATCH(x,""M""),1000000, 1)), base * mult ), 0 )"),1.38E9) -> 1380000000 | D24: =IFERROR(__xludf.DUMMYFUNCTION("IFERROR( LET( x, UPPER(SUBSTITUTE(TRIM(Data!C86),CHAR(160),"""")), base, VALUE(SUBSTITUTE(REGEXEXTRACT(x,""[0-9.,]+""),"","","""")), mult, IF(REGEXMATCH(x,""B""),1000000000, IF(REGEXMATCH(x,""M""),1000000, 1)), base * mult ), 0 )"),2.65E9) -> 2650000000 | E24: =IFERROR(__xludf.DUMMYFUNCTION("IFERROR( LET( x, UPPER(SUBSTITUTE(TRIM(Data!D86),CHAR(160),"""")), base, VALUE(SUBSTITUTE(REGEXEXTRACT(x,""[0-9.,]+""),"","","""")), mult, IF(REGEXMATCH(x,""B""),1000000000, IF(REGEXMATCH(x,""M""),1000000, 1)), base * mult ), 0 )"),2.85E9) -> 2850000000 | F24: =IFERROR(__xludf.DUMMYFUNCTION("IFERROR( LET( x, UPPER(SUBSTITUTE(TRIM(Data!E86),CHAR(160),"""")), base, VALUE(SUBSTITUTE(REGEXEXTRACT(x,""[0-9.,]+""),"","","""")), mult, IF(REGEXMATCH(x,""B""),1000000000, IF(REGEXMATCH(x,""M""),1000000, 1)), base * mult ), 0 )"),4.87E9) -> 4870000000 | G24: =IFERROR(__xludf.DUMMYFUNCTION("IFERROR( LET( x, UPPER(SUBSTITUTE(TRIM(Data!F86),CHAR(160),"""")), base, VALUE(SUBSTITUTE(REGEXEXTRACT(x,""[0-9.,]+""),"","","""")), mult, IF(REGEXMATCH(x,""B""),1000000000, IF(REGEXMATCH(x,""M""),1000000, 1)), base * mult ), 0 )"),7.1E9) -> 7100000000 | H24: =AVERAGE(C24:G24) -> 3770000000 | I24: =AVERAGE(D24:H24) -> 4248000000 | J24: =AVERAGE(E24:I24) -> 4567600000 | K24: =AVERAGE(F24:J24) -> 4911120000 | L24: =AVERAGE(G24:K24) -> 4919344000
B25: Total Current Assets | C25: =IFERROR(__xludf.DUMMYFUNCTION("IFERROR( LET( x, UPPER(SUBSTITUTE(TRIM(Data!B88),CHAR(160),"""")), base, VALUE(SUBSTITUTE(REGEXEXTRACT(x,""[0-9.,]+""),"","","""")), mult, IF(REGEXMATCH(x,""B""),1000000000, IF(REGEXMATCH(x,""M""),1000000, 1)), base * mult ), 0 )"),2.71E10) -> 27100000000 | D25: =IFERROR(__xludf.DUMMYFUNCTION("IFERROR( LET( x, UPPER(SUBSTITUTE(TRIM(Data!C88),CHAR(160),"""")), base, VALUE(SUBSTITUTE(REGEXEXTRACT(x,""[0-9.,]+""),"","","""")), mult, IF(REGEXMATCH(x,""B""),1000000000, IF(REGEXMATCH(x,""M""),1000000, 1)), base * mult ), 0 )"),4.092E10) -> 40920000000 | E25: =IFERROR(__xludf.DUMMYFUNCTION("IFERROR( LET( x, UPPER(SUBSTITUTE(TRIM(Data!D88),CHAR(160),"""")), base, VALUE(SUBSTITUTE(REGEXEXTRACT(x,""[0-9.,]+""),"","","""")), mult, IF(REGEXMATCH(x,""B""),1000000000, IF(REGEXMATCH(x,""M""),1000000, 1)), base * mult ), 0 )"),4.962E10) -> 49620000000 | F25: =IFERROR(__xludf.DUMMYFUNCTION("IFERROR( LET( x, UPPER(SUBSTITUTE(TRIM(Data!E88),CHAR(160),"""")), base, VALUE(SUBSTITUTE(REGEXEXTRACT(x,""[0-9.,]+""),"","","""")), mult, IF(REGEXMATCH(x,""B""),1000000000, IF(REGEXMATCH(x,""M""),1000000, 1)), base * mult ), 0 )"),5.836E10) -> 58360000000 | G25: =IFERROR(__xludf.DUMMYFUNCTION("IFERROR( LET( x, UPPER(SUBSTITUTE(TRIM(Data!F88),CHAR(160),"""")), base, VALUE(SUBSTITUTE(REGEXEXTRACT(x,""[0-9.,]+""),"","","""")), mult, IF(REGEXMATCH(x,""B""),1000000000, IF(REGEXMATCH(x,""M""),1000000, 1)), base * mult ), 0 )"),6.864E10) -> 68640000000 | H25: =FORECAST(H3,$C$25:G25,$C$3:G3) -> 79084000000 | I25: =FORECAST(I3,$C$25:H25,$C$3:H3) -> 89136000000 | J25: =FORECAST(J3,$C$25:I25,$C$3:I3) -> 99188000000 | K25: =FORECAST(K3,$C$25:J25,$C$3:J3) -> 109240000000 | L25: =FORECAST(L3,$C$25:K25,$C$3:K3) -> 119292000000
B26: Total Current Assets Growth | C26: - | D26: =D25/C25-1 -> 0.5099631 | E26: =E25/D25-1 -> 0.21260997 | F26: =F25/E25-1 -> 0.17613865 | G26: =G25/F25-1 -> 0.17614805 | H26: =H25/G25-1 -> 0.15215618 | I26: =I25/H25-1 -> 0.12710536 | J26: =J25/I25-1 -> 0.1127715 | K26: =K25/J25-1 -> 0.1013429 | L26: =L25/K25-1 -> 0.092017576
B29: Property, Plant & Equipment | C29: =IFERROR(__xludf.DUMMYFUNCTION("IFERROR( LET( x, UPPER(SUBSTITUTE(TRIM(Data!B90),CHAR(160),"""")), base, VALUE(SUBSTITUTE(REGEXEXTRACT(x,""[0-9.,]+""),"","","""")), mult, IF(REGEXMATCH(x,""B""),1000000000, IF(REGEXMATCH(x,""M""),1000000, 1)), base * mult ), 0 )"),3.987E10) -> 39870000000 | D29: =IFERROR(__xludf.DUMMYFUNCTION("IFERROR( LET( x, UPPER(SUBSTITUTE(TRIM(Data!C90),CHAR(160),"""")), base, VALUE(SUBSTITUTE(REGEXEXTRACT(x,""[0-9.,]+""),"","","""")), mult, IF(REGEXMATCH(x,""B""),1000000000, IF(REGEXMATCH(x,""M""),1000000, 1)), base * mult ), 0 )"),4.813E10) -> 48130000000 | E29: =IFERROR(__xludf.DUMMYFUNCTION("IFERROR( LET( x, UPPER(SUBSTITUTE(TRIM(Data!D90),CHAR(160),"""")), base, VALUE(SUBSTITUTE(REGEXEXTRACT(x,""[0-9.,]+""),"","","""")), mult, IF(REGEXMATCH(x,""B""),1000000000, IF(REGEXMATCH(x,""M""),1000000, 1)), base * mult ), 0 )"),6.02E10) -> 60200000000 | F29: =IFERROR(__xludf.DUMMYFUNCTION("IFERROR( LET( x, UPPER(SUBSTITUTE(TRIM(Data!E90),CHAR(160),"""")), base, VALUE(SUBSTITUTE(REGEXEXTRACT(x,""[0-9.,]+""),"","","""")), mult, IF(REGEXMATCH(x,""B""),1000000000, IF(REGEXMATCH(x,""M""),1000000, 1)), base * mult ), 0 )"),7.04E10) -> 70400000000 | G29: =IFERROR(__xludf.DUMMYFUNCTION("IFERROR( LET( x, UPPER(SUBSTITUTE(TRIM(Data!F90),CHAR(160),"""")), base, VALUE(SUBSTITUTE(REGEXEXTRACT(x,""[0-9.,]+""),"","","""")), mult, IF(REGEXMATCH(x,""B""),1000000000, IF(REGEXMATCH(x,""M""),1000000, 1)), base * mult ), 0 )"),7.963E10) -> 79630000000 | H29: =AVERAGE(C29:G29) -> 59646000000 | I29: =AVERAGE(D29:H29) -> 63601200000 | J29: =AVERAGE(E29:I29) -> 66695440000 | K29: =AVERAGE(F29:J29) -> 67994528000 | L29: =AVERAGE(G29:K29) -> 67513433600
B30: Accumulated Depreciation | C30: =IFERROR(__xludf.DUMMYFUNCTION("IFERROR( LET( x, UPPER(SUBSTITUTE(TRIM(Data!B95),CHAR(160),"""")), base, VALUE(SUBSTITUTE(REGEXEXTRACT(x,""[0-9.,]+""),"","","""")), mult, IF(REGEXMATCH(x,""B""),1000000000, IF(REGEXMATCH(x,""M""),1000000, 1)), base * mult ), 0 )"),8.69E9) -> 8690000000 | D30: =IFERROR(__xludf.DUMMYFUNCTION("IFERROR( LET( x, UPPER(SUBSTITUTE(TRIM(Data!C95),CHAR(160),"""")), base, VALUE(SUBSTITUTE(REGEXEXTRACT(x,""[0-9.,]+""),"","","""")), mult, IF(REGEXMATCH(x,""B""),1000000000, IF(REGEXMATCH(x,""M""),1000000, 1)), base * mult ), 0 )"),1.15E10) -> 11500000000 | E30: =IFERROR(__xludf.DUMMYFUNCTION("IFERROR( LET( x, UPPER(SUBSTITUTE(TRIM(Data!D95),CHAR(160),"""")), base, VALUE(SUBSTITUTE(REGEXEXTRACT(x,""[0-9.,]+""),"","","""")), mult, IF(REGEXMATCH(x,""B""),1000000000, IF(REGEXMATCH(x,""M""),1000000, 1)), base * mult ), 0 )"),1.508E10) -> 15080000000 | F30: =IFERROR(__xludf.DUMMYFUNCTION("IFERROR( LET( x, UPPER(SUBSTITUTE(TRIM(Data!E95),CHAR(160),"""")), base, VALUE(SUBSTITUTE(REGEXEXTRACT(x,""[0-9.,]+""),"","","""")), mult, IF(REGEXMATCH(x,""B""),1000000000, IF(REGEXMATCH(x,""M""),1000000, 1)), base * mult ), 0 )"),1.89E10) -> 18900000000 | G30: =IFERROR(__xludf.DUMMYFUNCTION("IFERROR( LET( x, UPPER(SUBSTITUTE(TRIM(Data!F95),CHAR(160),"""")), base, VALUE(SUBSTITUTE(REGEXEXTRACT(x,""[0-9.,]+""),"","","""")), mult, IF(REGEXMATCH(x,""B""),1000000000, IF(REGEXMATCH(x,""M""),1000000, 1)), base * mult ), 0 )"),2.344E10) -> 23440000000 | H30: =AVERAGE(C30:G30) -> 15522000000 | I30: =AVERAGE(D30:H30) -> 16888400000 | J30: =AVERAGE(E30:I30) -> 17966080000 | K30: =AVERAGE(F30:J30) -> 18543296000 | L30: =AVERAGE(G30:K30) -> 18471955200
B31: Net Property, Plant & Equipment | C31: =IFERROR(__xludf.DUMMYFUNCTION("IFERROR( LET( x, UPPER(SUBSTITUTE(TRIM(Data!B89),CHAR(160),"""")), base, VALUE(SUBSTITUTE(REGEXEXTRACT(x,""[0-9.,]+""),"","","""")), mult, IF(REGEXMATCH(x,""B""),1000000000, IF(REGEXMATCH(x,""M""),1000000, 1)), base * mult ), 0 )"),3.118E10) -> 31180000000 | D31: =IFERROR(__xludf.DUMMYFUNCTION("IFERROR( LET( x, UPPER(SUBSTITUTE(TRIM(Data!C89),CHAR(160),"""")), base, VALUE(SUBSTITUTE(REGEXEXTRACT(x,""[0-9.,]+""),"","","""")), mult, IF(REGEXMATCH(x,""B""),1000000000, IF(REGEXMATCH(x,""M""),1000000, 1)), base * mult ), 0 )"),3.664E10) -> 36640000000 | E31: =IFERROR(__xludf.DUMMYFUNCTION("IFERROR( LET( x, UPPER(SUBSTITUTE(TRIM(Data!D89),CHAR(160),"""")), base, VALUE(SUBSTITUTE(REGEXEXTRACT(x,""[0-9.,]+""),"","","""")), mult, IF(REGEXMATCH(x,""B""),1000000000, IF(REGEXMATCH(x,""M""),1000000, 1)), base * mult ), 0 )"),4.512E10) -> 45120000000 | F31: =IFERROR(__xludf.DUMMYFUNCTION("IFERROR( LET( x, UPPER(SUBSTITUTE(TRIM(Data!E89),CHAR(160),"""")), base, VALUE(SUBSTITUTE(REGEXEXTRACT(x,""[0-9.,]+""),"","","""")), mult, IF(REGEXMATCH(x,""B""),1000000000, IF(REGEXMATCH(x,""M""),1000000, 1)), base * mult ), 0 )"),5.15E10) -> 51500000000 | G31: =IFERROR(__xludf.DUMMYFUNCTION("IFERROR( LET( x, UPPER(SUBSTITUTE(TRIM(Data!F89),CHAR(160),"""")), base, VALUE(SUBSTITUTE(REGEXEXTRACT(x,""[0-9.,]+""),"","","""")), mult, IF(REGEXMATCH(x,""B""),1000000000, IF(REGEXMATCH(x,""M""),1000000, 1)), base * mult ), 0 )"),5.619E10) -> 56190000000 | H31: =AVERAGE(C31:G31) -> 44126000000 | I31: =AVERAGE(D31:H31) -> 46715200000 | J31: =AVERAGE(E31:I31) -> 48730240000 | K31: =AVERAGE(F31:J31) -> 49452288000 | L31: =AVERAGE(G31:K31) -> 49042745600
B34: Intangible Assets | C34: =IFERROR(__xludf.DUMMYFUNCTION("IFERROR( LET( x, UPPER(SUBSTITUTE(TRIM(Data!B99),CHAR(160),"""")), base, VALUE(SUBSTITUTE(REGEXEXTRACT(x,""[0-9.,]+""),"","","""")), mult, IF(REGEXMATCH(x,""B""),1000000000, IF(REGEXMATCH(x,""M""),1000000, 1)), base * mult ), )"),1.72E9) -> 1720000000 | D34: =IFERROR(__xludf.DUMMYFUNCTION("IFERROR( LET( x, UPPER(SUBSTITUTE(TRIM(Data!C99),CHAR(160),"""")), base, VALUE(SUBSTITUTE(REGEXEXTRACT(x,""[0-9.,]+""),"","","""")), mult, IF(REGEXMATCH(x,""B""),1000000000, IF(REGEXMATCH(x,""M""),1000000, 1)), base * mult ), )"),5.93E8) -> 593000000 | E34: =IFERROR(__xludf.DUMMYFUNCTION("IFERROR( LET( x, UPPER(SUBSTITUTE(TRIM(Data!D99),CHAR(160),"""")), base, VALUE(SUBSTITUTE(REGEXEXTRACT(x,""[0-9.,]+""),"","","""")), mult, IF(REGEXMATCH(x,""B""),1000000000, IF(REGEXMATCH(x,""M""),1000000, 1)), base * mult ), )"),6.15E8) -> 615000000 | F34: =IFERROR(__xludf.DUMMYFUNCTION("IFERROR( LET( x, UPPER(SUBSTITUTE(TRIM(Data!E99),CHAR(160),"""")), base, VALUE(SUBSTITUTE(REGEXEXTRACT(x,""[0-9.,]+""),"","","""")), mult, IF(REGEXMATCH(x,""B""),1000000000, IF(REGEXMATCH(x,""M""),1000000, 1)), base * mult ), )"),1.47E9) -> 1470000000 | G34: =IFERROR(__xludf.DUMMYFUNCTION("IFERROR( LET( x, UPPER(SUBSTITUTE(TRIM(Data!B99),CHAR(160),"""")), base, VALUE(SUBSTITUTE(REGEXEXTRACT(x,""[0-9.,]+""),"","","""")), mult, IF(REGEXMATCH(x,""B""),1000000000, IF(REGEXMATCH(x,""M""),1000000, 1)), base * mult ), 0 )"),1.72E9) -> 1720000000 | H34: =FORECAST(H3,$C$34:G34,$C$3:G3) -> 1486700000 | I34: =FORECAST(I3,$C$34:H34,$C$3:H3) -> 1574400000 | J34: =FORECAST(J3,$C$34:I34,$C$3:I3) -> 1662100000 | K34: =FORECAST(K3,$C$34:J34,$C$3:J3) -> 1749800000 | L34: =FORECAST(L3,$C$34:K34,$C$3:K3) -> 1837500000
B35: Other Assets | C35: =IFERROR(__xludf.DUMMYFUNCTION("IFERROR( LET( x, UPPER(SUBSTITUTE(TRIM(Data!B102),CHAR(160),"""")), base, VALUE(SUBSTITUTE(REGEXEXTRACT(x,""[0-9.,]+""),"","","""")), mult, IF(REGEXMATCH(x,""B""),1000000000, IF(REGEXMATCH(x,""M""),1000000, 1)), base * mult ), 0 )"),1.62E9) -> 1620000000 | D35: =IFERROR(__xludf.DUMMYFUNCTION("IFERROR( LET( x, UPPER(SUBSTITUTE(TRIM(Data!C102),CHAR(160),"""")), base, VALUE(SUBSTITUTE(REGEXEXTRACT(x,""[0-9.,]+""),"","","""")), mult, IF(REGEXMATCH(x,""B""),1000000000, IF(REGEXMATCH(x,""M""),1000000, 1)), base * mult ), 0 )"),3.54E9) -> 3540000000 | E35: =IFERROR(__xludf.DUMMYFUNCTION("IFERROR( LET( x, UPPER(SUBSTITUTE(TRIM(Data!D102),CHAR(160),"""")), base, VALUE(SUBSTITUTE(REGEXEXTRACT(x,""[0-9.,]+""),"","","""")), mult, IF(REGEXMATCH(x,""B""),1000000000, IF(REGEXMATCH(x,""M""),1000000, 1)), base * mult ), 0 )"),4.0199999999999995E9) -> 4020000000 | F35: =IFERROR(__xludf.DUMMYFUNCTION("IFERROR( LET( x, UPPER(SUBSTITUTE(TRIM(Data!E102),CHAR(160),"""")), base, VALUE(SUBSTITUTE(REGEXEXTRACT(x,""[0-9.,]+""),"","","""")), mult, IF(REGEXMATCH(x,""B""),1000000000, IF(REGEXMATCH(x,""M""),1000000, 1)), base * mult ), 0 )"),3.56E9) -> 3560000000 | G35: =IFERROR(__xludf.DUMMYFUNCTION("IFERROR( LET( x, UPPER(SUBSTITUTE(TRIM(Data!F102),CHAR(160),"""")), base, VALUE(SUBSTITUTE(REGEXEXTRACT(x,""[0-9.,]+""),"","","""")), mult, IF(REGEXMATCH(x,""B""),1000000000, IF(REGEXMATCH(x,""M""),1000000, 1)), base * mult ), 0 )"),2.56E9) -> 2560000000 | H35: =FORECAST(H3,$C$35:G35,$C$3:G3) -> 3630000000 | I35: =FORECAST(I3,$C$35:H35,$C$3:H3) -> 3820000000 | J35: =FORECAST(J3,$C$35:I35,$C$3:I3) -> 4010000000 | K35: =FORECAST(K3,$C$35:J35,$C$3:J3) -> 4200000000 | L35: =FORECAST(L3,$C$35:K35,$C$3:K3) -> 4390000000
B36: Total Assets | C36: =IFERROR(__xludf.DUMMYFUNCTION("regexreplace(Data!B103,""B"","""")*1000000000"),6.213E10) -> 62130000000 | D36: =IFERROR(__xludf.DUMMYFUNCTION("regexreplace(Data!C103,""B"","""")*1000000000"),8.234E10) -> 82340000000 | E36: =IFERROR(__xludf.DUMMYFUNCTION("regexreplace(Data!D103,""B"","""")*1000000000"),1.0662E11) -> 106620000000 | F36: =IFERROR(__xludf.DUMMYFUNCTION("regexreplace(Data!E103,""B"","""")*1000000000"),1.2207E11) -> 122070000000 | G36: =IFERROR(__xludf.DUMMYFUNCTION("regexreplace(Data!F103,""B"","""")*1000000000"),1.3781E11) -> 137810000000 | H36: =G36*(1+H37) -> 168180476065 | I36: =H36*(1+I37) -> 205243977429 | J36: =I36*(1+J37) -> 250475508553 | K36: =J36*(1+K37) -> 305675134396 | L36: =K36*(1+L37) -> 373039617038
B37: Total Assets Growth | C37: - | D37: =Data!C104 -> 0.3252 | E37: =Data!D104 -> 0.2949 | F37: =Data!E104 -> 0.1449 | G37: =Data!F104 -> 0.1289 | H37: =(G36/C36)^(1/4)-1 -> 0.22037933 | I37: =H37 -> 0.22037933 | J37: =I37 -> 0.22037933 | K37: =J37 -> 0.22037933 | L37: =K37 -> 0.22037933
B40: Short Term Debt | C40: =IFERROR(__xludf.DUMMYFUNCTION("IFERROR( LET( x, UPPER(SUBSTITUTE(TRIM(Data!B334),CHAR(160),"""")), base, VALUE(SUBSTITUTE(REGEXEXTRACT(x,""[0-9.,]+""),"","","""")), mult, IF(REGEXMATCH(x,""B""),1000000000, IF(REGEXMATCH(x,""M""),1000000, 1)), base * mult ), 0 )"),3.68E8) -> 368000000 | D40: =IFERROR(__xludf.DUMMYFUNCTION("IFERROR( LET( x, UPPER(SUBSTITUTE(TRIM(Data!C334),CHAR(160),"""")), base, VALUE(SUBSTITUTE(REGEXEXTRACT(x,""[0-9.,]+""),"","","""")), mult, IF(REGEXMATCH(x,""B""),1000000000, IF(REGEXMATCH(x,""M""),1000000, 1)), base * mult ), 0 )"),4.85E8) -> 485000000 | E40: =IFERROR(__xludf.DUMMYFUNCTION("IFERROR( LET( x, UPPER(SUBSTITUTE(TRIM(Data!D334),CHAR(160),"""")), base, VALUE(SUBSTITUTE(REGEXEXTRACT(x,""[0-9.,]+""),"","","""")), mult, IF(REGEXMATCH(x,""B""),1000000000, IF(REGEXMATCH(x,""M""),1000000, 1)), base * mult ), 0 )"),6.72E8) -> 672000000 | F40: =IFERROR(__xludf.DUMMYFUNCTION("IFERROR( LET( x, UPPER(SUBSTITUTE(TRIM(Data!E334),CHAR(160),"""")), base, VALUE(SUBSTITUTE(REGEXEXTRACT(x,""[0-9.,]+""),"","","""")), mult, IF(REGEXMATCH(x,""B""),1000000000, IF(REGEXMATCH(x,""M""),1000000, 1)), base * mult ), 0 )"),8.07E8) -> 807000000 | G40: =IFERROR(__xludf.DUMMYFUNCTION("IFERROR( LET( x, UPPER(SUBSTITUTE(TRIM(Data!F334),CHAR(160),"""")), base, VALUE(SUBSTITUTE(REGEXEXTRACT(x,""[0-9.,]+""),"","","""")), mult, IF(REGEXMATCH(x,""B""),1000000000, IF(REGEXMATCH(x,""M""),1000000, 1)), base * mult ), 0 )"),9.54E8) -> 954000000 | H40: =FORECAST(H3,$C$40:G40,$C$3:G3) -> 1105400000 | I40: =FORECAST(I3,$C$40:H40,$C$3:H3) -> 1254800000 | J40: =FORECAST(J3,$C$40:I40,$C$3:I3) -> 1404200000 | K40: =FORECAST(K3,$C$40:J40,$C$3:J3) -> 1553600000 | L40: =FORECAST(L3,$C$40:K40,$C$3:K3) -> 1703000000
B41: Current Portion of Long Term Debt | C41: =IFERROR(__xludf.DUMMYFUNCTION("IFERROR( LET( x, UPPER(SUBSTITUTE(TRIM(Data!B335),CHAR(160),"""")), base, VALUE(SUBSTITUTE(REGEXEXTRACT(x,""[0-9.,]+""),"","","""")), mult, IF(REGEXMATCH(x,""B""),1000000000, IF(REGEXMATCH(x,""M""),1000000, 1)), base * mult ), 0 )"),1.59E9) -> 1590000000 | D41: =IFERROR(__xludf.DUMMYFUNCTION("IFERROR( LET( x, UPPER(SUBSTITUTE(TRIM(Data!C335),CHAR(160),"""")), base, VALUE(SUBSTITUTE(REGEXEXTRACT(x,""[0-9.,]+""),"","","""")), mult, IF(REGEXMATCH(x,""B""),1000000000, IF(REGEXMATCH(x,""M""),1000000, 1)), base * mult ), 0 )"),1.5E9) -> 1500000000 | E41: =IFERROR(__xludf.DUMMYFUNCTION("IFERROR( LET( x, UPPER(SUBSTITUTE(TRIM(Data!D335),CHAR(160),"""")), base, VALUE(SUBSTITUTE(REGEXEXTRACT(x,""[0-9.,]+""),"","","""")), mult, IF(REGEXMATCH(x,""B""),1000000000, IF(REGEXMATCH(x,""M""),1000000, 1)), base * mult ), 0 )"),2.37E9) -> 2370000000 | F41: =IFERROR(__xludf.DUMMYFUNCTION("IFERROR( LET( x, UPPER(SUBSTITUTE(TRIM(Data!E335),CHAR(160),"""")), base, VALUE(SUBSTITUTE(REGEXEXTRACT(x,""[0-9.,]+""),"","","""")), mult, IF(REGEXMATCH(x,""B""),1000000000, IF(REGEXMATCH(x,""M""),1000000, 1)), base * mult ), 0 )"),2.46E9) -> 2460000000 | G41: =IFERROR(__xludf.DUMMYFUNCTION("IFERROR( LET( x, UPPER(SUBSTITUTE(TRIM(Data!F335),CHAR(160),"""")), base, VALUE(SUBSTITUTE(REGEXEXTRACT(x,""[0-9.,]+""),"","","""")), mult, IF(REGEXMATCH(x,""B""),1000000000, IF(REGEXMATCH(x,""M""),1000000, 1)), base * mult ), 0 )"),1.64E9) -> 1640000000 | H41: =AVERAGE(C41:G41) -> 1912000000 | I41: =AVERAGE(D41:H41) -> 1976400000 | J41: =AVERAGE(E41:I41) -> 2071680000 | K41: =AVERAGE(F41:J41) -> 2012016000 | L41: =AVERAGE(G41:K41) -> 1922419200
B42: ST Debt & Current Portion LT Debt | C42: =IFERROR(__xludf.DUMMYFUNCTION("IFERROR( LET( x, UPPER(SUBSTITUTE(TRIM(Data!B333),CHAR(160),"""")), base, VALUE(SUBSTITUTE(REGEXEXTRACT(x,""[0-9.,]+""),"","","""")), mult, IF(REGEXMATCH(x,""B""),1000000000, IF(REGEXMATCH(x,""M""),1000000, 1)), base * mult ), 0 )"),1.96E9) -> 1960000000 | D42: =IFERROR(__xludf.DUMMYFUNCTION("IFERROR( LET( x, UPPER(SUBSTITUTE(TRIM(Data!C333),CHAR(160),"""")), base, VALUE(SUBSTITUTE(REGEXEXTRACT(x,""[0-9.,]+""),"","","""")), mult, IF(REGEXMATCH(x,""B""),1000000000, IF(REGEXMATCH(x,""M""),1000000, 1)), base * mult ), 0 )"),1.99E9) -> 1990000000 | E42: =IFERROR(__xludf.DUMMYFUNCTION("IFERROR( LET( x, UPPER(SUBSTITUTE(TRIM(Data!D333),CHAR(160),"""")), base, VALUE(SUBSTITUTE(REGEXEXTRACT(x,""[0-9.,]+""),"","","""")), mult, IF(REGEXMATCH(x,""B""),1000000000, IF(REGEXMATCH(x,""M""),1000000, 1)), base * mult ), 0 )"),3.05E9) -> 3050000000 | F42: =IFERROR(__xludf.DUMMYFUNCTION("IFERROR( LET( x, UPPER(SUBSTITUTE(TRIM(Data!E333),CHAR(160),"""")), base, VALUE(SUBSTITUTE(REGEXEXTRACT(x,""[0-9.,]+""),"","","""")), mult, IF(REGEXMATCH(x,""B""),1000000000, IF(REGEXMATCH(x,""M""),1000000, 1)), base * mult ), 0 )"),3.26E9) -> 3260000000 | G42: =IFERROR(__xludf.DUMMYFUNCTION("IFERROR( LET( x, UPPER(SUBSTITUTE(TRIM(Data!F333),CHAR(160),"""")), base, VALUE(SUBSTITUTE(REGEXEXTRACT(x,""[0-9.,]+""),"","","""")), mult, IF(REGEXMATCH(x,""B""),1000000000, IF(REGEXMATCH(x,""M""),1000000, 1)), base * mult ), 0 )"),2.59E9) -> 2590000000 | H42: =FORECAST(H3,$C$42:G42,$C$3:G3) -> 3329000000 | I42: =FORECAST(I3,$C$42:H42,$C$3:H3) -> 3582000000 | J42: =FORECAST(J3,$C$42:I42,$C$3:I3) -> 3835000000 | K42: =FORECAST(K3,$C$42:J42,$C$3:J3) -> 4088000000 | L42: =FORECAST(L3,$C$42:K42,$C$3:K3) -> 4341000000

Sheet Cash Flow
B2: Balance Sheet | C2: FY | H2: Future FY
C3: 2020 | D3: 2021 | E3: 2022 | F3: 2023 | G3: 2024 | H3: 2025 | I3: 2026 | J3: 2027 | K3: 2028 | L3: 2029
B6: Net Income before Extraordinaries | C6: =IFERROR(__xludf.DUMMYFUNCTION("IFERROR( LET( x, UPPER(SUBSTITUTE(TRIM(Data!B112),CHAR(160),"""")), base, VALUE(SUBSTITUTE(REGEXEXTRACT(x,""[0-9.,]+""),"","","""")), mult, IF(REGEXMATCH(x,""B""),1000000000, IF(REGEXMATCH(x,""M""),1000000, 1)), base * mult ), 0 ) "),5.64E9) -> 5640000000 | D6: =IFERROR(__xludf.DUMMYFUNCTION("IFERROR( LET( x, UPPER(SUBSTITUTE(TRIM(Data!C112),CHAR(160),"""")), base, VALUE(SUBSTITUTE(REGEXEXTRACT(x,""[0-9.,]+""),"","","""")), mult, IF(REGEXMATCH(x,""B""),1000000000, IF(REGEXMATCH(x,""M""),1000000, 1)), base * mult ), )"),1.259E10) -> 12590000000 | E6: =IFERROR(__xludf.DUMMYFUNCTION("IFERROR( LET( x, UPPER(SUBSTITUTE(TRIM(Data!D112),CHAR(160),"""")), base, VALUE(SUBSTITUTE(REGEXEXTRACT(x,""[0-9.,]+""),"","","""")), mult, IF(REGEXMATCH(x,""B""),1000000000, IF(REGEXMATCH(x,""M""),1000000, 1)), base * mult ), )"),1.497E10) -> 14970000000 | F6: =IFERROR(__xludf.DUMMYFUNCTION("IFERROR( LET( x, UPPER(SUBSTITUTE(TRIM(Data!E112),CHAR(160),"""")), base, VALUE(SUBSTITUTE(REGEXEXTRACT(x,""[0-9.,]+""),"","","""")), mult, IF(REGEXMATCH(x,""B""),1000000000, IF(REGEXMATCH(x,""M""),1000000, 1)), base * mult ), )"),7.15E9) -> 7150000000 | G6: =IFERROR(__xludf.DUMMYFUNCTION("IFERROR( LET( x, UPPER(SUBSTITUTE(TRIM(Data!F112),CHAR(160),"""")), base, VALUE(SUBSTITUTE(REGEXEXTRACT(x,""[0-9.,]+""),"","","""")), mult, IF(REGEXMATCH(x,""B""),1000000000, IF(REGEXMATCH(x,""M""),1000000, 1)), base * mult ), )"),3.86E9) -> 3860000000 | H6: =FORECAST(H3,$C$6:G6,$C$3:G3) -> 6142000000 | I6: =FORECAST(I3,$C$6:H6,$C$3:H3) -> 5242000000 | J6: =FORECAST(J3,$C$6:I6,$C$3:I3) -> 4342000000 | K6: =FORECAST(K3,$C$6:J6,$C$3:J3) -> 3442000000 | L6: =FORECAST(L3,$C$6:K6,$C$3:K3) -> 2542000000
B7: Net Income Growth | C7: =Data!B113 -> - | D7: =Data!C113 -> 1.2302 | E7: =Data!D113 -> 0.1896 | F7: =Data!E113 -> -0.5223 | G7: =Data!F113 -> -0.4611 | H7: =H6/G6-1 -> 0.59119171 | I7: =I6/H6-1 -> -0.14653207 | J7: =J6/I6-1 -> -0.17169019 | K7: =K6/J6-1 -> -0.20727775 | L7: =L6/K6-1 -> -0.26147589
B10: Depreciation, Depletion & Amortization | C10: =IFERROR(__xludf.DUMMYFUNCTION("IFERROR( LET( x, UPPER(SUBSTITUTE(TRIM(Data!B114),CHAR(160),"""")), base, VALUE(SUBSTITUTE(REGEXEXTRACT(x,""[0-9.,]+""),"","","""")), mult, IF(REGEXMATCH(x,""B""),1000000000, IF(REGEXMATCH(x,""M""),1000000, 1)), base * mult ), 0 ) "),2.91E9) -> 2910000000 | D10: =IFERROR(__xludf.DUMMYFUNCTION("IFERROR( LET( x, UPPER(SUBSTITUTE(TRIM(Data!C114),CHAR(160),"""")), base, VALUE(SUBSTITUTE(REGEXEXTRACT(x,""[0-9.,]+""),"","","""")), mult, IF(REGEXMATCH(x,""B""),1000000000, IF(REGEXMATCH(x,""M""),1000000, 1)), base * mult ), 0 ) "),3.75E9) -> 3750000000 | E10: =IFERROR(__xludf.DUMMYFUNCTION("IFERROR( LET( x, UPPER(SUBSTITUTE(TRIM(Data!D114),CHAR(160),"""")), base, VALUE(SUBSTITUTE(REGEXEXTRACT(x,""[0-9.,]+""),"","","""")), mult, IF(REGEXMATCH(x,""B""),1000000000, IF(REGEXMATCH(x,""M""),1000000, 1)), base * mult ), 0 ) "),4.67E9) -> 4670000000 | F10: =IFERROR(__xludf.DUMMYFUNCTION("IFERROR( LET( x, UPPER(SUBSTITUTE(TRIM(Data!E114),CHAR(160),"""")), base, VALUE(SUBSTITUTE(REGEXEXTRACT(x,""[0-9.,]+""),"","","""")), mult, IF(REGEXMATCH(x,""B""),1000000000, IF(REGEXMATCH(x,""M""),1000000, 1)), base * mult ), 0 ) "),5.37E9) -> 5370000000 | G10: =IFERROR(__xludf.DUMMYFUNCTION("IFERROR( LET( x, UPPER(SUBSTITUTE(TRIM(Data!F114),CHAR(160),"""")), base, VALUE(SUBSTITUTE(REGEXEXTRACT(x,""[0-9.,]+""),"","","""")), mult, IF(REGEXMATCH(x,""B""),1000000000, IF(REGEXMATCH(x,""M""),1000000, 1)), base * mult ), 0 ) "),6.15E9) -> 6150000000 | H10: =FORECAST(H3,$C$10:G10,$C$3:G3) -> 7000000000 | I10: =FORECAST(I3,$C$10:H10,$C$3:H3) -> 7810000000 | J10: =FORECAST(J3,$C$10:I10,$C$3:I3) -> 8620000000 | K10: =FORECAST(K3,$C$10:J10,$C$3:J3) -> 9430000000 | L10: =FORECAST(L3,$C$10:K10,$C$3:K3) -> 10240000000
B13: Net Operating Cash Flow | C13: =IFERROR(__xludf.DUMMYFUNCTION("IFERROR( LET( x, UPPER(SUBSTITUTE(TRIM(Data!B127),CHAR(160),"""")), base, VALUE(SUBSTITUTE(REGEXEXTRACT(x,""[0-9.,]+""),"","","""")), mult, IF(REGEXMATCH(x,""B""),1000000000, IF(REGEXMATCH(x,""M""),1000000, 1)), base * mult ), 0 ) "),1.15E10) -> 11500000000 | D13: =IFERROR(__xludf.DUMMYFUNCTION("IFERROR( LET( x, UPPER(SUBSTITUTE(TRIM(Data!C127),CHAR(160),"""")), base, VALUE(SUBSTITUTE(REGEXEXTRACT(x,""[0-9.,]+""),"","","""")), mult, IF(REGEXMATCH(x,""B""),1000000000, IF(REGEXMATCH(x,""M""),1000000, 1)), base * mult ), 0 ) "),1.472E10) -> 14720000000 | E13: =IFERROR(__xludf.DUMMYFUNCTION("IFERROR( LET( x, UPPER(SUBSTITUTE(TRIM(Data!D127),CHAR(160),"""")), base, VALUE(SUBSTITUTE(REGEXEXTRACT(x,""[0-9.,]+""),"","","""")), mult, IF(REGEXMATCH(x,""B""),1000000000, IF(REGEXMATCH(x,""M""),1000000, 1)), base * mult ), 0 ) "),1.326E10) -> 13260000000 | F13: =IFERROR(__xludf.DUMMYFUNCTION("IFERROR( LET( x, UPPER(SUBSTITUTE(TRIM(Data!E127),CHAR(160),"""")), base, VALUE(SUBSTITUTE(REGEXEXTRACT(x,""[0-9.,]+""),"","","""")), mult, IF(REGEXMATCH(x,""B""),1000000000, IF(REGEXMATCH(x,""M""),1000000, 1)), base * mult ), 0 ) "),1.492E10) -> 14920000000 | G13: =IFERROR(__xludf.DUMMYFUNCTION("IFERROR( LET( x, UPPER(SUBSTITUTE(TRIM(Data!F127),CHAR(160),"""")), base, VALUE(SUBSTITUTE(REGEXEXTRACT(x,""[0-9.,]+""),"","","""")), mult, IF(REGEXMATCH(x,""B""),1000000000, IF(REGEXMATCH(x,""M""),1000000, 1)), base * mult ), 0 ) "),1.475E10) -> 14750000000 | H13: =FORECAST(H3,$C$13:G13,$C$3:G3) -> 15840000000 | I13: =FORECAST(I3,$C$13:H13,$C$3:H3) -> 16510000000 | J13: =FORECAST(J3,$C$13:I13,$C$3:I3) -> 17180000000 | K13: =FORECAST(K3,$C$13:J13,$C$3:J3) -> 17850000000 | L13: =FORECAST(L3,$C$13:K13,$C$3:K3) -> 18520000000
B14: Net Operating Cash Flow Growth | C14: =Data!B128 -> - | D14: =Data!C128 -> 0.2807 | E14: =Data!D128 -> -0.0997 | F14: =Data!E128 -> 0.1258 | G14: =Data!F128 -> -0.0118 | H14: =H13/G13-1 -> 0.073898305 | I14: =I13/H13-1 -> 0.04229798 | J14: =J13/I13-1 -> 0.040581466 | K14: =K13/J13-1 -> 0.038998836 | L14: =L13/K13-1 -> 0.037535014
B17: Net Change in Cash | C17: =IFERROR(__xludf.DUMMYFUNCTION("IFERROR( LET( x, UPPER(SUBSTITUTE(TRIM(Data!B153),CHAR(160),"""")), base, VALUE(SUBSTITUTE(REGEXEXTRACT(x,""[0-9.,]+""),"","","""")), mult, IF(REGEXMATCH(x,""B""),1000000000, IF(REGEXMATCH(x,""M""),1000000, 1)), base * mult ), 0 ) "),1.76E9) -> 1760000000 | D17: =IFERROR(__xludf.DUMMYFUNCTION("IFERROR( LET( x, UPPER(SUBSTITUTE(TRIM(Data!C153),CHAR(160),"""")), base, VALUE(SUBSTITUTE(REGEXEXTRACT(x,""[0-9.,]+""),"","","""")), mult, IF(REGEXMATCH(x,""B""),1000000000, IF(REGEXMATCH(x,""M""),1000000, 1)), base * mult ), 0 ) "),1.22E9) -> 1220000000 | E17: =IFERROR(__xludf.DUMMYFUNCTION("IFERROR( LET( x, UPPER(SUBSTITUTE(TRIM(Data!D153),CHAR(160),"""")), base, VALUE(SUBSTITUTE(REGEXEXTRACT(x,""[0-9.,]+""),"","","""")), mult, IF(REGEXMATCH(x,""B""),1000000000, IF(REGEXMATCH(x,""M""),1000000, 1)), base * mult ), 0 ) "),2.65E8) -> 265000000 | F17: =IFERROR(__xludf.DUMMYFUNCTION("IFERROR( LET( x, UPPER(SUBSTITUTE(TRIM(Data!E153),CHAR(160),"""")), base, VALUE(SUBSTITUTE(REGEXEXTRACT(x,""[0-9.,]+""),"","","""")), mult, IF(REGEXMATCH(x,""B""),1000000000, IF(REGEXMATCH(x,""M""),1000000, 1)), base * mult ), 0 ) "),1.52E8) -> 152000000 | G17: =IFERROR(__xludf.DUMMYFUNCTION("IFERROR( LET( x, UPPER(SUBSTITUTE(TRIM(Data!F153),CHAR(160),"""")), base, VALUE(SUBSTITUTE(REGEXEXTRACT(x,""[0-9.,]+""),"","","""")), mult, IF(REGEXMATCH(x,""B""),1000000000, IF(REGEXMATCH(x,""M""),1000000, 1)), base * mult ), 0 ) "),5.79E8) -> 579000000 | H17: =AVERAGEIF(C17:G17,">0.5") -> 795200000 | I17: =AVERAGEIF(D17:H17,">0.5") -> 602240000 | J17: =AVERAGEIF(E17:I17,">0.5") -> 478688000 | K17: =AVERAGEIF(F17:J17,">0.5") -> 521425600 | L17: =AVERAGEIF(G17:K17,">0.5") -> 595310720
B18: Free Cash Flow | C18: =IFERROR(__xludf.DUMMYFUNCTION("IFERROR( LET( x, UPPER(SUBSTITUTE(TRIM(Data!B154),CHAR(160),"""")), base, VALUE(SUBSTITUTE(REGEXEXTRACT(x,""[0-9.,]+""),"","","""")), mult, IF(REGEXMATCH(x,""B""),1000000000, IF(REGEXMATCH(x,""M""),1000000, 1)), base * mult ), 0 ) "),4.98E9) -> 4980000000 | D18: =IFERROR(__xludf.DUMMYFUNCTION("IFERROR( LET( x, UPPER(SUBSTITUTE(TRIM(Data!C154),CHAR(160),"""")), base, VALUE(SUBSTITUTE(REGEXEXTRACT(x,""[0-9.,]+""),"","","""")), mult, IF(REGEXMATCH(x,""B""),1000000000, IF(REGEXMATCH(x,""M""),1000000, 1)), base * mult ), 0 ) "),7.56E9) -> 7560000000 | E18: =IFERROR(__xludf.DUMMYFUNCTION("IFERROR( LET( x, UPPER(SUBSTITUTE(TRIM(Data!D154),CHAR(160),"""")), base, VALUE(SUBSTITUTE(REGEXEXTRACT(x,""[0-9.,]+""),"","","""")), mult, IF(REGEXMATCH(x,""B""),1000000000, IF(REGEXMATCH(x,""M""),1000000, 1)), base * mult ), 0 ) "),4.36E9) -> 4360000000 | F18: =IFERROR(__xludf.DUMMYFUNCTION("IFERROR( LET( x, UPPER(SUBSTITUTE(TRIM(Data!E154),CHAR(160),"""")), base, VALUE(SUBSTITUTE(REGEXEXTRACT(x,""[0-9.,]+""),"","","""")), mult, IF(REGEXMATCH(x,""B""),1000000000, IF(REGEXMATCH(x,""M""),1000000, 1)), base * mult ), 0 ) "),3.58E9) -> 3580000000 | G18: =IFERROR(__xludf.DUMMYFUNCTION("IFERROR( LET( x, UPPER(SUBSTITUTE(TRIM(Data!F154),CHAR(160),"""")), base, VALUE(SUBSTITUTE(REGEXEXTRACT(x,""[0-9.,]+""),"","","""")), mult, IF(REGEXMATCH(x,""B""),1000000000, IF(REGEXMATCH(x,""M""),1000000, 1)), base * mult ), 0 ) "),6.22E9) -> 6220000000 | H18: =G18*(1+H19) -> 6575528208 | I18: =H18*(1+I19) -> 6754112163 | J18: =I18*(1+J19) -> 6734922892 | K18: =J18*(1+K19) -> 6513740454 | L18: =K18*(1+L19) -> 6104409681
B19: Free Cash Flow Growth | C19: =Data!B155 -> - | D19: =Data!C155 -> 0.5174 | E19: =Data!D155 -> -0.4238 | F19: =Data!E155 -> -0.1781 | G19: =Data!F155 -> 0.7369 | H19: =(G18/C18)^(1/4)-1 -> 0.057158876 | I19: =H19-3% -> 0.027158876 | J19: =I19-3% -> -0.0028411241 | K19: =J19-3% -> -0.032841124 | L19: =K19-3% -> -0.062841124

Sheet DCF
G2: TradingView Revenue Estimates
B4: Discounted Cash Flow | C4: FY | H4: Future FY
C5: 2020 | D5: 2021 | E5: 2022 | F5: 2023 | G5: 2024 | H5: 2025 | I5: 2026 | J5: 2027 | K5: 2028
B8: Revenue | C8: ='Income Statement'!C15 -> 53820000000 | D8: ='Income Statement'!D15 -> 81460000000 | E8: ='Income Statement'!E15 -> 96770000000 | F8: ='Income Statement'!F15 -> 97690000000 | G8: ='Income Statement'!G15 -> 94830000000 | H8: 102430000000 | I8: 117900000000 | J8: 139270000000 | K8: 220000000000
B9: % growth | C9: - | D9: =D8/C8-1 -> 0.51356373 | E9: =E8/D8-1 -> 0.187945 | F9: =F8/E8-1 -> 0.0095070786 | G9: =G8/F8-1 -> -0.029276282 | H9: =H8/G8-1 -> 0.080143415 | I9: =I8/H8-1 -> 0.15102997 | J9: =J8/I8-1 -> 0.1812553 | K9: =K8/J8-1 -> 0.5796654
B12: EBIT | C12: =IFERROR(__xludf.DUMMYFUNCTION("IFERROR( LET( x, UPPER(SUBSTITUTE(TRIM(Data!B22),CHAR(160),"""")), neg, IF(LEFT(x,1)=""("", -1, 1), numtext, REGEXEXTRACT(x,""[0-9.,]+""), base, VALUE(SUBSTITUTE(numtext,"","","""")), mult, IF(REGEXMATCH(x,""B""),1000000000, IF(REGEX"&"MATCH(x,""M""),1000000, 1)), neg * base * mult ), 0 ) "),6.54E9) -> 6540000000 | D12: =IFERROR(__xludf.DUMMYFUNCTION("IFERROR( LET( x, UPPER(SUBSTITUTE(TRIM(Data!C22),CHAR(160),"""")), neg, IF(LEFT(x,1)=""("", -1, 1), numtext, REGEXEXTRACT(x,""[0-9.,]+""), base, VALUE(SUBSTITUTE(numtext,"","","""")), mult, IF(REGEXMATCH(x,""B""),1000000000, IF(REGEX"&"MATCH(x,""M""),1000000, 1)), neg * base * mult ), 0 ) "),1.368E10) -> 13680000000 | E12: =IFERROR(__xludf.DUMMYFUNCTION("IFERROR( LET( x, UPPER(SUBSTITUTE(TRIM(Data!D22),CHAR(160),"""")), neg, IF(LEFT(x,1)=""("", -1, 1), numtext, REGEXEXTRACT(x,""[0-9.,]+""), base, VALUE(SUBSTITUTE(numtext,"","","""")), mult, IF(REGEXMATCH(x,""B""),1000000000, IF(REGEX"&"MATCH(x,""M""),1000000, 1)), neg * base * mult ), 0 ) "),8.89E9) -> 8890000000 | F12: =IFERROR(__xludf.DUMMYFUNCTION("IFERROR( LET( x, UPPER(SUBSTITUTE(TRIM(Data!E22),CHAR(160),"""")), neg, IF(LEFT(x,1)=""("", -1, 1), numtext, REGEXEXTRACT(x,""[0-9.,]+""), base, VALUE(SUBSTITUTE(numtext,"","","""")), mult, IF(REGEXMATCH(x,""B""),1000000000, IF(REGEX"&"MATCH(x,""M""),1000000, 1)), neg * base * mult ), 0 ) "),7.09E9) -> 7090000000 | G12: =IFERROR(__xludf.DUMMYFUNCTION("IFERROR( LET( x, UPPER(SUBSTITUTE(TRIM(Data!F22),CHAR(160),"""")), neg, IF(LEFT(x,1)=""("", -1, 1), numtext, REGEXEXTRACT(x,""[0-9.,]+""), base, VALUE(SUBSTITUTE(numtext,"","","""")), mult, IF(REGEXMATCH(x,""B""),1000000000, IF(REGEX"&"MATCH(x,""M""),1000000, 1)), neg * base * mult ), 0 ) "),4.29E9) -> 4290000000 | H12: =H8*H13 -> 7159265647 | I12: =I8*I13 -> 8240529335 | J12: =J8*J13 -> 9734168960 | K12: =K8*K13 -> 15376729887
B13: % of sales | C13: =C12/C8 -> 0.12151616 | D13: =D12/D8 -> 0.16793518 | E13: =E12/E8 -> 0.091867314 | F13: =F12/F8 -> 0.072576518 | G13: =G12/G8 -> 0.045238848 | H13: =AVERAGEIF(E13:G13,">0.01") -> 0.069894227 | I13: =H13 -> 0.069894227 | J13: =I13 -> 0.069894227 | K13: =J13 -> 0.069894227
B16: Taxes | C16: =IFERROR(__xludf.DUMMYFUNCTION("IFERROR( LET( x, UPPER(SUBSTITUTE(TRIM(Data!B33),CHAR(160),"""")), neg, IF(LEFT(x,1)=""("", -1, 1), numtext, REGEXEXTRACT(x,""[0-9.,]+""), base, VALUE(SUBSTITUTE(numtext,"","","""")), mult, IF(REGEXMATCH(x,""B""),1000000000, IF(REGEX"&"MATCH(x,""M""),1000000, 1)), neg * base * mult ), 0 ) "),6.99E8) -> 699000000 | D16: =IFERROR(__xludf.DUMMYFUNCTION("IFERROR( LET( x, UPPER(SUBSTITUTE(TRIM(Data!C33),CHAR(160),"""")), neg, IF(LEFT(x,1)=""("", -1, 1), numtext, REGEXEXTRACT(x,""[0-9.,]+""), base, VALUE(SUBSTITUTE(numtext,"","","""")), mult, IF(REGEXMATCH(x,""B""),1000000000, IF(REGEX"&"MATCH(x,""M""),1000000, 1)), neg * base * mult ), 0 ) "),1.13E9) -> 1130000000 | E16: =IFERROR(__xludf.DUMMYFUNCTION("IFERROR( LET( x, UPPER(SUBSTITUTE(TRIM(Data!D33),CHAR(160),"""")), neg, IF(LEFT(x,1)=""("", -1, 1), numtext, REGEXEXTRACT(x,""[0-9.,]+""), base, VALUE(SUBSTITUTE(numtext,"","","""")), mult, IF(REGEXMATCH(x,""B""),1000000000, IF(REGEX"&"MATCH(x,""M""),1000000, 1)), neg * base * mult ), 0 ) "),-5.0E9) -> -5000000000 | F16: =IFERROR(__xludf.DUMMYFUNCTION("IFERROR( LET( x, UPPER(SUBSTITUTE(TRIM(Data!E33),CHAR(160),"""")), neg, IF(LEFT(x,1)=""("", -1, 1), numtext, REGEXEXTRACT(x,""[0-9.,]+""), base, VALUE(SUBSTITUTE(numtext,"","","""")), mult, IF(REGEXMATCH(x,""B""),1000000000, IF(REGEX"&"MATCH(x,""M""),1000000, 1)), neg * base * mult ), 0 ) "),1.84E9) -> 1840000000 | G16: =IFERROR(__xludf.DUMMYFUNCTION("IFERROR( LET( x, UPPER(SUBSTITUTE(TRIM(Data!F33),CHAR(160),"""")), neg, IF(LEFT(x,1)=""("", -1, 1), numtext, REGEXEXTRACT(x,""[0-9.,]+""), base, VALUE(SUBSTITUTE(numtext,"","","""")), mult, IF(REGEXMATCH(x,""B""),1000000000, IF(REGEX"&"MATCH(x,""M""),1000000, 1)), neg * base * mult ), 0 ) "),1.42E9) -> 1420000000 | H16: =H17*H12 -> 2113854735 | I16: =I17*I12 -> 2433110155 | J16: =J17*J12 -> 2874124269 | K16: =K17*K12 -> 4540154658
B17: % of EBIT | C17: =C16/C12 -> 0.10688073 | D17: =D16/D12 -> 0.082602339 | E17: =E16/E12 -> -0.5624297 | F17: =F16/F12 -> 0.25952045 | G17: =G16/G12 -> 0.33100233 | H17: =AVERAGEIF(E17:G17,">0.01") -> 0.29526139 | I17: =H17 -> 0.29526139 | J17: =I17 -> 0.29526139 | K17: =J17 -> 0.29526139
B20: EBIAT | C20: - | D20: - | E20: - | F20: - | G20: - | H20: =H12-H16 -> 5045410912 | I20: =I12-I16 -> 5807419179 | J20: =J12-J16 -> 6860044691 | K20: =K12-K16 -> 10836575229
B23: D&A | C23: =IFERROR(__xludf.DUMMYFUNCTION("IFERROR( LET( x, UPPER(SUBSTITUTE(TRIM(Data!B114),CHAR(160),"""")), neg, IF(LEFT(x,1)=""("", -1, 1), numtext, REGEXEXTRACT(x,""[0-9.,]+""), base, VALUE(SUBSTITUTE(numtext,"","","""")), mult, IF(REGEXMATCH(x,""B""),1000000000, IF(REGE"&"XMATCH(x,""M""),1000000, 1)), neg * base * mult ), 0 ) "),2.91E9) -> 2910000000 | D23: =IFERROR(__xludf.DUMMYFUNCTION("IFERROR( LET( x, UPPER(SUBSTITUTE(TRIM(Data!C114),CHAR(160),"""")), neg, IF(LEFT(x,1)=""("", -1, 1), numtext, REGEXEXTRACT(x,""[0-9.,]+""), base, VALUE(SUBSTITUTE(numtext,"","","""")), mult, IF(REGEXMATCH(x,""B""),1000000000, IF(REGE"&"XMATCH(x,""M""),1000000, 1)), neg * base * mult ), 0 ) "),3.75E9) -> 3750000000 | E23: =IFERROR(__xludf.DUMMYFUNCTION("IFERROR( LET( x, UPPER(SUBSTITUTE(TRIM(Data!D114),CHAR(160),"""")), neg, IF(LEFT(x,1)=""("", -1, 1), numtext, REGEXEXTRACT(x,""[0-9.,]+""), base, VALUE(SUBSTITUTE(numtext,"","","""")), mult, IF(REGEXMATCH(x,""B""),1000000000, IF(REGE"&"XMATCH(x,""M""),1000000, 1)), neg * base * mult ), 0 ) "),4.67E9) -> 4670000000 | F23: =IFERROR(__xludf.DUMMYFUNCTION("IFERROR( LET( x, UPPER(SUBSTITUTE(TRIM(Data!E114),CHAR(160),"""")), neg, IF(LEFT(x,1)=""("", -1, 1), numtext, REGEXEXTRACT(x,""[0-9.,]+""), base, VALUE(SUBSTITUTE(numtext,"","","""")), mult, IF(REGEXMATCH(x,""B""),1000000000, IF(REGE"&"XMATCH(x,""M""),1000000, 1)), neg * base * mult ), 0 ) "),5.37E9) -> 5370000000 | G23: =IFERROR(__xludf.DUMMYFUNCTION("IFERROR( LET( x, UPPER(SUBSTITUTE(TRIM(Data!F114),CHAR(160),"""")), neg, IF(LEFT(x,1)=""("", -1, 1), numtext, REGEXEXTRACT(x,""[0-9.,]+""), base, VALUE(SUBSTITUTE(numtext,"","","""")), mult, IF(REGEXMATCH(x,""B""),1000000000, IF(REGE"&"XMATCH(x,""M""),1000000, 1)), neg * base * mult ), 0 ) "),6.15E9) -> 6150000000 | H23: =H8*H24 -> 5738861144 | I23: =I8*I24 -> 6605601180 | J23: =J8*J24 -> 7802901411 | K23: =K8*K24 -> 12325973364
B24: % of sales | C24: =C23/C8 -> 0.054069119 | D24: =D23/D8 -> 0.046034864 | E24: =E23/E8 -> 0.048258758 | F24: =F23/F8 -> 0.054969802 | G24: =G23/G8 -> 0.064852895 | H24: =AVERAGE(E24:G24) -> 0.056027152 | I24: =H24 -> 0.056027152 | J24: =I24 -> 0.056027152 | K24: =J24 -> 0.056027152
B27: CapEx | C27: =IFERROR(__xludf.DUMMYFUNCTION("IFERROR( LET( x, UPPER(SUBSTITUTE(TRIM(Data!B380),CHAR(160),"""")), neg, IF(LEFT(x,1)=""("", -1, 1), numtext, REGEXEXTRACT(x,""[0-9.,]+""), base, VALUE(SUBSTITUTE(numtext,"","","""")), mult, IF(REGEXMATCH(x,""B""),1000000000, IF(REGE"&"XMATCH(x,""M""),1000000, 1)), neg * base * mult ), 0 ) "),-8.01E9) -> -8010000000 | D27: =IFERROR(__xludf.DUMMYFUNCTION("IFERROR( LET( x, UPPER(SUBSTITUTE(TRIM(Data!C380),CHAR(160),"""")), neg, IF(LEFT(x,1)=""("", -1, 1), numtext, REGEXEXTRACT(x,""[0-9.,]+""), base, VALUE(SUBSTITUTE(numtext,"","","""")), mult, IF(REGEXMATCH(x,""B""),1000000000, IF(REGE"&"XMATCH(x,""M""),1000000, 1)), neg * base * mult ), 0 ) "),-7.17E9) -> -7170000000 | E27: =IFERROR(__xludf.DUMMYFUNCTION("IFERROR( LET( x, UPPER(SUBSTITUTE(TRIM(Data!D380),CHAR(160),"""")), neg, IF(LEFT(x,1)=""("", -1, 1), numtext, REGEXEXTRACT(x,""[0-9.,]+""), base, VALUE(SUBSTITUTE(numtext,"","","""")), mult, IF(REGEXMATCH(x,""B""),1000000000, IF(REGE"&"XMATCH(x,""M""),1000000, 1)), neg * base * mult ), 0 ) "),-8.9E9) -> -8900000000 | F27: =IFERROR(__xludf.DUMMYFUNCTION("IFERROR( LET( x, UPPER(SUBSTITUTE(TRIM(Data!E380),CHAR(160),"""")), neg, IF(LEFT(x,1)=""("", -1, 1), numtext, REGEXEXTRACT(x,""[0-9.,]+""), base, VALUE(SUBSTITUTE(numtext,"","","""")), mult, IF(REGEXMATCH(x,""B""),1000000000, IF(REGE"&"XMATCH(x,""M""),1000000, 1)), neg * base * mult ), 0 ) "),-1.134E10) -> -11340000000 | G27: =IFERROR(__xludf.DUMMYFUNCTION("IFERROR( LET( x, UPPER(SUBSTITUTE(TRIM(Data!F380),CHAR(160),"""")), neg, IF(LEFT(x,1)=""("", -1, 1), numtext, REGEXEXTRACT(x,""[0-9.,]+""), base, VALUE(SUBSTITUTE(numtext,"","","""")), mult, IF(REGEXMATCH(x,""B""),1000000000, IF(REGE"&"XMATCH(x,""M""),1000000, 1)), neg * base * mult ), 0 ) "),-8.529999999999999E9) -> -8530000000 | H27: =H28*H8 -> -10174801147 | I27: =I28*I8 -> -11711501077 | J27: =J28*J8 -> -13834272731 | K27: =K28*K8 -> -21853521941
B28: % of sales | C28: =C27/C8 -> -0.14882943 | D28: =D27/D8 -> -0.088018659 | E28: =E27/E8 -> -0.091970652 | F28: =F27/F8 -> -0.11608148 | G28: =G27/G8 -> -0.089950438 | H28: =AVERAGE(E28:G28) -> -0.099334191 | I28: =H28 -> -0.099334191 | J28: =I28 -> -0.099334191 | K28: =J28 -> -0.099334191
B31: Changes in NWC | C31: =IFERROR(__xludf.DUMMYFUNCTION("IFERROR( LET( x, UPPER(SUBSTITUTE(TRIM(Data!B123),CHAR(160),"""")), neg, IF(LEFT(x,1)=""("", -1, 1), numtext, REGEXEXTRACT(x,""[0-9.,]+""), base, VALUE(SUBSTITUTE(numtext,"","","""")), mult, IF(REGEXMATCH(x,""B""),1000000000, IF(REGE"&"XMATCH(x,""M""),1000000, 1)), neg * base * mult ), 0 ) "),5.18E8) -> 518000000 | D31: =IFERROR(__xludf.DUMMYFUNCTION("IFERROR( LET( x, UPPER(SUBSTITUTE(TRIM(Data!C123),CHAR(160),"""")), neg, IF(LEFT(x,1)=""("", -1, 1), numtext, REGEXEXTRACT(x,""[0-9.,]+""), base, VALUE(SUBSTITUTE(numtext,"","","""")), mult, IF(REGEXMATCH(x,""B""),1000000000, IF(REGE"&"XMATCH(x,""M""),1000000, 1)), neg * base * mult ), 0 ) "),-3.91E9) -> -3910000000 | E31: =IFERROR(__xludf.DUMMYFUNCTION("IFERROR( LET( x, UPPER(SUBSTITUTE(TRIM(Data!D123),CHAR(160),"""")), neg, IF(LEFT(x,1)=""("", -1, 1), numtext, REGEXEXTRACT(x,""[0-9.,]+""), base, VALUE(SUBSTITUTE(numtext,"","","""")), mult, IF(REGEXMATCH(x,""B""),1000000000, IF(REGE"&"XMATCH(x,""M""),1000000, 1)), neg * base * mult ), 0 ) "),-2.25E9) -> -2250000000 | F31: =IFERROR(__xludf.DUMMYFUNCTION("IFERROR( LET( x, UPPER(SUBSTITUTE(TRIM(Data!E123),CHAR(160),"""")), neg, IF(LEFT(x,1)=""("", -1, 1), numtext, REGEXEXTRACT(x,""[0-9.,]+""), base, VALUE(SUBSTITUTE(numtext,"","","""")), mult, IF(REGEXMATCH(x,""B""),1000000000, IF(REGE"&"XMATCH(x,""M""),1000000, 1)), neg * base * mult ), 0 ) "),8.1E7) -> 81000000 | G31: =IFERROR(__xludf.DUMMYFUNCTION("IFERROR( LET( x, UPPER(SUBSTITUTE(TRIM(Data!F123),CHAR(160),"""")), neg, IF(LEFT(x,1)=""("", -1, 1), numtext, REGEXEXTRACT(x,""[0-9.,]+""), base, VALUE(SUBSTITUTE(numtext,"","","""")), mult, IF(REGEXMATCH(x,""B""),1000000000, IF(REGE"&"XMATCH(x,""M""),1000000, 1)), neg * base * mult ), 0 ) "),6.42E8) -> 642000000 | H31: =H32*H8 -> -5.3440615e+08 | I31: =I32*I8 -> -6.1511749e+08 | J31: =J32*J8 -> -7.266108e+08 | K31: =K32*K8 -> -1147801938
B32: % of sales | C32: =C31/C8 -> 0.0096246748 | D32: =D31/D8 -> -0.047999018 | E32: =E31/E8 -> -0.023251008 | F32: =F31/F8 -> 0.00082915344 | G32: =G31/G8 -> 0.0067700095 | H32: =AVERAGE(E32:G32) -> -0.0052172815 | I32: =H32 -> -0.0052172815 | J32: =I32 -> -0.0052172815 | K32: =J32 -> -0.0052172815
B35: Unlevered Free Cash Flow | C35: =C20 -> - | D35: =D20 -> - | E35: =E20 -> - | F35: =F20 -> - | G35: =G20 -> - | H35: =H20+H23-H27-H31 -> 21493479352 | I35: =I20+I23-I27-I31 -> 24739638929 | J35: =J20+J23-J27-J31 -> 29223829633 | K35: =K20+K23-K27-K31 -> 46163872472
B38: Discount Rate
B39: Discount Period | C39: - | D39: - | E39: - | F39: - | G39: -
B40: Discount Factor | C40: - | D40: - | E40: - | F40: - | G40: -
B43: Present Value of FCF | C43: - | D43: - | E43: - | F43: - | G43: - | H43: =H35/(1+$C$66)^1 -> 19621152929 | I43: =I35/(1+$C$66)^2 -> 20617165318 | J43: =J35/(1+$C$66)^3 -> 22232613700 | K43: =K35/(1+$C$66)^4 -> 32060731385
B46: Weighted Average Cost of Capital
B49: Equity Value | C49: =IFERROR(__xludf.DUMMYFUNCTION("GOOGLEFINANCE('Income Statement'!D1,""marketcap"")"),1.23286380975E12) -> 1232863809750
B50: % Equity | C50: =C49/C63 -> 0.99025698
B51: Cost of Equity | C51: =C52+(C53*C54) -> 0.096143
B52: Risk Free Rate | C52: =Data!A399 -> 0.0449
B53: Beta | C53: =Data!C315 -> 0.93
B54: Market Risk Premium | C54: =10%-C52 -> 0.0551
B57: Debt | C57: =IFERROR(__xludf.DUMMYFUNCTION("IFERROR( LET( x, UPPER(SUBSTITUTE(TRIM(Data!F344),CHAR(160),"""")), neg, IF(LEFT(x,1)=""("", -1, 1), numtext, REGEXEXTRACT(x,""[0-9.,]+""), base, VALUE(SUBSTITUTE(numtext,"","","""")), mult, IF(REGEXMATCH(x,""B""),1000000000, IF(REGE"&"XMATCH(x,""M""),1000000, 1)), neg * base * mult ), 0 ) "),1.213E10) -> 12130000000
B58: % Debt | C58: =C57/C63 -> 0.0097430203
B59: Cost of Debt | C59: =IFERROR(__xludf.DUMMYFUNCTION("((IFERROR( LET( x, UPPER(SUBSTITUTE(TRIM(Data!F26),CHAR(160),"""")), neg, IF(LEFT(x,1)=""("", -1, 1), numtext, REGEXEXTRACT(x,""[0-9.,]+""), base, VALUE(SUBSTITUTE(numtext,"","","""")), mult, IF(REGEXMATCH(x,""B""),1000000000, IF(REG"&"EXMATCH(x,""M""),1000000, 1)), neg * base * mult ), 0 ))/C57)*(1-C60)"),0.022333635614179722) -> 0.022333636
B60: Tax Rate | C60: =Data!D320 -> 0.1985
B63: Debt+Equity | C63: =C57+C49 -> 1244993809750
B66: Weighted Average Cost of Capital | C66: =(C50*C51)+(C58*C59) -> 0.095423874
B68: Terminal Value Calculation
B71: Terminal Growth Rate | C71: 0.02
B72: Terminal Value | C72: =(K35*(1+C71))/(C66-C71) -> 624300337685
B73: Present Value of Terminal Value | C73: =C72/((1+C66)^4) -> 433575529050
B74: Enterprise Value | C74: =SUM(H43,C73) -> 453196681980
B77: Implied Value per Share
B78: Enterprise Value | C78: =C74 -> 453196681980
B79: Cash + Short Term Investments | C79: =IFERROR(__xludf.DUMMYFUNCTION("IFERROR( LET( x, UPPER(SUBSTITUTE(TRIM(Data!F69),CHAR(160),"""")), neg, IF(LEFT(x,1)=""("", -1, 1), numtext, REGEXEXTRACT(x,""[0-9.,]+""), base, VALUE(SUBSTITUTE(numtext,"","","""")), mult, IF(REGEXMATCH(x,""B""),1000000000, IF(REGEX"&"MATCH(x,""M""),1000000, 1)), neg * base * mult ), 0 ) "),4.445E10) -> 44450000000
B80: Debt | C80: =C57 -> 12130000000
B81: Equity Value | C81: =C78+C79-C80 -> 485516681980
B84: Diluted Shares | C84: =IFERROR(__xludf.DUMMYFUNCTION("IFERROR( LET( x, UPPER(SUBSTITUTE(TRIM(Data!F58),CHAR(160),"""")), neg, IF(LEFT(x,1)=""("", -1, 1), numtext, REGEXEXTRACT(x,""[0-9.,]+""), base, VALUE(SUBSTITUTE(numtext,"","","""")), mult, IF(REGEXMATCH(x,""B""),1000000000, IF(REGEX"&"MATCH(x,""M""),1000000, 1)), neg * base * mult ), 0 ) "),3.53E9) -> 3530000000
B85: Implied Value per Share | C85: =C81/C84 -> 137.54014
B89: Sensitivity Table | D89: Terminal Growth Rate
B90: Implied Share Price (USD) | C90: =C85 -> 137.54014 | D90: =E90-0.5% -> 0.01 | E90: =F90-0.5% -> 0.015 | F90: =C71 -> 0.02 | G90: =F90+0.5% -> 0.025 | H90: =G90+0.5% -> 0.03
C91: =C92-0.5% -> 0.080423874 | D91: =(((DCF!$K$35*(1+DCF!$C$71))/(C91-$D$90))/((1+C91)^4)+DCF!$H$43+DCF!$C$79-DCF!$C$80)/DCF!$C$84 -> 153.71942 | E91: =(((DCF!$K$35*(1+DCF!$C$71))/(C91-$E$90))/((1+C91)^4)+DCF!$H$43+DCF!$C$79-DCF!$C$80)/DCF!$C$84 -> 164.34286 | F91: =(((DCF!$K$35*(1+DCF!$C$71))/(C91-$F$90))/((1+C91)^4)+DCF!$H$43+DCF!$C$79-DCF!$C$80)/DCF!$C$84 -> 176.72444 | G91: =(((DCF!$K$35*(1+DCF!$C$71))/(C91-$G$90))/((1+C91)^4)+DCF!$H$43+DCF!$C$79-DCF!$C$80)/DCF!$C$84 -> 191.34 | H91: =(((DCF!$K$35*(1+DCF!$C$71))/(C91-$H$90))/((1+C91)^4)+DCF!$H$43+DCF!$C$79-DCF!$C$80)/DCF!$C$84 -> 208.85411
C92: =C93-0.5% -> 0.085423874 | D92: =(((DCF!$K$35*(1+DCF!$C$71))/(C92-$D$90))/((1+C92)^4)+DCF!$H$43+DCF!$C$79-DCF!$C$80)/DCF!$C$84 -> 142.12945 | E92: =(((DCF!$K$35*(1+DCF!$C$71))/(C92-$E$90))/((1+C92)^4)+DCF!$H$43+DCF!$C$79-DCF!$C$80)/DCF!$C$84 -> 151.17576 | F92: =(((DCF!$K$35*(1+DCF!$C$71))/(C92-$F$90))/((1+C92)^4)+DCF!$H$43+DCF!$C$79-DCF!$C$80)/DCF!$C$84 -> 161.60479 | G92: =(((DCF!$K$35*(1+DCF!$C$71))/(C92-$G$90))/((1+C92)^4)+DCF!$H$43+DCF!$C$79-DCF!$C$80)/DCF!$C$84 -> 173.75981 | H92: =(((DCF!$K$35*(1+DCF!$C$71))/(C92-$H$90))/((1+C92)^4)+DCF!$H$43+DCF!$C$79-DCF!$C$80)/DCF!$C$84 -> 188.10792
C93: =C94-0.5% -> 0.090423874 | D93: =(((DCF!$K$35*(1+DCF!$C$71))/(C93-$D$90))/((1+C93)^4)+DCF!$H$43+DCF!$C$79-DCF!$C$80)/DCF!$C$84 -> 132.0313 | E93: =(((DCF!$K$35*(1+DCF!$C$71))/(C93-$E$90))/((1+C93)^4)+DCF!$H$43+DCF!$C$79-DCF!$C$80)/DCF!$C$84 -> 139.80849 | F93: =(((DCF!$K$35*(1+DCF!$C$71))/(C93-$F$90))/((1+C93)^4)+DCF!$H$43+DCF!$C$79-DCF!$C$80)/DCF!$C$84 -> 148.69001 | G93: =(((DCF!$K$35*(1+DCF!$C$71))/(C93-$G$90))/((1+C93)^4)+DCF!$H$43+DCF!$C$79-DCF!$C$80)/DCF!$C$84 -> 158.92908 | H93: =(((DCF!$K$35*(1+DCF!$C$71))/(C93-$H$90))/((1+C93)^4)+DCF!$H$43+DCF!$C$79-DCF!$C$80)/DCF!$C$84 -> 170.86268
B94: WACC | C94: =C66 -> 0.095423874 | D94: =(((DCF!$K$35*(1+DCF!$C$71))/(C94-$D$90))/((1+C94)^4)+DCF!$H$43+DCF!$C$79-DCF!$C$80)/DCF!$C$84 -> 123.16173 | E94: =(((DCF!$K$35*(1+DCF!$C$71))/(C94-$E$90))/((1+C94)^4)+DCF!$H$43+DCF!$C$79-DCF!$C$80)/DCF!$C$84 -> 129.90398 | F94: =(((DCF!$K$35*(1+DCF!$C$71))/(C94-$F$90))/((1+C94)^4)+DCF!$H$43+DCF!$C$79-DCF!$C$80)/DCF!$C$84 -> 137.54014 | G94: =(((DCF!$K$35*(1+DCF!$C$71))/(C94-$G$90))/((1+C94)^4)+DCF!$H$43+DCF!$C$79-DCF!$C$80)/DCF!$C$84 -> 146.26061 | H94: =(((DCF!$K$35*(1+DCF!$C$71))/(C94-$H$90))/((1+C94)^4)+DCF!$H$43+DCF!$C$79-DCF!$C$80)/DCF!$C$84 -> 156.31401
C95: =C94+0.5% -> 0.10042387 | D95: =(((DCF!$K$35*(1+DCF!$C$71))/(C95-$D$90))/((1+C95)^4)+DCF!$H$43+DCF!$C$79-DCF!$C$80)/DCF!$C$84 -> 115.31574 | E95: =(((DCF!$K$35*(1+DCF!$C$71))/(C95-$E$90))/((1+C95)^4)+DCF!$H$43+DCF!$C$79-DCF!$C$80)/DCF!$C$84 -> 121.20411 | F95: =(((DCF!$K$35*(1+DCF!$C$71))/(C95-$F$90))/((1+C95)^4)+DCF!$H$43+DCF!$C$79-DCF!$C$80)/DCF!$C$84 -> 127.82465 | G95: =(((DCF!$K$35*(1+DCF!$C$71))/(C95-$G$90))/((1+C95)^4)+DCF!$H$43+DCF!$C$79-DCF!$C$80)/DCF!$C$84 -> 135.32297 | H95: =(((DCF!$K$35*(1+DCF!$C$71))/(C95-$H$90))/((1+C95)^4)+DCF!$H$43+DCF!$C$79-DCF!$C$80)/DCF!$C$84 -> 143.88603
C96: =C95+0.5% -> 0.10542387 | D96: =(((DCF!$K$35*(1+DCF!$C$71))/(C96-$D$90))/((1+C96)^4)+DCF!$H$43+DCF!$C$79-DCF!$C$80)/DCF!$C$84 -> 108.33133 | E96: =(((DCF!$K$35*(1+DCF!$C$71))/(C96-$E$90))/((1+C96)^4)+DCF!$H$43+DCF!$C$79-DCF!$C$80)/DCF!$C$84 -> 113.5079 | F96: =(((DCF!$K$35*(1+DCF!$C$71))/(C96-$F$90))/((1+C96)^4)+DCF!$H$43+DCF!$C$79-DCF!$C$80)/DCF!$C$84 -> 119.29046 | G96: =(((DCF!$K$35*(1+DCF!$C$71))/(C96-$G$90))/((1+C96)^4)+DCF!$H$43+DCF!$C$79-DCF!$C$80)/DCF!$C$84 -> 125.79203 | H96: =(((DCF!$K$35*(1+DCF!$C$71))/(C96-$H$90))/((1+C96)^4)+DCF!$H$43+DCF!$C$79-DCF!$C$80)/DCF!$C$84 -> 133.1556
C97: =C96+0.5% -> 0.11042387 | D97: =(((DCF!$K$35*(1+DCF!$C$71))/(C97-$D$90))/((1+C97)^4)+DCF!$H$43+DCF!$C$79-DCF!$C$80)/DCF!$C$84 -> 102.07882 | E97: =(((DCF!$K$35*(1+DCF!$C$71))/(C97-$E$90))/((1+C97)^4)+DCF!$H$43+DCF!$C$79-DCF!$C$80)/DCF!$C$84 -> 106.65654 | F97: =(((DCF!$K$35*(1+DCF!$C$71))/(C97-$F$90))/((1+C97)^4)+DCF!$H$43+DCF!$C$79-DCF!$C$80)/DCF!$C$84 -> 111.7405 | G97: =(((DCF!$K$35*(1+DCF!$C$71))/(C97-$G$90))/((1+C97)^4)+DCF!$H$43+DCF!$C$79-DCF!$C$80)/DCF!$C$84 -> 117.41961 | H97: =(((DCF!$K$35*(1+DCF!$C$71))/(C97-$H$90))/((1+C97)^4)+DCF!$H$43+DCF!$C$79-DCF!$C$80)/DCF!$C$84 -> 123.80486

Sheet Data
I1: GLITCH may occur where the data tables don't load
I2: Which will leave to a #DIV/0 error
I3: In this case, go to each cell N/A cell here, remove the number at the end of the equation, then click enter
A4: =IFERROR(__xludf.DUMMYFUNCTION("IMPORTHTML(CONCAT(CONCAT(""https://www.marketwatch.com/investing/stock/"",'Income Statement'!D1),""/financials?mod=mw_quote_tab""),""table"",4) "),"Item Item") -> Item Item | B4: =IFERROR(__xludf.DUMMYFUNCTION("""COMPUTED_VALUE"""),2021.0) -> 2021 | C4: =IFERROR(__xludf.DUMMYFUNCTION("""COMPUTED_VALUE"""),2022.0) -> 2022 | D4: =IFERROR(__xludf.DUMMYFUNCTION("""COMPUTED_VALUE"""),2023.0) -> 2023 | E4: =IFERROR(__xludf.DUMMYFUNCTION("""COMPUTED_VALUE"""),2024.0) -> 2024 | F4: =IFERROR(__xludf.DUMMYFUNCTION("""COMPUTED_VALUE"""),2025.0) -> 2025 | G4: =IFERROR(__xludf.DUMMYFUNCTION("""COMPUTED_VALUE"""),"5-year trend") -> 5-year trend | I4: Then re-write that number again
A5: =IFERROR(__xludf.DUMMYFUNCTION("""COMPUTED_VALUE"""),"Sales/Revenue Sales/Revenue") -> Sales/Revenue Sales/Revenue | B5: =IFERROR(__xludf.DUMMYFUNCTION("""COMPUTED_VALUE"""),"53.82B") -> 53.82B | C5: =IFERROR(__xludf.DUMMYFUNCTION("""COMPUTED_VALUE"""),"81.46B") -> 81.46B | D5: =IFERROR(__xludf.DUMMYFUNCTION("""COMPUTED_VALUE"""),"96.77B") -> 96.77B | E5: =IFERROR(__xludf.DUMMYFUNCTION("""COMPUTED_VALUE"""),"97.69B") -> 97.69B | F5: =IFERROR(__xludf.DUMMYFUNCTION("""COMPUTED_VALUE"""),"94.83B") -> 94.83B | I5: Repeat for all the cells which say N/A
A6: =IFERROR(__xludf.DUMMYFUNCTION("""COMPUTED_VALUE"""),"Sales Growth Sales Growth") -> Sales Growth Sales Growth | B6: =IFERROR(__xludf.DUMMYFUNCTION("""COMPUTED_VALUE"""),"-") -> - | C6: =IFERROR(__xludf.DUMMYFUNCTION("""COMPUTED_VALUE"""),0.5135) -> 0.5135 | D6: =IFERROR(__xludf.DUMMYFUNCTION("""COMPUTED_VALUE"""),0.188) -> 0.188 | E6: =IFERROR(__xludf.DUMMYFUNCTION("""COMPUTED_VALUE"""),0.0095) -> 0.0095 | F6: =IFERROR(__xludf.DUMMYFUNCTION("""COMPUTED_VALUE"""),-0.0293) -> -0.0293
A7: =IFERROR(__xludf.DUMMYFUNCTION("""COMPUTED_VALUE"""),"Cost of Goods Sold (COGS) incl. D&A Cost of Goods Sold (COGS) incl. D&A") -> Cost of Goods Sold (COGS) incl. D&A Cost of Goods Sold (COGS) incl. D&A | B7: =IFERROR(__xludf.DUMMYFUNCTION("""COMPUTED_VALUE"""),"40.22B") -> 40.22B | C7: =IFERROR(__xludf.DUMMYFUNCTION("""COMPUTED_VALUE"""),"60.61B") -> 60.61B | D7: =IFERROR(__xludf.DUMMYFUNCTION("""COMPUTED_VALUE"""),"79.11B") -> 79.11B | E7: =IFERROR(__xludf.DUMMYFUNCTION("""COMPUTED_VALUE"""),"80.24B") -> 80.24B | F7: =IFERROR(__xludf.DUMMYFUNCTION("""COMPUTED_VALUE"""),"77.73B") -> 77.73B
A8: =IFERROR(__xludf.DUMMYFUNCTION("""COMPUTED_VALUE"""),"COGS Growth COGS Growth") -> COGS Growth COGS Growth | B8: =IFERROR(__xludf.DUMMYFUNCTION("""COMPUTED_VALUE"""),"-") -> - | C8: =IFERROR(__xludf.DUMMYFUNCTION("""COMPUTED_VALUE"""),0.507) -> 0.507 | D8: =IFERROR(__xludf.DUMMYFUNCTION("""COMPUTED_VALUE"""),0.3053) -> 0.3053 | E8: =IFERROR(__xludf.DUMMYFUNCTION("""COMPUTED_VALUE"""),0.0142) -> 0.0142 | F8: =IFERROR(__xludf.DUMMYFUNCTION("""COMPUTED_VALUE"""),-0.0312) -> -0.0312
A9: =IFERROR(__xludf.DUMMYFUNCTION("""COMPUTED_VALUE"""),"COGS excluding D&A COGS excluding D&A") -> COGS excluding D&A COGS excluding D&A | B9: =IFERROR(__xludf.DUMMYFUNCTION("""COMPUTED_VALUE"""),"37.31B") -> 37.31B | C9: =IFERROR(__xludf.DUMMYFUNCTION("""COMPUTED_VALUE"""),"57.07B") -> 57.07B | D9: =IFERROR(__xludf.DUMMYFUNCTION("""COMPUTED_VALUE"""),"74.45B") -> 74.45B | E9: =IFERROR(__xludf.DUMMYFUNCTION("""COMPUTED_VALUE"""),"74.87B") -> 74.87B | F9: =IFERROR(__xludf.DUMMYFUNCTION("""COMPUTED_VALUE"""),"71.59B") -> 71.59B
A10: =IFERROR(__xludf.DUMMYFUNCTION("""COMPUTED_VALUE"""),"Depreciation & Amortization Expense Depreciation & Amortization Expense") -> Depreciation & Amortization Expense Depreciation & Amortization Expense | B10: =IFERROR(__xludf.DUMMYFUNCTION("""COMPUTED_VALUE"""),"2.91B") -> 2.91B | C10: =IFERROR(__xludf.DUMMYFUNCTION("""COMPUTED_VALUE"""),"3.54B") -> 3.54B | D10: =IFERROR(__xludf.DUMMYFUNCTION("""COMPUTED_VALUE"""),"4.67B") -> 4.67B | E10: =IFERROR(__xludf.DUMMYFUNCTION("""COMPUTED_VALUE"""),"5.37B") -> 5.37B | F10: =IFERROR(__xludf.DUMMYFUNCTION("""COMPUTED_VALUE"""),"6.15B") -> 6.15B
A11: =IFERROR(__xludf.DUMMYFUNCTION("""COMPUTED_VALUE"""),"Depreciation Depreciation") -> Depreciation Depreciation | B11: =IFERROR(__xludf.DUMMYFUNCTION("""COMPUTED_VALUE"""),"1.91B") -> 1.91B | C11: =IFERROR(__xludf.DUMMYFUNCTION("""COMPUTED_VALUE"""),"2.66B") -> 2.66B | D11: =IFERROR(__xludf.DUMMYFUNCTION("""COMPUTED_VALUE"""),"3.57B") -> 3.57B | E11: =IFERROR(__xludf.DUMMYFUNCTION("""COMPUTED_VALUE"""),"4.12B") -> 4.12B | F11: =IFERROR(__xludf.DUMMYFUNCTION("""COMPUTED_VALUE"""),"5.03B") -> 5.03B
A12: =IFERROR(__xludf.DUMMYFUNCTION("""COMPUTED_VALUE"""),"Amortization of Intangibles Amortization of Intangibles") -> Amortization of Intangibles Amortization of Intangibles | B12: =IFERROR(__xludf.DUMMYFUNCTION("""COMPUTED_VALUE"""),"1B") -> 1B | C12: =IFERROR(__xludf.DUMMYFUNCTION("""COMPUTED_VALUE"""),"888M") -> 888M | D12: =IFERROR(__xludf.DUMMYFUNCTION("""COMPUTED_VALUE"""),"1.1B") -> 1.1B | E12: =IFERROR(__xludf.DUMMYFUNCTION("""COMPUTED_VALUE"""),"1.25B") -> 1.25B | F12: =IFERROR(__xludf.DUMMYFUNCTION("""COMPUTED_VALUE"""),"1.12B") -> 1.12B
A13: =IFERROR(__xludf.DUMMYFUNCTION("""COMPUTED_VALUE"""),"Gross Income Gross Income") -> Gross Income Gross Income | B13: =IFERROR(__xludf.DUMMYFUNCTION("""COMPUTED_VALUE"""),"13.61B") -> 13.61B | C13: =IFERROR(__xludf.DUMMYFUNCTION("""COMPUTED_VALUE"""),"20.85B") -> 20.85B | D13: =IFERROR(__xludf.DUMMYFUNCTION("""COMPUTED_VALUE"""),"17.66B") -> 17.66B | E13: =IFERROR(__xludf.DUMMYFUNCTION("""COMPUTED_VALUE"""),"17.45B") -> 17.45B | F13: =IFERROR(__xludf.DUMMYFUNCTION("""COMPUTED_VALUE"""),"17.09B") -> 17.09B
A14: =IFERROR(__xludf.DUMMYFUNCTION("""COMPUTED_VALUE"""),"Gross Income Growth Gross Income Growth") -> Gross Income Growth Gross Income Growth | B14: =IFERROR(__xludf.DUMMYFUNCTION("""COMPUTED_VALUE"""),"-") -> - | C14: =IFERROR(__xludf.DUMMYFUNCTION("""COMPUTED_VALUE"""),0.5326) -> 0.5326 | D14: =IFERROR(__xludf.DUMMYFUNCTION("""COMPUTED_VALUE"""),-0.1531) -> -0.1531 | E14: =IFERROR(__xludf.DUMMYFUNCTION("""COMPUTED_VALUE"""),-0.0119) -> -0.0119 | F14: =IFERROR(__xludf.DUMMYFUNCTION("""COMPUTED_VALUE"""),-0.0204) -> -0.0204
A15: =IFERROR(__xludf.DUMMYFUNCTION("""COMPUTED_VALUE"""),"Gross Profit Margin Gross Profit Margin") -> Gross Profit Margin Gross Profit Margin | B15: =IFERROR(__xludf.DUMMYFUNCTION("""COMPUTED_VALUE"""),"-") -> - | C15: =IFERROR(__xludf.DUMMYFUNCTION("""COMPUTED_VALUE"""),"-") -> - | D15: =IFERROR(__xludf.DUMMYFUNCTION("""COMPUTED_VALUE"""),"-") -> - | E15: =IFERROR(__xludf.DUMMYFUNCTION("""COMPUTED_VALUE"""),"-") -> - | F15: =IFERROR(__xludf.DUMMYFUNCTION("""COMPUTED_VALUE"""),0.1803) -> 0.1803
A16: =IFERROR(__xludf.DUMMYFUNCTION("""COMPUTED_VALUE"""),"SG&A Expense SG&A Expense") -> SG&A Expense SG&A Expense | B16: =IFERROR(__xludf.DUMMYFUNCTION("""COMPUTED_VALUE"""),"7.11B") -> 7.11B | C16: =IFERROR(__xludf.DUMMYFUNCTION("""COMPUTED_VALUE"""),"7.02B") -> 7.02B | D16: =IFERROR(__xludf.DUMMYFUNCTION("""COMPUTED_VALUE"""),"8.77B") -> 8.77B | E16: =IFERROR(__xludf.DUMMYFUNCTION("""COMPUTED_VALUE"""),"9.69B") -> 9.69B | F16: =IFERROR(__xludf.DUMMYFUNCTION("""COMPUTED_VALUE"""),"12.25B") -> 12.25B
A17: =IFERROR(__xludf.DUMMYFUNCTION("""COMPUTED_VALUE"""),"SGA Growth SGA Growth") -> SGA Growth SGA Growth | B17: =IFERROR(__xludf.DUMMYFUNCTION("""COMPUTED_VALUE"""),"-") -> - | C17: =IFERROR(__xludf.DUMMYFUNCTION("""COMPUTED_VALUE"""),-0.0125) -> -0.0125 | D17: =IFERROR(__xludf.DUMMYFUNCTION("""COMPUTED_VALUE"""),0.249) -> 0.249 | E17: =IFERROR(__xludf.DUMMYFUNCTION("""COMPUTED_VALUE"""),0.105) -> 0.105 | F17: =IFERROR(__xludf.DUMMYFUNCTION("""COMPUTED_VALUE"""),0.2637) -> 0.2637
A18: =IFERROR(__xludf.DUMMYFUNCTION("""COMPUTED_VALUE"""),"Research & Development Research & Development") -> Research & Development Research & Development | B18: =IFERROR(__xludf.DUMMYFUNCTION("""COMPUTED_VALUE"""),"2.59B") -> 2.59B | C18: =IFERROR(__xludf.DUMMYFUNCTION("""COMPUTED_VALUE"""),"3.08B") -> 3.08B | D18: =IFERROR(__xludf.DUMMYFUNCTION("""COMPUTED_VALUE"""),"3.97B") -> 3.97B | E18: =IFERROR(__xludf.DUMMYFUNCTION("""COMPUTED_VALUE"""),"4.54B") -> 4.54B | F18: =IFERROR(__xludf.DUMMYFUNCTION("""COMPUTED_VALUE"""),"6.41B") -> 6.41B
A19: =IFERROR(__xludf.DUMMYFUNCTION("""COMPUTED_VALUE"""),"Other SG&A Other SG&A") -> Other SG&A Other SG&A | B19: =IFERROR(__xludf.DUMMYFUNCTION("""COMPUTED_VALUE"""),"4.52B") -> 4.52B | C19: =IFERROR(__xludf.DUMMYFUNCTION("""COMPUTED_VALUE"""),"3.95B") -> 3.95B | D19: =IFERROR(__xludf.DUMMYFUNCTION("""COMPUTED_VALUE"""),"4.8B") -> 4.8B | E19: =IFERROR(__xludf.DUMMYFUNCTION("""COMPUTED_VALUE"""),"5.15B") -> 5.15B | F19: =IFERROR(__xludf.DUMMYFUNCTION("""COMPUTED_VALUE"""),"5.83B") -> 5.83B
A20: =IFERROR(__xludf.DUMMYFUNCTION("""COMPUTED_VALUE"""),"Other Operating Expense Other Operating Expense") -> Other Operating Expense Other Operating Expense | B20: =IFERROR(__xludf.DUMMYFUNCTION("""COMPUTED_VALUE"""),"-") -> - | C20: =IFERROR(__xludf.DUMMYFUNCTION("""COMPUTED_VALUE"""),"-") -> - | D20: =IFERROR(__xludf.DUMMYFUNCTION("""COMPUTED_VALUE"""),"-") -> - | E20: =IFERROR(__xludf.DUMMYFUNCTION("""COMPUTED_VALUE"""),"-") -> - | F20: =IFERROR(__xludf.DUMMYFUNCTION("""COMPUTED_VALUE"""),"-") -> -
A21: =IFERROR(__xludf.DUMMYFUNCTION("""COMPUTED_VALUE"""),"Unusual Expense Unusual Expense") -> Unusual Expense Unusual Expense | B21: =IFERROR(__xludf.DUMMYFUNCTION("""COMPUTED_VALUE"""),"(40M)") -> (40M) | C21: =IFERROR(__xludf.DUMMYFUNCTION("""COMPUTED_VALUE"""),"150M") -> 150M | D21: =IFERROR(__xludf.DUMMYFUNCTION("""COMPUTED_VALUE"""),"4M") -> 4M | E21: =IFERROR(__xludf.DUMMYFUNCTION("""COMPUTED_VALUE"""),"670M") -> 670M | F21: =IFERROR(__xludf.DUMMYFUNCTION("""COMPUTED_VALUE"""),"562M") -> 562M
A22: =IFERROR(__xludf.DUMMYFUNCTION("""COMPUTED_VALUE"""),"EBIT after Unusual Expense EBIT after Unusual Expense") -> EBIT after Unusual Expense EBIT after Unusual Expense | B22: =IFERROR(__xludf.DUMMYFUNCTION("""COMPUTED_VALUE"""),"6.54B") -> 6.54B | C22: =IFERROR(__xludf.DUMMYFUNCTION("""COMPUTED_VALUE"""),"13.68B") -> 13.68B | D22: =IFERROR(__xludf.DUMMYFUNCTION("""COMPUTED_VALUE"""),"8.89B") -> 8.89B | E22: =IFERROR(__xludf.DUMMYFUNCTION("""COMPUTED_VALUE"""),"7.09B") -> 7.09B | F22: =IFERROR(__xludf.DUMMYFUNCTION("""COMPUTED_VALUE"""),"4.29B") -> 4.29B
A23: =IFERROR(__xludf.DUMMYFUNCTION("""COMPUTED_VALUE"""),"Non Operating Income/Expense Non Operating Income/Expense") -> Non Operating Income/Expense Non Operating Income/Expense | B23: =IFERROR(__xludf.DUMMYFUNCTION("""COMPUTED_VALUE"""),"122M") -> 122M | C23: =IFERROR(__xludf.DUMMYFUNCTION("""COMPUTED_VALUE"""),"(69M)") -> (69M) | D23: =IFERROR(__xludf.DUMMYFUNCTION("""COMPUTED_VALUE"""),"176M") -> 176M | E23: =IFERROR(__xludf.DUMMYFUNCTION("""COMPUTED_VALUE"""),"681M") -> 681M | F23: =IFERROR(__xludf.DUMMYFUNCTION("""COMPUTED_VALUE"""),"(351M)") -> (351M)
A24: =IFERROR(__xludf.DUMMYFUNCTION("""COMPUTED_VALUE"""),"Non-Operating Interest Income Non-Operating Interest Income") -> Non-Operating Interest Income Non-Operating Interest Income | B24: =IFERROR(__xludf.DUMMYFUNCTION("""COMPUTED_VALUE"""),"56M") -> 56M | C24: =IFERROR(__xludf.DUMMYFUNCTION("""COMPUTED_VALUE"""),"297M") -> 297M | D24: =IFERROR(__xludf.DUMMYFUNCTION("""COMPUTED_VALUE"""),"1.07B") -> 1.07B | E24: =IFERROR(__xludf.DUMMYFUNCTION("""COMPUTED_VALUE"""),"1.57B") -> 1.57B | F24: =IFERROR(__xludf.DUMMYFUNCTION("""COMPUTED_VALUE"""),"1.68B") -> 1.68B
A25: =IFERROR(__xludf.DUMMYFUNCTION("""COMPUTED_VALUE"""),"Equity in Affiliates (Pretax) Equity in Affiliates (Pretax)") -> Equity in Affiliates (Pretax) Equity in Affiliates (Pretax) | B25: =IFERROR(__xludf.DUMMYFUNCTION("""COMPUTED_VALUE"""),"-") -> - | C25: =IFERROR(__xludf.DUMMYFUNCTION("""COMPUTED_VALUE"""),"-") -> - | D25: =IFERROR(__xludf.DUMMYFUNCTION("""COMPUTED_VALUE"""),"-") -> - | E25: =IFERROR(__xludf.DUMMYFUNCTION("""COMPUTED_VALUE"""),"-") -> - | F25: =IFERROR(__xludf.DUMMYFUNCTION("""COMPUTED_VALUE"""),"-") -> -
A26: =IFERROR(__xludf.DUMMYFUNCTION("""COMPUTED_VALUE"""),"Interest Expense Interest Expense") -> Interest Expense Interest Expense | B26: =IFERROR(__xludf.DUMMYFUNCTION("""COMPUTED_VALUE"""),"371M") -> 371M | C26: =IFERROR(__xludf.DUMMYFUNCTION("""COMPUTED_VALUE"""),"191M") -> 191M | D26: =IFERROR(__xludf.DUMMYFUNCTION("""COMPUTED_VALUE"""),"156M") -> 156M | E26: =IFERROR(__xludf.DUMMYFUNCTION("""COMPUTED_VALUE"""),"350M") -> 350M | F26: =IFERROR(__xludf.DUMMYFUNCTION("""COMPUTED_VALUE"""),"338M") -> 338M
A27: =IFERROR(__xludf.DUMMYFUNCTION("""COMPUTED_VALUE"""),"Interest Expense Growth Interest Expense Growth") -> Interest Expense Growth Interest Expense Growth | B27: =IFERROR(__xludf.DUMMYFUNCTION("""COMPUTED_VALUE"""),"-") -> - | C27: =IFERROR(__xludf.DUMMYFUNCTION("""COMPUTED_VALUE"""),-0.4852) -> -0.4852 | D27: =IFERROR(__xludf.DUMMYFUNCTION("""COMPUTED_VALUE"""),-0.1832) -> -0.1832 | E27: =IFERROR(__xludf.DUMMYFUNCTION("""COMPUTED_VALUE"""),1.2436) -> 1.2436 | F27: =IFERROR(__xludf.DUMMYFUNCTION("""COMPUTED_VALUE"""),-0.0343) -> -0.0343
A28: =IFERROR(__xludf.DUMMYFUNCTION("""COMPUTED_VALUE"""),"Gross Interest Expense Gross Interest Expense") -> Gross Interest Expense Gross Interest Expense | B28: =IFERROR(__xludf.DUMMYFUNCTION("""COMPUTED_VALUE"""),"424M") -> 424M | C28: =IFERROR(__xludf.DUMMYFUNCTION("""COMPUTED_VALUE"""),"191M") -> 191M | D28: =IFERROR(__xludf.DUMMYFUNCTION("""COMPUTED_VALUE"""),"156M") -> 156M | E28: =IFERROR(__xludf.DUMMYFUNCTION("""COMPUTED_VALUE"""),"350M") -> 350M | F28: =IFERROR(__xludf.DUMMYFUNCTION("""COMPUTED_VALUE"""),"338M") -> 338M
A29: =IFERROR(__xludf.DUMMYFUNCTION("""COMPUTED_VALUE"""),"Interest Capitalized Interest Capitalized") -> Interest Capitalized Interest Capitalized | B29: =IFERROR(__xludf.DUMMYFUNCTION("""COMPUTED_VALUE"""),"53M") -> 53M | C29: =IFERROR(__xludf.DUMMYFUNCTION("""COMPUTED_VALUE"""),"-") -> - | D29: =IFERROR(__xludf.DUMMYFUNCTION("""COMPUTED_VALUE"""),"-") -> - | E29: =IFERROR(__xludf.DUMMYFUNCTION("""COMPUTED_VALUE"""),"-") -> - | F29: =IFERROR(__xludf.DUMMYFUNCTION("""COMPUTED_VALUE"""),"-") -> -
A30: =IFERROR(__xludf.DUMMYFUNCTION("""COMPUTED_VALUE"""),"Pretax Income Pretax Income") -> Pretax Income Pretax Income | B30: =IFERROR(__xludf.DUMMYFUNCTION("""COMPUTED_VALUE"""),"6.34B") -> 6.34B | C30: =IFERROR(__xludf.DUMMYFUNCTION("""COMPUTED_VALUE"""),"13.72B") -> 13.72B | D30: =IFERROR(__xludf.DUMMYFUNCTION("""COMPUTED_VALUE"""),"9.97B") -> 9.97B | E30: =IFERROR(__xludf.DUMMYFUNCTION("""COMPUTED_VALUE"""),"8.99B") -> 8.99B | F30: =IFERROR(__xludf.DUMMYFUNCTION("""COMPUTED_VALUE"""),"5.28B") -> 5.28B
A31: =IFERROR(__xludf.DUMMYFUNCTION("""COMPUTED_VALUE"""),"Pretax Income Growth Pretax Income Growth") -> Pretax Income Growth Pretax Income Growth | B31: =IFERROR(__xludf.DUMMYFUNCTION("""COMPUTED_VALUE"""),"-") -> - | C31: =IFERROR(__xludf.DUMMYFUNCTION("""COMPUTED_VALUE"""),1.1629) -> 1.1629 | D31: =IFERROR(__xludf.DUMMYFUNCTION("""COMPUTED_VALUE"""),-0.2731) -> -0.2731 | E31: =IFERROR(__xludf.DUMMYFUNCTION("""COMPUTED_VALUE"""),-0.0986) -> -0.0986 | F31: =IFERROR(__xludf.DUMMYFUNCTION("""COMPUTED_VALUE"""),-0.4129) -> -0.4129
A32: =IFERROR(__xludf.DUMMYFUNCTION("""COMPUTED_VALUE"""),"Pretax Margin Pretax Margin") -> Pretax Margin Pretax Margin | B32: =IFERROR(__xludf.DUMMYFUNCTION("""COMPUTED_VALUE"""),"-") -> - | C32: =IFERROR(__xludf.DUMMYFUNCTION("""COMPUTED_VALUE"""),"-") -> - | D32: =IFERROR(__xludf.DUMMYFUNCTION("""COMPUTED_VALUE"""),"-") -> - | E32: =IFERROR(__xludf.DUMMYFUNCTION("""COMPUTED_VALUE"""),"-") -> - | F32: =IFERROR(__xludf.DUMMYFUNCTION("""COMPUTED_VALUE"""),0.0557) -> 0.0557
A33: =IFERROR(__xludf.DUMMYFUNCTION("""COMPUTED_VALUE"""),"Income Tax Income Tax") -> Income Tax Income Tax | B33: =IFERROR(__xludf.DUMMYFUNCTION("""COMPUTED_VALUE"""),"699M") -> 699M | C33: =IFERROR(__xludf.DUMMYFUNCTION("""COMPUTED_VALUE"""),"1.13B") -> 1.13B | D33: =IFERROR(__xludf.DUMMYFUNCTION("""COMPUTED_VALUE"""),"(5B)") -> (5B) | E33: =IFERROR(__xludf.DUMMYFUNCTION("""COMPUTED_VALUE"""),"1.84B") -> 1.84B | F33: =IFERROR(__xludf.DUMMYFUNCTION("""COMPUTED_VALUE"""),"1.42B") -> 1.42B
A34: =IFERROR(__xludf.DUMMYFUNCTION("""COMPUTED_VALUE"""),"Income Tax - Current Domestic Income Tax - Current Domestic") -> Income Tax - Current Domestic Income Tax - Current Domestic | B34: =IFERROR(__xludf.DUMMYFUNCTION("""COMPUTED_VALUE"""),"9M") -> 9M | C34: =IFERROR(__xludf.DUMMYFUNCTION("""COMPUTED_VALUE"""),"62M") -> 62M | D34: =IFERROR(__xludf.DUMMYFUNCTION("""COMPUTED_VALUE"""),"105M") -> 105M | E34: =IFERROR(__xludf.DUMMYFUNCTION("""COMPUTED_VALUE"""),"45M") -> 45M | F34: =IFERROR(__xludf.DUMMYFUNCTION("""COMPUTED_VALUE"""),"5M") -> 5M
A35: =IFERROR(__xludf.DUMMYFUNCTION("""COMPUTED_VALUE"""),"Income Tax - Current Foreign Income Tax - Current Foreign") -> Income Tax - Current Foreign Income Tax - Current Foreign | B35: =IFERROR(__xludf.DUMMYFUNCTION("""COMPUTED_VALUE"""),"839M") -> 839M | C35: =IFERROR(__xludf.DUMMYFUNCTION("""COMPUTED_VALUE"""),"1.27B") -> 1.27B | D35: =IFERROR(__xludf.DUMMYFUNCTION("""COMPUTED_VALUE"""),"1.24B") -> 1.24B | E35: =IFERROR(__xludf.DUMMYFUNCTION("""COMPUTED_VALUE"""),"1.32B") -> 1.32B | F35: =IFERROR(__xludf.DUMMYFUNCTION("""COMPUTED_VALUE"""),"1.3B") -> 1.3B
A36: =IFERROR(__xludf.DUMMYFUNCTION("""COMPUTED_VALUE"""),"Income Tax - Deferred Domestic Income Tax - Deferred Domestic") -> Income Tax - Deferred Domestic Income Tax - Deferred Domestic | B36: =IFERROR(__xludf.DUMMYFUNCTION("""COMPUTED_VALUE"""),"-") -> - | C36: =IFERROR(__xludf.DUMMYFUNCTION("""COMPUTED_VALUE"""),"27M") -> 27M | D36: =IFERROR(__xludf.DUMMYFUNCTION("""COMPUTED_VALUE"""),"(5.9B)") -> (5.9B) | E36: =IFERROR(__xludf.DUMMYFUNCTION("""COMPUTED_VALUE"""),"782M") -> 782M | F36: =IFERROR(__xludf.DUMMYFUNCTION("""COMPUTED_VALUE"""),"455M") -> 455M
A37: =IFERROR(__xludf.DUMMYFUNCTION("""COMPUTED_VALUE"""),"Income Tax - Deferred Foreign Income Tax - Deferred Foreign") -> Income Tax - Deferred Foreign Income Tax - Deferred Foreign | B37: =IFERROR(__xludf.DUMMYFUNCTION("""COMPUTED_VALUE"""),"(149M)") -> (149M) | C37: =IFERROR(__xludf.DUMMYFUNCTION("""COMPUTED_VALUE"""),"(223M)") -> (223M) | D37: =IFERROR(__xludf.DUMMYFUNCTION("""COMPUTED_VALUE"""),"(450M)") -> (450M) | E37: =IFERROR(__xludf.DUMMYFUNCTION("""COMPUTED_VALUE"""),"(305M)") -> (305M) | F37: =IFERROR(__xludf.DUMMYFUNCTION("""COMPUTED_VALUE"""),"(332M)") -> (332M)
A38: =IFERROR(__xludf.DUMMYFUNCTION("""COMPUTED_VALUE"""),"Income Tax Credits Income Tax Credits") -> Income Tax Credits Income Tax Credits | B38: =IFERROR(__xludf.DUMMYFUNCTION("""COMPUTED_VALUE"""),"-") -> - | C38: =IFERROR(__xludf.DUMMYFUNCTION("""COMPUTED_VALUE"""),"-") -> - | D38: =IFERROR(__xludf.DUMMYFUNCTION("""COMPUTED_VALUE"""),"-") -> - | E38: =IFERROR(__xludf.DUMMYFUNCTION("""COMPUTED_VALUE"""),"-") -> - | F38: =IFERROR(__xludf.DUMMYFUNCTION("""COMPUTED_VALUE"""),"-") -> -
A39: =IFERROR(__xludf.DUMMYFUNCTION("""COMPUTED_VALUE"""),"Equity in Affiliates Equity in Affiliates") -> Equity in Affiliates Equity in Affiliates | B39: =IFERROR(__xludf.DUMMYFUNCTION("""COMPUTED_VALUE"""),"-") -> - | C39: =IFERROR(__xludf.DUMMYFUNCTION("""COMPUTED_VALUE"""),"-") -> - | D39: =IFERROR(__xludf.DUMMYFUNCTION("""COMPUTED_VALUE"""),"-") -> - | E39: =IFERROR(__xludf.DUMMYFUNCTION("""COMPUTED_VALUE"""),"-") -> - | F39: =IFERROR(__xludf.DUMMYFUNCTION("""COMPUTED_VALUE"""),"-") -> -
A40: =IFERROR(__xludf.DUMMYFUNCTION("""COMPUTED_VALUE"""),"Other After Tax Income (Expense) Other After Tax Income (Expense)") -> Other After Tax Income (Expense) Other After Tax Income (Expense) | B40: =IFERROR(__xludf.DUMMYFUNCTION("""COMPUTED_VALUE"""),"5M") -> 5M | C40: =IFERROR(__xludf.DUMMYFUNCTION("""COMPUTED_VALUE"""),"27M") -> 27M | D40: =IFERROR(__xludf.DUMMYFUNCTION("""COMPUTED_VALUE"""),"2M") -> 2M | E40: =IFERROR(__xludf.DUMMYFUNCTION("""COMPUTED_VALUE"""),"39M") -> 39M | F40: =IFERROR(__xludf.DUMMYFUNCTION("""COMPUTED_VALUE"""),"-") -> -
A41: =IFERROR(__xludf.DUMMYFUNCTION("""COMPUTED_VALUE"""),"Consolidated Net Income Consolidated Net Income") -> Consolidated Net Income Consolidated Net Income | B41: =IFERROR(__xludf.DUMMYFUNCTION("""COMPUTED_VALUE"""),"5.65B") -> 5.65B | C41: =IFERROR(__xludf.DUMMYFUNCTION("""COMPUTED_VALUE"""),"12.61B") -> 12.61B | D41: =IFERROR(__xludf.DUMMYFUNCTION("""COMPUTED_VALUE"""),"14.98B") -> 14.98B | E41: =IFERROR(__xludf.DUMMYFUNCTION("""COMPUTED_VALUE"""),"7.19B") -> 7.19B | F41: =IFERROR(__xludf.DUMMYFUNCTION("""COMPUTED_VALUE"""),"3.86B") -> 3.86B
A42: =IFERROR(__xludf.DUMMYFUNCTION("""COMPUTED_VALUE"""),"Minority Interest Expense Minority Interest Expense") -> Minority Interest Expense Minority Interest Expense | B42: =IFERROR(__xludf.DUMMYFUNCTION("""COMPUTED_VALUE"""),"125M") -> 125M | C42: =IFERROR(__xludf.DUMMYFUNCTION("""COMPUTED_VALUE"""),"31M") -> 31M | D42: =IFERROR(__xludf.DUMMYFUNCTION("""COMPUTED_VALUE"""),"(23M)") -> (23M) | E42: =IFERROR(__xludf.DUMMYFUNCTION("""COMPUTED_VALUE"""),"62M") -> 62M | F42: =IFERROR(__xludf.DUMMYFUNCTION("""COMPUTED_VALUE"""),"61M") -> 61M
A43: =IFERROR(__xludf.DUMMYFUNCTION("""COMPUTED_VALUE"""),"Net Income Net Income") -> Net Income Net Income | B43: =IFERROR(__xludf.DUMMYFUNCTION("""COMPUTED_VALUE"""),"5.52B") -> 5.52B | C43: =IFERROR(__xludf.DUMMYFUNCTION("""COMPUTED_VALUE"""),"12.58B") -> 12.58B | D43: =IFERROR(__xludf.DUMMYFUNCTION("""COMPUTED_VALUE"""),"15B") -> 15B | E43: =IFERROR(__xludf.DUMMYFUNCTION("""COMPUTED_VALUE"""),"7.13B") -> 7.13B | F43: =IFERROR(__xludf.DUMMYFUNCTION("""COMPUTED_VALUE"""),"3.79B") -> 3.79B
A44: =IFERROR(__xludf.DUMMYFUNCTION("""COMPUTED_VALUE"""),"Net Income Growth Net Income Growth") -> Net Income Growth Net Income Growth | B44: =IFERROR(__xludf.DUMMYFUNCTION("""COMPUTED_VALUE"""),"-") -> - | C44: =IFERROR(__xludf.DUMMYFUNCTION("""COMPUTED_VALUE"""),1.2779) -> 1.2779 | D44: =IFERROR(__xludf.DUMMYFUNCTION("""COMPUTED_VALUE"""),0.192) -> 0.192 | E44: =IFERROR(__xludf.DUMMYFUNCTION("""COMPUTED_VALUE"""),-0.5246) -> -0.5246 | F44: =IFERROR(__xludf.DUMMYFUNCTION("""COMPUTED_VALUE"""),-0.4679) -> -0.4679
A45: =IFERROR(__xludf.DUMMYFUNCTION("""COMPUTED_VALUE"""),"Net Margin Growth Net Margin Growth") -> Net Margin Growth Net Margin Growth | B45: =IFERROR(__xludf.DUMMYFUNCTION("""COMPUTED_VALUE"""),"-") -> - | C45: =IFERROR(__xludf.DUMMYFUNCTION("""COMPUTED_VALUE"""),"-") -> - | D45: =IFERROR(__xludf.DUMMYFUNCTION("""COMPUTED_VALUE"""),"-") -> - | E45: =IFERROR(__xludf.DUMMYFUNCTION("""COMPUTED_VALUE"""),"-") -> - | F45: =IFERROR(__xludf.DUMMYFUNCTION("""COMPUTED_VALUE"""),0.04) -> 0.04
A46: =IFERROR(__xludf.DUMMYFUNCTION("""COMPUTED_VALUE"""),"Extraordinaries & Discontinued Operations Extraordinaries & Discontinued Operations") -> Extraordinaries & Discontinued Operations Extraordinaries & Discontinued Operations | B46: =IFERROR(__xludf.DUMMYFUNCTION("""COMPUTED_VALUE"""),"-") -> - | C46: =IFERROR(__xludf.DUMMYFUNCTION("""COMPUTED_VALUE"""),"-") -> - | D46: =IFERROR(__xludf.DUMMYFUNCTION("""COMPUTED_VALUE"""),"-") -> - | E46: =IFERROR(__xludf.DUMMYFUNCTION("""COMPUTED_VALUE"""),"-") -> - | F46: =IFERROR(__xludf.DUMMYFUNCTION("""COMPUTED_VALUE"""),"-") -> -
A47: =IFERROR(__xludf.DUMMYFUNCTION("""COMPUTED_VALUE"""),"Extra Items & Gain/Loss Sale Of Assets Extra Items & Gain/Loss Sale Of Assets") -> Extra Items & Gain/Loss Sale Of Assets Extra Items & Gain/Loss Sale Of Assets | B47: =IFERROR(__xludf.DUMMYFUNCTION("""COMPUTED_VALUE"""),"-") -> - | C47: =IFERROR(__xludf.DUMMYFUNCTION("""COMPUTED_VALUE"""),"-") -> - | D47: =IFERROR(__xludf.DUMMYFUNCTION("""COMPUTED_VALUE"""),"-") -> - | E47: =IFERROR(__xludf.DUMMYFUNCTION("""COMPUTED_VALUE"""),"-") -> - | F47: =IFERROR(__xludf.DUMMYFUNCTION("""COMPUTED_VALUE"""),"-") -> -
A48: =IFERROR(__xludf.DUMMYFUNCTION("""COMPUTED_VALUE"""),"Cumulative Effect - Accounting Chg Cumulative Effect - Accounting Chg") -> Cumulative Effect - Accounting Chg Cumulative Effect - Accounting Chg | B48: =IFERROR(__xludf.DUMMYFUNCTION("""COMPUTED_VALUE"""),"-") -> - | C48: =IFERROR(__xludf.DUMMYFUNCTION("""COMPUTED_VALUE"""),"-") -> - | D48: =IFERROR(__xludf.DUMMYFUNCTION("""COMPUTED_VALUE"""),"-") -> - | E48: =IFERROR(__xludf.DUMMYFUNCTION("""COMPUTED_VALUE"""),"-") -> - | F48: =IFERROR(__xludf.DUMMYFUNCTION("""COMPUTED_VALUE"""),"-") -> -
A49: =IFERROR(__xludf.DUMMYFUNCTION("""COMPUTED_VALUE"""),"Discontinued Operations Discontinued Operations") -> Discontinued Operations Discontinued Operations | B49: =IFERROR(__xludf.DUMMYFUNCTION("""COMPUTED_VALUE"""),"-") -> - | C49: =IFERROR(__xludf.DUMMYFUNCTION("""COMPUTED_VALUE"""),"-") -> - | D49: =IFERROR(__xludf.DUMMYFUNCTION("""COMPUTED_VALUE"""),"-") -> - | E49: =IFERROR(__xludf.DUMMYFUNCTION("""COMPUTED_VALUE"""),"-") -> - | F49: =IFERROR(__xludf.DUMMYFUNCTION("""COMPUTED_VALUE"""),"-") -> -
A50: =IFERROR(__xludf.DUMMYFUNCTION("""COMPUTED_VALUE"""),"Net Income After Extraordinaries Net Income After Extraordinaries") -> Net Income After Extraordinaries Net Income After Extraordinaries | B50: =IFERROR(__xludf.DUMMYFUNCTION("""COMPUTED_VALUE"""),"5.52B") -> 5.52B | C50: =IFERROR(__xludf.DUMMYFUNCTION("""COMPUTED_VALUE"""),"12.58B") -> 12.58B | D50: =IFERROR(__xludf.DUMMYFUNCTION("""COMPUTED_VALUE"""),"15B") -> 15B | E50: =IFERROR(__xludf.DUMMYFUNCTION("""COMPUTED_VALUE"""),"7.13B") -> 7.13B | F50: =IFERROR(__xludf.DUMMYFUNCTION("""COMPUTED_VALUE"""),"3.79B") -> 3.79B
A51: =IFERROR(__xludf.DUMMYFUNCTION("""COMPUTED_VALUE"""),"Preferred Dividends Preferred Dividends") -> Preferred Dividends Preferred Dividends | B51: =IFERROR(__xludf.DUMMYFUNCTION("""COMPUTED_VALUE"""),"-") -> - | C51: =IFERROR(__xludf.DUMMYFUNCTION("""COMPUTED_VALUE"""),"-") -> - | D51: =IFERROR(__xludf.DUMMYFUNCTION("""COMPUTED_VALUE"""),"-") -> - | E51: =IFERROR(__xludf.DUMMYFUNCTION("""COMPUTED_VALUE"""),"-") -> - | F51: =IFERROR(__xludf.DUMMYFUNCTION("""COMPUTED_VALUE"""),"-") -> -
A52: =IFERROR(__xludf.DUMMYFUNCTION("""COMPUTED_VALUE"""),"Net Income Available to Common Net Income Available to Common") -> Net Income Available to Common Net Income Available to Common | B52: =IFERROR(__xludf.DUMMYFUNCTION("""COMPUTED_VALUE"""),"5.52B") -> 5.52B | C52: =IFERROR(__xludf.DUMMYFUNCTION("""COMPUTED_VALUE"""),"12.58B") -> 12.58B | D52: =IFERROR(__xludf.DUMMYFUNCTION("""COMPUTED_VALUE"""),"15B") -> 15B | E52: =IFERROR(__xludf.DUMMYFUNCTION("""COMPUTED_VALUE"""),"7.13B") -> 7.13B | F52: =IFERROR(__xludf.DUMMYFUNCTION("""COMPUTED_VALUE"""),"3.79B") -> 3.79B
A53: =IFERROR(__xludf.DUMMYFUNCTION("""COMPUTED_VALUE"""),"EPS (Basic) EPS (Basic)") -> EPS (Basic) EPS (Basic) | B53: =IFERROR(__xludf.DUMMYFUNCTION("""COMPUTED_VALUE"""),1.87) -> 1.87 | C53: =IFERROR(__xludf.DUMMYFUNCTION("""COMPUTED_VALUE"""),4.02) -> 4.02 | D53: =IFERROR(__xludf.DUMMYFUNCTION("""COMPUTED_VALUE"""),4.73) -> 4.73 | E53: =IFERROR(__xludf.DUMMYFUNCTION("""COMPUTED_VALUE"""),2.23) -> 2.23 | F53: =IFERROR(__xludf.DUMMYFUNCTION("""COMPUTED_VALUE"""),1.18) -> 1.18
A54: =IFERROR(__xludf.DUMMYFUNCTION("""COMPUTED_VALUE"""),"EPS (Basic) Growth EPS (Basic) Growth") -> EPS (Basic) Growth EPS (Basic) Growth | B54: =IFERROR(__xludf.DUMMYFUNCTION("""COMPUTED_VALUE"""),"-") -> - | C54: =IFERROR(__xludf.DUMMYFUNCTION("""COMPUTED_VALUE"""),1.1527) -> 1.1527 | D54: =IFERROR(__xludf.DUMMYFUNCTION("""COMPUTED_VALUE"""),0.1755) -> 0.1755 | E54: =IFERROR(__xludf.DUMMYFUNCTION("""COMPUTED_VALUE"""),-0.5281) -> -0.5281 | F54: =IFERROR(__xludf.DUMMYFUNCTION("""COMPUTED_VALUE"""),-0.4725) -> -0.4725
A55: =IFERROR(__xludf.DUMMYFUNCTION("""COMPUTED_VALUE"""),"Basic Shares Outstanding Basic Shares Outstanding") -> Basic Shares Outstanding Basic Shares Outstanding | B55: =IFERROR(__xludf.DUMMYFUNCTION("""COMPUTED_VALUE"""),"2.96B") -> 2.96B | C55: =IFERROR(__xludf.DUMMYFUNCTION("""COMPUTED_VALUE"""),"3.13B") -> 3.13B | D55: =IFERROR(__xludf.DUMMYFUNCTION("""COMPUTED_VALUE"""),"3.17B") -> 3.17B | E55: =IFERROR(__xludf.DUMMYFUNCTION("""COMPUTED_VALUE"""),"3.2B") -> 3.2B | F55: =IFERROR(__xludf.DUMMYFUNCTION("""COMPUTED_VALUE"""),"3.23B") -> 3.23B
A56: =IFERROR(__xludf.DUMMYFUNCTION("""COMPUTED_VALUE"""),"EPS (Diluted) EPS (Diluted)") -> EPS (Diluted) EPS (Diluted) | B56: =IFERROR(__xludf.DUMMYFUNCTION("""COMPUTED_VALUE"""),1.63) -> 1.63 | C56: =IFERROR(__xludf.DUMMYFUNCTION("""COMPUTED_VALUE"""),3.62) -> 3.62 | D56: =IFERROR(__xludf.DUMMYFUNCTION("""COMPUTED_VALUE"""),4.3) -> 4.3 | E56: =IFERROR(__xludf.DUMMYFUNCTION("""COMPUTED_VALUE"""),2.04) -> 2.04 | F56: =IFERROR(__xludf.DUMMYFUNCTION("""COMPUTED_VALUE"""),1.08) -> 1.08
A57: =IFERROR(__xludf.DUMMYFUNCTION("""COMPUTED_VALUE"""),"EPS (Diluted) Growth EPS (Diluted) Growth") -> EPS (Diluted) Growth EPS (Diluted) Growth | B57: =IFERROR(__xludf.DUMMYFUNCTION("""COMPUTED_VALUE"""),"-") -> - | C57: =IFERROR(__xludf.DUMMYFUNCTION("""COMPUTED_VALUE"""),1.2204) -> 1.2204 | D57: =IFERROR(__xludf.DUMMYFUNCTION("""COMPUTED_VALUE"""),0.1885) -> 0.1885 | E57: =IFERROR(__xludf.DUMMYFUNCTION("""COMPUTED_VALUE"""),-0.5264) -> -0.5264 | F57: =IFERROR(__xludf.DUMMYFUNCTION("""COMPUTED_VALUE"""),-0.4724) -> -0.4724
A58: =IFERROR(__xludf.DUMMYFUNCTION("""COMPUTED_VALUE"""),"Diluted Shares Outstanding Diluted Shares Outstanding") -> Diluted Shares Outstanding Diluted Shares Outstanding | B58: =IFERROR(__xludf.DUMMYFUNCTION("""COMPUTED_VALUE"""),"3.39B") -> 3.39B | C58: =IFERROR(__xludf.DUMMYFUNCTION("""COMPUTED_VALUE"""),"3.48B") -> 3.48B | D58: =IFERROR(__xludf.DUMMYFUNCTION("""COMPUTED_VALUE"""),"3.49B") -> 3.49B | E58: =IFERROR(__xludf.DUMMYFUNCTION("""COMPUTED_VALUE"""),"3.5B") -> 3.5B | F58: =IFERROR(__xludf.DUMMYFUNCTION("""COMPUTED_VALUE"""),"3.53B") -> 3.53B
A59: =IFERROR(__xludf.DUMMYFUNCTION("""COMPUTED_VALUE"""),"EBITDA EBITDA") -> EBITDA EBITDA | B59: =IFERROR(__xludf.DUMMYFUNCTION("""COMPUTED_VALUE"""),"9.41B") -> 9.41B | C59: =IFERROR(__xludf.DUMMYFUNCTION("""COMPUTED_VALUE"""),"17.38B") -> 17.38B | D59: =IFERROR(__xludf.DUMMYFUNCTION("""COMPUTED_VALUE"""),"13.56B") -> 13.56B | E59: =IFERROR(__xludf.DUMMYFUNCTION("""COMPUTED_VALUE"""),"13.13B") -> 13.13B | F59: =IFERROR(__xludf.DUMMYFUNCTION("""COMPUTED_VALUE"""),"11B") -> 11B
A60: =IFERROR(__xludf.DUMMYFUNCTION("""COMPUTED_VALUE"""),"EBITDA Growth EBITDA Growth") -> EBITDA Growth EBITDA Growth | B60: =IFERROR(__xludf.DUMMYFUNCTION("""COMPUTED_VALUE"""),"-") -> - | C60: =IFERROR(__xludf.DUMMYFUNCTION("""COMPUTED_VALUE"""),0.847) -> 0.847 | D60: =IFERROR(__xludf.DUMMYFUNCTION("""COMPUTED_VALUE"""),-0.2197) -> -0.2197 | E60: =IFERROR(__xludf.DUMMYFUNCTION("""COMPUTED_VALUE"""),-0.0317) -> -0.0317 | F60: =IFERROR(__xludf.DUMMYFUNCTION("""COMPUTED_VALUE"""),-0.1623) -> -0.1623
A61: =IFERROR(__xludf.DUMMYFUNCTION("""COMPUTED_VALUE"""),"EBITDA Margin EBITDA Margin") -> EBITDA Margin EBITDA Margin | B61: =IFERROR(__xludf.DUMMYFUNCTION("""COMPUTED_VALUE"""),"-") -> - | C61: =IFERROR(__xludf.DUMMYFUNCTION("""COMPUTED_VALUE"""),"-") -> - | D61: =IFERROR(__xludf.DUMMYFUNCTION("""COMPUTED_VALUE"""),"-") -> - | E61: =IFERROR(__xludf.DUMMYFUNCTION("""COMPUTED_VALUE"""),"-") -> - | F61: =IFERROR(__xludf.DUMMYFUNCTION("""COMPUTED_VALUE"""),0.116) -> 0.116
A68: =IFERROR(__xludf.DUMMYFUNCTION("IMPORTHTML(CONCAT(CONCAT(""https://www.marketwatch.com/investing/stock/"",'Income Statement'!D1),""/financials/balance-sheet""),""table"",4) "),"Item Item") -> Item Item | B68: =IFERROR(__xludf.DUMMYFUNCTION("""COMPUTED_VALUE"""),2021.0) -> 2021 | C68: =IFERROR(__xludf.DUMMYFUNCTION("""COMPUTED_VALUE"""),2022.0) -> 2022 | D68: =IFERROR(__xludf.DUMMYFUNCTION("""COMPUTED_VALUE"""),2023.0) -> 2023 | E68: =IFERROR(__xludf.DUMMYFUNCTION("""COMPUTED_VALUE"""),2024.0) -> 2024 | F68: =IFERROR(__xludf.DUMMYFUNCTION("""COMPUTED_VALUE"""),2025.0) -> 2025 | G68: =IFERROR(__xludf.DUMMYFUNCTION("""COMPUTED_VALUE"""),"5-year trend") -> 5-year trend
A69: =IFERROR(__xludf.DUMMYFUNCTION("""COMPUTED_VALUE"""),"Cash & Short Term Investments Cash & Short Term Investments") -> Cash & Short Term Investments Cash & Short Term Investments | B69: =IFERROR(__xludf.DUMMYFUNCTION("""COMPUTED_VALUE"""),"18.05B") -> 18.05B | C69: =IFERROR(__xludf.DUMMYFUNCTION("""COMPUTED_VALUE"""),"22.48B") -> 22.48B | D69: =IFERROR(__xludf.DUMMYFUNCTION("""COMPUTED_VALUE"""),"29.64B") -> 29.64B | E69: =IFERROR(__xludf.DUMMYFUNCTION("""COMPUTED_VALUE"""),"37.06B") -> 37.06B | F69: =IFERROR(__xludf.DUMMYFUNCTION("""COMPUTED_VALUE"""),"44.45B") -> 44.45B
A70: =IFERROR(__xludf.DUMMYFUNCTION("""COMPUTED_VALUE"""),"Cash & Short Term Investments Growth Cash & Short Term Investments Growth") -> Cash & Short Term Investments Growth Cash & Short Term Investments Growth | B70: =IFERROR(__xludf.DUMMYFUNCTION("""COMPUTED_VALUE"""),"-") -> - | C70: =IFERROR(__xludf.DUMMYFUNCTION("""COMPUTED_VALUE"""),0.2452) -> 0.2452 | D70: =IFERROR(__xludf.DUMMYFUNCTION("""COMPUTED_VALUE"""),0.3184) -> 0.3184 | E70: =IFERROR(__xludf.DUMMYFUNCTION("""COMPUTED_VALUE"""),0.2504) -> 0.2504 | F70: =IFERROR(__xludf.DUMMYFUNCTION("""COMPUTED_VALUE"""),0.1994) -> 0.1994
A71: =IFERROR(__xludf.DUMMYFUNCTION("""COMPUTED_VALUE"""),"Cash Only Cash Only") -> Cash Only Cash Only | B71: =IFERROR(__xludf.DUMMYFUNCTION("""COMPUTED_VALUE"""),"17.92B") -> 17.92B | C71: =IFERROR(__xludf.DUMMYFUNCTION("""COMPUTED_VALUE"""),"16.55B") -> 16.55B | D71: =IFERROR(__xludf.DUMMYFUNCTION("""COMPUTED_VALUE"""),"16.94B") -> 16.94B | E71: =IFERROR(__xludf.DUMMYFUNCTION("""COMPUTED_VALUE"""),"16.63B") -> 16.63B | F71: =IFERROR(__xludf.DUMMYFUNCTION("""COMPUTED_VALUE"""),"16.9B") -> 16.9B
A72: =IFERROR(__xludf.DUMMYFUNCTION("""COMPUTED_VALUE"""),"Short-Term Investments Short-Term Investments") -> Short-Term Investments Short-Term Investments | B72: =IFERROR(__xludf.DUMMYFUNCTION("""COMPUTED_VALUE"""),"-") -> - | C72: =IFERROR(__xludf.DUMMYFUNCTION("""COMPUTED_VALUE"""),"-") -> - | D72: =IFERROR(__xludf.DUMMYFUNCTION("""COMPUTED_VALUE"""),"-") -> - | E72: =IFERROR(__xludf.DUMMYFUNCTION("""COMPUTED_VALUE"""),"-") -> - | F72: =IFERROR(__xludf.DUMMYFUNCTION("""COMPUTED_VALUE"""),"-") -> -
A73: =IFERROR(__xludf.DUMMYFUNCTION("""COMPUTED_VALUE"""),"Cash & ST Investments / Total Assets Cash & ST Investments / Total Assets") -> Cash & ST Investments / Total Assets Cash & ST Investments / Total Assets | B73: =IFERROR(__xludf.DUMMYFUNCTION("""COMPUTED_VALUE"""),0.2905) -> 0.2905 | C73: =IFERROR(__xludf.DUMMYFUNCTION("""COMPUTED_VALUE"""),0.273) -> 0.273 | D73: =IFERROR(__xludf.DUMMYFUNCTION("""COMPUTED_VALUE"""),0.278) -> 0.278 | E73: =IFERROR(__xludf.DUMMYFUNCTION("""COMPUTED_VALUE"""),0.3036) -> 0.3036 | F73: =IFERROR(__xludf.DUMMYFUNCTION("""COMPUTED_VALUE"""),0.3225) -> 0.3225
A74: =IFERROR(__xludf.DUMMYFUNCTION("""COMPUTED_VALUE"""),"Total Accounts Receivable Total Accounts Receivable") -> Total Accounts Receivable Total Accounts Receivable | B74: =IFERROR(__xludf.DUMMYFUNCTION("""COMPUTED_VALUE"""),"1.91B") -> 1.91B | C74: =IFERROR(__xludf.DUMMYFUNCTION("""COMPUTED_VALUE"""),"2.95B") -> 2.95B | D74: =IFERROR(__xludf.DUMMYFUNCTION("""COMPUTED_VALUE"""),"3.51B") -> 3.51B | E74: =IFERROR(__xludf.DUMMYFUNCTION("""COMPUTED_VALUE"""),"4.42B") -> 4.42B | F74: =IFERROR(__xludf.DUMMYFUNCTION("""COMPUTED_VALUE"""),"4.71B") -> 4.71B
A75: =IFERROR(__xludf.DUMMYFUNCTION("""COMPUTED_VALUE"""),"Total Accounts Receivable Growth Total Accounts Receivable Growth") -> Total Accounts Receivable Growth Total Accounts Receivable Growth | B75: =IFERROR(__xludf.DUMMYFUNCTION("""COMPUTED_VALUE"""),"-") -> - | C75: =IFERROR(__xludf.DUMMYFUNCTION("""COMPUTED_VALUE"""),0.5431) -> 0.5431 | D75: =IFERROR(__xludf.DUMMYFUNCTION("""COMPUTED_VALUE"""),0.1883) -> 0.1883 | E75: =IFERROR(__xludf.DUMMYFUNCTION("""COMPUTED_VALUE"""),0.2594) -> 0.2594 | F75: =IFERROR(__xludf.DUMMYFUNCTION("""COMPUTED_VALUE"""),0.0652) -> 0.0652
A76: =IFERROR(__xludf.DUMMYFUNCTION("""COMPUTED_VALUE"""),"Accounts Receivables, Net Accounts Receivables, Net") -> Accounts Receivables, Net Accounts Receivables, Net | B76: =IFERROR(__xludf.DUMMYFUNCTION("""COMPUTED_VALUE"""),"1.91B") -> 1.91B | C76: =IFERROR(__xludf.DUMMYFUNCTION("""COMPUTED_VALUE"""),"2.95B") -> 2.95B | D76: =IFERROR(__xludf.DUMMYFUNCTION("""COMPUTED_VALUE"""),"3.51B") -> 3.51B | E76: =IFERROR(__xludf.DUMMYFUNCTION("""COMPUTED_VALUE"""),"4.42B") -> 4.42B | F76: =IFERROR(__xludf.DUMMYFUNCTION("""COMPUTED_VALUE"""),"4.58B") -> 4.58B
A77: =IFERROR(__xludf.DUMMYFUNCTION("""COMPUTED_VALUE"""),"Accounts Receivables, Gross Accounts Receivables, Gross") -> Accounts Receivables, Gross Accounts Receivables, Gross | B77: =IFERROR(__xludf.DUMMYFUNCTION("""COMPUTED_VALUE"""),"1.91B") -> 1.91B | C77: =IFERROR(__xludf.DUMMYFUNCTION("""COMPUTED_VALUE"""),"2.95B") -> 2.95B | D77: =IFERROR(__xludf.DUMMYFUNCTION("""COMPUTED_VALUE"""),"3.51B") -> 3.51B | E77: =IFERROR(__xludf.DUMMYFUNCTION("""COMPUTED_VALUE"""),"4.42B") -> 4.42B | F77: =IFERROR(__xludf.DUMMYFUNCTION("""COMPUTED_VALUE"""),"4.58B") -> 4.58B
A78: =IFERROR(__xludf.DUMMYFUNCTION("""COMPUTED_VALUE"""),"Bad Debt/Doubtful Accounts Bad Debt/Doubtful Accounts") -> Bad Debt/Doubtful Accounts Bad Debt/Doubtful Accounts | B78: =IFERROR(__xludf.DUMMYFUNCTION("""COMPUTED_VALUE"""),"-") -> - | C78: =IFERROR(__xludf.DUMMYFUNCTION("""COMPUTED_VALUE"""),"-") -> - | D78: =IFERROR(__xludf.DUMMYFUNCTION("""COMPUTED_VALUE"""),"-") -> - | E78: =IFERROR(__xludf.DUMMYFUNCTION("""COMPUTED_VALUE"""),"-") -> - | F78: =IFERROR(__xludf.DUMMYFUNCTION("""COMPUTED_VALUE"""),"-") -> -
A79: =IFERROR(__xludf.DUMMYFUNCTION("""COMPUTED_VALUE"""),"Other Receivable Other Receivable") -> Other Receivable Other Receivable | B79: =IFERROR(__xludf.DUMMYFUNCTION("""COMPUTED_VALUE"""),"-") -> - | C79: =IFERROR(__xludf.DUMMYFUNCTION("""COMPUTED_VALUE"""),"-") -> - | D79: =IFERROR(__xludf.DUMMYFUNCTION("""COMPUTED_VALUE"""),"-") -> - | E79: =IFERROR(__xludf.DUMMYFUNCTION("""COMPUTED_VALUE"""),"-") -> - | F79: =IFERROR(__xludf.DUMMYFUNCTION("""COMPUTED_VALUE"""),"130M") -> 130M
A80: =IFERROR(__xludf.DUMMYFUNCTION("""COMPUTED_VALUE"""),"Accounts Receivable Turnover Accounts Receivable Turnover") -> Accounts Receivable Turnover Accounts Receivable Turnover | B80: =IFERROR(__xludf.DUMMYFUNCTION("""COMPUTED_VALUE"""),28.14) -> 28.14 | C80: =IFERROR(__xludf.DUMMYFUNCTION("""COMPUTED_VALUE"""),27.6) -> 27.6 | D80: =IFERROR(__xludf.DUMMYFUNCTION("""COMPUTED_VALUE"""),27.59) -> 27.59 | E80: =IFERROR(__xludf.DUMMYFUNCTION("""COMPUTED_VALUE"""),22.11) -> 22.11 | F80: =IFERROR(__xludf.DUMMYFUNCTION("""COMPUTED_VALUE"""),20.15) -> 20.15
A81: =IFERROR(__xludf.DUMMYFUNCTION("""COMPUTED_VALUE"""),"Inventories Inventories") -> Inventories Inventories | B81: =IFERROR(__xludf.DUMMYFUNCTION("""COMPUTED_VALUE"""),"5.76B") -> 5.76B | C81: =IFERROR(__xludf.DUMMYFUNCTION("""COMPUTED_VALUE"""),"12.84B") -> 12.84B | D81: =IFERROR(__xludf.DUMMYFUNCTION("""COMPUTED_VALUE"""),"13.63B") -> 13.63B | E81: =IFERROR(__xludf.DUMMYFUNCTION("""COMPUTED_VALUE"""),"12.02B") -> 12.02B | F81: =IFERROR(__xludf.DUMMYFUNCTION("""COMPUTED_VALUE"""),"12.39B") -> 12.39B
A82: =IFERROR(__xludf.DUMMYFUNCTION("""COMPUTED_VALUE"""),"Finished Goods Finished Goods") -> Finished Goods Finished Goods | B82: =IFERROR(__xludf.DUMMYFUNCTION("""COMPUTED_VALUE"""),"1.28B") -> 1.28B | C82: =IFERROR(__xludf.DUMMYFUNCTION("""COMPUTED_VALUE"""),"3.48B") -> 3.48B | D82: =IFERROR(__xludf.DUMMYFUNCTION("""COMPUTED_VALUE"""),"5.05B") -> 5.05B | E82: =IFERROR(__xludf.DUMMYFUNCTION("""COMPUTED_VALUE"""),"3.94B") -> 3.94B | F82: =IFERROR(__xludf.DUMMYFUNCTION("""COMPUTED_VALUE"""),"4.85B") -> 4.85B
A83: =IFERROR(__xludf.DUMMYFUNCTION("""COMPUTED_VALUE"""),"Work in Progress Work in Progress") -> Work in Progress Work in Progress | B83: =IFERROR(__xludf.DUMMYFUNCTION("""COMPUTED_VALUE"""),"1.09B") -> 1.09B | C83: =IFERROR(__xludf.DUMMYFUNCTION("""COMPUTED_VALUE"""),"2.39B") -> 2.39B | D83: =IFERROR(__xludf.DUMMYFUNCTION("""COMPUTED_VALUE"""),"2.02B") -> 2.02B | E83: =IFERROR(__xludf.DUMMYFUNCTION("""COMPUTED_VALUE"""),"1.53B") -> 1.53B | F83: =IFERROR(__xludf.DUMMYFUNCTION("""COMPUTED_VALUE"""),"1.73B") -> 1.73B
A84: =IFERROR(__xludf.DUMMYFUNCTION("""COMPUTED_VALUE"""),"Raw Materials Raw Materials") -> Raw Materials Raw Materials | B84: =IFERROR(__xludf.DUMMYFUNCTION("""COMPUTED_VALUE"""),"3.39B") -> 3.39B | C84: =IFERROR(__xludf.DUMMYFUNCTION("""COMPUTED_VALUE"""),"6.98B") -> 6.98B | D84: =IFERROR(__xludf.DUMMYFUNCTION("""COMPUTED_VALUE"""),"6.56B") -> 6.56B | E84: =IFERROR(__xludf.DUMMYFUNCTION("""COMPUTED_VALUE"""),"6.55B") -> 6.55B | F84: =IFERROR(__xludf.DUMMYFUNCTION("""COMPUTED_VALUE"""),"5.82B") -> 5.82B
A85: =IFERROR(__xludf.DUMMYFUNCTION("""COMPUTED_VALUE"""),"Progress Payments & Other Progress Payments & Other") -> Progress Payments & Other Progress Payments & Other | B85: =IFERROR(__xludf.DUMMYFUNCTION("""COMPUTED_VALUE"""),"-") -> - | C85: =IFERROR(__xludf.DUMMYFUNCTION("""COMPUTED_VALUE"""),"-") -> - | D85: =IFERROR(__xludf.DUMMYFUNCTION("""COMPUTED_VALUE"""),"-") -> - | E85: =IFERROR(__xludf.DUMMYFUNCTION("""COMPUTED_VALUE"""),"-") -> - | F85: =IFERROR(__xludf.DUMMYFUNCTION("""COMPUTED_VALUE"""),"-") -> -
A86: =IFERROR(__xludf.DUMMYFUNCTION("""COMPUTED_VALUE"""),"Other Current Assets Other Current Assets") -> Other Current Assets Other Current Assets | B86: =IFERROR(__xludf.DUMMYFUNCTION("""COMPUTED_VALUE"""),"1.38B") -> 1.38B | C86: =IFERROR(__xludf.DUMMYFUNCTION("""COMPUTED_VALUE"""),"2.65B") -> 2.65B | D86: =IFERROR(__xludf.DUMMYFUNCTION("""COMPUTED_VALUE"""),"2.85B") -> 2.85B | E86: =IFERROR(__xludf.DUMMYFUNCTION("""COMPUTED_VALUE"""),"4.87B") -> 4.87B | F86: =IFERROR(__xludf.DUMMYFUNCTION("""COMPUTED_VALUE"""),"7.1B") -> 7.1B
A87: =IFERROR(__xludf.DUMMYFUNCTION("""COMPUTED_VALUE"""),"Miscellaneous Current Assets Miscellaneous Current Assets") -> Miscellaneous Current Assets Miscellaneous Current Assets | B87: =IFERROR(__xludf.DUMMYFUNCTION("""COMPUTED_VALUE"""),"1.38B") -> 1.38B | C87: =IFERROR(__xludf.DUMMYFUNCTION("""COMPUTED_VALUE"""),"2.65B") -> 2.65B | D87: =IFERROR(__xludf.DUMMYFUNCTION("""COMPUTED_VALUE"""),"2.85B") -> 2.85B | E87: =IFERROR(__xludf.DUMMYFUNCTION("""COMPUTED_VALUE"""),"4.87B") -> 4.87B | F87: =IFERROR(__xludf.DUMMYFUNCTION("""COMPUTED_VALUE"""),"7.1B") -> 7.1B
A88: =IFERROR(__xludf.DUMMYFUNCTION("""COMPUTED_VALUE"""),"Total Current Assets Total Current Assets") -> Total Current Assets Total Current Assets | B88: =IFERROR(__xludf.DUMMYFUNCTION("""COMPUTED_VALUE"""),"27.1B") -> 27.1B | C88: =IFERROR(__xludf.DUMMYFUNCTION("""COMPUTED_VALUE"""),"40.92B") -> 40.92B | D88: =IFERROR(__xludf.DUMMYFUNCTION("""COMPUTED_VALUE"""),"49.62B") -> 49.62B | E88: =IFERROR(__xludf.DUMMYFUNCTION("""COMPUTED_VALUE"""),"58.36B") -> 58.36B | F88: =IFERROR(__xludf.DUMMYFUNCTION("""COMPUTED_VALUE"""),"68.64B") -> 68.64B
A89: =IFERROR(__xludf.DUMMYFUNCTION("""COMPUTED_VALUE"""),"Net Property, Plant & Equipment Net Property, Plant & Equipment") -> Net Property, Plant & Equipment Net Property, Plant & Equipment | B89: =IFERROR(__xludf.DUMMYFUNCTION("""COMPUTED_VALUE"""),"31.18B") -> 31.18B | C89: =IFERROR(__xludf.DUMMYFUNCTION("""COMPUTED_VALUE"""),"36.64B") -> 36.64B | D89: =IFERROR(__xludf.DUMMYFUNCTION("""COMPUTED_VALUE"""),"45.12B") -> 45.12B | E89: =IFERROR(__xludf.DUMMYFUNCTION("""COMPUTED_VALUE"""),"51.5B") -> 51.5B | F89: =IFERROR(__xludf.DUMMYFUNCTION("""COMPUTED_VALUE"""),"56.19B") -> 56.19B
A90: =IFERROR(__xludf.DUMMYFUNCTION("""COMPUTED_VALUE"""),"Property, Plant & Equipment - Gross Property, Plant & Equipment - Gross") -> Property, Plant & Equipment - Gross Property, Plant & Equipment - Gross | B90: =IFERROR(__xludf.DUMMYFUNCTION("""COMPUTED_VALUE"""),"39.87B") -> 39.87B | C90: =IFERROR(__xludf.DUMMYFUNCTION("""COMPUTED_VALUE"""),"48.13B") -> 48.13B | D90: =IFERROR(__xludf.DUMMYFUNCTION("""COMPUTED_VALUE"""),"60.2B") -> 60.2B | E90: =IFERROR(__xludf.DUMMYFUNCTION("""COMPUTED_VALUE"""),"70.4B") -> 70.4B | F90: =IFERROR(__xludf.DUMMYFUNCTION("""COMPUTED_VALUE"""),"79.63B") -> 79.63B
A91: =IFERROR(__xludf.DUMMYFUNCTION("""COMPUTED_VALUE"""),"Buildings Buildings") -> Buildings Buildings | B91: =IFERROR(__xludf.DUMMYFUNCTION("""COMPUTED_VALUE"""),"4.68B") -> 4.68B | C91: =IFERROR(__xludf.DUMMYFUNCTION("""COMPUTED_VALUE"""),"7.75B") -> 7.75B | D91: =IFERROR(__xludf.DUMMYFUNCTION("""COMPUTED_VALUE"""),"9.51B") -> 9.51B | E91: =IFERROR(__xludf.DUMMYFUNCTION("""COMPUTED_VALUE"""),"10.68B") -> 10.68B | F91: =IFERROR(__xludf.DUMMYFUNCTION("""COMPUTED_VALUE"""),"11.84B") -> 11.84B
A92: =IFERROR(__xludf.DUMMYFUNCTION("""COMPUTED_VALUE"""),"Land & Improvements Land & Improvements") -> Land & Improvements Land & Improvements | B92: =IFERROR(__xludf.DUMMYFUNCTION("""COMPUTED_VALUE"""),"-") -> - | C92: =IFERROR(__xludf.DUMMYFUNCTION("""COMPUTED_VALUE"""),"-") -> - | D92: =IFERROR(__xludf.DUMMYFUNCTION("""COMPUTED_VALUE"""),"-") -> - | E92: =IFERROR(__xludf.DUMMYFUNCTION("""COMPUTED_VALUE"""),"-") -> - | F92: =IFERROR(__xludf.DUMMYFUNCTION("""COMPUTED_VALUE"""),"-") -> -
A93: =IFERROR(__xludf.DUMMYFUNCTION("""COMPUTED_VALUE"""),"Computer Software and Equipment Computer Software and Equipment") -> Computer Software and Equipment Computer Software and Equipment | B93: =IFERROR(__xludf.DUMMYFUNCTION("""COMPUTED_VALUE"""),"1.41B") -> 1.41B | C93: =IFERROR(__xludf.DUMMYFUNCTION("""COMPUTED_VALUE"""),"2.07B") -> 2.07B | D93: =IFERROR(__xludf.DUMMYFUNCTION("""COMPUTED_VALUE"""),"3.8B") -> 3.8B | E93: =IFERROR(__xludf.DUMMYFUNCTION("""COMPUTED_VALUE"""),"2.9B") -> 2.9B | F93: =IFERROR(__xludf.DUMMYFUNCTION("""COMPUTED_VALUE"""),"3.21B") -> 3.21B
A94: =IFERROR(__xludf.DUMMYFUNCTION("""COMPUTED_VALUE"""),"Other Property, Plant & Equipment Other Property, Plant & Equipment") -> Other Property, Plant & Equipment Other Property, Plant & Equipment | B94: =IFERROR(__xludf.DUMMYFUNCTION("""COMPUTED_VALUE"""),"18.73B") -> 18.73B | C94: =IFERROR(__xludf.DUMMYFUNCTION("""COMPUTED_VALUE"""),"22.83B") -> 22.83B | D94: =IFERROR(__xludf.DUMMYFUNCTION("""COMPUTED_VALUE"""),"26.41B") -> 26.41B | E94: =IFERROR(__xludf.DUMMYFUNCTION("""COMPUTED_VALUE"""),"33.96B") -> 33.96B | F94: =IFERROR(__xludf.DUMMYFUNCTION("""COMPUTED_VALUE"""),"38.78B") -> 38.78B
A95: =IFERROR(__xludf.DUMMYFUNCTION("""COMPUTED_VALUE"""),"Accumulated Depreciation Accumulated Depreciation") -> Accumulated Depreciation Accumulated Depreciation | B95: =IFERROR(__xludf.DUMMYFUNCTION("""COMPUTED_VALUE"""),"8.69B") -> 8.69B | C95: =IFERROR(__xludf.DUMMYFUNCTION("""COMPUTED_VALUE"""),"11.5B") -> 11.5B | D95: =IFERROR(__xludf.DUMMYFUNCTION("""COMPUTED_VALUE"""),"15.08B") -> 15.08B | E95: =IFERROR(__xludf.DUMMYFUNCTION("""COMPUTED_VALUE"""),"18.9B") -> 18.9B | F95: =IFERROR(__xludf.DUMMYFUNCTION("""COMPUTED_VALUE"""),"23.44B") -> 23.44B
A96: =IFERROR(__xludf.DUMMYFUNCTION("""COMPUTED_VALUE"""),"Total Investments and Advances Total Investments and Advances") -> Total Investments and Advances Total Investments and Advances | B96: =IFERROR(__xludf.DUMMYFUNCTION("""COMPUTED_VALUE"""),"223M") -> 223M | C96: =IFERROR(__xludf.DUMMYFUNCTION("""COMPUTED_VALUE"""),"377M") -> 377M | D96: =IFERROR(__xludf.DUMMYFUNCTION("""COMPUTED_VALUE"""),"248M") -> 248M | E96: =IFERROR(__xludf.DUMMYFUNCTION("""COMPUTED_VALUE"""),"404M") -> 404M | F96: =IFERROR(__xludf.DUMMYFUNCTION("""COMPUTED_VALUE"""),"714M") -> 714M
A97: =IFERROR(__xludf.DUMMYFUNCTION("""COMPUTED_VALUE"""),"Other Long-Term Investments Other Long-Term Investments") -> Other Long-Term Investments Other Long-Term Investments | B97: =IFERROR(__xludf.DUMMYFUNCTION("""COMPUTED_VALUE"""),"223M") -> 223M | C97: =IFERROR(__xludf.DUMMYFUNCTION("""COMPUTED_VALUE"""),"377M") -> 377M | D97: =IFERROR(__xludf.DUMMYFUNCTION("""COMPUTED_VALUE"""),"248M") -> 248M | E97: =IFERROR(__xludf.DUMMYFUNCTION("""COMPUTED_VALUE"""),"404M") -> 404M | F97: =IFERROR(__xludf.DUMMYFUNCTION("""COMPUTED_VALUE"""),"714M") -> 714M
A98: =IFERROR(__xludf.DUMMYFUNCTION("""COMPUTED_VALUE"""),"Long-Term Note Receivables Long-Term Note Receivables") -> Long-Term Note Receivables Long-Term Note Receivables | B98: =IFERROR(__xludf.DUMMYFUNCTION("""COMPUTED_VALUE"""),"299M") -> 299M | C98: =IFERROR(__xludf.DUMMYFUNCTION("""COMPUTED_VALUE"""),"280M") -> 280M | D98: =IFERROR(__xludf.DUMMYFUNCTION("""COMPUTED_VALUE"""),"266M") -> 266M | E98: =IFERROR(__xludf.DUMMYFUNCTION("""COMPUTED_VALUE"""),"248M") -> 248M | F98: =IFERROR(__xludf.DUMMYFUNCTION("""COMPUTED_VALUE"""),"1.4B") -> 1.4B
A99: =IFERROR(__xludf.DUMMYFUNCTION("""COMPUTED_VALUE"""),"Intangible Assets Intangible Assets") -> Intangible Assets Intangible Assets | B99: =IFERROR(__xludf.DUMMYFUNCTION("""COMPUTED_VALUE"""),"1.72B") -> 1.72B | C99: =IFERROR(__xludf.DUMMYFUNCTION("""COMPUTED_VALUE"""),"593M") -> 593M | D99: =IFERROR(__xludf.DUMMYFUNCTION("""COMPUTED_VALUE"""),"615M") -> 615M | E99: =IFERROR(__xludf.DUMMYFUNCTION("""COMPUTED_VALUE"""),"1.47B") -> 1.47B | F99: =IFERROR(__xludf.DUMMYFUNCTION("""COMPUTED_VALUE"""),"1.39B") -> 1.39B
A100: =IFERROR(__xludf.DUMMYFUNCTION("""COMPUTED_VALUE"""),"Net Goodwill Net Goodwill") -> Net Goodwill Net Goodwill | B100: =IFERROR(__xludf.DUMMYFUNCTION("""COMPUTED_VALUE"""),"200M") -> 200M | C100: =IFERROR(__xludf.DUMMYFUNCTION("""COMPUTED_VALUE"""),"194M") -> 194M | D100: =IFERROR(__xludf.DUMMYFUNCTION("""COMPUTED_VALUE"""),"253M") -> 253M | E100: =IFERROR(__xludf.DUMMYFUNCTION("""COMPUTED_VALUE"""),"244M") -> 244M | F100: =IFERROR(__xludf.DUMMYFUNCTION("""COMPUTED_VALUE"""),"257M") -> 257M
A101: =IFERROR(__xludf.DUMMYFUNCTION("""COMPUTED_VALUE"""),"Net Other Intangibles Net Other Intangibles") -> Net Other Intangibles Net Other Intangibles | B101: =IFERROR(__xludf.DUMMYFUNCTION("""COMPUTED_VALUE"""),"1.52B") -> 1.52B | C101: =IFERROR(__xludf.DUMMYFUNCTION("""COMPUTED_VALUE"""),"399M") -> 399M | D101: =IFERROR(__xludf.DUMMYFUNCTION("""COMPUTED_VALUE"""),"362M") -> 362M | E101: =IFERROR(__xludf.DUMMYFUNCTION("""COMPUTED_VALUE"""),"1.23B") -> 1.23B | F101: =IFERROR(__xludf.DUMMYFUNCTION("""COMPUTED_VALUE"""),"1.13B") -> 1.13B
A102: =IFERROR(__xludf.DUMMYFUNCTION("""COMPUTED_VALUE"""),"Other Assets Other Assets") -> Other Assets Other Assets | B102: =IFERROR(__xludf.DUMMYFUNCTION("""COMPUTED_VALUE"""),"1.62B") -> 1.62B | C102: =IFERROR(__xludf.DUMMYFUNCTION("""COMPUTED_VALUE"""),"3.54B") -> 3.54B | D102: =IFERROR(__xludf.DUMMYFUNCTION("""COMPUTED_VALUE"""),"4.02B") -> 4.02B | E102: =IFERROR(__xludf.DUMMYFUNCTION("""COMPUTED_VALUE"""),"3.56B") -> 3.56B | F102: =IFERROR(__xludf.DUMMYFUNCTION("""COMPUTED_VALUE"""),"2.56B") -> 2.56B
A103: =IFERROR(__xludf.DUMMYFUNCTION("""COMPUTED_VALUE"""),"Total Assets Total Assets") -> Total Assets Total Assets | B103: =IFERROR(__xludf.DUMMYFUNCTION("""COMPUTED_VALUE"""),"62.13B") -> 62.13B | C103: =IFERROR(__xludf.DUMMYFUNCTION("""COMPUTED_VALUE"""),"82.34B") -> 82.34B | D103: =IFERROR(__xludf.DUMMYFUNCTION("""COMPUTED_VALUE"""),"106.62B") -> 106.62B | E103: =IFERROR(__xludf.DUMMYFUNCTION("""COMPUTED_VALUE"""),"122.07B") -> 122.07B | F103: =IFERROR(__xludf.DUMMYFUNCTION("""COMPUTED_VALUE"""),"137.81B") -> 137.81B
A104: =IFERROR(__xludf.DUMMYFUNCTION("""COMPUTED_VALUE"""),"Total Assets Growth Total Assets Growth") -> Total Assets Growth Total Assets Growth | B104: =IFERROR(__xludf.DUMMYFUNCTION("""COMPUTED_VALUE"""),"-") -> - | C104: =IFERROR(__xludf.DUMMYFUNCTION("""COMPUTED_VALUE"""),0.3252) -> 0.3252 | D104: =IFERROR(__xludf.DUMMYFUNCTION("""COMPUTED_VALUE"""),0.2949) -> 0.2949 | E104: =IFERROR(__xludf.DUMMYFUNCTION("""COMPUTED_VALUE"""),0.1449) -> 0.1449 | F104: =IFERROR(__xludf.DUMMYFUNCTION("""COMPUTED_VALUE"""),0.1289) -> 0.1289
A111: =IFERROR(__xludf.DUMMYFUNCTION("IMPORTHTML(CONCAT(CONCAT(""https://www.marketwatch.com/investing/stock/"",'Income Statement'!D1),""/financials/cash-flow""),""table"",4) "),"Item Item") -> Item Item | B111: =IFERROR(__xludf.DUMMYFUNCTION("""COMPUTED_VALUE"""),2021.0) -> 2021 | C111: =IFERROR(__xludf.DUMMYFUNCTION("""COMPUTED_VALUE"""),2022.0) -> 2022 | D111: =IFERROR(__xludf.DUMMYFUNCTION("""COMPUTED_VALUE"""),2023.0) -> 2023 | E111: =IFERROR(__xludf.DUMMYFUNCTION("""COMPUTED_VALUE"""),2024.0) -> 2024 | F111: =IFERROR(__xludf.DUMMYFUNCTION("""COMPUTED_VALUE"""),2025.0) -> 2025 | G111: =IFERROR(__xludf.DUMMYFUNCTION("""COMPUTED_VALUE"""),"5-year trend") -> 5-year trend
A112: =IFERROR(__xludf.DUMMYFUNCTION("""COMPUTED_VALUE"""),"Net Income before Extraordinaries Net Income before Extraordinaries") -> Net Income before Extraordinaries Net Income before Extraordinaries | B112: =IFERROR(__xludf.DUMMYFUNCTION("""COMPUTED_VALUE"""),"5.64B") -> 5.64B | C112: =IFERROR(__xludf.DUMMYFUNCTION("""COMPUTED_VALUE"""),"12.59B") -> 12.59B | D112: =IFERROR(__xludf.DUMMYFUNCTION("""COMPUTED_VALUE"""),"14.97B") -> 14.97B | E112: =IFERROR(__xludf.DUMMYFUNCTION("""COMPUTED_VALUE"""),"7.15B") -> 7.15B | F112: =IFERROR(__xludf.DUMMYFUNCTION("""COMPUTED_VALUE"""),"3.86B") -> 3.86B
...
